Workbook

Sheet Capa_Cover
B2: AMAZON PORTUGAL DSP Modelo Financeiro / Financial Model
B5: Lisboa / Lisbon - Inicio/Start Set/Sep 2026 - Anos civis 2026 | 2027 (pressupostos lado a lado)
B7: PARAMETROS-CHAVE / KEY PARAMETERS
B8: Estrutura / Structure | F8: Semanas (Set-Out 26) + meses (Nov-Dez 26) + trimestres (2027)
B9: Pressupostos / Assumptions | F9: 2 colunas lado a lado: Valor 2026 | Valor 2027
B10: Taxa base / Base rate | F10: €17.90/h x 9h = €161.10/rota
B11: PPR | F11: 2026: €0.08 (c/ ramp) | 2027: €0.04 (so core)
B12: Rotas / Routes | F12: Ramp 5->25 (8 sem) | Pico ate 50 (Nov-Dez)
B13: Mao-de-obra / Labour | F13: Permanentes + Temporarios ETT nos picos
B14: Prazos / Terms | F14: Recebimento Amazon Net 45 | fornecedores Net 30 (editavel)
B15: Capital inicial | F15: €80,000
B16: ESTRUTURA / STRUCTURE
B17: 2 | C17: Pressupostos / Assumptions | F17: Inputs 2026 | 2027 lado a lado + calendario operacional
B18: 3 | C18: Operacao / Operations | F18: Rotas e volumes (detalhe + trimestral)
B19: 4 | C19: Receita / Revenue | F19: Taxa base, PPR, combustivel, portagens, SLS
B20: 5 | C20: Salarios / Wages | F20: Permanentes + Temporarios ETT + gestor + admin
B21: 6 | C21: Custos / Costs | F21: Mao-de-obra, frota, overheads
B22: 7 | C22: DRE / P&L | F22: Resultados (detalhe + trimestral)
B23: 8 | C23: Tesouraria / Cash Flow | F23: Fluxo de caixa e saldo (inclui impacto IVA)
B24: 9 | C24: IVA / VAT | F24: Apuramento detalhado e impacto na caixa
B25: 10 | C25: Ponto Critico / Break-Even | F25: Rotas minimas (regime 2026)

Sheet Pressupostos_Assumpt
B1: PRESSUPOSTOS / ASSUMPTIONS - Valores 2026 | 2027 lado a lado / side by side
B2: Edita a coluna do ano respetivo. Onde o valor nao muda, 2026 e 2027 sao iguais. / Edit each year column; equal where unchanged.
B4: A. RECEITA / REVENUE
B5: Parametro / Parameter | C5: Valor 2026 | D5: Valor 2027 | E5: Unidade / Unit | F5: Fonte-Nota / Source-Note
B6: Taxa horaria base / Hourly base rate | C6: 17.9 | D6: 17.9 | E6: €/h | F6: Amazon PT DSP Guide (2027: revisao anual)
B7: Duracao rota / Route duration | C7: 9 | D7: 9 | E7: h | F7: Amazon PT DSP Guide
B8: Pagamento rota (base x h) / Route payment | C8: =C6*C7 -> 161.1 | D8: =D6*D7 -> 161.1 | E8: €/rota | F8: Calculado / Calculated
B9: PPR - base / core | C9: 0.04 | D9: 0.04 | E9: €/enc | F9: Amazon PT DSP Guide
B10: PPR - incentivo ramp / ramp incentive | C10: 0.04 | D10: 0 | E10: €/enc | F10: 2027: incentivo de ramp acaba no ano 1 / ends Y1
B11: PPR total | C11: =C9+C10 -> 0.08 | D11: =D9+D10 -> 0.04 | E11: €/enc | F11: Calculado
B12: Encomendas/rota / Packages per route | C12: 86 | D12: 86 | E12: enc | F12: Amazon PT DSP Guide
B13: Km por rota / km per route | C13: 70 | D13: 70 | E13: km | F13: Amazon PT DSP Guide
B14: Preco gasoleo / Diesel price | C14: 1.65 | D14: 1.7 | E14: €/L | F14: DGEG (2027: estimativa subida)
B15: Consumo / Consumption | C15: 10 | D15: 10 | E15: L/100km | F15: Est. Sprinter/Crafter
B16: Reembolso combustivel/rota / Fuel reimb. | C16: =C13*(C14/100)*C15 -> 11.55 | D16: =D13*(D14/100)*D15 -> 11.9 | E16: €/rota | F16: Calculado
B17: Portagens/rota / Tolls per route | C17: 3.5 | D17: 3.5 | E17: €/rota | F17: Est. A1/A8 Lisboa
B18: Incentivo SLS / SLS incentive (mensal) | C18: 500 | D18: 500 | E18: €/mes | F18: Sujeito a desempenho
B20: B. OPERACAO / OPERATIONS
B21: Parametro / Parameter | C21: Valor 2026 | D21: Valor 2027 | E21: Unidade / Unit | F21: Fonte-Nota / Source-Note
B22: Rotas arranque (Sem1) / Launch routes (W1) | C22: 5 | D22: 5 | E22: rotas/dia | F22: Amazon PT DSP Guide
B23: Rotas regime / Steady-state routes | C23: 25 | D23: 25 | E23: rotas/dia | F23: Amazon PT DSP Guide - base permanente | J23: Analisar melhor algumas assumptions
B24: Rotas pico / Peak routes (Nov-Dez) | C24: 50 | D24: 50 | E24: rotas/dia | F24: Amazon PT DSP Guide
B25: Dias operacionais/semana / Op. days per week | C25: 5 | D25: 5 | E25: dias | F25: Seg-Sab / Mon-Sat
B26: Dias operacionais/mes / Op. days per month | C26: 22 | D26: 22 | E26: dias | F26: Media / Average
B28: C. FROTA E CAPEX / FLEET & CAPEX
B29: Parametro / Parameter | C29: Valor 2026 | D29: Valor 2027 | E29: Unidade / Unit | F29: Fonte-Nota / Source-Note
B30: Frota propria / Own fleet (regime) | C30: 25 | D30: 25 | E30: vans | F30: rotas regime
B31: Buffer de frota / Fleet buffer % | C31: 0.15 | D31: 0.15 | E31: % | F31: Carrinhas de reserva p/ avarias/manutencao/inspecoes (15%)
B32: Leasing por van/mes / Lease per van/month | C32: 800 | D32: 800 | E32: €/van | F32: Est. 36m (contrato fixo)
B33: Seguro por van/mes / Insurance per van/month | C33: 120 | D33: 125 | E33: €/van | F33: Apolice frota (2027: +)
B34: Manutencao por van/mes / Maintenance per van/month | C34: 150 | D34: 160 | E34: €/van | F34: Padrao (2027: vans + velhas)
B35: Aluguer pico por van/mes / Peak rental per van/month | C35: 1400 | D35: 1450 | E35: €/van | F35: Aluguer 3m
B36: Reserva dispositivos / Device reserve | C36: 100 | D36: 100 | E36: €/mes | F36: Contrato Amazon
B38: D. MAO-DE-OBRA / LABOUR
B39: Parametro / Parameter | C39: Valor 2026 | D39: Valor 2027 | E39: Unidade / Unit | F39: Fonte-Nota / Source-Note
B40: Salario DA por hora (bruto) / DA hourly wage (gross) | C40: 6.2 | D40: 6.2 | E40: €/h | F40: Acima do minimo (€5,88/h); compromisso competitividade/rentabilidade
B41: Salario DA mensal (=hora x 2080/12) / DA monthly wage | C41: =C40*2080/12 -> 1074.6667 | D41: =D40*2080/12 -> 1074.6667 | E41: €/mes | F41: Calculado: hora x 2080h/ano / 12 meses (metodo PT)
B42: Taxa SS patronal / Employer SS rate | C42: 0.2375 | D42: 0.2375 | E42: % | F42: Seg. Social PT - 23.75%
B43: Custo total DA c/SS / DA total cost incl. SS | C43: =C41*(1+C42) -> 1329.9 | D43: =D41*(1+D42) -> 1329.9 | E43: €/mes | F43: Calculado
B44: Salario gestor por hora (bruto) / Manager hourly wage | C44: 11.5 | D44: 11.85 | E44: €/h | F44: Gestor de operacoes c/ CAM - acima do motorista (2027: +~3%)
B45: Salario gestor mensal (=hora x 2080/12) / Manager monthly | C45: =C44*2080/12 -> 1993.3333 | D45: =D44*2080/12 -> 2054 | E45: €/mes | F45: Calculado: hora x 2080h/ano / 12 meses
B46: Custo total gestor c/SS / Manager total cost | C46: =C45*(1+C42) -> 2466.75 | D46: =D45*(1+D42) -> 2541.825 | E46: €/mes | F46: Calculado
B47: Rotatividade anual DA / DA annual turnover | C47: 0.15 | D47: 0.15 | E47: % | F47: Reduzida por salario competitivo (vs 25% no minimo)
B48: Custo recrutamento/DA / Recruitment cost per DA | C48: 150 | D48: 150 | E48: €/contrat | F48: Anuncios+onboarding
B49: Buffer de motoristas / Driver buffer % | C49: 0.15 | D49: 0.15 | E49: % | F49: Reserva p/ ferias(~9%)+faltas/baixas(~6%)+formacao(~5%)=20%
B50: Fator depreciacao mensal / Monthly depreciation | C50: 0 | D50: 0 | E50: %/mes | F50: Sobre valor frota
B52: E. SALARIOS DETALHADOS / DETAILED WAGES
B53: Parametro / Parameter | C53: Valor 2026 | D53: Valor 2027 | E53: Unidade / Unit | F53: Fonte-Nota / Source-Note
B54: Meses pagos / Months paid (14/12) | C54: =14/12 -> 1.1666667 | D54: =14/12 -> 1.1666667 | E54: fator | F54: Subs. Natal+ferias
B55: SS trabalhador / Employee SS | C55: 0.11 | D55: 0.11 | E55: % | F55: Seg. Social PT - 11%
B56: Subsidio alimentacao/dia / Food subsidy per day | C56: 6 | D56: 6 | E56: €/dia | F56: Isento ate ao limite; acima paga SS
B57: Limite isencao SS subsidio (dinheiro=6 / cartao=10,46) / Exempt limit | C57: 6 | D57: 6 | E57: €/dia | F57: Dinheiro: isento ate €6,00; cartao: ate €10,46. Acima -> SS sobre excesso
B58: Dias uteis/mes / Working days per month | C58: 22 | D58: 22 | E58: dias | F58: Para sub. alimentacao
B59: Retencao IRS - DA / IRS withholding - driver | C59: 0.083 | D59: 0.083 | E59: % | F59: Tabela IRS PT
B60: Retencao IRS - Gestor / IRS - manager | C60: 0.143 | D60: 0.143 | E60: % | F60: Tabela IRS PT
B61: Nº gestores / Managers | C61: 1 | D61: 1 | E61: pessoas | F61: Gestor operacoes
B62: Salario admin por hora (bruto) / Admin hourly wage | C62: 7.2 | D62: 7.4 | E62: €/h | F62: Assistente administrativo - acima do minimo (2027: +~3%)
B63: Salario admin mensal (=hora x 2080/12) / Admin monthly | C63: =C62*2080/12 -> 1248 | D63: =D62*2080/12 -> 1282.6667 | E63: €/mes | F63: Calculado: hora x 2080h/ano / 12 meses
B64: Nº administrativos / Admin staff | C64: 1 | D64: 1 | E64: pessoas | F64: Apoio administrativo
B65: Coef. trabalho temporario (ETT) / Temp agency coeff. | C65: 1.5 | D65: 1.5 | E65: fator | F65: Salario x coef (inclui SS, subsidios e margem da agencia)
B67: F. OVERHEADS FIXOS / FIXED OVERHEAD
B68: Parametro / Parameter | C68: Valor 2026 | D68: Valor 2027 | E68: Unidade / Unit | F68: Fonte-Nota / Source-Note
B69: Contabilidade / Accounting | C69: 200 | D69: 206 | E69: €/mes | F69: Contabilista (2027: +~3%)
B70: Seguro resp. civil / GL insurance | C70: 250 | D70: 258 | E70: €/mes | F70: €1M (2027: +~3%)
B71: Dispositivos/SIM por DA / Devices per DA | C71: 15 | D71: 15 | E71: €/DA/mes | F71: SIM + dispositivo
B72: Diversos/contingencia / Misc | C72: 300 | D72: 309 | E72: €/mes | F72: Fardas (2027: +~3%)
B73: Capital inicial disponivel / Initial capital | C73: 80000 | D73: 80000 | E73: € | F73: Amazon PT DSP Guide
B74: IRC (taxa) / Corporate tax rate | C74: 0.21 | D74: 0.21 | E74: % | F74: IRC PT
B76: G. INSTALACOES / FACILITIES (parque das carrinhas / van yard)
B77: Parametro / Parameter | C77: Valor 2026 | D77: Valor 2027 | E77: Unidade / Unit | F77: Fonte-Nota / Source-Note
B78: Aluguer parque/armazem / Yard-warehouse rent | C78: 2000 | D78: 2060 | E78: €/mes | F78: Espaco com lugares p/ todas as carrinhas (2027: +~3%)
B80: H. IVA / VAT
B81: Parametro / Parameter | C81: Valor 2026 | D81: Valor 2027 | E81: Unidade / Unit | F81: Fonte-Nota / Source-Note
B82: Taxa IVA normal / Standard VAT rate | C82: 0.23 | D82: 0.23 | E82: % | F82: Taxa normal PT - 23%
B83: % IVA dedutivel combustivel / VAT deductible on fuel | C83: 0.5 | D83: 0.5 | E83: % | F83: Gasoleo em ligeiros: deducao parcial PT (~50%)
B84: % IVA dedutivel viaturas/leasing / VAT deductible on vehicles | C84: 1 | D84: 1 | E84: % | F84: Viaturas ligeiras de passageiros: nao dedutivel; comerciais: 100% (ajustar)
B85: Periodicidade IVA (meses) / VAT period (months) | C85: 3 | D85: 3 | E85: meses | F85: Trimestral (volume>=650k: mensal)
B87: I. PRAZOS DE PAGAMENTO / PAYMENT TERMS (tesouraria / cash timing)
B88: Parametro / Parameter | C88: Valor 2026 | D88: Valor 2027 | E88: Unidade / Unit | F88: Fonte-Nota / Source-Note
B89: Prazo recebimento Amazon (DSO) / Days to receive from Amazon | C89: 45 | D89: 45 | E89: dias | F89: Net 45 estimado (negociar c/ BDM) / estimate
B90: Prazo pagamento fornecedores (DPO) / Days to pay suppliers | C90: 30 | D90: 30 | E90: dias | F90: Frota/servicos/overheads ~Net 30
B91: Prazo pagamento salarios / Days to pay wages | C91: 0 | D91: 0 | E91: dias | F91: Salarios pagos no mes (imediato)
B92: Linha de credito disponivel / Credit line limit | C92: 100000 | D92: 100000 | E92: € | F92: Conta-corrente caucionada p/ cobrir pico de tesouraria
B93: Taxa juro anual linha credito / Annual interest rate | C93: 0.08 | D93: 0.08 | E93: % | F93: Estimativa (Euribor+spread) - negociar c/ banco
B95: J. CALENDARIO OPERACIONAL POR PERIODO / OPERATIONAL SCHEDULE BY PERIOD (editavel)
B96: Parametro / Parameter | C96: S1 Set/Sep 26 | D96: S2 Set/Sep 26 | E96: S3 Set/Sep 26 | F96: S4 Set/Sep 26 | G96: S5 Out/Oct 26 | H96: S6 Out/Oct 26 | I96: S7 Out/Oct 26 | J96: S8 Out/Oct 26 | K96: Nov Nov 26 (Pico/Peak) | L96: Dez Dez/Dec 26 (Pico/Peak) | M96: Q1'27 Jan-Mar 27 | N96: Q2'27 Abr-Jun/Apr-Jun 27 | O96: Q3'27 Jul-Set/Jul-Sep 27 | P96: Out'27 Out/Oct 27 | Q96: Nov'27 Nov 27 (Pico/Peak) | R96: Dez'27 Dez/Dec 27 (Pico/Peak)
B97: Dias operacionais / Operating days | C97: =Pressupostos_Assumpt!C25 -> 5 | D97: =Pressupostos_Assumpt!C25 -> 5 | E97: =Pressupostos_Assumpt!C25 -> 5 | F97: =Pressupostos_Assumpt!C25 -> 5 | G97: =Pressupostos_Assumpt!C25 -> 5 | H97: =Pressupostos_Assumpt!C25 -> 5 | I97: =Pressupostos_Assumpt!C25 -> 5 | J97: =Pressupostos_Assumpt!C25 -> 5 | K97: =Pressupostos_Assumpt!C26 -> 22 | L97: =Pressupostos_Assumpt!C26 -> 22 | M97: =Pressupostos_Assumpt!D26*3 -> 66 | N97: =Pressupostos_Assumpt!D26*3 -> 66 | O97: =Pressupostos_Assumpt!D26*3 -> 66 | P97: =Pressupostos_Assumpt!D26 -> 22 | Q97: =Pressupostos_Assumpt!D26 -> 22 | R97: =Pressupostos_Assumpt!D26 -> 22
B98: Rotas/dia (plano) / Routes/day (plan) | C98: 5 | D98: 8 | E98: 12 | F98: 16 | G98: 20 | H98: 23 | I98: 25 | J98: 25 | K98: 50 | L98: 50 | M98: 25 | N98: 25 | O98: 25 | P98: 25 | Q98: 50 | R98: 50
B99: Indice volume / Volume index | C99: 1 | D99: 1 | E99: 1 | F99: 1 | G99: 1 | H99: 1 | I99: 1 | J99: 1 | K99: 1.05 | L99: 1.05 | M99: 0.9 | N99: 1.05 | O99: 1.05 | P99: 1.05 | Q99: 1.1 | R99: 1.1

Sheet Operacao_Operations
B1: OPERACAO - ROTAS E VOLUMES / OPERATIONS - ROUTES & VOLUMES
C2: ANO 2026 / YEAR 2026 (Ago-Dez/Aug-Dec) | M2: ANO 2027 / YEAR 2027
B3: Rubrica / Item | C3: S1 Set/Sep 26 | D3: S2 Set/Sep 26 | E3: S3 Set/Sep 26 | F3: S4 Set/Sep 26 | G3: S5 Out/Oct 26 | H3: S6 Out/Oct 26 | I3: S7 Out/Oct 26 | J3: S8 Out/Oct 26 | K3: Nov Nov 26 (Pico/Peak) | L3: Dez Dez/Dec 26 (Pico/Peak) | M3: Q1'27 Jan-Mar 27 | N3: Q2'27 Abr-Jun/Apr-Jun 27 | O3: Q3'27 Jul-Set/Jul-Sep 27 | P3: Out'27 Out/Oct 27 | Q3: Nov'27 Nov 27 (Pico/Peak) | R3: Dez'27 Dez/Dec 27 (Pico/Peak) | S3: Total 2026 | T3: Total 2027
B4: Dias operacionais / Operating days | C4: =Pressupostos_Assumpt!C97 -> 5 | D4: =Pressupostos_Assumpt!D97 -> 5 | E4: =Pressupostos_Assumpt!E97 -> 5 | F4: =Pressupostos_Assumpt!F97 -> 5 | G4: =Pressupostos_Assumpt!G97 -> 5 | H4: =Pressupostos_Assumpt!H97 -> 5 | I4: =Pressupostos_Assumpt!I97 -> 5 | J4: =Pressupostos_Assumpt!J97 -> 5 | ... R4: =Pressupostos_Assumpt!R97 -> 22 | S4: =C4+D4+E4+F4+G4+H4+I4+J4+K4+L4 -> 84 | T4: =M4+N4+O4+P4+Q4+R4 -> 264
B5: Periodos-mes (dias/26) / Period-months | C5: =C4/Pressupostos_Assumpt!C26 -> 0.22727273 | D5: =D4/Pressupostos_Assumpt!C26 -> 0.22727273 | E5: =E4/Pressupostos_Assumpt!C26 -> 0.22727273 | F5: =F4/Pressupostos_Assumpt!C26 -> 0.22727273 | G5: =G4/Pressupostos_Assumpt!C26 -> 0.22727273 | H5: =H4/Pressupostos_Assumpt!C26 -> 0.22727273 | I5: =I4/Pressupostos_Assumpt!C26 -> 0.22727273 | J5: =J4/Pressupostos_Assumpt!C26 -> 0.22727273 | K5: =K4/Pressupostos_Assumpt!C26 -> 1 | L5: =L4/Pressupostos_Assumpt!C26 -> 1 | M5: =M4/Pressupostos_Assumpt!D26 -> 3 | N5: =N4/Pressupostos_Assumpt!D26 -> 3 | O5: =O4/Pressupostos_Assumpt!D26 -> 3 | P5: =P4/Pressupostos_Assumpt!D26 -> 1 | Q5: =Q4/Pressupostos_Assumpt!D26 -> 1 | R5: =R4/Pressupostos_Assumpt!D26 -> 1
B6: Rotas/dia (plano) / Routes/day (plan) | C6: =Pressupostos_Assumpt!C98 -> 5 | D6: =Pressupostos_Assumpt!D98 -> 8 | E6: =Pressupostos_Assumpt!E98 -> 12 | F6: =Pressupostos_Assumpt!F98 -> 16 | G6: =Pressupostos_Assumpt!G98 -> 20 | H6: =Pressupostos_Assumpt!H98 -> 23 | I6: =Pressupostos_Assumpt!I98 -> 25 | J6: =Pressupostos_Assumpt!J98 -> 25 | ... R6: =Pressupostos_Assumpt!R98 -> 50
B7: Rotas-dia totais / Total route-days | C7: =C6*C4 -> 25 | D7: =D6*D4 -> 40 | E7: =E6*E4 -> 60 | F7: =F6*F4 -> 80 | G7: =G6*G4 -> 100 | H7: =H6*H4 -> 115 | I7: =I6*I4 -> 125 | J7: =J6*J4 -> 125 | ... R7: =R6*R4 -> 1100 | S7: =C7+D7+E7+F7+G7+H7+I7+J7+K7+L7 -> 2870 | T7: =M7+N7+O7+P7+Q7+R7 -> 7700
B8: Indice volume / Volume index | C8: =Pressupostos_Assumpt!C99 -> 1 | D8: =Pressupostos_Assumpt!D99 -> 1 | E8: =Pressupostos_Assumpt!E99 -> 1 | F8: =Pressupostos_Assumpt!F99 -> 1 | G8: =Pressupostos_Assumpt!G99 -> 1 | H8: =Pressupostos_Assumpt!H99 -> 1 | I8: =Pressupostos_Assumpt!I99 -> 1 | J8: =Pressupostos_Assumpt!J99 -> 1 | ... R8: =Pressupostos_Assumpt!R99 -> 1.1
B9: Encomendas/rota / Packages per route | C9: =Pressupostos_Assumpt!C12 -> 86 | D9: =Pressupostos_Assumpt!C12 -> 86 | E9: =Pressupostos_Assumpt!C12 -> 86 | F9: =Pressupostos_Assumpt!C12 -> 86 | G9: =Pressupostos_Assumpt!C12 -> 86 | H9: =Pressupostos_Assumpt!C12 -> 86 | I9: =Pressupostos_Assumpt!C12 -> 86 | J9: =Pressupostos_Assumpt!C12 -> 86 | K9: =Pressupostos_Assumpt!C12 -> 86 | L9: =Pressupostos_Assumpt!C12 -> 86 | M9: =Pressupostos_Assumpt!D12 -> 86 | N9: =Pressupostos_Assumpt!D12 -> 86 | O9: =Pressupostos_Assumpt!D12 -> 86 | P9: =Pressupostos_Assumpt!D12 -> 86 | Q9: =Pressupostos_Assumpt!D12 -> 86 | R9: =Pressupostos_Assumpt!D12 -> 86
B10: Encomendas totais / Total packages | C10: =C7*C9*C8 -> 2150 | D10: =D7*D9*D8 -> 3440 | E10: =E7*E9*E8 -> 5160 | F10: =F7*F9*F8 -> 6880 | G10: =G7*G9*G8 -> 8600 | H10: =H7*H9*H8 -> 9890 | I10: =I7*I9*I8 -> 10750 | J10: =J7*J9*J8 -> 10750 | ... R10: =R7*R9*R8 -> 104060 | S10: =C10+D10+E10+F10+G10+H10+I10+J10+K10+L10 -> 256280 | T10: =M10+N10+O10+P10+Q10+R10 -> 683485
B11: CARRINHAS DISPONIVEIS / VANS AVAILABLE
B12: Carrinhas proprias (leasing) / Own vans (leasing) | C12: =CEILING(MIN(C6,Pressupostos_Assumpt!C23)*(1+Pressupostos_Assumpt!C31),1) -> 6 | D12: =CEILING(MIN(D6,Pressupostos_Assumpt!C23)*(1+Pressupostos_Assumpt!C31),1) -> 10 | E12: =CEILING(MIN(E6,Pressupostos_Assumpt!C23)*(1+Pressupostos_Assumpt!C31),1) -> 14 | F12: =CEILING(MIN(F6,Pressupostos_Assumpt!C23)*(1+Pressupostos_Assumpt!C31),1) -> 19 | G12: =CEILING(MIN(G6,Pressupostos_Assumpt!C23)*(1+Pressupostos_Assumpt!C31),1) -> 23 | H12: =CEILING(MIN(H6,Pressupostos_Assumpt!C23)*(1+Pressupostos_Assumpt!C31),1) -> 27 | I12: =CEILING(MIN(I6,Pressupostos_Assumpt!C23)*(1+Pressupostos_Assumpt!C31),1) -> 29 | J12: =CEILING(MIN(J6,Pressupostos_Assumpt!C23)*(1+Pressupostos_Assumpt!C31),1) -> 29 | K12: =CEILING(MIN(K6,Pressupostos_Assumpt!C23)*(1+Pressupostos_Assumpt!C31),1) -> 29 | L12: =CEILING(MIN(L6,Pressupostos_Assumpt!C23)*(1+Pressupostos_Assumpt!C31),1) -> 29 | M12: =CEILING(MIN(M6,Pressupostos_Assumpt!D23)*(1+Pressupostos_Assumpt!D31),1) -> 29 | N12: =CEILING(MIN(N6,Pressupostos_Assumpt!D23)*(1+Pressupostos_Assumpt!D31),1) -> 29 | O12: =CEILING(MIN(O6,Pressupostos_Assumpt!D23)*(1+Pressupostos_Assumpt!D31),1) -> 29 | P12: =CEILING(MIN(P6,Pressupostos_Assumpt!D23)*(1+Pressupostos_Assumpt!D31),1) -> 29 | Q12: =CEILING(MIN(Q6,Pressupostos_Assumpt!D23)*(1+Pressupostos_Assumpt!D31),1) -> 29 | R12: =CEILING(MIN(R6,Pressupostos_Assumpt!D23)*(1+Pressupostos_Assumpt!D31),1) -> 29 | S12: =MAX(C12:L12) -> 29 | T12: =MAX(M12:R12) -> 29
B13: Carrinhas aluguer pico / Peak rental vans | C13: =CEILING(MAX(0,C6-Pressupostos_Assumpt!C23)*(1+Pressupostos_Assumpt!C31),1) -> 0 | D13: =CEILING(MAX(0,D6-Pressupostos_Assumpt!C23)*(1+Pressupostos_Assumpt!C31),1) -> 0 | E13: =CEILING(MAX(0,E6-Pressupostos_Assumpt!C23)*(1+Pressupostos_Assumpt!C31),1) -> 0 | F13: =CEILING(MAX(0,F6-Pressupostos_Assumpt!C23)*(1+Pressupostos_Assumpt!C31),1) -> 0 | G13: =CEILING(MAX(0,G6-Pressupostos_Assumpt!C23)*(1+Pressupostos_Assumpt!C31),1) -> 0 | H13: =CEILING(MAX(0,H6-Pressupostos_Assumpt!C23)*(1+Pressupostos_Assumpt!C31),1) -> 0 | I13: =CEILING(MAX(0,I6-Pressupostos_Assumpt!C23)*(1+Pressupostos_Assumpt!C31),1) -> 0 | J13: =CEILING(MAX(0,J6-Pressupostos_Assumpt!C23)*(1+Pressupostos_Assumpt!C31),1) -> 0 | K13: =CEILING(MAX(0,K6-Pressupostos_Assumpt!C23)*(1+Pressupostos_Assumpt!C31),1) -> 29 | L13: =CEILING(MAX(0,L6-Pressupostos_Assumpt!C23)*(1+Pressupostos_Assumpt!C31),1) -> 29 | M13: =CEILING(MAX(0,M6-Pressupostos_Assumpt!D23)*(1+Pressupostos_Assumpt!D31),1) -> 0 | N13: =CEILING(MAX(0,N6-Pressupostos_Assumpt!D23)*(1+Pressupostos_Assumpt!D31),1) -> 0 | O13: =CEILING(MAX(0,O6-Pressupostos_Assumpt!D23)*(1+Pressupostos_Assumpt!D31),1) -> 0 | P13: =CEILING(MAX(0,P6-Pressupostos_Assumpt!D23)*(1+Pressupostos_Assumpt!D31),1) -> 0 | Q13: =CEILING(MAX(0,Q6-Pressupostos_Assumpt!D23)*(1+Pressupostos_Assumpt!D31),1) -> 29 | R13: =CEILING(MAX(0,R6-Pressupostos_Assumpt!D23)*(1+Pressupostos_Assumpt!D31),1) -> 29 | S13: =MAX(C13:L13) -> 29 | T13: =MAX(M13:R13) -> 29
B14: TOTAL CARRINHAS DISPONIVEIS / TOTAL VANS | C14: =C12+C13 -> 6 | D14: =D12+D13 -> 10 | E14: =E12+E13 -> 14 | F14: =F12+F13 -> 19 | G14: =G12+G13 -> 23 | H14: =H12+H13 -> 27 | I14: =I12+I13 -> 29 | J14: =J12+J13 -> 29 | ... R14: =R12+R13 -> 58 | S14: =MAX(C14:L14) -> 58 | T14: =MAX(M14:R14) -> 58
B15: MOTORISTAS DISPONIVEIS / DRIVERS AVAILABLE
B16: Motoristas permanentes / Permanent drivers | C16: =CEILING(MIN(C6,Pressupostos_Assumpt!C23)*(1+Pressupostos_Assumpt!C49),1) -> 6 | D16: =CEILING(MIN(D6,Pressupostos_Assumpt!C23)*(1+Pressupostos_Assumpt!C49),1) -> 10 | E16: =CEILING(MIN(E6,Pressupostos_Assumpt!C23)*(1+Pressupostos_Assumpt!C49),1) -> 14 | F16: =CEILING(MIN(F6,Pressupostos_Assumpt!C23)*(1+Pressupostos_Assumpt!C49),1) -> 19 | G16: =CEILING(MIN(G6,Pressupostos_Assumpt!C23)*(1+Pressupostos_Assumpt!C49),1) -> 23 | H16: =CEILING(MIN(H6,Pressupostos_Assumpt!C23)*(1+Pressupostos_Assumpt!C49),1) -> 27 | I16: =CEILING(MIN(I6,Pressupostos_Assumpt!C23)*(1+Pressupostos_Assumpt!C49),1) -> 29 | J16: =CEILING(MIN(J6,Pressupostos_Assumpt!C23)*(1+Pressupostos_Assumpt!C49),1) -> 29 | K16: =CEILING(MIN(K6,Pressupostos_Assumpt!C23)*(1+Pressupostos_Assumpt!C49),1) -> 29 | L16: =CEILING(MIN(L6,Pressupostos_Assumpt!C23)*(1+Pressupostos_Assumpt!C49),1) -> 29 | M16: =CEILING(MIN(M6,Pressupostos_Assumpt!D23)*(1+Pressupostos_Assumpt!D49),1) -> 29 | N16: =CEILING(MIN(N6,Pressupostos_Assumpt!D23)*(1+Pressupostos_Assumpt!D49),1) -> 29 | O16: =CEILING(MIN(O6,Pressupostos_Assumpt!D23)*(1+Pressupostos_Assumpt!D49),1) -> 29 | P16: =CEILING(MIN(P6,Pressupostos_Assumpt!D23)*(1+Pressupostos_Assumpt!D49),1) -> 29 | Q16: =CEILING(MIN(Q6,Pressupostos_Assumpt!D23)*(1+Pressupostos_Assumpt!D49),1) -> 29 | R16: =CEILING(MIN(R6,Pressupostos_Assumpt!D23)*(1+Pressupostos_Assumpt!D49),1) -> 29 | S16: =MAX(C16:L16) -> 29 | T16: =MAX(M16:R16) -> 29
B17: Motoristas temporarios ETT / Temp agency drivers | C17: =CEILING(MAX(0,C6-Pressupostos_Assumpt!C23)*(1+Pressupostos_Assumpt!C49),1) -> 0 | D17: =CEILING(MAX(0,D6-Pressupostos_Assumpt!C23)*(1+Pressupostos_Assumpt!C49),1) -> 0 | E17: =CEILING(MAX(0,E6-Pressupostos_Assumpt!C23)*(1+Pressupostos_Assumpt!C49),1) -> 0 | F17: =CEILING(MAX(0,F6-Pressupostos_Assumpt!C23)*(1+Pressupostos_Assumpt!C49),1) -> 0 | G17: =CEILING(MAX(0,G6-Pressupostos_Assumpt!C23)*(1+Pressupostos_Assumpt!C49),1) -> 0 | H17: =CEILING(MAX(0,H6-Pressupostos_Assumpt!C23)*(1+Pressupostos_Assumpt!C49),1) -> 0 | I17: =CEILING(MAX(0,I6-Pressupostos_Assumpt!C23)*(1+Pressupostos_Assumpt!C49),1) -> 0 | J17: =CEILING(MAX(0,J6-Pressupostos_Assumpt!C23)*(1+Pressupostos_Assumpt!C49),1) -> 0 | K17: =CEILING(MAX(0,K6-Pressupostos_Assumpt!C23)*(1+Pressupostos_Assumpt!C49),1) -> 29 | L17: =CEILING(MAX(0,L6-Pressupostos_Assumpt!C23)*(1+Pressupostos_Assumpt!C49),1) -> 29 | M17: =CEILING(MAX(0,M6-Pressupostos_Assumpt!D23)*(1+Pressupostos_Assumpt!D49),1) -> 0 | N17: =CEILING(MAX(0,N6-Pressupostos_Assumpt!D23)*(1+Pressupostos_Assumpt!D49),1) -> 0 | O17: =CEILING(MAX(0,O6-Pressupostos_Assumpt!D23)*(1+Pressupostos_Assumpt!D49),1) -> 0 | P17: =CEILING(MAX(0,P6-Pressupostos_Assumpt!D23)*(1+Pressupostos_Assumpt!D49),1) -> 0 | Q17: =CEILING(MAX(0,Q6-Pressupostos_Assumpt!D23)*(1+Pressupostos_Assumpt!D49),1) -> 29 | R17: =CEILING(MAX(0,R6-Pressupostos_Assumpt!D23)*(1+Pressupostos_Assumpt!D49),1) -> 29 | S17: =MAX(C17:L17) -> 29 | T17: =MAX(M17:R17) -> 29
B18: TOTAL MOTORISTAS DISPONIVEIS / TOTAL DRIVERS | C18: =C16+C17 -> 6 | D18: =D16+D17 -> 10 | E18: =E16+E17 -> 14 | F18: =F16+F17 -> 19 | G18: =G16+G17 -> 23 | H18: =H16+H17 -> 27 | I18: =I16+I17 -> 29 | J18: =J16+J17 -> 29 | ... R18: =R16+R17 -> 58 | S18: =MAX(C18:L18) -> 58 | T18: =MAX(M18:R18) -> 58
B21: RESUMO MENSAL / MONTHLY BREAKDOWN
C22: 2026 (Set-Dez) | G22: 2027
B23: POR MES / BY MONTH | C23: Set/Sep 26 | D23: Out/Oct 26 | E23: Nov 26 | F23: Dez/Dec 26 | G23: Jan 27 | H23: Fev/Feb 27 | I23: Mar 27 | J23: Abr/Apr 27 | K23: Mai/May 27 | L23: Jun 27 | M23: Jul 27 | N23: Ago/Aug 27 | O23: Set/Sep 27 | P23: Out/Oct 27 | Q23: Nov 27 | R23: Dez/Dec 27
B24: Rotas-dia totais / Total route-days | C24: =C7+D7+E7+F7 -> 205 | D24: =G7+H7+I7+J7 -> 465 | E24: =K7 -> 1100 | F24: =L7 -> 1100 | G24: =(M7)/3 -> 550 | H24: =(M7)/3 -> 550 | I24: =(M7)/3 -> 550 | J24: =(N7)/3 -> 550 | K24: =(N7)/3 -> 550 | L24: =(N7)/3 -> 550 | M24: =(O7)/3 -> 550 | N24: =(O7)/3 -> 550 | O24: =(O7)/3 -> 550 | P24: =P7 -> 550 | Q24: =Q7 -> 1100 | R24: =R7 -> 1100
B25: Encomendas totais / Total packages | C25: =C10+D10+E10+F10 -> 17630 | D25: =G10+H10+I10+J10 -> 39990 | E25: =K10 -> 99330 | F25: =L10 -> 99330 | G25: =(M10)/3 -> 42570 | H25: =(M10)/3 -> 42570 | I25: =(M10)/3 -> 42570 | J25: =(N10)/3 -> 49665 | K25: =(N10)/3 -> 49665 | L25: =(N10)/3 -> 49665 | M25: =(O10)/3 -> 49665 | N25: =(O10)/3 -> 49665 | O25: =(O10)/3 -> 49665 | P25: =P10 -> 49665 | Q25: =Q10 -> 104060 | R25: =R10 -> 104060
B26: Carrinhas proprias (max) / Own vans | C26: =MAX(C12,D12,E12,F12) -> 19 | D26: =MAX(G12,H12,I12,J12) -> 29 | E26: =MAX(K12) -> 29 | F26: =MAX(L12) -> 29 | G26: =MAX(M12) -> 29 | H26: =MAX(M12) -> 29 | I26: =MAX(M12) -> 29 | J26: =MAX(N12) -> 29 | K26: =MAX(N12) -> 29 | L26: =MAX(N12) -> 29 | M26: =MAX(O12) -> 29 | N26: =MAX(O12) -> 29 | O26: =MAX(O12) -> 29 | P26: =MAX(P12) -> 29 | Q26: =MAX(Q12) -> 29 | R26: =MAX(R12) -> 29
B27: Carrinhas aluguer (max) / Rental vans | C27: =MAX(C13,D13,E13,F13) -> 0 | D27: =MAX(G13,H13,I13,J13) -> 0 | E27: =MAX(K13) -> 29 | F27: =MAX(L13) -> 29 | G27: =MAX(M13) -> 0 | H27: =MAX(M13) -> 0 | I27: =MAX(M13) -> 0 | J27: =MAX(N13) -> 0 | K27: =MAX(N13) -> 0 | L27: =MAX(N13) -> 0 | M27: =MAX(O13) -> 0 | N27: =MAX(O13) -> 0 | O27: =MAX(O13) -> 0 | P27: =MAX(P13) -> 0 | Q27: =MAX(Q13) -> 29 | R27: =MAX(R13) -> 29
B28: TOTAL carrinhas (max) / Total vans | C28: =MAX(C14,D14,E14,F14) -> 19 | D28: =MAX(G14,H14,I14,J14) -> 29 | E28: =MAX(K14) -> 58 | F28: =MAX(L14) -> 58 | G28: =MAX(M14) -> 29 | H28: =MAX(M14) -> 29 | I28: =MAX(M14) -> 29 | J28: =MAX(N14) -> 29 | K28: =MAX(N14) -> 29 | L28: =MAX(N14) -> 29 | M28: =MAX(O14) -> 29 | N28: =MAX(O14) -> 29 | O28: =MAX(O14) -> 29 | P28: =MAX(P14) -> 29 | Q28: =MAX(Q14) -> 58 | R28: =MAX(R14) -> 58
B29: Motoristas permanentes (max) / Permanent | C29: =MAX(C16,D16,E16,F16) -> 19 | D29: =MAX(G16,H16,I16,J16) -> 29 | E29: =MAX(K16) -> 29 | F29: =MAX(L16) -> 29 | G29: =MAX(M16) -> 29 | H29: =MAX(M16) -> 29 | I29: =MAX(M16) -> 29 | J29: =MAX(N16) -> 29 | K29: =MAX(N16) -> 29 | L29: =MAX(N16) -> 29 | M29: =MAX(O16) -> 29 | N29: =MAX(O16) -> 29 | O29: =MAX(O16) -> 29 | P29: =MAX(P16) -> 29 | Q29: =MAX(Q16) -> 29 | R29: =MAX(R16) -> 29
B30: Motoristas temp ETT (max) / Temp | C30: =MAX(C17,D17,E17,F17) -> 0 | D30: =MAX(G17,H17,I17,J17) -> 0 | E30: =MAX(K17) -> 29 | F30: =MAX(L17) -> 29 | G30: =MAX(M17) -> 0 | H30: =MAX(M17) -> 0 | I30: =MAX(M17) -> 0 | J30: =MAX(N17) -> 0 | K30: =MAX(N17) -> 0 | L30: =MAX(N17) -> 0 | M30: =MAX(O17) -> 0 | N30: =MAX(O17) -> 0 | O30: =MAX(O17) -> 0 | P30: =MAX(P17) -> 0 | Q30: =MAX(Q17) -> 29 | R30: =MAX(R17) -> 29
B31: TOTAL motoristas (max) / Total drivers | C31: =MAX(C18,D18,E18,F18) -> 19 | D31: =MAX(G18,H18,I18,J18) -> 29 | E31: =MAX(K18) -> 58 | F31: =MAX(L18) -> 58 | G31: =MAX(M18) -> 29 | H31: =MAX(M18) -> 29 | I31: =MAX(M18) -> 29 | J31: =MAX(N18) -> 29 | K31: =MAX(N18) -> 29 | L31: =MAX(N18) -> 29 | M31: =MAX(O18) -> 29 | N31: =MAX(O18) -> 29 | O31: =MAX(O18) -> 29 | P31: =MAX(P18) -> 29 | Q31: =MAX(Q18) -> 58 | R31: =MAX(R18) -> 58
B34: RESUMO TRIMESTRAL / QUARTERLY BREAKDOWN
C35: 2026 | E35: 2027
B36: POR TRIMESTRE / BY QUARTER | C36: Q3 2026 Set/Sep 26 | D36: Q4 2026 Out-Dez/Oct-Dec 26 | E36: Q1 2027 Jan-Mar 27 | F36: Q2 2027 Abr-Jun/Apr-Jun 27 | G36: Q3 2027 Jul-Set/Jul-Sep 27 | H36: Q4 2027 Out-Dez/Oct-Dec 27
B37: Rotas-dia totais / Total route-days | C37: =SUM(C7:F7) -> 205 | D37: =SUM(G7:L7) -> 2665 | E37: =SUM(M7:M7) -> 1650 | F37: =SUM(N7:N7) -> 1650 | G37: =SUM(O7:O7) -> 1650 | H37: =SUM(P7:R7) -> 2750
B38: Encomendas totais / Total packages | C38: =SUM(C10:F10) -> 17630 | D38: =SUM(G10:L10) -> 238650 | E38: =SUM(M10:M10) -> 127710 | F38: =SUM(N10:N10) -> 148995 | G38: =SUM(O10:O10) -> 148995 | H38: =SUM(P10:R10) -> 257785
B39: Carrinhas proprias (max) / Own vans | C39: =MAX(C12:F12) -> 19 | D39: =MAX(G12:L12) -> 29 | E39: =MAX(M12:M12) -> 29 | F39: =MAX(N12:N12) -> 29 | G39: =MAX(O12:O12) -> 29 | H39: =MAX(P12:R12) -> 29
B40: Carrinhas aluguer (max) / Rental vans | C40: =MAX(C13:F13) -> 0 | D40: =MAX(G13:L13) -> 29 | E40: =MAX(M13:M13) -> 0 | F40: =MAX(N13:N13) -> 0 | G40: =MAX(O13:O13) -> 0 | H40: =MAX(P13:R13) -> 29
B41: TOTAL carrinhas (max) / Total vans | C41: =MAX(C14:F14) -> 19 | D41: =MAX(G14:L14) -> 58 | E41: =MAX(M14:M14) -> 29 | F41: =MAX(N14:N14) -> 29 | G41: =MAX(O14:O14) -> 29 | H41: =MAX(P14:R14) -> 58
B42: Motoristas permanentes (max) / Permanent | C42: =MAX(C16:F16) -> 19 | D42: =MAX(G16:L16) -> 29 | E42: =MAX(M16:M16) -> 29 | F42: =MAX(N16:N16) -> 29 | G42: =MAX(O16:O16) -> 29 | H42: =MAX(P16:R16) -> 29
B43: Motoristas temp ETT (max) / Temp | C43: =MAX(C17:F17) -> 0 | D43: =MAX(G17:L17) -> 29 | E43: =MAX(M17:M17) -> 0 | F43: =MAX(N17:N17) -> 0 | G43: =MAX(O17:O17) -> 0 | H43: =MAX(P17:R17) -> 29
B44: TOTAL motoristas (max) / Total drivers | C44: =MAX(C18:F18) -> 19 | D44: =MAX(G18:L18) -> 58 | E44: =MAX(M18:M18) -> 29 | F44: =MAX(N18:N18) -> 29 | G44: =MAX(O18:O18) -> 29 | H44: =MAX(P18:R18) -> 58

Sheet Receita_Revenue
B1: RECEITA / REVENUE
C2: ANO 2026 / YEAR 2026 (Ago-Dez/Aug-Dec) | M2: ANO 2027 / YEAR 2027
B3: Rubrica / Item | C3: S1 Set/Sep 26 | D3: S2 Set/Sep 26 | E3: S3 Set/Sep 26 | F3: S4 Set/Sep 26 | G3: S5 Out/Oct 26 | H3: S6 Out/Oct 26 | I3: S7 Out/Oct 26 | J3: S8 Out/Oct 26 | K3: Nov Nov 26 (Pico/Peak) | L3: Dez Dez/Dec 26 (Pico/Peak) | M3: Q1'27 Jan-Mar 27 | N3: Q2'27 Abr-Jun/Apr-Jun 27 | O3: Q3'27 Jul-Set/Jul-Sep 27 | P3: Out'27 Out/Oct 27 | Q3: Nov'27 Nov 27 (Pico/Peak) | R3: Dez'27 Dez/Dec 27 (Pico/Peak) | S3: Total 2026 | T3: Total 2027
B4: A. Receita rota (taxa base) / Route revenue | C4: =Operacao_Operations!C7*Pressupostos_Assumpt!C8 -> 4027.5 | D4: =Operacao_Operations!D7*Pressupostos_Assumpt!C8 -> 6444 | E4: =Operacao_Operations!E7*Pressupostos_Assumpt!C8 -> 9666 | F4: =Operacao_Operations!F7*Pressupostos_Assumpt!C8 -> 12888 | G4: =Operacao_Operations!G7*Pressupostos_Assumpt!C8 -> 16110 | H4: =Operacao_Operations!H7*Pressupostos_Assumpt!C8 -> 18526.5 | I4: =Operacao_Operations!I7*Pressupostos_Assumpt!C8 -> 20137.5 | J4: =Operacao_Operations!J7*Pressupostos_Assumpt!C8 -> 20137.5 | K4: =Operacao_Operations!K7*Pressupostos_Assumpt!C8 -> 177210 | L4: =Operacao_Operations!L7*Pressupostos_Assumpt!C8 -> 177210 | M4: =Operacao_Operations!M7*Pressupostos_Assumpt!D8 -> 265815 | N4: =Operacao_Operations!N7*Pressupostos_Assumpt!D8 -> 265815 | O4: =Operacao_Operations!O7*Pressupostos_Assumpt!D8 -> 265815 | P4: =Operacao_Operations!P7*Pressupostos_Assumpt!D8 -> 88605 | Q4: =Operacao_Operations!Q7*Pressupostos_Assumpt!D8 -> 177210 | R4: =Operacao_Operations!R7*Pressupostos_Assumpt!D8 -> 177210 | S4: =C4+D4+E4+F4+G4+H4+I4+J4+K4+L4 -> 462357 | T4: =M4+N4+O4+P4+Q4+R4 -> 1240470
B5: B. Receita por peca / PPR | C5: =Operacao_Operations!C10*Pressupostos_Assumpt!C11 -> 172 | D5: =Operacao_Operations!D10*Pressupostos_Assumpt!C11 -> 275.2 | E5: =Operacao_Operations!E10*Pressupostos_Assumpt!C11 -> 412.8 | F5: =Operacao_Operations!F10*Pressupostos_Assumpt!C11 -> 550.4 | G5: =Operacao_Operations!G10*Pressupostos_Assumpt!C11 -> 688 | H5: =Operacao_Operations!H10*Pressupostos_Assumpt!C11 -> 791.2 | I5: =Operacao_Operations!I10*Pressupostos_Assumpt!C11 -> 860 | J5: =Operacao_Operations!J10*Pressupostos_Assumpt!C11 -> 860 | K5: =Operacao_Operations!K10*Pressupostos_Assumpt!C11 -> 7946.4 | L5: =Operacao_Operations!L10*Pressupostos_Assumpt!C11 -> 7946.4 | M5: =Operacao_Operations!M10*Pressupostos_Assumpt!D11 -> 5108.4 | N5: =Operacao_Operations!N10*Pressupostos_Assumpt!D11 -> 5959.8 | O5: =Operacao_Operations!O10*Pressupostos_Assumpt!D11 -> 5959.8 | P5: =Operacao_Operations!P10*Pressupostos_Assumpt!D11 -> 1986.6 | Q5: =Operacao_Operations!Q10*Pressupostos_Assumpt!D11 -> 4162.4 | R5: =Operacao_Operations!R10*Pressupostos_Assumpt!D11 -> 4162.4 | S5: =C5+D5+E5+F5+G5+H5+I5+J5+K5+L5 -> 20502.4 | T5: =M5+N5+O5+P5+Q5+R5 -> 27339.4
B6: C. Reembolso combustivel / Fuel reimb. | C6: =Operacao_Operations!C7*Pressupostos_Assumpt!C16 -> 288.75 | D6: =Operacao_Operations!D7*Pressupostos_Assumpt!C16 -> 462 | E6: =Operacao_Operations!E7*Pressupostos_Assumpt!C16 -> 693 | F6: =Operacao_Operations!F7*Pressupostos_Assumpt!C16 -> 924 | G6: =Operacao_Operations!G7*Pressupostos_Assumpt!C16 -> 1155 | H6: =Operacao_Operations!H7*Pressupostos_Assumpt!C16 -> 1328.25 | I6: =Operacao_Operations!I7*Pressupostos_Assumpt!C16 -> 1443.75 | J6: =Operacao_Operations!J7*Pressupostos_Assumpt!C16 -> 1443.75 | K6: =Operacao_Operations!K7*Pressupostos_Assumpt!C16 -> 12705 | L6: =Operacao_Operations!L7*Pressupostos_Assumpt!C16 -> 12705 | M6: =Operacao_Operations!M7*Pressupostos_Assumpt!D16 -> 19635 | N6: =Operacao_Operations!N7*Pressupostos_Assumpt!D16 -> 19635 | O6: =Operacao_Operations!O7*Pressupostos_Assumpt!D16 -> 19635 | P6: =Operacao_Operations!P7*Pressupostos_Assumpt!D16 -> 6545 | Q6: =Operacao_Operations!Q7*Pressupostos_Assumpt!D16 -> 13090 | R6: =Operacao_Operations!R7*Pressupostos_Assumpt!D16 -> 13090 | S6: =C6+D6+E6+F6+G6+H6+I6+J6+K6+L6 -> 33148.5 | T6: =M6+N6+O6+P6+Q6+R6 -> 91630
B7: D. Reembolso portagens / Tolls reimb. | C7: =Operacao_Operations!C7*Pressupostos_Assumpt!C17 -> 87.5 | D7: =Operacao_Operations!D7*Pressupostos_Assumpt!C17 -> 140 | E7: =Operacao_Operations!E7*Pressupostos_Assumpt!C17 -> 210 | F7: =Operacao_Operations!F7*Pressupostos_Assumpt!C17 -> 280 | G7: =Operacao_Operations!G7*Pressupostos_Assumpt!C17 -> 350 | H7: =Operacao_Operations!H7*Pressupostos_Assumpt!C17 -> 402.5 | I7: =Operacao_Operations!I7*Pressupostos_Assumpt!C17 -> 437.5 | J7: =Operacao_Operations!J7*Pressupostos_Assumpt!C17 -> 437.5 | K7: =Operacao_Operations!K7*Pressupostos_Assumpt!C17 -> 3850 | L7: =Operacao_Operations!L7*Pressupostos_Assumpt!C17 -> 3850 | M7: =Operacao_Operations!M7*Pressupostos_Assumpt!D17 -> 5775 | N7: =Operacao_Operations!N7*Pressupostos_Assumpt!D17 -> 5775 | O7: =Operacao_Operations!O7*Pressupostos_Assumpt!D17 -> 5775 | P7: =Operacao_Operations!P7*Pressupostos_Assumpt!D17 -> 1925 | Q7: =Operacao_Operations!Q7*Pressupostos_Assumpt!D17 -> 3850 | R7: =Operacao_Operations!R7*Pressupostos_Assumpt!D17 -> 3850 | S7: =C7+D7+E7+F7+G7+H7+I7+J7+K7+L7 -> 10045 | T7: =M7+N7+O7+P7+Q7+R7 -> 26950
B8: E. Incentivo SLS / SLS incentive | C8: =Pressupostos_Assumpt!C18*Operacao_Operations!C5 -> 113.63636 | D8: =Pressupostos_Assumpt!C18*Operacao_Operations!D5 -> 113.63636 | E8: =Pressupostos_Assumpt!C18*Operacao_Operations!E5 -> 113.63636 | F8: =Pressupostos_Assumpt!C18*Operacao_Operations!F5 -> 113.63636 | G8: =Pressupostos_Assumpt!C18*Operacao_Operations!G5 -> 113.63636 | H8: =Pressupostos_Assumpt!C18*Operacao_Operations!H5 -> 113.63636 | I8: =Pressupostos_Assumpt!C18*Operacao_Operations!I5 -> 113.63636 | J8: =Pressupostos_Assumpt!C18*Operacao_Operations!J5 -> 113.63636 | K8: =Pressupostos_Assumpt!C18*Operacao_Operations!K5 -> 500 | L8: =Pressupostos_Assumpt!C18*Operacao_Operations!L5 -> 500 | M8: =Pressupostos_Assumpt!D18*Operacao_Operations!M5 -> 1500 | N8: =Pressupostos_Assumpt!D18*Operacao_Operations!N5 -> 1500 | O8: =Pressupostos_Assumpt!D18*Operacao_Operations!O5 -> 1500 | P8: =Pressupostos_Assumpt!D18*Operacao_Operations!P5 -> 500 | Q8: =Pressupostos_Assumpt!D18*Operacao_Operations!Q5 -> 500 | R8: =Pressupostos_Assumpt!D18*Operacao_Operations!R5 -> 500 | S8: =C8+D8+E8+F8+G8+H8+I8+J8+K8+L8 -> 1909.0909 | T8: =M8+N8+O8+P8+Q8+R8 -> 6000
B9: RECEITA TOTAL / TOTAL REVENUE | C9: =SUM(C4:C8) -> 4689.3864 | D9: =SUM(D4:D8) -> 7434.8364 | E9: =SUM(E4:E8) -> 11095.436 | F9: =SUM(F4:F8) -> 14756.036 | G9: =SUM(G4:G8) -> 18416.636 | H9: =SUM(H4:H8) -> 21162.086 | I9: =SUM(I4:I8) -> 22992.386 | J9: =SUM(J4:J8) -> 22992.386 | ... R9: =SUM(R4:R8) -> 198812.4 | S9: =C9+D9+E9+F9+G9+H9+I9+J9+K9+L9 -> 527961.99 | T9: =M9+N9+O9+P9+Q9+R9 -> 1392389.4
B12: RESUMO MENSAL / MONTHLY BREAKDOWN
C13: 2026 (Set-Dez) | G13: 2027
B14: POR MES / BY MONTH | C14: Set/Sep 26 | D14: Out/Oct 26 | E14: Nov 26 | F14: Dez/Dec 26 | G14: Jan 27 | H14: Fev/Feb 27 | I14: Mar 27 | J14: Abr/Apr 27 | K14: Mai/May 27 | L14: Jun 27 | M14: Jul 27 | N14: Ago/Aug 27 | O14: Set/Sep 27 | P14: Out/Oct 27 | Q14: Nov 27 | R14: Dez/Dec 27
B15: A. Receita rota / Route revenue | C15: =C4+D4+E4+F4 -> 33025.5 | D15: =G4+H4+I4+J4 -> 74911.5 | E15: =K4 -> 177210 | F15: =L4 -> 177210 | G15: =(M4)/3 -> 88605 | H15: =(M4)/3 -> 88605 | I15: =(M4)/3 -> 88605 | J15: =(N4)/3 -> 88605 | K15: =(N4)/3 -> 88605 | L15: =(N4)/3 -> 88605 | M15: =(O4)/3 -> 88605 | N15: =(O4)/3 -> 88605 | O15: =(O4)/3 -> 88605 | P15: =P4 -> 88605 | Q15: =Q4 -> 177210 | R15: =R4 -> 177210
B16: B. PPR | C16: =C5+D5+E5+F5 -> 1410.4 | D16: =G5+H5+I5+J5 -> 3199.2 | E16: =K5 -> 7946.4 | F16: =L5 -> 7946.4 | G16: =(M5)/3 -> 1702.8 | H16: =(M5)/3 -> 1702.8 | I16: =(M5)/3 -> 1702.8 | J16: =(N5)/3 -> 1986.6 | K16: =(N5)/3 -> 1986.6 | L16: =(N5)/3 -> 1986.6 | M16: =(O5)/3 -> 1986.6 | N16: =(O5)/3 -> 1986.6 | O16: =(O5)/3 -> 1986.6 | P16: =P5 -> 1986.6 | Q16: =Q5 -> 4162.4 | R16: =R5 -> 4162.4
B17: C. Combustivel / Fuel | C17: =C6+D6+E6+F6 -> 2367.75 | D17: =G6+H6+I6+J6 -> 5370.75 | E17: =K6 -> 12705 | F17: =L6 -> 12705 | G17: =(M6)/3 -> 6545 | H17: =(M6)/3 -> 6545 | I17: =(M6)/3 -> 6545 | J17: =(N6)/3 -> 6545 | K17: =(N6)/3 -> 6545 | L17: =(N6)/3 -> 6545 | M17: =(O6)/3 -> 6545 | N17: =(O6)/3 -> 6545 | O17: =(O6)/3 -> 6545 | P17: =P6 -> 6545 | Q17: =Q6 -> 13090 | R17: =R6 -> 13090
B18: D. Portagens / Tolls | C18: =C7+D7+E7+F7 -> 717.5 | D18: =G7+H7+I7+J7 -> 1627.5 | E18: =K7 -> 3850 | F18: =L7 -> 3850 | G18: =(M7)/3 -> 1925 | H18: =(M7)/3 -> 1925 | I18: =(M7)/3 -> 1925 | J18: =(N7)/3 -> 1925 | K18: =(N7)/3 -> 1925 | L18: =(N7)/3 -> 1925 | M18: =(O7)/3 -> 1925 | N18: =(O7)/3 -> 1925 | O18: =(O7)/3 -> 1925 | P18: =P7 -> 1925 | Q18: =Q7 -> 3850 | R18: =R7 -> 3850
B19: E. SLS | C19: =C8+D8+E8+F8 -> 454.54545 | D19: =G8+H8+I8+J8 -> 454.54545 | E19: =K8 -> 500 | F19: =L8 -> 500 | G19: =(M8)/3 -> 500 | H19: =(M8)/3 -> 500 | I19: =(M8)/3 -> 500 | J19: =(N8)/3 -> 500 | K19: =(N8)/3 -> 500 | L19: =(N8)/3 -> 500 | M19: =(O8)/3 -> 500 | N19: =(O8)/3 -> 500 | O19: =(O8)/3 -> 500 | P19: =P8 -> 500 | Q19: =Q8 -> 500 | R19: =R8 -> 500
B20: RECEITA TOTAL / TOTAL REVENUE | C20: =C9+D9+E9+F9 -> 37975.695 | D20: =G9+H9+I9+J9 -> 85563.495 | E20: =K9 -> 202211.4 | F20: =L9 -> 202211.4 | G20: =(M9)/3 -> 99277.8 | H20: =(M9)/3 -> 99277.8 | I20: =(M9)/3 -> 99277.8 | J20: =(N9)/3 -> 99561.6 | K20: =(N9)/3 -> 99561.6 | L20: =(N9)/3 -> 99561.6 | M20: =(O9)/3 -> 99561.6 | N20: =(O9)/3 -> 99561.6 | O20: =(O9)/3 -> 99561.6 | P20: =P9 -> 99561.6 | Q20: =Q9 -> 198812.4 | R20: =R9 -> 198812.4
B23: RESUMO TRIMESTRAL / QUARTERLY BREAKDOWN
C24: 2026 | E24: 2027
B25: POR TRIMESTRE / BY QUARTER | C25: Q3 2026 Set/Sep 26 | D25: Q4 2026 Out-Dez/Oct-Dec 26 | E25: Q1 2027 Jan-Mar 27 | F25: Q2 2027 Abr-Jun/Apr-Jun 27 | G25: Q3 2027 Jul-Set/Jul-Sep 27 | H25: Q4 2027 Out-Dez/Oct-Dec 27
B26: A. Receita rota / Route revenue | C26: =SUM(C4:F4) -> 33025.5 | D26: =SUM(G4:L4) -> 429331.5 | E26: =SUM(M4:M4) -> 265815 | F26: =SUM(N4:N4) -> 265815 | G26: =SUM(O4:O4) -> 265815 | H26: =SUM(P4:R4) -> 443025
B27: B. PPR | C27: =SUM(C5:F5) -> 1410.4 | D27: =SUM(G5:L5) -> 19092 | E27: =SUM(M5:M5) -> 5108.4 | F27: =SUM(N5:N5) -> 5959.8 | G27: =SUM(O5:O5) -> 5959.8 | H27: =SUM(P5:R5) -> 10311.4
B28: C. Combustivel / Fuel | C28: =SUM(C6:F6) -> 2367.75 | D28: =SUM(G6:L6) -> 30780.75 | E28: =SUM(M6:M6) -> 19635 | F28: =SUM(N6:N6) -> 19635 | G28: =SUM(O6:O6) -> 19635 | H28: =SUM(P6:R6) -> 32725
B29: D. Portagens / Tolls | C29: =SUM(C7:F7) -> 717.5 | D29: =SUM(G7:L7) -> 9327.5 | E29: =SUM(M7:M7) -> 5775 | F29: =SUM(N7:N7) -> 5775 | G29: =SUM(O7:O7) -> 5775 | H29: =SUM(P7:R7) -> 9625
B30: E. SLS | C30: =SUM(C8:F8) -> 454.54545 | D30: =SUM(G8:L8) -> 1454.5455 | E30: =SUM(M8:M8) -> 1500 | F30: =SUM(N8:N8) -> 1500 | G30: =SUM(O8:O8) -> 1500 | H30: =SUM(P8:R8) -> 1500
B31: RECEITA TOTAL / TOTAL REVENUE | C31: =SUM(C9:F9) -> 37975.695 | D31: =SUM(G9:L9) -> 489986.3 | E31: =SUM(M9:M9) -> 297833.4 | F31: =SUM(N9:N9) -> 298684.8 | G31: =SUM(O9:O9) -> 298684.8 | H31: =SUM(P9:R9) -> 497186.4

Sheet Salarios_Wages
B1: SALARIOS, SUBSIDIOS E ENCARGOS / WAGES, ALLOWANCES & CONTRIBUTIONS
B2: Metodologia PT: 14 meses em 12 | Sub.alimentacao isento | SS trab.11% + patronal 23.75% | IRS por funcao | Temporarios via ETT = salario x coef. (agencia trata SS/subsidios/margem). Valores 2026/2027 conforme Pressupostos.
C3: ANO 2026 / YEAR 2026 (Ago-Dez/Aug-Dec) | M3: ANO 2027 / YEAR 2027
B4: Rubrica / Item | C4: S1 Set/Sep 26 | D4: S2 Set/Sep 26 | E4: S3 Set/Sep 26 | F4: S4 Set/Sep 26 | G4: S5 Out/Oct 26 | H4: S6 Out/Oct 26 | I4: S7 Out/Oct 26 | J4: S8 Out/Oct 26 | K4: Nov Nov 26 (Pico/Peak) | L4: Dez Dez/Dec 26 (Pico/Peak) | M4: Q1'27 Jan-Mar 27 | N4: Q2'27 Abr-Jun/Apr-Jun 27 | O4: Q3'27 Jul-Set/Jul-Sep 27 | P4: Out'27 Out/Oct 27 | Q4: Nov'27 Nov 27 (Pico/Peak) | R4: Dez'27 Dez/Dec 27 (Pico/Peak) | S4: Total 2026 | T4: Total 2027
B5: A. MOTORISTAS PERMANENTES / PERMANENT DRIVERS
B6: Nº permanentes / Permanent headcount | C6: =Operacao_Operations!C16 -> 6 | D6: =Operacao_Operations!D16 -> 10 | E6: =Operacao_Operations!E16 -> 14 | F6: =Operacao_Operations!F16 -> 19 | G6: =Operacao_Operations!G16 -> 23 | H6: =Operacao_Operations!H16 -> 27 | I6: =Operacao_Operations!I16 -> 29 | J6: =Operacao_Operations!J16 -> 29 | ... R6: =Operacao_Operations!R16 -> 29
B7: Salario base bruto / Gross base wage | C7: =Operacao_Operations!C16*Pressupostos_Assumpt!C41*Operacao_Operations!C5 -> 1465.4545 | D7: =Operacao_Operations!D16*Pressupostos_Assumpt!C41*Operacao_Operations!D5 -> 2442.4242 | E7: =Operacao_Operations!E16*Pressupostos_Assumpt!C41*Operacao_Operations!E5 -> 3419.3939 | F7: =Operacao_Operations!F16*Pressupostos_Assumpt!C41*Operacao_Operations!F5 -> 4640.6061 | G7: =Operacao_Operations!G16*Pressupostos_Assumpt!C41*Operacao_Operations!G5 -> 5617.5758 | H7: =Operacao_Operations!H16*Pressupostos_Assumpt!C41*Operacao_Operations!H5 -> 6594.5455 | I7: =Operacao_Operations!I16*Pressupostos_Assumpt!C41*Operacao_Operations!I5 -> 7083.0303 | J7: =Operacao_Operations!J16*Pressupostos_Assumpt!C41*Operacao_Operations!J5 -> 7083.0303 | K7: =Operacao_Operations!K16*Pressupostos_Assumpt!C41*Operacao_Operations!K5 -> 31165.333 | L7: =Operacao_Operations!L16*Pressupostos_Assumpt!C41*Operacao_Operations!L5 -> 31165.333 | M7: =Operacao_Operations!M16*Pressupostos_Assumpt!D41*Operacao_Operations!M5 -> 93496 | N7: =Operacao_Operations!N16*Pressupostos_Assumpt!D41*Operacao_Operations!N5 -> 93496 | O7: =Operacao_Operations!O16*Pressupostos_Assumpt!D41*Operacao_Operations!O5 -> 93496 | P7: =Operacao_Operations!P16*Pressupostos_Assumpt!D41*Operacao_Operations!P5 -> 31165.333 | Q7: =Operacao_Operations!Q16*Pressupostos_Assumpt!D41*Operacao_Operations!Q5 -> 31165.333 | R7: =Operacao_Operations!R16*Pressupostos_Assumpt!D41*Operacao_Operations!R5 -> 31165.333 | S7: =C7+D7+E7+F7+G7+H7+I7+J7+K7+L7 -> 100676.73 | T7: =M7+N7+O7+P7+Q7+R7 -> 373984
B8: Subs. Natal+ferias / Christmas+holiday | C8: =Operacao_Operations!C16*Pressupostos_Assumpt!C41*(Pressupostos_Assumpt!C54-1)*Operacao_Operations!C5 -> 244.24242 | D8: =Operacao_Operations!D16*Pressupostos_Assumpt!C41*(Pressupostos_Assumpt!C54-1)*Operacao_Operations!D5 -> 407.07071 | E8: =Operacao_Operations!E16*Pressupostos_Assumpt!C41*(Pressupostos_Assumpt!C54-1)*Operacao_Operations!E5 -> 569.89899 | F8: =Operacao_Operations!F16*Pressupostos_Assumpt!C41*(Pressupostos_Assumpt!C54-1)*Operacao_Operations!F5 -> 773.43434 | G8: =Operacao_Operations!G16*Pressupostos_Assumpt!C41*(Pressupostos_Assumpt!C54-1)*Operacao_Operations!G5 -> 936.26263 | H8: =Operacao_Operations!H16*Pressupostos_Assumpt!C41*(Pressupostos_Assumpt!C54-1)*Operacao_Operations!H5 -> 1099.0909 | I8: =Operacao_Operations!I16*Pressupostos_Assumpt!C41*(Pressupostos_Assumpt!C54-1)*Operacao_Operations!I5 -> 1180.5051 | J8: =Operacao_Operations!J16*Pressupostos_Assumpt!C41*(Pressupostos_Assumpt!C54-1)*Operacao_Operations!J5 -> 1180.5051 | K8: =Operacao_Operations!K16*Pressupostos_Assumpt!C41*(Pressupostos_Assumpt!C54-1)*Operacao_Operations!K5 -> 5194.2222 | L8: =Operacao_Operations!L16*Pressupostos_Assumpt!C41*(Pressupostos_Assumpt!C54-1)*Operacao_Operations!L5 -> 5194.2222 | M8: =Operacao_Operations!M16*Pressupostos_Assumpt!D41*(Pressupostos_Assumpt!D54-1)*Operacao_Operations!M5 -> 15582.667 | N8: =Operacao_Operations!N16*Pressupostos_Assumpt!D41*(Pressupostos_Assumpt!D54-1)*Operacao_Operations!N5 -> 15582.667 | O8: =Operacao_Operations!O16*Pressupostos_Assumpt!D41*(Pressupostos_Assumpt!D54-1)*Operacao_Operations!O5 -> 15582.667 | P8: =Operacao_Operations!P16*Pressupostos_Assumpt!D41*(Pressupostos_Assumpt!D54-1)*Operacao_Operations!P5 -> 5194.2222 | Q8: =Operacao_Operations!Q16*Pressupostos_Assumpt!D41*(Pressupostos_Assumpt!D54-1)*Operacao_Operations!Q5 -> 5194.2222 | R8: =Operacao_Operations!R16*Pressupostos_Assumpt!D41*(Pressupostos_Assumpt!D54-1)*Operacao_Operations!R5 -> 5194.2222 | S8: =C8+D8+E8+F8+G8+H8+I8+J8+K8+L8 -> 16779.455 | T8: =M8+N8+O8+P8+Q8+R8 -> 62330.667
B9: Subs. alimentacao / Food subsidy | C9: =Operacao_Operations!C16*Pressupostos_Assumpt!C56*Pressupostos_Assumpt!C58*Operacao_Operations!C5 -> 180 | D9: =Operacao_Operations!D16*Pressupostos_Assumpt!C56*Pressupostos_Assumpt!C58*Operacao_Operations!D5 -> 300 | E9: =Operacao_Operations!E16*Pressupostos_Assumpt!C56*Pressupostos_Assumpt!C58*Operacao_Operations!E5 -> 420 | F9: =Operacao_Operations!F16*Pressupostos_Assumpt!C56*Pressupostos_Assumpt!C58*Operacao_Operations!F5 -> 570 | G9: =Operacao_Operations!G16*Pressupostos_Assumpt!C56*Pressupostos_Assumpt!C58*Operacao_Operations!G5 -> 690 | H9: =Operacao_Operations!H16*Pressupostos_Assumpt!C56*Pressupostos_Assumpt!C58*Operacao_Operations!H5 -> 810 | I9: =Operacao_Operations!I16*Pressupostos_Assumpt!C56*Pressupostos_Assumpt!C58*Operacao_Operations!I5 -> 870 | J9: =Operacao_Operations!J16*Pressupostos_Assumpt!C56*Pressupostos_Assumpt!C58*Operacao_Operations!J5 -> 870 | K9: =Operacao_Operations!K16*Pressupostos_Assumpt!C56*Pressupostos_Assumpt!C58*Operacao_Operations!K5 -> 3828 | L9: =Operacao_Operations!L16*Pressupostos_Assumpt!C56*Pressupostos_Assumpt!C58*Operacao_Operations!L5 -> 3828 | M9: =Operacao_Operations!M16*Pressupostos_Assumpt!D56*Pressupostos_Assumpt!D58*Operacao_Operations!M5 -> 11484 | N9: =Operacao_Operations!N16*Pressupostos_Assumpt!D56*Pressupostos_Assumpt!D58*Operacao_Operations!N5 -> 11484 | O9: =Operacao_Operations!O16*Pressupostos_Assumpt!D56*Pressupostos_Assumpt!D58*Operacao_Operations!O5 -> 11484 | P9: =Operacao_Operations!P16*Pressupostos_Assumpt!D56*Pressupostos_Assumpt!D58*Operacao_Operations!P5 -> 3828 | Q9: =Operacao_Operations!Q16*Pressupostos_Assumpt!D56*Pressupostos_Assumpt!D58*Operacao_Operations!Q5 -> 3828 | R9: =Operacao_Operations!R16*Pressupostos_Assumpt!D56*Pressupostos_Assumpt!D58*Operacao_Operations!R5 -> 3828 | S9: =C9+D9+E9+F9+G9+H9+I9+J9+K9+L9 -> 12366 | T9: =M9+N9+O9+P9+Q9+R9 -> 45936
B10: Remuneracao bruta total / Total gross | C10: =C7+C8+C9 -> 1889.697 | D10: =D7+D8+D9 -> 3149.4949 | E10: =E7+E8+E9 -> 4409.2929 | F10: =F7+F8+F9 -> 5984.0404 | G10: =G7+G8+G9 -> 7243.8384 | H10: =H7+H8+H9 -> 8503.6364 | I10: =I7+I8+I9 -> 9133.5354 | J10: =J7+J8+J9 -> 9133.5354 | ... R10: =R7+R8+R9 -> 40187.556 | S10: =C10+D10+E10+F10+G10+H10+I10+J10+K10+L10 -> 129822.18 | T10: =M10+N10+O10+P10+Q10+R10 -> 482250.67
B11: SS patronal (23.75%) + s/ excesso sub. / Employer SS | C11: =(C7+C8)*Pressupostos_Assumpt!C42+Operacao_Operations!C16*MAX(0,Pressupostos_Assumpt!C56-Pressupostos_Assumpt!C57)*Pressupostos_Assumpt!C58*Pressupostos_Assumpt!C42*Operacao_Operations!C5 -> 406.05303 | D11: =(D7+D8)*Pressupostos_Assumpt!C42+Operacao_Operations!D16*MAX(0,Pressupostos_Assumpt!C56-Pressupostos_Assumpt!C57)*Pressupostos_Assumpt!C58*Pressupostos_Assumpt!C42*Operacao_Operations!D5 -> 676.75505 | E11: =(E7+E8)*Pressupostos_Assumpt!C42+Operacao_Operations!E16*MAX(0,Pressupostos_Assumpt!C56-Pressupostos_Assumpt!C57)*Pressupostos_Assumpt!C58*Pressupostos_Assumpt!C42*Operacao_Operations!E5 -> 947.45707 | F11: =(F7+F8)*Pressupostos_Assumpt!C42+Operacao_Operations!F16*MAX(0,Pressupostos_Assumpt!C56-Pressupostos_Assumpt!C57)*Pressupostos_Assumpt!C58*Pressupostos_Assumpt!C42*Operacao_Operations!F5 -> 1285.8346 | G11: =(G7+G8)*Pressupostos_Assumpt!C42+Operacao_Operations!G16*MAX(0,Pressupostos_Assumpt!C56-Pressupostos_Assumpt!C57)*Pressupostos_Assumpt!C58*Pressupostos_Assumpt!C42*Operacao_Operations!G5 -> 1556.5366 | H11: =(H7+H8)*Pressupostos_Assumpt!C42+Operacao_Operations!H16*MAX(0,Pressupostos_Assumpt!C56-Pressupostos_Assumpt!C57)*Pressupostos_Assumpt!C58*Pressupostos_Assumpt!C42*Operacao_Operations!H5 -> 1827.2386 | I11: =(I7+I8)*Pressupostos_Assumpt!C42+Operacao_Operations!I16*MAX(0,Pressupostos_Assumpt!C56-Pressupostos_Assumpt!C57)*Pressupostos_Assumpt!C58*Pressupostos_Assumpt!C42*Operacao_Operations!I5 -> 1962.5896 | J11: =(J7+J8)*Pressupostos_Assumpt!C42+Operacao_Operations!J16*MAX(0,Pressupostos_Assumpt!C56-Pressupostos_Assumpt!C57)*Pressupostos_Assumpt!C58*Pressupostos_Assumpt!C42*Operacao_Operations!J5 -> 1962.5896 | K11: =(K7+K8)*Pressupostos_Assumpt!C42+Operacao_Operations!K16*MAX(0,Pressupostos_Assumpt!C56-Pressupostos_Assumpt!C57)*Pressupostos_Assumpt!C58*Pressupostos_Assumpt!C42*Operacao_Operations!K5 -> 8635.3944 | L11: =(L7+L8)*Pressupostos_Assumpt!C42+Operacao_Operations!L16*MAX(0,Pressupostos_Assumpt!C56-Pressupostos_Assumpt!C57)*Pressupostos_Assumpt!C58*Pressupostos_Assumpt!C42*Operacao_Operations!L5 -> 8635.3944 | M11: =(M7+M8)*Pressupostos_Assumpt!D42+Operacao_Operations!M16*MAX(0,Pressupostos_Assumpt!D56-Pressupostos_Assumpt!D57)*Pressupostos_Assumpt!D58*Pressupostos_Assumpt!D42*Operacao_Operations!M5 -> 25906.183 | N11: =(N7+N8)*Pressupostos_Assumpt!D42+Operacao_Operations!N16*MAX(0,Pressupostos_Assumpt!D56-Pressupostos_Assumpt!D57)*Pressupostos_Assumpt!D58*Pressupostos_Assumpt!D42*Operacao_Operations!N5 -> 25906.183 | O11: =(O7+O8)*Pressupostos_Assumpt!D42+Operacao_Operations!O16*MAX(0,Pressupostos_Assumpt!D56-Pressupostos_Assumpt!D57)*Pressupostos_Assumpt!D58*Pressupostos_Assumpt!D42*Operacao_Operations!O5 -> 25906.183 | P11: =(P7+P8)*Pressupostos_Assumpt!D42+Operacao_Operations!P16*MAX(0,Pressupostos_Assumpt!D56-Pressupostos_Assumpt!D57)*Pressupostos_Assumpt!D58*Pressupostos_Assumpt!D42*Operacao_Operations!P5 -> 8635.3944 | Q11: =(Q7+Q8)*Pressupostos_Assumpt!D42+Operacao_Operations!Q16*MAX(0,Pressupostos_Assumpt!D56-Pressupostos_Assumpt!D57)*Pressupostos_Assumpt!D58*Pressupostos_Assumpt!D42*Operacao_Operations!Q5 -> 8635.3944 | R11: =(R7+R8)*Pressupostos_Assumpt!D42+Operacao_Operations!R16*MAX(0,Pressupostos_Assumpt!D56-Pressupostos_Assumpt!D57)*Pressupostos_Assumpt!D58*Pressupostos_Assumpt!D42*Operacao_Operations!R5 -> 8635.3944 | S11: =C11+D11+E11+F11+G11+H11+I11+J11+K11+L11 -> 27895.843 | T11: =M11+N11+O11+P11+Q11+R11 -> 103624.73
B12: SS trabalhador (11%) / Employee SS | C12: =(C7+C8)*Pressupostos_Assumpt!C55 -> 188.06667 | D12: =(D7+D8)*Pressupostos_Assumpt!C55 -> 313.44444 | E12: =(E7+E8)*Pressupostos_Assumpt!C55 -> 438.82222 | F12: =(F7+F8)*Pressupostos_Assumpt!C55 -> 595.54444 | G12: =(G7+G8)*Pressupostos_Assumpt!C55 -> 720.92222 | H12: =(H7+H8)*Pressupostos_Assumpt!C55 -> 846.3 | I12: =(I7+I8)*Pressupostos_Assumpt!C55 -> 908.98889 | J12: =(J7+J8)*Pressupostos_Assumpt!C55 -> 908.98889 | K12: =(K7+K8)*Pressupostos_Assumpt!C55 -> 3999.5511 | L12: =(L7+L8)*Pressupostos_Assumpt!C55 -> 3999.5511 | M12: =(M7+M8)*Pressupostos_Assumpt!D55 -> 11998.653 | N12: =(N7+N8)*Pressupostos_Assumpt!D55 -> 11998.653 | O12: =(O7+O8)*Pressupostos_Assumpt!D55 -> 11998.653 | P12: =(P7+P8)*Pressupostos_Assumpt!D55 -> 3999.5511 | Q12: =(Q7+Q8)*Pressupostos_Assumpt!D55 -> 3999.5511 | R12: =(R7+R8)*Pressupostos_Assumpt!D55 -> 3999.5511 | S12: =C12+D12+E12+F12+G12+H12+I12+J12+K12+L12 -> 12920.18 | T12: =M12+N12+O12+P12+Q12+R12 -> 47994.613
B13: Retencao IRS / IRS withholding | C13: =(C7+C8)*Pressupostos_Assumpt!C59 -> 141.90485 | D13: =(D7+D8)*Pressupostos_Assumpt!C59 -> 236.50808 | E13: =(E7+E8)*Pressupostos_Assumpt!C59 -> 331.11131 | F13: =(F7+F8)*Pressupostos_Assumpt!C59 -> 449.36535 | G13: =(G7+G8)*Pressupostos_Assumpt!C59 -> 543.96859 | H13: =(H7+H8)*Pressupostos_Assumpt!C59 -> 638.57182 | I13: =(I7+I8)*Pressupostos_Assumpt!C59 -> 685.87343 | J13: =(J7+J8)*Pressupostos_Assumpt!C59 -> 685.87343 | K13: =(K7+K8)*Pressupostos_Assumpt!C59 -> 3017.8431 | L13: =(L7+L8)*Pressupostos_Assumpt!C59 -> 3017.8431 | M13: =(M7+M8)*Pressupostos_Assumpt!D59 -> 9053.5293 | N13: =(N7+N8)*Pressupostos_Assumpt!D59 -> 9053.5293 | O13: =(O7+O8)*Pressupostos_Assumpt!D59 -> 9053.5293 | P13: =(P7+P8)*Pressupostos_Assumpt!D59 -> 3017.8431 | Q13: =(Q7+Q8)*Pressupostos_Assumpt!D59 -> 3017.8431 | R13: =(R7+R8)*Pressupostos_Assumpt!D59 -> 3017.8431 | S13: =C13+D13+E13+F13+G13+H13+I13+J13+K13+L13 -> 9748.8631 | T13: =M13+N13+O13+P13+Q13+R13 -> 36214.117
B14: Salario liquido / Net wage | C14: =C7+C8+C9-C12-C13 -> 1559.7255 | D14: =D7+D8+D9-D12-D13 -> 2599.5424 | E14: =E7+E8+E9-E12-E13 -> 3639.3594 | F14: =F7+F8+F9-F12-F13 -> 4939.1306 | G14: =G7+G8+G9-G12-G13 -> 5978.9476 | H14: =H7+H8+H9-H12-H13 -> 7018.7645 | I14: =I7+I8+I9-I12-I13 -> 7538.673 | J14: =J7+J8+J9-J12-J13 -> 7538.673 | ... R14: =R7+R8+R9-R12-R13 -> 33170.161 | S14: =C14+D14+E14+F14+G14+H14+I14+J14+K14+L14 -> 107153.14 | T14: =M14+N14+O14+P14+Q14+R14 -> 398041.94
B15: CUSTO EMPRESA Permanentes / TOTAL PERMANENT COST | C15: =C10+C11 -> 2295.75 | D15: =D10+D11 -> 3826.25 | E15: =E10+E11 -> 5356.75 | F15: =F10+F11 -> 7269.875 | G15: =G10+G11 -> 8800.375 | H15: =H10+H11 -> 10330.875 | I15: =I10+I11 -> 11096.125 | J15: =J10+J11 -> 11096.125 | ... R15: =R10+R11 -> 48822.95 | S15: =C15+D15+E15+F15+G15+H15+I15+J15+K15+L15 -> 157718.03 | T15: =M15+N15+O15+P15+Q15+R15 -> 585875.4
B17: B. MOTORISTAS TEMPORARIOS - ETT / TEMPORARY AGENCY DRIVERS
B18: Nº temporarios / Temp headcount | C18: =Operacao_Operations!C17 -> 0 | D18: =Operacao_Operations!D17 -> 0 | E18: =Operacao_Operations!E17 -> 0 | F18: =Operacao_Operations!F17 -> 0 | G18: =Operacao_Operations!G17 -> 0 | H18: =Operacao_Operations!H17 -> 0 | I18: =Operacao_Operations!I17 -> 0 | J18: =Operacao_Operations!J17 -> 0 | ... R18: =Operacao_Operations!R17 -> 29
B19: Custo faturado base (salario x meses) / Billed base | C19: =Operacao_Operations!C17*Pressupostos_Assumpt!C41*Operacao_Operations!C5 -> 0 | D19: =Operacao_Operations!D17*Pressupostos_Assumpt!C41*Operacao_Operations!D5 -> 0 | E19: =Operacao_Operations!E17*Pressupostos_Assumpt!C41*Operacao_Operations!E5 -> 0 | F19: =Operacao_Operations!F17*Pressupostos_Assumpt!C41*Operacao_Operations!F5 -> 0 | G19: =Operacao_Operations!G17*Pressupostos_Assumpt!C41*Operacao_Operations!G5 -> 0 | H19: =Operacao_Operations!H17*Pressupostos_Assumpt!C41*Operacao_Operations!H5 -> 0 | I19: =Operacao_Operations!I17*Pressupostos_Assumpt!C41*Operacao_Operations!I5 -> 0 | J19: =Operacao_Operations!J17*Pressupostos_Assumpt!C41*Operacao_Operations!J5 -> 0 | K19: =Operacao_Operations!K17*Pressupostos_Assumpt!C41*Operacao_Operations!K5 -> 31165.333 | L19: =Operacao_Operations!L17*Pressupostos_Assumpt!C41*Operacao_Operations!L5 -> 31165.333 | M19: =Operacao_Operations!M17*Pressupostos_Assumpt!D41*Operacao_Operations!M5 -> 0 | N19: =Operacao_Operations!N17*Pressupostos_Assumpt!D41*Operacao_Operations!N5 -> 0 | O19: =Operacao_Operations!O17*Pressupostos_Assumpt!D41*Operacao_Operations!O5 -> 0 | P19: =Operacao_Operations!P17*Pressupostos_Assumpt!D41*Operacao_Operations!P5 -> 0 | Q19: =Operacao_Operations!Q17*Pressupostos_Assumpt!D41*Operacao_Operations!Q5 -> 31165.333 | R19: =Operacao_Operations!R17*Pressupostos_Assumpt!D41*Operacao_Operations!R5 -> 31165.333 | S19: =C19+D19+E19+F19+G19+H19+I19+J19+K19+L19 -> 62330.667 | T19: =M19+N19+O19+P19+Q19+R19 -> 62330.667
B20: CUSTO EMPRESA Temporarios (x coef.) / TOTAL TEMP COST | C20: =C19*Pressupostos_Assumpt!C65 -> 0 | D20: =D19*Pressupostos_Assumpt!C65 -> 0 | E20: =E19*Pressupostos_Assumpt!C65 -> 0 | F20: =F19*Pressupostos_Assumpt!C65 -> 0 | G20: =G19*Pressupostos_Assumpt!C65 -> 0 | H20: =H19*Pressupostos_Assumpt!C65 -> 0 | I20: =I19*Pressupostos_Assumpt!C65 -> 0 | J20: =J19*Pressupostos_Assumpt!C65 -> 0 | K20: =K19*Pressupostos_Assumpt!C65 -> 46748 | L20: =L19*Pressupostos_Assumpt!C65 -> 46748 | M20: =M19*Pressupostos_Assumpt!D65 -> 0 | N20: =N19*Pressupostos_Assumpt!D65 -> 0 | O20: =O19*Pressupostos_Assumpt!D65 -> 0 | P20: =P19*Pressupostos_Assumpt!D65 -> 0 | Q20: =Q19*Pressupostos_Assumpt!D65 -> 46748 | R20: =R19*Pressupostos_Assumpt!D65 -> 46748 | S20: =C20+D20+E20+F20+G20+H20+I20+J20+K20+L20 -> 93496 | T20: =M20+N20+O20+P20+Q20+R20 -> 93496
B22: C. GESTOR DE OPERACOES / OPERATIONS MANAGER
B23: Salario base bruto / Gross base wage | C23: =Pressupostos_Assumpt!C61*Pressupostos_Assumpt!C45*Operacao_Operations!C5 -> 453.0303 | D23: =Pressupostos_Assumpt!C61*Pressupostos_Assumpt!C45*Operacao_Operations!D5 -> 453.0303 | E23: =Pressupostos_Assumpt!C61*Pressupostos_Assumpt!C45*Operacao_Operations!E5 -> 453.0303 | F23: =Pressupostos_Assumpt!C61*Pressupostos_Assumpt!C45*Operacao_Operations!F5 -> 453.0303 | G23: =Pressupostos_Assumpt!C61*Pressupostos_Assumpt!C45*Operacao_Operations!G5 -> 453.0303 | H23: =Pressupostos_Assumpt!C61*Pressupostos_Assumpt!C45*Operacao_Operations!H5 -> 453.0303 | I23: =Pressupostos_Assumpt!C61*Pressupostos_Assumpt!C45*Operacao_Operations!I5 -> 453.0303 | J23: =Pressupostos_Assumpt!C61*Pressupostos_Assumpt!C45*Operacao_Operations!J5 -> 453.0303 | K23: =Pressupostos_Assumpt!C61*Pressupostos_Assumpt!C45*Operacao_Operations!K5 -> 1993.3333 | L23: =Pressupostos_Assumpt!C61*Pressupostos_Assumpt!C45*Operacao_Operations!L5 -> 1993.3333 | M23: =Pressupostos_Assumpt!D61*Pressupostos_Assumpt!D45*Operacao_Operations!M5 -> 6162 | N23: =Pressupostos_Assumpt!D61*Pressupostos_Assumpt!D45*Operacao_Operations!N5 -> 6162 | O23: =Pressupostos_Assumpt!D61*Pressupostos_Assumpt!D45*Operacao_Operations!O5 -> 6162 | P23: =Pressupostos_Assumpt!D61*Pressupostos_Assumpt!D45*Operacao_Operations!P5 -> 2054 | Q23: =Pressupostos_Assumpt!D61*Pressupostos_Assumpt!D45*Operacao_Operations!Q5 -> 2054 | R23: =Pressupostos_Assumpt!D61*Pressupostos_Assumpt!D45*Operacao_Operations!R5 -> 2054 | S23: =C23+D23+E23+F23+G23+H23+I23+J23+K23+L23 -> 7610.9091 | T23: =M23+N23+O23+P23+Q23+R23 -> 24648
B24: Subs. Natal+ferias / Christmas+holiday | C24: =Pressupostos_Assumpt!C61*Pressupostos_Assumpt!C45*(Pressupostos_Assumpt!C54-1)*Operacao_Operations!C5 -> 75.505051 | D24: =Pressupostos_Assumpt!C61*Pressupostos_Assumpt!C45*(Pressupostos_Assumpt!C54-1)*Operacao_Operations!D5 -> 75.505051 | E24: =Pressupostos_Assumpt!C61*Pressupostos_Assumpt!C45*(Pressupostos_Assumpt!C54-1)*Operacao_Operations!E5 -> 75.505051 | F24: =Pressupostos_Assumpt!C61*Pressupostos_Assumpt!C45*(Pressupostos_Assumpt!C54-1)*Operacao_Operations!F5 -> 75.505051 | G24: =Pressupostos_Assumpt!C61*Pressupostos_Assumpt!C45*(Pressupostos_Assumpt!C54-1)*Operacao_Operations!G5 -> 75.505051 | H24: =Pressupostos_Assumpt!C61*Pressupostos_Assumpt!C45*(Pressupostos_Assumpt!C54-1)*Operacao_Operations!H5 -> 75.505051 | I24: =Pressupostos_Assumpt!C61*Pressupostos_Assumpt!C45*(Pressupostos_Assumpt!C54-1)*Operacao_Operations!I5 -> 75.505051 | J24: =Pressupostos_Assumpt!C61*Pressupostos_Assumpt!C45*(Pressupostos_Assumpt!C54-1)*Operacao_Operations!J5 -> 75.505051 | K24: =Pressupostos_Assumpt!C61*Pressupostos_Assumpt!C45*(Pressupostos_Assumpt!C54-1)*Operacao_Operations!K5 -> 332.22222 | L24: =Pressupostos_Assumpt!C61*Pressupostos_Assumpt!C45*(Pressupostos_Assumpt!C54-1)*Operacao_Operations!L5 -> 332.22222 | M24: =Pressupostos_Assumpt!D61*Pressupostos_Assumpt!D45*(Pressupostos_Assumpt!D54-1)*Operacao_Operations!M5 -> 1027 | N24: =Pressupostos_Assumpt!D61*Pressupostos_Assumpt!D45*(Pressupostos_Assumpt!D54-1)*Operacao_Operations!N5 -> 1027 | O24: =Pressupostos_Assumpt!D61*Pressupostos_Assumpt!D45*(Pressupostos_Assumpt!D54-1)*Operacao_Operations!O5 -> 1027 | P24: =Pressupostos_Assumpt!D61*Pressupostos_Assumpt!D45*(Pressupostos_Assumpt!D54-1)*Operacao_Operations!P5 -> 342.33333 | Q24: =Pressupostos_Assumpt!D61*Pressupostos_Assumpt!D45*(Pressupostos_Assumpt!D54-1)*Operacao_Operations!Q5 -> 342.33333 | R24: =Pressupostos_Assumpt!D61*Pressupostos_Assumpt!D45*(Pressupostos_Assumpt!D54-1)*Operacao_Operations!R5 -> 342.33333 | S24: =C24+D24+E24+F24+G24+H24+I24+J24+K24+L24 -> 1268.4848 | T24: =M24+N24+O24+P24+Q24+R24 -> 4108
B25: Subs. alimentacao / Food subsidy | C25: =Pressupostos_Assumpt!C61*Pressupostos_Assumpt!C56*Pressupostos_Assumpt!C58*Operacao_Operations!C5 -> 30 | D25: =Pressupostos_Assumpt!C61*Pressupostos_Assumpt!C56*Pressupostos_Assumpt!C58*Operacao_Operations!D5 -> 30 | E25: =Pressupostos_Assumpt!C61*Pressupostos_Assumpt!C56*Pressupostos_Assumpt!C58*Operacao_Operations!E5 -> 30 | F25: =Pressupostos_Assumpt!C61*Pressupostos_Assumpt!C56*Pressupostos_Assumpt!C58*Operacao_Operations!F5 -> 30 | G25: =Pressupostos_Assumpt!C61*Pressupostos_Assumpt!C56*Pressupostos_Assumpt!C58*Operacao_Operations!G5 -> 30 | H25: =Pressupostos_Assumpt!C61*Pressupostos_Assumpt!C56*Pressupostos_Assumpt!C58*Operacao_Operations!H5 -> 30 | I25: =Pressupostos_Assumpt!C61*Pressupostos_Assumpt!C56*Pressupostos_Assumpt!C58*Operacao_Operations!I5 -> 30 | J25: =Pressupostos_Assumpt!C61*Pressupostos_Assumpt!C56*Pressupostos_Assumpt!C58*Operacao_Operations!J5 -> 30 | K25: =Pressupostos_Assumpt!C61*Pressupostos_Assumpt!C56*Pressupostos_Assumpt!C58*Operacao_Operations!K5 -> 132 | L25: =Pressupostos_Assumpt!C61*Pressupostos_Assumpt!C56*Pressupostos_Assumpt!C58*Operacao_Operations!L5 -> 132 | M25: =Pressupostos_Assumpt!D61*Pressupostos_Assumpt!D56*Pressupostos_Assumpt!D58*Operacao_Operations!M5 -> 396 | N25: =Pressupostos_Assumpt!D61*Pressupostos_Assumpt!D56*Pressupostos_Assumpt!D58*Operacao_Operations!N5 -> 396 | O25: =Pressupostos_Assumpt!D61*Pressupostos_Assumpt!D56*Pressupostos_Assumpt!D58*Operacao_Operations!O5 -> 396 | P25: =Pressupostos_Assumpt!D61*Pressupostos_Assumpt!D56*Pressupostos_Assumpt!D58*Operacao_Operations!P5 -> 132 | Q25: =Pressupostos_Assumpt!D61*Pressupostos_Assumpt!D56*Pressupostos_Assumpt!D58*Operacao_Operations!Q5 -> 132 | R25: =Pressupostos_Assumpt!D61*Pressupostos_Assumpt!D56*Pressupostos_Assumpt!D58*Operacao_Operations!R5 -> 132 | S25: =C25+D25+E25+F25+G25+H25+I25+J25+K25+L25 -> 504 | T25: =M25+N25+O25+P25+Q25+R25 -> 1584
B26: Remuneracao bruta total / Total gross | C26: =C23+C24+C25 -> 558.53535 | D26: =D23+D24+D25 -> 558.53535 | E26: =E23+E24+E25 -> 558.53535 | F26: =F23+F24+F25 -> 558.53535 | G26: =G23+G24+G25 -> 558.53535 | H26: =H23+H24+H25 -> 558.53535 | I26: =I23+I24+I25 -> 558.53535 | J26: =J23+J24+J25 -> 558.53535 | ... R26: =R23+R24+R25 -> 2528.3333 | S26: =C26+D26+E26+F26+G26+H26+I26+J26+K26+L26 -> 9383.3939 | T26: =M26+N26+O26+P26+Q26+R26 -> 30340
B27: SS patronal (23.75%) + s/ excesso sub. / Employer SS | C27: =(C23+C24)*Pressupostos_Assumpt!C42+Pressupostos_Assumpt!C61*MAX(0,Pressupostos_Assumpt!C56-Pressupostos_Assumpt!C57)*Pressupostos_Assumpt!C58*Pressupostos_Assumpt!C42*Operacao_Operations!C5 -> 125.52715 | D27: =(D23+D24)*Pressupostos_Assumpt!C42+Pressupostos_Assumpt!C61*MAX(0,Pressupostos_Assumpt!C56-Pressupostos_Assumpt!C57)*Pressupostos_Assumpt!C58*Pressupostos_Assumpt!C42*Operacao_Operations!D5 -> 125.52715 | E27: =(E23+E24)*Pressupostos_Assumpt!C42+Pressupostos_Assumpt!C61*MAX(0,Pressupostos_Assumpt!C56-Pressupostos_Assumpt!C57)*Pressupostos_Assumpt!C58*Pressupostos_Assumpt!C42*Operacao_Operations!E5 -> 125.52715 | F27: =(F23+F24)*Pressupostos_Assumpt!C42+Pressupostos_Assumpt!C61*MAX(0,Pressupostos_Assumpt!C56-Pressupostos_Assumpt!C57)*Pressupostos_Assumpt!C58*Pressupostos_Assumpt!C42*Operacao_Operations!F5 -> 125.52715 | G27: =(G23+G24)*Pressupostos_Assumpt!C42+Pressupostos_Assumpt!C61*MAX(0,Pressupostos_Assumpt!C56-Pressupostos_Assumpt!C57)*Pressupostos_Assumpt!C58*Pressupostos_Assumpt!C42*Operacao_Operations!G5 -> 125.52715 | H27: =(H23+H24)*Pressupostos_Assumpt!C42+Pressupostos_Assumpt!C61*MAX(0,Pressupostos_Assumpt!C56-Pressupostos_Assumpt!C57)*Pressupostos_Assumpt!C58*Pressupostos_Assumpt!C42*Operacao_Operations!H5 -> 125.52715 | I27: =(I23+I24)*Pressupostos_Assumpt!C42+Pressupostos_Assumpt!C61*MAX(0,Pressupostos_Assumpt!C56-Pressupostos_Assumpt!C57)*Pressupostos_Assumpt!C58*Pressupostos_Assumpt!C42*Operacao_Operations!I5 -> 125.52715 | J27: =(J23+J24)*Pressupostos_Assumpt!C42+Pressupostos_Assumpt!C61*MAX(0,Pressupostos_Assumpt!C56-Pressupostos_Assumpt!C57)*Pressupostos_Assumpt!C58*Pressupostos_Assumpt!C42*Operacao_Operations!J5 -> 125.52715 | K27: =(K23+K24)*Pressupostos_Assumpt!C42+Pressupostos_Assumpt!C61*MAX(0,Pressupostos_Assumpt!C56-Pressupostos_Assumpt!C57)*Pressupostos_Assumpt!C58*Pressupostos_Assumpt!C42*Operacao_Operations!K5 -> 552.31944 | L27: =(L23+L24)*Pressupostos_Assumpt!C42+Pressupostos_Assumpt!C61*MAX(0,Pressupostos_Assumpt!C56-Pressupostos_Assumpt!C57)*Pressupostos_Assumpt!C58*Pressupostos_Assumpt!C42*Operacao_Operations!L5 -> 552.31944 | M27: =(M23+M24)*Pressupostos_Assumpt!D42+Pressupostos_Assumpt!D61*MAX(0,Pressupostos_Assumpt!D56-Pressupostos_Assumpt!D57)*Pressupostos_Assumpt!D58*Pressupostos_Assumpt!D42*Operacao_Operations!M5 -> 1707.3875 | N27: =(N23+N24)*Pressupostos_Assumpt!D42+Pressupostos_Assumpt!D61*MAX(0,Pressupostos_Assumpt!D56-Pressupostos_Assumpt!D57)*Pressupostos_Assumpt!D58*Pressupostos_Assumpt!D42*Operacao_Operations!N5 -> 1707.3875 | O27: =(O23+O24)*Pressupostos_Assumpt!D42+Pressupostos_Assumpt!D61*MAX(0,Pressupostos_Assumpt!D56-Pressupostos_Assumpt!D57)*Pressupostos_Assumpt!D58*Pressupostos_Assumpt!D42*Operacao_Operations!O5 -> 1707.3875 | P27: =(P23+P24)*Pressupostos_Assumpt!D42+Pressupostos_Assumpt!D61*MAX(0,Pressupostos_Assumpt!D56-Pressupostos_Assumpt!D57)*Pressupostos_Assumpt!D58*Pressupostos_Assumpt!D42*Operacao_Operations!P5 -> 569.12917 | Q27: =(Q23+Q24)*Pressupostos_Assumpt!D42+Pressupostos_Assumpt!D61*MAX(0,Pressupostos_Assumpt!D56-Pressupostos_Assumpt!D57)*Pressupostos_Assumpt!D58*Pressupostos_Assumpt!D42*Operacao_Operations!Q5 -> 569.12917 | R27: =(R23+R24)*Pressupostos_Assumpt!D42+Pressupostos_Assumpt!D61*MAX(0,Pressupostos_Assumpt!D56-Pressupostos_Assumpt!D57)*Pressupostos_Assumpt!D58*Pressupostos_Assumpt!D42*Operacao_Operations!R5 -> 569.12917 | S27: =C27+D27+E27+F27+G27+H27+I27+J27+K27+L27 -> 2108.8561 | T27: =M27+N27+O27+P27+Q27+R27 -> 6829.55
B28: CUSTO EMPRESA Gestor / TOTAL MANAGER COST | C28: =C26+C27 -> 684.0625 | D28: =D26+D27 -> 684.0625 | E28: =E26+E27 -> 684.0625 | F28: =F26+F27 -> 684.0625 | G28: =G26+G27 -> 684.0625 | H28: =H26+H27 -> 684.0625 | I28: =I26+I27 -> 684.0625 | J28: =J26+J27 -> 684.0625 | ... R28: =R26+R27 -> 3097.4625 | S28: =C28+D28+E28+F28+G28+H28+I28+J28+K28+L28 -> 11492.25 | T28: =M28+N28+O28+P28+Q28+R28 -> 37169.55
B30: D. ASSISTENTE ADMINISTRATIVO / ADMIN ASSISTANT
B31: Salario base bruto / Gross base wage | C31: =Pressupostos_Assumpt!C64*Pressupostos_Assumpt!C63*Operacao_Operations!C5 -> 283.63636 | D31: =Pressupostos_Assumpt!C64*Pressupostos_Assumpt!C63*Operacao_Operations!D5 -> 283.63636 | E31: =Pressupostos_Assumpt!C64*Pressupostos_Assumpt!C63*Operacao_Operations!E5 -> 283.63636 | F31: =Pressupostos_Assumpt!C64*Pressupostos_Assumpt!C63*Operacao_Operations!F5 -> 283.63636 | G31: =Pressupostos_Assumpt!C64*Pressupostos_Assumpt!C63*Operacao_Operations!G5 -> 283.63636 | H31: =Pressupostos_Assumpt!C64*Pressupostos_Assumpt!C63*Operacao_Operations!H5 -> 283.63636 | I31: =Pressupostos_Assumpt!C64*Pressupostos_Assumpt!C63*Operacao_Operations!I5 -> 283.63636 | J31: =Pressupostos_Assumpt!C64*Pressupostos_Assumpt!C63*Operacao_Operations!J5 -> 283.63636 | K31: =Pressupostos_Assumpt!C64*Pressupostos_Assumpt!C63*Operacao_Operations!K5 -> 1248 | L31: =Pressupostos_Assumpt!C64*Pressupostos_Assumpt!C63*Operacao_Operations!L5 -> 1248 | M31: =Pressupostos_Assumpt!D64*Pressupostos_Assumpt!D63*Operacao_Operations!M5 -> 3848 | N31: =Pressupostos_Assumpt!D64*Pressupostos_Assumpt!D63*Operacao_Operations!N5 -> 3848 | O31: =Pressupostos_Assumpt!D64*Pressupostos_Assumpt!D63*Operacao_Operations!O5 -> 3848 | P31: =Pressupostos_Assumpt!D64*Pressupostos_Assumpt!D63*Operacao_Operations!P5 -> 1282.6667 | Q31: =Pressupostos_Assumpt!D64*Pressupostos_Assumpt!D63*Operacao_Operations!Q5 -> 1282.6667 | R31: =Pressupostos_Assumpt!D64*Pressupostos_Assumpt!D63*Operacao_Operations!R5 -> 1282.6667 | S31: =C31+D31+E31+F31+G31+H31+I31+J31+K31+L31 -> 4765.0909 | T31: =M31+N31+O31+P31+Q31+R31 -> 15392
B32: Subs. Natal+ferias / Christmas+holiday | C32: =Pressupostos_Assumpt!C64*Pressupostos_Assumpt!C63*(Pressupostos_Assumpt!C54-1)*Operacao_Operations!C5 -> 47.272727 | D32: =Pressupostos_Assumpt!C64*Pressupostos_Assumpt!C63*(Pressupostos_Assumpt!C54-1)*Operacao_Operations!D5 -> 47.272727 | E32: =Pressupostos_Assumpt!C64*Pressupostos_Assumpt!C63*(Pressupostos_Assumpt!C54-1)*Operacao_Operations!E5 -> 47.272727 | F32: =Pressupostos_Assumpt!C64*Pressupostos_Assumpt!C63*(Pressupostos_Assumpt!C54-1)*Operacao_Operations!F5 -> 47.272727 | G32: =Pressupostos_Assumpt!C64*Pressupostos_Assumpt!C63*(Pressupostos_Assumpt!C54-1)*Operacao_Operations!G5 -> 47.272727 | H32: =Pressupostos_Assumpt!C64*Pressupostos_Assumpt!C63*(Pressupostos_Assumpt!C54-1)*Operacao_Operations!H5 -> 47.272727 | I32: =Pressupostos_Assumpt!C64*Pressupostos_Assumpt!C63*(Pressupostos_Assumpt!C54-1)*Operacao_Operations!I5 -> 47.272727 | J32: =Pressupostos_Assumpt!C64*Pressupostos_Assumpt!C63*(Pressupostos_Assumpt!C54-1)*Operacao_Operations!J5 -> 47.272727 | K32: =Pressupostos_Assumpt!C64*Pressupostos_Assumpt!C63*(Pressupostos_Assumpt!C54-1)*Operacao_Operations!K5 -> 208 | L32: =Pressupostos_Assumpt!C64*Pressupostos_Assumpt!C63*(Pressupostos_Assumpt!C54-1)*Operacao_Operations!L5 -> 208 | M32: =Pressupostos_Assumpt!D64*Pressupostos_Assumpt!D63*(Pressupostos_Assumpt!D54-1)*Operacao_Operations!M5 -> 641.33333 | N32: =Pressupostos_Assumpt!D64*Pressupostos_Assumpt!D63*(Pressupostos_Assumpt!D54-1)*Operacao_Operations!N5 -> 641.33333 | O32: =Pressupostos_Assumpt!D64*Pressupostos_Assumpt!D63*(Pressupostos_Assumpt!D54-1)*Operacao_Operations!O5 -> 641.33333 | P32: =Pressupostos_Assumpt!D64*Pressupostos_Assumpt!D63*(Pressupostos_Assumpt!D54-1)*Operacao_Operations!P5 -> 213.77778 | Q32: =Pressupostos_Assumpt!D64*Pressupostos_Assumpt!D63*(Pressupostos_Assumpt!D54-1)*Operacao_Operations!Q5 -> 213.77778 | R32: =Pressupostos_Assumpt!D64*Pressupostos_Assumpt!D63*(Pressupostos_Assumpt!D54-1)*Operacao_Operations!R5 -> 213.77778 | S32: =C32+D32+E32+F32+G32+H32+I32+J32+K32+L32 -> 794.18182 | T32: =M32+N32+O32+P32+Q32+R32 -> 2565.3333
B33: Subs. alimentacao / Food subsidy | C33: =Pressupostos_Assumpt!C64*Pressupostos_Assumpt!C56*Pressupostos_Assumpt!C58*Operacao_Operations!C5 -> 30 | D33: =Pressupostos_Assumpt!C64*Pressupostos_Assumpt!C56*Pressupostos_Assumpt!C58*Operacao_Operations!D5 -> 30 | E33: =Pressupostos_Assumpt!C64*Pressupostos_Assumpt!C56*Pressupostos_Assumpt!C58*Operacao_Operations!E5 -> 30 | F33: =Pressupostos_Assumpt!C64*Pressupostos_Assumpt!C56*Pressupostos_Assumpt!C58*Operacao_Operations!F5 -> 30 | G33: =Pressupostos_Assumpt!C64*Pressupostos_Assumpt!C56*Pressupostos_Assumpt!C58*Operacao_Operations!G5 -> 30 | H33: =Pressupostos_Assumpt!C64*Pressupostos_Assumpt!C56*Pressupostos_Assumpt!C58*Operacao_Operations!H5 -> 30 | I33: =Pressupostos_Assumpt!C64*Pressupostos_Assumpt!C56*Pressupostos_Assumpt!C58*Operacao_Operations!I5 -> 30 | J33: =Pressupostos_Assumpt!C64*Pressupostos_Assumpt!C56*Pressupostos_Assumpt!C58*Operacao_Operations!J5 -> 30 | K33: =Pressupostos_Assumpt!C64*Pressupostos_Assumpt!C56*Pressupostos_Assumpt!C58*Operacao_Operations!K5 -> 132 | L33: =Pressupostos_Assumpt!C64*Pressupostos_Assumpt!C56*Pressupostos_Assumpt!C58*Operacao_Operations!L5 -> 132 | M33: =Pressupostos_Assumpt!D64*Pressupostos_Assumpt!D56*Pressupostos_Assumpt!D58*Operacao_Operations!M5 -> 396 | N33: =Pressupostos_Assumpt!D64*Pressupostos_Assumpt!D56*Pressupostos_Assumpt!D58*Operacao_Operations!N5 -> 396 | O33: =Pressupostos_Assumpt!D64*Pressupostos_Assumpt!D56*Pressupostos_Assumpt!D58*Operacao_Operations!O5 -> 396 | P33: =Pressupostos_Assumpt!D64*Pressupostos_Assumpt!D56*Pressupostos_Assumpt!D58*Operacao_Operations!P5 -> 132 | Q33: =Pressupostos_Assumpt!D64*Pressupostos_Assumpt!D56*Pressupostos_Assumpt!D58*Operacao_Operations!Q5 -> 132 | R33: =Pressupostos_Assumpt!D64*Pressupostos_Assumpt!D56*Pressupostos_Assumpt!D58*Operacao_Operations!R5 -> 132 | S33: =C33+D33+E33+F33+G33+H33+I33+J33+K33+L33 -> 504 | T33: =M33+N33+O33+P33+Q33+R33 -> 1584
B34: Remuneracao bruta total / Total gross | C34: =C31+C32+C33 -> 360.90909 | D34: =D31+D32+D33 -> 360.90909 | E34: =E31+E32+E33 -> 360.90909 | F34: =F31+F32+F33 -> 360.90909 | G34: =G31+G32+G33 -> 360.90909 | H34: =H31+H32+H33 -> 360.90909 | I34: =I31+I32+I33 -> 360.90909 | J34: =J31+J32+J33 -> 360.90909 | ... R34: =R31+R32+R33 -> 1628.4444 | S34: =C34+D34+E34+F34+G34+H34+I34+J34+K34+L34 -> 6063.2727 | T34: =M34+N34+O34+P34+Q34+R34 -> 19541.333
B35: SS patronal (23.75%) + s/ excesso sub. / Employer SS | C35: =(C31+C32)*Pressupostos_Assumpt!C42+Pressupostos_Assumpt!C64*MAX(0,Pressupostos_Assumpt!C56-Pressupostos_Assumpt!C57)*Pressupostos_Assumpt!C58*Pressupostos_Assumpt!C42*Operacao_Operations!C5 -> 78.590909 | D35: =(D31+D32)*Pressupostos_Assumpt!C42+Pressupostos_Assumpt!C64*MAX(0,Pressupostos_Assumpt!C56-Pressupostos_Assumpt!C57)*Pressupostos_Assumpt!C58*Pressupostos_Assumpt!C42*Operacao_Operations!D5 -> 78.590909 | E35: =(E31+E32)*Pressupostos_Assumpt!C42+Pressupostos_Assumpt!C64*MAX(0,Pressupostos_Assumpt!C56-Pressupostos_Assumpt!C57)*Pressupostos_Assumpt!C58*Pressupostos_Assumpt!C42*Operacao_Operations!E5 -> 78.590909 | F35: =(F31+F32)*Pressupostos_Assumpt!C42+Pressupostos_Assumpt!C64*MAX(0,Pressupostos_Assumpt!C56-Pressupostos_Assumpt!C57)*Pressupostos_Assumpt!C58*Pressupostos_Assumpt!C42*Operacao_Operations!F5 -> 78.590909 | G35: =(G31+G32)*Pressupostos_Assumpt!C42+Pressupostos_Assumpt!C64*MAX(0,Pressupostos_Assumpt!C56-Pressupostos_Assumpt!C57)*Pressupostos_Assumpt!C58*Pressupostos_Assumpt!C42*Operacao_Operations!G5 -> 78.590909 | H35: =(H31+H32)*Pressupostos_Assumpt!C42+Pressupostos_Assumpt!C64*MAX(0,Pressupostos_Assumpt!C56-Pressupostos_Assumpt!C57)*Pressupostos_Assumpt!C58*Pressupostos_Assumpt!C42*Operacao_Operations!H5 -> 78.590909 | I35: =(I31+I32)*Pressupostos_Assumpt!C42+Pressupostos_Assumpt!C64*MAX(0,Pressupostos_Assumpt!C56-Pressupostos_Assumpt!C57)*Pressupostos_Assumpt!C58*Pressupostos_Assumpt!C42*Operacao_Operations!I5 -> 78.590909 | J35: =(J31+J32)*Pressupostos_Assumpt!C42+Pressupostos_Assumpt!C64*MAX(0,Pressupostos_Assumpt!C56-Pressupostos_Assumpt!C57)*Pressupostos_Assumpt!C58*Pressupostos_Assumpt!C42*Operacao_Operations!J5 -> 78.590909 | K35: =(K31+K32)*Pressupostos_Assumpt!C42+Pressupostos_Assumpt!C64*MAX(0,Pressupostos_Assumpt!C56-Pressupostos_Assumpt!C57)*Pressupostos_Assumpt!C58*Pressupostos_Assumpt!C42*Operacao_Operations!K5 -> 345.8 | L35: =(L31+L32)*Pressupostos_Assumpt!C42+Pressupostos_Assumpt!C64*MAX(0,Pressupostos_Assumpt!C56-Pressupostos_Assumpt!C57)*Pressupostos_Assumpt!C58*Pressupostos_Assumpt!C42*Operacao_Operations!L5 -> 345.8 | M35: =(M31+M32)*Pressupostos_Assumpt!D42+Pressupostos_Assumpt!D64*MAX(0,Pressupostos_Assumpt!D56-Pressupostos_Assumpt!D57)*Pressupostos_Assumpt!D58*Pressupostos_Assumpt!D42*Operacao_Operations!M5 -> 1066.2167 | N35: =(N31+N32)*Pressupostos_Assumpt!D42+Pressupostos_Assumpt!D64*MAX(0,Pressupostos_Assumpt!D56-Pressupostos_Assumpt!D57)*Pressupostos_Assumpt!D58*Pressupostos_Assumpt!D42*Operacao_Operations!N5 -> 1066.2167 | O35: =(O31+O32)*Pressupostos_Assumpt!D42+Pressupostos_Assumpt!D64*MAX(0,Pressupostos_Assumpt!D56-Pressupostos_Assumpt!D57)*Pressupostos_Assumpt!D58*Pressupostos_Assumpt!D42*Operacao_Operations!O5 -> 1066.2167 | P35: =(P31+P32)*Pressupostos_Assumpt!D42+Pressupostos_Assumpt!D64*MAX(0,Pressupostos_Assumpt!D56-Pressupostos_Assumpt!D57)*Pressupostos_Assumpt!D58*Pressupostos_Assumpt!D42*Operacao_Operations!P5 -> 355.40556 | Q35: =(Q31+Q32)*Pressupostos_Assumpt!D42+Pressupostos_Assumpt!D64*MAX(0,Pressupostos_Assumpt!D56-Pressupostos_Assumpt!D57)*Pressupostos_Assumpt!D58*Pressupostos_Assumpt!D42*Operacao_Operations!Q5 -> 355.40556 | R35: =(R31+R32)*Pressupostos_Assumpt!D42+Pressupostos_Assumpt!D64*MAX(0,Pressupostos_Assumpt!D56-Pressupostos_Assumpt!D57)*Pressupostos_Assumpt!D58*Pressupostos_Assumpt!D42*Operacao_Operations!R5 -> 355.40556 | S35: =C35+D35+E35+F35+G35+H35+I35+J35+K35+L35 -> 1320.3273 | T35: =M35+N35+O35+P35+Q35+R35 -> 4264.8667
B36: CUSTO EMPRESA Admin / TOTAL ADMIN COST | C36: =C34+C35 -> 439.5 | D36: =D34+D35 -> 439.5 | E36: =E34+E35 -> 439.5 | F36: =F34+F35 -> 439.5 | G36: =G34+G35 -> 439.5 | H36: =H34+H35 -> 439.5 | I36: =I34+I35 -> 439.5 | J36: =J34+J35 -> 439.5 | ... R36: =R34+R35 -> 1983.85 | S36: =C36+D36+E36+F36+G36+H36+I36+J36+K36+L36 -> 7383.6 | T36: =M36+N36+O36+P36+Q36+R36 -> 23806.2
B38: E. RECRUTAMENTO / RECRUITMENT (so permanentes)
B39: Custo recrutamento (turnover) / Recruitment | C39: =Operacao_Operations!C16*Pressupostos_Assumpt!C48*Pressupostos_Assumpt!C47/12*Operacao_Operations!C5 -> 2.5568182 | D39: =Operacao_Operations!D16*Pressupostos_Assumpt!C48*Pressupostos_Assumpt!C47/12*Operacao_Operations!D5 -> 4.2613636 | E39: =Operacao_Operations!E16*Pressupostos_Assumpt!C48*Pressupostos_Assumpt!C47/12*Operacao_Operations!E5 -> 5.9659091 | F39: =Operacao_Operations!F16*Pressupostos_Assumpt!C48*Pressupostos_Assumpt!C47/12*Operacao_Operations!F5 -> 8.0965909 | G39: =Operacao_Operations!G16*Pressupostos_Assumpt!C48*Pressupostos_Assumpt!C47/12*Operacao_Operations!G5 -> 9.8011364 | H39: =Operacao_Operations!H16*Pressupostos_Assumpt!C48*Pressupostos_Assumpt!C47/12*Operacao_Operations!H5 -> 11.505682 | I39: =Operacao_Operations!I16*Pressupostos_Assumpt!C48*Pressupostos_Assumpt!C47/12*Operacao_Operations!I5 -> 12.357955 | J39: =Operacao_Operations!J16*Pressupostos_Assumpt!C48*Pressupostos_Assumpt!C47/12*Operacao_Operations!J5 -> 12.357955 | K39: =Operacao_Operations!K16*Pressupostos_Assumpt!C48*Pressupostos_Assumpt!C47/12*Operacao_Operations!K5 -> 54.375 | L39: =Operacao_Operations!L16*Pressupostos_Assumpt!C48*Pressupostos_Assumpt!C47/12*Operacao_Operations!L5 -> 54.375 | M39: =Operacao_Operations!M16*Pressupostos_Assumpt!D48*Pressupostos_Assumpt!D47/12*Operacao_Operations!M5 -> 163.125 | N39: =Operacao_Operations!N16*Pressupostos_Assumpt!D48*Pressupostos_Assumpt!D47/12*Operacao_Operations!N5 -> 163.125 | O39: =Operacao_Operations!O16*Pressupostos_Assumpt!D48*Pressupostos_Assumpt!D47/12*Operacao_Operations!O5 -> 163.125 | P39: =Operacao_Operations!P16*Pressupostos_Assumpt!D48*Pressupostos_Assumpt!D47/12*Operacao_Operations!P5 -> 54.375 | Q39: =Operacao_Operations!Q16*Pressupostos_Assumpt!D48*Pressupostos_Assumpt!D47/12*Operacao_Operations!Q5 -> 54.375 | R39: =Operacao_Operations!R16*Pressupostos_Assumpt!D48*Pressupostos_Assumpt!D47/12*Operacao_Operations!R5 -> 54.375 | S39: =C39+D39+E39+F39+G39+H39+I39+J39+K39+L39 -> 175.65341 | T39: =M39+N39+O39+P39+Q39+R39 -> 652.5
B41: F. RESUMO CUSTOS COM PESSOAL / STAFF COST SUMMARY
B42: Permanentes (motoristas) / Permanent drivers | C42: =C15 -> 2295.75 | D42: =D15 -> 3826.25 | E42: =E15 -> 5356.75 | F42: =F15 -> 7269.875 | G42: =G15 -> 8800.375 | H42: =H15 -> 10330.875 | I42: =I15 -> 11096.125 | J42: =J15 -> 11096.125 | ... R42: =R15 -> 48822.95 | S42: =C42+D42+E42+F42+G42+H42+I42+J42+K42+L42 -> 157718.03 | T42: =M42+N42+O42+P42+Q42+R42 -> 585875.4
B43: Temporarios ETT / Temp agency | C43: =C20 -> 0 | D43: =D20 -> 0 | E43: =E20 -> 0 | F43: =F20 -> 0 | G43: =G20 -> 0 | H43: =H20 -> 0 | I43: =I20 -> 0 | J43: =J20 -> 0 | ... R43: =R20 -> 46748 | S43: =C43+D43+E43+F43+G43+H43+I43+J43+K43+L43 -> 93496 | T43: =M43+N43+O43+P43+Q43+R43 -> 93496
B44: Gestor + Admin / Manager + Admin | C44: =C28+C36 -> 1123.5625 | D44: =D28+D36 -> 1123.5625 | E44: =E28+E36 -> 1123.5625 | F44: =F28+F36 -> 1123.5625 | G44: =G28+G36 -> 1123.5625 | H44: =H28+H36 -> 1123.5625 | I44: =I28+I36 -> 1123.5625 | J44: =J28+J36 -> 1123.5625 | ... R44: =R28+R36 -> 5081.3125 | S44: =C44+D44+E44+F44+G44+H44+I44+J44+K44+L44 -> 18875.85 | T44: =M44+N44+O44+P44+Q44+R44 -> 60975.75
B45: Recrutamento / Recruitment | C45: =C39 -> 2.5568182 | D45: =D39 -> 4.2613636 | E45: =E39 -> 5.9659091 | F45: =F39 -> 8.0965909 | G45: =G39 -> 9.8011364 | H45: =H39 -> 11.505682 | I45: =I39 -> 12.357955 | J45: =J39 -> 12.357955 | ... R45: =R39 -> 54.375 | S45: =C45+D45+E45+F45+G45+H45+I45+J45+K45+L45 -> 175.65341 | T45: =M45+N45+O45+P45+Q45+R45 -> 652.5
B46: CUSTO TOTAL PESSOAL / TOTAL STAFF COST | C46: =C42+C43+C44+C45 -> 3421.8693 | D46: =D42+D43+D44+D45 -> 4954.0739 | E46: =E42+E43+E44+E45 -> 6486.2784 | F46: =F42+F43+F44+F45 -> 8401.5341 | G46: =G42+G43+G44+G45 -> 9933.7386 | H46: =H42+H43+H44+H45 -> 11465.943 | I46: =I42+I43+I44+I45 -> 12232.045 | J46: =J42+J43+J44+J45 -> 12232.045 | ... R46: =R42+R43+R44+R45 -> 100706.64 | S46: =C46+D46+E46+F46+G46+H46+I46+J46+K46+L46 -> 270265.53 | T46: =M46+N46+O46+P46+Q46+R46 -> 740999.65
B47: (memo) SS+IRS a entregar / SS+IRS payable | C47: =C11+C27+C35+C12+C13 -> 940.1426 | D47: =D11+D27+D35+D12+D13 -> 1430.8256 | E47: =E11+E27+E35+E12+E13 -> 1921.5087 | F47: =F11+F27+F35+F12+F13 -> 2534.8624 | G47: =G11+G27+G35+G12+G13 -> 3025.5455 | H47: =H11+H27+H35+H12+H13 -> 3516.2285 | I47: =I11+I27+I35+I12+I13 -> 3761.57 | J47: =J11+J27+J35+J12+J13 -> 3761.57 | ... R47: =R11+R27+R35+R12+R13 -> 16577.323 | S47: =C47+D47+E47+F47+G47+H47+I47+J47+K47+L47 -> 53994.07 | T47: =M47+N47+O47+P47+Q47+R47 -> 198927.88
B50: RESUMO MENSAL / MONTHLY BREAKDOWN
C51: 2026 (Set-Dez) | G51: 2027
B52: POR MES / BY MONTH | C52: Set/Sep 26 | D52: Out/Oct 26 | E52: Nov 26 | F52: Dez/Dec 26 | G52: Jan 27 | H52: Fev/Feb 27 | I52: Mar 27 | J52: Abr/Apr 27 | K52: Mai/May 27 | L52: Jun 27 | M52: Jul 27 | N52: Ago/Aug 27 | O52: Set/Sep 27 | P52: Out/Oct 27 | Q52: Nov 27 | R52: Dez/Dec 27
B53: Permanentes / Permanent | C53: =C42+D42+E42+F42 -> 18748.625 | D53: =G42+H42+I42+J42 -> 41323.5 | E53: =K42 -> 48822.95 | F53: =L42 -> 48822.95 | G53: =(M42)/3 -> 48822.95 | H53: =(M42)/3 -> 48822.95 | I53: =(M42)/3 -> 48822.95 | J53: =(N42)/3 -> 48822.95 | K53: =(N42)/3 -> 48822.95 | L53: =(N42)/3 -> 48822.95 | M53: =(O42)/3 -> 48822.95 | N53: =(O42)/3 -> 48822.95 | O53: =(O42)/3 -> 48822.95 | P53: =P42 -> 48822.95 | Q53: =Q42 -> 48822.95 | R53: =R42 -> 48822.95
B54: Temporarios ETT / Temp agency | C54: =C43+D43+E43+F43 -> 0 | D54: =G43+H43+I43+J43 -> 0 | E54: =K43 -> 46748 | F54: =L43 -> 46748 | G54: =(M43)/3 -> 0 | H54: =(M43)/3 -> 0 | I54: =(M43)/3 -> 0 | J54: =(N43)/3 -> 0 | K54: =(N43)/3 -> 0 | L54: =(N43)/3 -> 0 | M54: =(O43)/3 -> 0 | N54: =(O43)/3 -> 0 | O54: =(O43)/3 -> 0 | P54: =P43 -> 0 | Q54: =Q43 -> 46748 | R54: =R43 -> 46748
B55: Gestor + Admin / Manager + Admin | C55: =C44+D44+E44+F44 -> 4494.25 | D55: =G44+H44+I44+J44 -> 4494.25 | E55: =K44 -> 4943.675 | F55: =L44 -> 4943.675 | G55: =(M44)/3 -> 5081.3125 | H55: =(M44)/3 -> 5081.3125 | I55: =(M44)/3 -> 5081.3125 | J55: =(N44)/3 -> 5081.3125 | K55: =(N44)/3 -> 5081.3125 | L55: =(N44)/3 -> 5081.3125 | M55: =(O44)/3 -> 5081.3125 | N55: =(O44)/3 -> 5081.3125 | O55: =(O44)/3 -> 5081.3125 | P55: =P44 -> 5081.3125 | Q55: =Q44 -> 5081.3125 | R55: =R44 -> 5081.3125
B56: Recrutamento / Recruitment | C56: =C45+D45+E45+F45 -> 20.880682 | D56: =G45+H45+I45+J45 -> 46.022727 | E56: =K45 -> 54.375 | F56: =L45 -> 54.375 | G56: =(M45)/3 -> 54.375 | H56: =(M45)/3 -> 54.375 | I56: =(M45)/3 -> 54.375 | J56: =(N45)/3 -> 54.375 | K56: =(N45)/3 -> 54.375 | L56: =(N45)/3 -> 54.375 | M56: =(O45)/3 -> 54.375 | N56: =(O45)/3 -> 54.375 | O56: =(O45)/3 -> 54.375 | P56: =P45 -> 54.375 | Q56: =Q45 -> 54.375 | R56: =R45 -> 54.375
B57: CUSTO TOTAL PESSOAL / TOTAL STAFF COST | C57: =C46+D46+E46+F46 -> 23263.756 | D57: =G46+H46+I46+J46 -> 45863.773 | E57: =K46 -> 100569 | F57: =L46 -> 100569 | G57: =(M46)/3 -> 53958.638 | H57: =(M46)/3 -> 53958.638 | I57: =(M46)/3 -> 53958.638 | J57: =(N46)/3 -> 53958.638 | K57: =(N46)/3 -> 53958.638 | L57: =(N46)/3 -> 53958.638 | M57: =(O46)/3 -> 53958.638 | N57: =(O46)/3 -> 53958.638 | O57: =(O46)/3 -> 53958.638 | P57: =P46 -> 53958.638 | Q57: =Q46 -> 100706.64 | R57: =R46 -> 100706.64
B60: RESUMO TRIMESTRAL / QUARTERLY BREAKDOWN
C61: 2026 | E61: 2027
B62: POR TRIMESTRE / BY QUARTER | C62: Q3 2026 Set/Sep 26 | D62: Q4 2026 Out-Dez/Oct-Dec 26 | E62: Q1 2027 Jan-Mar 27 | F62: Q2 2027 Abr-Jun/Apr-Jun 27 | G62: Q3 2027 Jul-Set/Jul-Sep 27 | H62: Q4 2027 Out-Dez/Oct-Dec 27
B63: Permanentes / Permanent | C63: =SUM(C42:F42) -> 18748.625 | D63: =SUM(G42:L42) -> 138969.4 | E63: =SUM(M42:M42) -> 146468.85 | F63: =SUM(N42:N42) -> 146468.85 | G63: =SUM(O42:O42) -> 146468.85 | H63: =SUM(P42:R42) -> 146468.85
B64: Temporarios ETT / Temp agency | C64: =SUM(C43:F43) -> 0 | D64: =SUM(G43:L43) -> 93496 | E64: =SUM(M43:M43) -> 0 | F64: =SUM(N43:N43) -> 0 | G64: =SUM(O43:O43) -> 0 | H64: =SUM(P43:R43) -> 93496
B65: Gestor + Admin / Manager + Admin | C65: =SUM(C44:F44) -> 4494.25 | D65: =SUM(G44:L44) -> 14381.6 | E65: =SUM(M44:M44) -> 15243.938 | F65: =SUM(N44:N44) -> 15243.938 | G65: =SUM(O44:O44) -> 15243.938 | H65: =SUM(P44:R44) -> 15243.938
B66: Recrutamento / Recruitment | C66: =SUM(C45:F45) -> 20.880682 | D66: =SUM(G45:L45) -> 154.77273 | E66: =SUM(M45:M45) -> 163.125 | F66: =SUM(N45:N45) -> 163.125 | G66: =SUM(O45:O45) -> 163.125 | H66: =SUM(P45:R45) -> 163.125
B67: CUSTO TOTAL PESSOAL / TOTAL STAFF COST | C67: =SUM(C46:F46) -> 23263.756 | D67: =SUM(G46:L46) -> 247001.77 | E67: =SUM(M46:M46) -> 161875.91 | F67: =SUM(N46:N46) -> 161875.91 | G67: =SUM(O46:O46) -> 161875.91 | H67: =SUM(P46:R46) -> 255371.91

Sheet Custos_Costs
B1: CUSTOS / COSTS
C2: ANO 2026 / YEAR 2026 (Ago-Dez/Aug-Dec) | M2: ANO 2027 / YEAR 2027
B3: Rubrica / Item | C3: S1 Set/Sep 26 | D3: S2 Set/Sep 26 | E3: S3 Set/Sep 26 | F3: S4 Set/Sep 26 | G3: S5 Out/Oct 26 | H3: S6 Out/Oct 26 | I3: S7 Out/Oct 26 | J3: S8 Out/Oct 26 | K3: Nov Nov 26 (Pico/Peak) | L3: Dez Dez/Dec 26 (Pico/Peak) | M3: Q1'27 Jan-Mar 27 | N3: Q2'27 Abr-Jun/Apr-Jun 27 | O3: Q3'27 Jul-Set/Jul-Sep 27 | P3: Out'27 Out/Oct 27 | Q3: Nov'27 Nov 27 (Pico/Peak) | R3: Dez'27 Dez/Dec 27 (Pico/Peak) | S3: Total 2026 | T3: Total 2027
B4: -- MAO-DE-OBRA / LABOUR --
B5: Permanentes (motoristas) / Permanent drivers | C5: =Salarios_Wages!C42 -> 2295.75 | D5: =Salarios_Wages!D42 -> 3826.25 | E5: =Salarios_Wages!E42 -> 5356.75 | F5: =Salarios_Wages!F42 -> 7269.875 | G5: =Salarios_Wages!G42 -> 8800.375 | H5: =Salarios_Wages!H42 -> 10330.875 | I5: =Salarios_Wages!I42 -> 11096.125 | J5: =Salarios_Wages!J42 -> 11096.125 | ... R5: =Salarios_Wages!R42 -> 48822.95 | S5: =C5+D5+E5+F5+G5+H5+I5+J5+K5+L5 -> 157718.03 | T5: =M5+N5+O5+P5+Q5+R5 -> 585875.4
B6: Temporarios ETT / Temp agency | C6: =Salarios_Wages!C43 -> 0 | D6: =Salarios_Wages!D43 -> 0 | E6: =Salarios_Wages!E43 -> 0 | F6: =Salarios_Wages!F43 -> 0 | G6: =Salarios_Wages!G43 -> 0 | H6: =Salarios_Wages!H43 -> 0 | I6: =Salarios_Wages!I43 -> 0 | J6: =Salarios_Wages!J43 -> 0 | ... R6: =Salarios_Wages!R43 -> 46748 | S6: =C6+D6+E6+F6+G6+H6+I6+J6+K6+L6 -> 93496 | T6: =M6+N6+O6+P6+Q6+R6 -> 93496
B7: Gestor + Admin / Manager + Admin | C7: =Salarios_Wages!C44 -> 1123.5625 | D7: =Salarios_Wages!D44 -> 1123.5625 | E7: =Salarios_Wages!E44 -> 1123.5625 | F7: =Salarios_Wages!F44 -> 1123.5625 | G7: =Salarios_Wages!G44 -> 1123.5625 | H7: =Salarios_Wages!H44 -> 1123.5625 | I7: =Salarios_Wages!I44 -> 1123.5625 | J7: =Salarios_Wages!J44 -> 1123.5625 | ... R7: =Salarios_Wages!R44 -> 5081.3125 | S7: =C7+D7+E7+F7+G7+H7+I7+J7+K7+L7 -> 18875.85 | T7: =M7+N7+O7+P7+Q7+R7 -> 60975.75
B8: Recrutamento / Recruitment | C8: =Salarios_Wages!C45 -> 2.5568182 | D8: =Salarios_Wages!D45 -> 4.2613636 | E8: =Salarios_Wages!E45 -> 5.9659091 | F8: =Salarios_Wages!F45 -> 8.0965909 | G8: =Salarios_Wages!G45 -> 9.8011364 | H8: =Salarios_Wages!H45 -> 11.505682 | I8: =Salarios_Wages!I45 -> 12.357955 | J8: =Salarios_Wages!J45 -> 12.357955 | ... R8: =Salarios_Wages!R45 -> 54.375 | S8: =C8+D8+E8+F8+G8+H8+I8+J8+K8+L8 -> 175.65341 | T8: =M8+N8+O8+P8+Q8+R8 -> 652.5
B9: SUBTOTAL MAO-DE-OBRA / LABOUR | C9: =SUM(C5:C8) -> 3421.8693 | D9: =SUM(D5:D8) -> 4954.0739 | E9: =SUM(E5:E8) -> 6486.2784 | F9: =SUM(F5:F8) -> 8401.5341 | G9: =SUM(G5:G8) -> 9933.7386 | H9: =SUM(H5:H8) -> 11465.943 | I9: =SUM(I5:I8) -> 12232.045 | J9: =SUM(J5:J8) -> 12232.045 | ... R9: =SUM(R5:R8) -> 100706.64 | S9: =C9+D9+E9+F9+G9+H9+I9+J9+K9+L9 -> 270265.53 | T9: =M9+N9+O9+P9+Q9+R9 -> 740999.65
B10: -- FROTA / FLEET --
B11: Leasing frota propria / Own fleet lease | C11: =Operacao_Operations!C12*Pressupostos_Assumpt!C32*Operacao_Operations!C5 -> 1090.9091 | D11: =Operacao_Operations!D12*Pressupostos_Assumpt!C32*Operacao_Operations!D5 -> 1818.1818 | E11: =Operacao_Operations!E12*Pressupostos_Assumpt!C32*Operacao_Operations!E5 -> 2545.4545 | F11: =Operacao_Operations!F12*Pressupostos_Assumpt!C32*Operacao_Operations!F5 -> 3454.5455 | G11: =Operacao_Operations!G12*Pressupostos_Assumpt!C32*Operacao_Operations!G5 -> 4181.8182 | H11: =Operacao_Operations!H12*Pressupostos_Assumpt!C32*Operacao_Operations!H5 -> 4909.0909 | I11: =Operacao_Operations!I12*Pressupostos_Assumpt!C32*Operacao_Operations!I5 -> 5272.7273 | J11: =Operacao_Operations!J12*Pressupostos_Assumpt!C32*Operacao_Operations!J5 -> 5272.7273 | K11: =Operacao_Operations!K12*Pressupostos_Assumpt!C32*Operacao_Operations!K5 -> 23200 | L11: =Operacao_Operations!L12*Pressupostos_Assumpt!C32*Operacao_Operations!L5 -> 23200 | M11: =Operacao_Operations!M12*Pressupostos_Assumpt!D32*Operacao_Operations!M5 -> 69600 | N11: =Operacao_Operations!N12*Pressupostos_Assumpt!D32*Operacao_Operations!N5 -> 69600 | O11: =Operacao_Operations!O12*Pressupostos_Assumpt!D32*Operacao_Operations!O5 -> 69600 | P11: =Operacao_Operations!P12*Pressupostos_Assumpt!D32*Operacao_Operations!P5 -> 23200 | Q11: =Operacao_Operations!Q12*Pressupostos_Assumpt!D32*Operacao_Operations!Q5 -> 23200 | R11: =Operacao_Operations!R12*Pressupostos_Assumpt!D32*Operacao_Operations!R5 -> 23200 | S11: =C11+D11+E11+F11+G11+H11+I11+J11+K11+L11 -> 74945.455 | T11: =M11+N11+O11+P11+Q11+R11 -> 278400
B12: Seguro frota / Fleet insurance | C12: =Operacao_Operations!C12*Pressupostos_Assumpt!C33*Operacao_Operations!C5 -> 163.63636 | D12: =Operacao_Operations!D12*Pressupostos_Assumpt!C33*Operacao_Operations!D5 -> 272.72727 | E12: =Operacao_Operations!E12*Pressupostos_Assumpt!C33*Operacao_Operations!E5 -> 381.81818 | F12: =Operacao_Operations!F12*Pressupostos_Assumpt!C33*Operacao_Operations!F5 -> 518.18182 | G12: =Operacao_Operations!G12*Pressupostos_Assumpt!C33*Operacao_Operations!G5 -> 627.27273 | H12: =Operacao_Operations!H12*Pressupostos_Assumpt!C33*Operacao_Operations!H5 -> 736.36364 | I12: =Operacao_Operations!I12*Pressupostos_Assumpt!C33*Operacao_Operations!I5 -> 790.90909 | J12: =Operacao_Operations!J12*Pressupostos_Assumpt!C33*Operacao_Operations!J5 -> 790.90909 | K12: =Operacao_Operations!K12*Pressupostos_Assumpt!C33*Operacao_Operations!K5 -> 3480 | L12: =Operacao_Operations!L12*Pressupostos_Assumpt!C33*Operacao_Operations!L5 -> 3480 | M12: =Operacao_Operations!M12*Pressupostos_Assumpt!D33*Operacao_Operations!M5 -> 10875 | N12: =Operacao_Operations!N12*Pressupostos_Assumpt!D33*Operacao_Operations!N5 -> 10875 | O12: =Operacao_Operations!O12*Pressupostos_Assumpt!D33*Operacao_Operations!O5 -> 10875 | P12: =Operacao_Operations!P12*Pressupostos_Assumpt!D33*Operacao_Operations!P5 -> 3625 | Q12: =Operacao_Operations!Q12*Pressupostos_Assumpt!D33*Operacao_Operations!Q5 -> 3625 | R12: =Operacao_Operations!R12*Pressupostos_Assumpt!D33*Operacao_Operations!R5 -> 3625 | S12: =C12+D12+E12+F12+G12+H12+I12+J12+K12+L12 -> 11241.818 | T12: =M12+N12+O12+P12+Q12+R12 -> 43500
B13: Manutencao / Maintenance | C13: =Operacao_Operations!C12*Pressupostos_Assumpt!C34*Operacao_Operations!C5 -> 204.54545 | D13: =Operacao_Operations!D12*Pressupostos_Assumpt!C34*Operacao_Operations!D5 -> 340.90909 | E13: =Operacao_Operations!E12*Pressupostos_Assumpt!C34*Operacao_Operations!E5 -> 477.27273 | F13: =Operacao_Operations!F12*Pressupostos_Assumpt!C34*Operacao_Operations!F5 -> 647.72727 | G13: =Operacao_Operations!G12*Pressupostos_Assumpt!C34*Operacao_Operations!G5 -> 784.09091 | H13: =Operacao_Operations!H12*Pressupostos_Assumpt!C34*Operacao_Operations!H5 -> 920.45455 | I13: =Operacao_Operations!I12*Pressupostos_Assumpt!C34*Operacao_Operations!I5 -> 988.63636 | J13: =Operacao_Operations!J12*Pressupostos_Assumpt!C34*Operacao_Operations!J5 -> 988.63636 | K13: =Operacao_Operations!K12*Pressupostos_Assumpt!C34*Operacao_Operations!K5 -> 4350 | L13: =Operacao_Operations!L12*Pressupostos_Assumpt!C34*Operacao_Operations!L5 -> 4350 | M13: =Operacao_Operations!M12*Pressupostos_Assumpt!D34*Operacao_Operations!M5 -> 13920 | N13: =Operacao_Operations!N12*Pressupostos_Assumpt!D34*Operacao_Operations!N5 -> 13920 | O13: =Operacao_Operations!O12*Pressupostos_Assumpt!D34*Operacao_Operations!O5 -> 13920 | P13: =Operacao_Operations!P12*Pressupostos_Assumpt!D34*Operacao_Operations!P5 -> 4640 | Q13: =Operacao_Operations!Q12*Pressupostos_Assumpt!D34*Operacao_Operations!Q5 -> 4640 | R13: =Operacao_Operations!R12*Pressupostos_Assumpt!D34*Operacao_Operations!R5 -> 4640 | S13: =C13+D13+E13+F13+G13+H13+I13+J13+K13+L13 -> 14052.273 | T13: =M13+N13+O13+P13+Q13+R13 -> 55680
B14: Aluguer pico / Peak rental | C14: =Operacao_Operations!C13*Pressupostos_Assumpt!C35*Operacao_Operations!C5 -> 0 | D14: =Operacao_Operations!D13*Pressupostos_Assumpt!C35*Operacao_Operations!D5 -> 0 | E14: =Operacao_Operations!E13*Pressupostos_Assumpt!C35*Operacao_Operations!E5 -> 0 | F14: =Operacao_Operations!F13*Pressupostos_Assumpt!C35*Operacao_Operations!F5 -> 0 | G14: =Operacao_Operations!G13*Pressupostos_Assumpt!C35*Operacao_Operations!G5 -> 0 | H14: =Operacao_Operations!H13*Pressupostos_Assumpt!C35*Operacao_Operations!H5 -> 0 | I14: =Operacao_Operations!I13*Pressupostos_Assumpt!C35*Operacao_Operations!I5 -> 0 | J14: =Operacao_Operations!J13*Pressupostos_Assumpt!C35*Operacao_Operations!J5 -> 0 | K14: =Operacao_Operations!K13*Pressupostos_Assumpt!C35*Operacao_Operations!K5 -> 40600 | L14: =Operacao_Operations!L13*Pressupostos_Assumpt!C35*Operacao_Operations!L5 -> 40600 | M14: =Operacao_Operations!M13*Pressupostos_Assumpt!D35*Operacao_Operations!M5 -> 0 | N14: =Operacao_Operations!N13*Pressupostos_Assumpt!D35*Operacao_Operations!N5 -> 0 | O14: =Operacao_Operations!O13*Pressupostos_Assumpt!D35*Operacao_Operations!O5 -> 0 | P14: =Operacao_Operations!P13*Pressupostos_Assumpt!D35*Operacao_Operations!P5 -> 0 | Q14: =Operacao_Operations!Q13*Pressupostos_Assumpt!D35*Operacao_Operations!Q5 -> 42050 | R14: =Operacao_Operations!R13*Pressupostos_Assumpt!D35*Operacao_Operations!R5 -> 42050 | S14: =C14+D14+E14+F14+G14+H14+I14+J14+K14+L14 -> 81200 | T14: =M14+N14+O14+P14+Q14+R14 -> 84100
B15: Reserva dispositivos / Device reserve | C15: =Pressupostos_Assumpt!C36*Operacao_Operations!C5 -> 22.727273 | D15: =Pressupostos_Assumpt!C36*Operacao_Operations!D5 -> 22.727273 | E15: =Pressupostos_Assumpt!C36*Operacao_Operations!E5 -> 22.727273 | F15: =Pressupostos_Assumpt!C36*Operacao_Operations!F5 -> 22.727273 | G15: =Pressupostos_Assumpt!C36*Operacao_Operations!G5 -> 22.727273 | H15: =Pressupostos_Assumpt!C36*Operacao_Operations!H5 -> 22.727273 | I15: =Pressupostos_Assumpt!C36*Operacao_Operations!I5 -> 22.727273 | J15: =Pressupostos_Assumpt!C36*Operacao_Operations!J5 -> 22.727273 | K15: =Pressupostos_Assumpt!C36*Operacao_Operations!K5 -> 100 | L15: =Pressupostos_Assumpt!C36*Operacao_Operations!L5 -> 100 | M15: =Pressupostos_Assumpt!D36*Operacao_Operations!M5 -> 300 | N15: =Pressupostos_Assumpt!D36*Operacao_Operations!N5 -> 300 | O15: =Pressupostos_Assumpt!D36*Operacao_Operations!O5 -> 300 | P15: =Pressupostos_Assumpt!D36*Operacao_Operations!P5 -> 100 | Q15: =Pressupostos_Assumpt!D36*Operacao_Operations!Q5 -> 100 | R15: =Pressupostos_Assumpt!D36*Operacao_Operations!R5 -> 100 | S15: =C15+D15+E15+F15+G15+H15+I15+J15+K15+L15 -> 381.81818 | T15: =M15+N15+O15+P15+Q15+R15 -> 1200
B16: SUBTOTAL FROTA / FLEET | C16: =SUM(C11:C15) -> 1481.8182 | D16: =SUM(D11:D15) -> 2454.5455 | E16: =SUM(E11:E15) -> 3427.2727 | F16: =SUM(F11:F15) -> 4643.1818 | G16: =SUM(G11:G15) -> 5615.9091 | H16: =SUM(H11:H15) -> 6588.6364 | I16: =SUM(I11:I15) -> 7075 | J16: =SUM(J11:J15) -> 7075 | ... R16: =SUM(R11:R15) -> 73615 | S16: =C16+D16+E16+F16+G16+H16+I16+J16+K16+L16 -> 181821.36 | T16: =M16+N16+O16+P16+Q16+R16 -> 462880
B17: -- OVERHEADS / OVERHEAD --
B18: Contabilidade / Accounting | C18: =Pressupostos_Assumpt!C69*Operacao_Operations!C5 -> 45.454545 | D18: =Pressupostos_Assumpt!C69*Operacao_Operations!D5 -> 45.454545 | E18: =Pressupostos_Assumpt!C69*Operacao_Operations!E5 -> 45.454545 | F18: =Pressupostos_Assumpt!C69*Operacao_Operations!F5 -> 45.454545 | G18: =Pressupostos_Assumpt!C69*Operacao_Operations!G5 -> 45.454545 | H18: =Pressupostos_Assumpt!C69*Operacao_Operations!H5 -> 45.454545 | I18: =Pressupostos_Assumpt!C69*Operacao_Operations!I5 -> 45.454545 | J18: =Pressupostos_Assumpt!C69*Operacao_Operations!J5 -> 45.454545 | K18: =Pressupostos_Assumpt!C69*Operacao_Operations!K5 -> 200 | L18: =Pressupostos_Assumpt!C69*Operacao_Operations!L5 -> 200 | M18: =Pressupostos_Assumpt!D69*Operacao_Operations!M5 -> 618 | N18: =Pressupostos_Assumpt!D69*Operacao_Operations!N5 -> 618 | O18: =Pressupostos_Assumpt!D69*Operacao_Operations!O5 -> 618 | P18: =Pressupostos_Assumpt!D69*Operacao_Operations!P5 -> 206 | Q18: =Pressupostos_Assumpt!D69*Operacao_Operations!Q5 -> 206 | R18: =Pressupostos_Assumpt!D69*Operacao_Operations!R5 -> 206 | S18: =C18+D18+E18+F18+G18+H18+I18+J18+K18+L18 -> 763.63636 | T18: =M18+N18+O18+P18+Q18+R18 -> 2472
B19: Seguro resp. civil / GL insurance | C19: =Pressupostos_Assumpt!C70*Operacao_Operations!C5 -> 56.818182 | D19: =Pressupostos_Assumpt!C70*Operacao_Operations!D5 -> 56.818182 | E19: =Pressupostos_Assumpt!C70*Operacao_Operations!E5 -> 56.818182 | F19: =Pressupostos_Assumpt!C70*Operacao_Operations!F5 -> 56.818182 | G19: =Pressupostos_Assumpt!C70*Operacao_Operations!G5 -> 56.818182 | H19: =Pressupostos_Assumpt!C70*Operacao_Operations!H5 -> 56.818182 | I19: =Pressupostos_Assumpt!C70*Operacao_Operations!I5 -> 56.818182 | J19: =Pressupostos_Assumpt!C70*Operacao_Operations!J5 -> 56.818182 | K19: =Pressupostos_Assumpt!C70*Operacao_Operations!K5 -> 250 | L19: =Pressupostos_Assumpt!C70*Operacao_Operations!L5 -> 250 | M19: =Pressupostos_Assumpt!D70*Operacao_Operations!M5 -> 774 | N19: =Pressupostos_Assumpt!D70*Operacao_Operations!N5 -> 774 | O19: =Pressupostos_Assumpt!D70*Operacao_Operations!O5 -> 774 | P19: =Pressupostos_Assumpt!D70*Operacao_Operations!P5 -> 258 | Q19: =Pressupostos_Assumpt!D70*Operacao_Operations!Q5 -> 258 | R19: =Pressupostos_Assumpt!D70*Operacao_Operations!R5 -> 258 | S19: =C19+D19+E19+F19+G19+H19+I19+J19+K19+L19 -> 954.54545 | T19: =M19+N19+O19+P19+Q19+R19 -> 3096
B20: Dispositivos/SIM / Devices-SIMs | C20: =Operacao_Operations!C6*Pressupostos_Assumpt!C71*Operacao_Operations!C5 -> 17.045455 | D20: =Operacao_Operations!D6*Pressupostos_Assumpt!C71*Operacao_Operations!D5 -> 27.272727 | E20: =Operacao_Operations!E6*Pressupostos_Assumpt!C71*Operacao_Operations!E5 -> 40.909091 | F20: =Operacao_Operations!F6*Pressupostos_Assumpt!C71*Operacao_Operations!F5 -> 54.545455 | G20: =Operacao_Operations!G6*Pressupostos_Assumpt!C71*Operacao_Operations!G5 -> 68.181818 | H20: =Operacao_Operations!H6*Pressupostos_Assumpt!C71*Operacao_Operations!H5 -> 78.409091 | I20: =Operacao_Operations!I6*Pressupostos_Assumpt!C71*Operacao_Operations!I5 -> 85.227273 | J20: =Operacao_Operations!J6*Pressupostos_Assumpt!C71*Operacao_Operations!J5 -> 85.227273 | K20: =Operacao_Operations!K6*Pressupostos_Assumpt!C71*Operacao_Operations!K5 -> 750 | L20: =Operacao_Operations!L6*Pressupostos_Assumpt!C71*Operacao_Operations!L5 -> 750 | M20: =Operacao_Operations!M6*Pressupostos_Assumpt!D71*Operacao_Operations!M5 -> 1125 | N20: =Operacao_Operations!N6*Pressupostos_Assumpt!D71*Operacao_Operations!N5 -> 1125 | O20: =Operacao_Operations!O6*Pressupostos_Assumpt!D71*Operacao_Operations!O5 -> 1125 | P20: =Operacao_Operations!P6*Pressupostos_Assumpt!D71*Operacao_Operations!P5 -> 375 | Q20: =Operacao_Operations!Q6*Pressupostos_Assumpt!D71*Operacao_Operations!Q5 -> 750 | R20: =Operacao_Operations!R6*Pressupostos_Assumpt!D71*Operacao_Operations!R5 -> 750 | S20: =C20+D20+E20+F20+G20+H20+I20+J20+K20+L20 -> 1956.8182 | T20: =M20+N20+O20+P20+Q20+R20 -> 5250
B21: Diversos / Miscellaneous | C21: =Pressupostos_Assumpt!C72*Operacao_Operations!C5 -> 68.181818 | D21: =Pressupostos_Assumpt!C72*Operacao_Operations!D5 -> 68.181818 | E21: =Pressupostos_Assumpt!C72*Operacao_Operations!E5 -> 68.181818 | F21: =Pressupostos_Assumpt!C72*Operacao_Operations!F5 -> 68.181818 | G21: =Pressupostos_Assumpt!C72*Operacao_Operations!G5 -> 68.181818 | H21: =Pressupostos_Assumpt!C72*Operacao_Operations!H5 -> 68.181818 | I21: =Pressupostos_Assumpt!C72*Operacao_Operations!I5 -> 68.181818 | J21: =Pressupostos_Assumpt!C72*Operacao_Operations!J5 -> 68.181818 | K21: =Pressupostos_Assumpt!C72*Operacao_Operations!K5 -> 300 | L21: =Pressupostos_Assumpt!C72*Operacao_Operations!L5 -> 300 | M21: =Pressupostos_Assumpt!D72*Operacao_Operations!M5 -> 927 | N21: =Pressupostos_Assumpt!D72*Operacao_Operations!N5 -> 927 | O21: =Pressupostos_Assumpt!D72*Operacao_Operations!O5 -> 927 | P21: =Pressupostos_Assumpt!D72*Operacao_Operations!P5 -> 309 | Q21: =Pressupostos_Assumpt!D72*Operacao_Operations!Q5 -> 309 | R21: =Pressupostos_Assumpt!D72*Operacao_Operations!R5 -> 309 | S21: =C21+D21+E21+F21+G21+H21+I21+J21+K21+L21 -> 1145.4545 | T21: =M21+N21+O21+P21+Q21+R21 -> 3708
B22: SUBTOTAL OVERHEADS / OVERHEAD | C22: =SUM(C18:C21) -> 187.5 | D22: =SUM(D18:D21) -> 197.72727 | E22: =SUM(E18:E21) -> 211.36364 | F22: =SUM(F18:F21) -> 225 | G22: =SUM(G18:G21) -> 238.63636 | H22: =SUM(H18:H21) -> 248.86364 | I22: =SUM(I18:I21) -> 255.68182 | J22: =SUM(J18:J21) -> 255.68182 | ... R22: =SUM(R18:R21) -> 1523 | S22: =C22+D22+E22+F22+G22+H22+I22+J22+K22+L22 -> 4820.4545 | T22: =M22+N22+O22+P22+Q22+R22 -> 14526
B23: -- INSTALACOES / FACILITIES --
B24: Aluguer parque carrinhas / Van yard rent | C24: =Pressupostos_Assumpt!C78*0.25 -> 500 | D24: =Pressupostos_Assumpt!C78*0.25 -> 500 | E24: =Pressupostos_Assumpt!C78*0.25 -> 500 | F24: =Pressupostos_Assumpt!C78*0.25 -> 500 | G24: =Pressupostos_Assumpt!C78*0.25 -> 500 | H24: =Pressupostos_Assumpt!C78*0.25 -> 500 | I24: =Pressupostos_Assumpt!C78*0.25 -> 500 | J24: =Pressupostos_Assumpt!C78*0.25 -> 500 | K24: =Pressupostos_Assumpt!C78*1 -> 2000 | L24: =Pressupostos_Assumpt!C78*1 -> 2000 | M24: =Pressupostos_Assumpt!D78*3 -> 6180 | N24: =Pressupostos_Assumpt!D78*3 -> 6180 | O24: =Pressupostos_Assumpt!D78*3 -> 6180 | P24: =Pressupostos_Assumpt!D78*1 -> 2060 | Q24: =Pressupostos_Assumpt!D78*1 -> 2060 | R24: =Pressupostos_Assumpt!D78*1 -> 2060 | S24: =C24+D24+E24+F24+G24+H24+I24+J24+K24+L24 -> 8000 | T24: =M24+N24+O24+P24+Q24+R24 -> 24720
B25: SUBTOTAL INSTALACOES / FACILITIES | C25: =SUM(C24:C24) -> 500 | D25: =SUM(D24:D24) -> 500 | E25: =SUM(E24:E24) -> 500 | F25: =SUM(F24:F24) -> 500 | G25: =SUM(G24:G24) -> 500 | H25: =SUM(H24:H24) -> 500 | I25: =SUM(I24:I24) -> 500 | J25: =SUM(J24:J24) -> 500 | ... R25: =SUM(R24:R24) -> 2060 | S25: =C25+D25+E25+F25+G25+H25+I25+J25+K25+L25 -> 8000 | T25: =M25+N25+O25+P25+Q25+R25 -> 24720
B26: CUSTOS OPERACIONAIS TOTAIS / TOTAL OPERATING COSTS | C26: =C9+C16+C22+C25 -> 5591.1875 | D26: =D9+D16+D22+D25 -> 8106.3466 | E26: =E9+E16+E22+E25 -> 10624.915 | F26: =F9+F16+F22+F25 -> 13769.716 | G26: =G9+G16+G22+G25 -> 16288.284 | H26: =H9+H16+H22+H25 -> 18803.443 | I26: =I9+I16+I22+I25 -> 20062.727 | J26: =J9+J16+J22+J25 -> 20062.727 | ... R26: =R9+R16+R22+R25 -> 177904.64 | S26: =C26+D26+E26+F26+G26+H26+I26+J26+K26+L26 -> 464907.35 | T26: =M26+N26+O26+P26+Q26+R26 -> 1243125.6
B29: RESUMO MENSAL / MONTHLY BREAKDOWN
C30: 2026 (Set-Dez) | G30: 2027
B31: POR MES / BY MONTH | C31: Set/Sep 26 | D31: Out/Oct 26 | E31: Nov 26 | F31: Dez/Dec 26 | G31: Jan 27 | H31: Fev/Feb 27 | I31: Mar 27 | J31: Abr/Apr 27 | K31: Mai/May 27 | L31: Jun 27 | M31: Jul 27 | N31: Ago/Aug 27 | O31: Set/Sep 27 | P31: Out/Oct 27 | Q31: Nov 27 | R31: Dez/Dec 27
B32: Mao-de-obra / Labour | C32: =C9+D9+E9+F9 -> 23263.756 | D32: =G9+H9+I9+J9 -> 45863.773 | E32: =K9 -> 100569 | F32: =L9 -> 100569 | G32: =(M9)/3 -> 53958.638 | H32: =(M9)/3 -> 53958.638 | I32: =(M9)/3 -> 53958.638 | J32: =(N9)/3 -> 53958.638 | K32: =(N9)/3 -> 53958.638 | L32: =(N9)/3 -> 53958.638 | M32: =(O9)/3 -> 53958.638 | N32: =(O9)/3 -> 53958.638 | O32: =(O9)/3 -> 53958.638 | P32: =P9 -> 53958.638 | Q32: =Q9 -> 100706.64 | R32: =R9 -> 100706.64
B33: Frota / Fleet | C33: =C16+D16+E16+F16 -> 12006.818 | D33: =G16+H16+I16+J16 -> 26354.545 | E33: =K16 -> 71730 | F33: =L16 -> 71730 | G33: =(M16)/3 -> 31565 | H33: =(M16)/3 -> 31565 | I33: =(M16)/3 -> 31565 | J33: =(N16)/3 -> 31565 | K33: =(N16)/3 -> 31565 | L33: =(N16)/3 -> 31565 | M33: =(O16)/3 -> 31565 | N33: =(O16)/3 -> 31565 | O33: =(O16)/3 -> 31565 | P33: =P16 -> 31565 | Q33: =Q16 -> 73615 | R33: =R16 -> 73615
B34: Overheads / Overhead | C34: =C22+D22+E22+F22 -> 821.59091 | D34: =G22+H22+I22+J22 -> 998.86364 | E34: =K22 -> 1500 | F34: =L22 -> 1500 | G34: =(M22)/3 -> 1148 | H34: =(M22)/3 -> 1148 | I34: =(M22)/3 -> 1148 | J34: =(N22)/3 -> 1148 | K34: =(N22)/3 -> 1148 | L34: =(N22)/3 -> 1148 | M34: =(O22)/3 -> 1148 | N34: =(O22)/3 -> 1148 | O34: =(O22)/3 -> 1148 | P34: =P22 -> 1148 | Q34: =Q22 -> 1523 | R34: =R22 -> 1523
B35: Instalacoes / Facilities | C35: =C25+D25+E25+F25 -> 2000 | D35: =G25+H25+I25+J25 -> 2000 | E35: =K25 -> 2000 | F35: =L25 -> 2000 | G35: =(M25)/3 -> 2060 | H35: =(M25)/3 -> 2060 | I35: =(M25)/3 -> 2060 | J35: =(N25)/3 -> 2060 | K35: =(N25)/3 -> 2060 | L35: =(N25)/3 -> 2060 | M35: =(O25)/3 -> 2060 | N35: =(O25)/3 -> 2060 | O35: =(O25)/3 -> 2060 | P35: =P25 -> 2060 | Q35: =Q25 -> 2060 | R35: =R25 -> 2060
B36: CUSTOS OPERACIONAIS TOTAIS / TOTAL | C36: =C26+D26+E26+F26 -> 38092.165 | D36: =G26+H26+I26+J26 -> 75217.182 | E36: =K26 -> 175799 | F36: =L26 -> 175799 | G36: =(M26)/3 -> 88731.637 | H36: =(M26)/3 -> 88731.637 | I36: =(M26)/3 -> 88731.637 | J36: =(N26)/3 -> 88731.637 | K36: =(N26)/3 -> 88731.637 | L36: =(N26)/3 -> 88731.637 | M36: =(O26)/3 -> 88731.637 | N36: =(O26)/3 -> 88731.637 | O36: =(O26)/3 -> 88731.637 | P36: =P26 -> 88731.638 | Q36: =Q26 -> 177904.64 | R36: =R26 -> 177904.64
B39: RESUMO TRIMESTRAL / QUARTERLY BREAKDOWN
C40: 2026 | E40: 2027
B41: POR TRIMESTRE / BY QUARTER | C41: Q3 2026 Set/Sep 26 | D41: Q4 2026 Out-Dez/Oct-Dec 26 | E41: Q1 2027 Jan-Mar 27 | F41: Q2 2027 Abr-Jun/Apr-Jun 27 | G41: Q3 2027 Jul-Set/Jul-Sep 27 | H41: Q4 2027 Out-Dez/Oct-Dec 27
B42: Mao-de-obra / Labour | C42: =SUM(C9:F9) -> 23263.756 | D42: =SUM(G9:L9) -> 247001.77 | E42: =SUM(M9:M9) -> 161875.91 | F42: =SUM(N9:N9) -> 161875.91 | G42: =SUM(O9:O9) -> 161875.91 | H42: =SUM(P9:R9) -> 255371.91
B43: Frota / Fleet | C43: =SUM(C16:F16) -> 12006.818 | D43: =SUM(G16:L16) -> 169814.55 | E43: =SUM(M16:M16) -> 94695 | F43: =SUM(N16:N16) -> 94695 | G43: =SUM(O16:O16) -> 94695 | H43: =SUM(P16:R16) -> 178795
B44: Overheads / Overhead | C44: =SUM(C22:F22) -> 821.59091 | D44: =SUM(G22:L22) -> 3998.8636 | E44: =SUM(M22:M22) -> 3444 | F44: =SUM(N22:N22) -> 3444 | G44: =SUM(O22:O22) -> 3444 | H44: =SUM(P22:R22) -> 4194
B45: Instalacoes / Facilities | C45: =SUM(C25:F25) -> 2000 | D45: =SUM(G25:L25) -> 6000 | E45: =SUM(M25:M25) -> 6180 | F45: =SUM(N25:N25) -> 6180 | G45: =SUM(O25:O25) -> 6180 | H45: =SUM(P25:R25) -> 6180
B46: CUSTOS OPERACIONAIS TOTAIS / TOTAL | C46: =SUM(C26:F26) -> 38092.165 | D46: =SUM(G26:L26) -> 426815.18 | E46: =SUM(M26:M26) -> 266194.91 | F46: =SUM(N26:N26) -> 266194.91 | G46: =SUM(O26:O26) -> 266194.91 | H46: =SUM(P26:R26) -> 444540.91

Sheet DRE_PL
B1: DEMONSTRACAO DE RESULTADOS / PROFIT & LOSS
C2: ANO 2026 / YEAR 2026 (Ago-Dez/Aug-Dec) | M2: ANO 2027 / YEAR 2027
B3: Rubrica / Item | C3: S1 Set/Sep 26 | D3: S2 Set/Sep 26 | E3: S3 Set/Sep 26 | F3: S4 Set/Sep 26 | G3: S5 Out/Oct 26 | H3: S6 Out/Oct 26 | I3: S7 Out/Oct 26 | J3: S8 Out/Oct 26 | K3: Nov Nov 26 (Pico/Peak) | L3: Dez Dez/Dec 26 (Pico/Peak) | M3: Q1'27 Jan-Mar 27 | N3: Q2'27 Abr-Jun/Apr-Jun 27 | O3: Q3'27 Jul-Set/Jul-Sep 27 | P3: Out'27 Out/Oct 27 | Q3: Nov'27 Nov 27 (Pico/Peak) | R3: Dez'27 Dez/Dec 27 (Pico/Peak) | S3: Total 2026 | T3: Total 2027
B4: RECEITA TOTAL / TOTAL REVENUE | C4: =Receita_Revenue!C9 -> 4689.3864 | D4: =Receita_Revenue!D9 -> 7434.8364 | E4: =Receita_Revenue!E9 -> 11095.436 | F4: =Receita_Revenue!F9 -> 14756.036 | G4: =Receita_Revenue!G9 -> 18416.636 | H4: =Receita_Revenue!H9 -> 21162.086 | I4: =Receita_Revenue!I9 -> 22992.386 | J4: =Receita_Revenue!J9 -> 22992.386 | ... R4: =Receita_Revenue!R9 -> 198812.4 | S4: =C4+D4+E4+F4+G4+H4+I4+J4+K4+L4 -> 527961.99 | T4: =M4+N4+O4+P4+Q4+R4 -> 1392389.4
B5: Custos operacionais / Operating costs | C5: =Custos_Costs!C26 -> 5591.1875 | D5: =Custos_Costs!D26 -> 8106.3466 | E5: =Custos_Costs!E26 -> 10624.915 | F5: =Custos_Costs!F26 -> 13769.716 | G5: =Custos_Costs!G26 -> 16288.284 | H5: =Custos_Costs!H26 -> 18803.443 | I5: =Custos_Costs!I26 -> 20062.727 | J5: =Custos_Costs!J26 -> 20062.727 | ... R5: =Custos_Costs!R26 -> 177904.64 | S5: =C5+D5+E5+F5+G5+H5+I5+J5+K5+L5 -> 464907.35 | T5: =M5+N5+O5+P5+Q5+R5 -> 1243125.6
B6: EBITDA | C6: =C4-C5 -> -901.80114 | D6: =D4-D5 -> -671.51023 | E6: =E4-E5 -> 470.52159 | F6: =F4-F5 -> 986.32045 | G6: =G4-G5 -> 2128.3523 | H6: =H4-H5 -> 2358.6432 | I6: =I4-I5 -> 2929.6591 | J6: =J4-J5 -> 2929.6591 | ... R6: =R4-R5 -> 20907.762 | S6: =C6+D6+E6+F6+G6+H6+I6+J6+K6+L6 -> 63054.644 | T6: =M6+N6+O6+P6+Q6+R6 -> 149263.75
B7: Margem EBITDA / EBITDA margin % | C7: =IF(C4=0,0,C6/C4) -> -0.19230685 | D7: =IF(D4=0,0,D6/D4) -> -0.090319436 | E7: =IF(E4=0,0,E6/E4) -> 0.042406768 | F7: =IF(F4=0,0,F6/F4) -> 0.066841829 | G7: =IF(G4=0,0,G6/G4) -> 0.11556683 | H7: =IF(H4=0,0,H6/H4) -> 0.11145608 | I7: =IF(I4=0,0,I6/I4) -> 0.12741866 | J7: =IF(J4=0,0,J6/J4) -> 0.12741866 | ... T7: =IF(T4=0,0,T6/T4) -> 0.10719972
B8: Depreciacao / Depreciation | C8: =Operacao_Operations!C12*Pressupostos_Assumpt!C32*Pressupostos_Assumpt!C50*Operacao_Operations!C5 -> 0 | D8: =Operacao_Operations!D12*Pressupostos_Assumpt!C32*Pressupostos_Assumpt!C50*Operacao_Operations!D5 -> 0 | E8: =Operacao_Operations!E12*Pressupostos_Assumpt!C32*Pressupostos_Assumpt!C50*Operacao_Operations!E5 -> 0 | F8: =Operacao_Operations!F12*Pressupostos_Assumpt!C32*Pressupostos_Assumpt!C50*Operacao_Operations!F5 -> 0 | G8: =Operacao_Operations!G12*Pressupostos_Assumpt!C32*Pressupostos_Assumpt!C50*Operacao_Operations!G5 -> 0 | H8: =Operacao_Operations!H12*Pressupostos_Assumpt!C32*Pressupostos_Assumpt!C50*Operacao_Operations!H5 -> 0 | I8: =Operacao_Operations!I12*Pressupostos_Assumpt!C32*Pressupostos_Assumpt!C50*Operacao_Operations!I5 -> 0 | J8: =Operacao_Operations!J12*Pressupostos_Assumpt!C32*Pressupostos_Assumpt!C50*Operacao_Operations!J5 -> 0 | K8: =Operacao_Operations!K12*Pressupostos_Assumpt!C32*Pressupostos_Assumpt!C50*Operacao_Operations!K5 -> 0 | L8: =Operacao_Operations!L12*Pressupostos_Assumpt!C32*Pressupostos_Assumpt!C50*Operacao_Operations!L5 -> 0 | M8: =Operacao_Operations!M12*Pressupostos_Assumpt!D32*Pressupostos_Assumpt!D50*Operacao_Operations!M5 -> 0 | N8: =Operacao_Operations!N12*Pressupostos_Assumpt!D32*Pressupostos_Assumpt!D50*Operacao_Operations!N5 -> 0 | O8: =Operacao_Operations!O12*Pressupostos_Assumpt!D32*Pressupostos_Assumpt!D50*Operacao_Operations!O5 -> 0 | P8: =Operacao_Operations!P12*Pressupostos_Assumpt!D32*Pressupostos_Assumpt!D50*Operacao_Operations!P5 -> 0 | Q8: =Operacao_Operations!Q12*Pressupostos_Assumpt!D32*Pressupostos_Assumpt!D50*Operacao_Operations!Q5 -> 0 | R8: =Operacao_Operations!R12*Pressupostos_Assumpt!D32*Pressupostos_Assumpt!D50*Operacao_Operations!R5 -> 0 | S8: =C8+D8+E8+F8+G8+H8+I8+J8+K8+L8 -> 0 | T8: =M8+N8+O8+P8+Q8+R8 -> 0
B9: EBIT | C9: =C6-C8 -> -901.80114 | D9: =D6-D8 -> -671.51023 | E9: =E6-E8 -> 470.52159 | F9: =F6-F8 -> 986.32045 | G9: =G6-G8 -> 2128.3523 | H9: =H6-H8 -> 2358.6432 | I9: =I6-I8 -> 2929.6591 | J9: =J6-J8 -> 2929.6591 | ... R9: =R6-R8 -> 20907.762 | S9: =C9+D9+E9+F9+G9+H9+I9+J9+K9+L9 -> 63054.644 | T9: =M9+N9+O9+P9+Q9+R9 -> 149263.75
B10: Juros / Interest | C10: 0 | D10: 0 | E10: 0 | F10: 0 | G10: 0 | H10: 0 | I10: 0 | J10: 0 | K10: 0 | L10: 0 | M10: 0 | N10: 0 | O10: 0 | P10: 0 | Q10: 0 | R10: 0 | S10: =C10+D10+E10+F10+G10+H10+I10+J10+K10+L10 -> 0 | T10: =M10+N10+O10+P10+Q10+R10 -> 0
B11: EBT (Result. antes imp.) / Pre-tax | C11: =C9-C10 -> -901.80114 | D11: =D9-D10 -> -671.51023 | E11: =E9-E10 -> 470.52159 | F11: =F9-F10 -> 986.32045 | G11: =G9-G10 -> 2128.3523 | H11: =H9-H10 -> 2358.6432 | I11: =I9-I10 -> 2929.6591 | J11: =J9-J10 -> 2929.6591 | ... R11: =R9-R10 -> 20907.762 | S11: =C11+D11+E11+F11+G11+H11+I11+J11+K11+L11 -> 63054.644 | T11: =M11+N11+O11+P11+Q11+R11 -> 149263.75
B12: IRC (21%) | C12: =IF(C11>0,C11*Pressupostos_Assumpt!C74,0) -> 0 | D12: =IF(D11>0,D11*Pressupostos_Assumpt!C74,0) -> 0 | E12: =IF(E11>0,E11*Pressupostos_Assumpt!C74,0) -> 98.809534 | F12: =IF(F11>0,F11*Pressupostos_Assumpt!C74,0) -> 207.1273 | G12: =IF(G11>0,G11*Pressupostos_Assumpt!C74,0) -> 446.95398 | H12: =IF(H11>0,H11*Pressupostos_Assumpt!C74,0) -> 495.31507 | I12: =IF(I11>0,I11*Pressupostos_Assumpt!C74,0) -> 615.22841 | J12: =IF(J11>0,J11*Pressupostos_Assumpt!C74,0) -> 615.22841 | K12: =IF(K11>0,K11*Pressupostos_Assumpt!C74,0) -> 5546.604 | L12: =IF(L11>0,L11*Pressupostos_Assumpt!C74,0) -> 5546.604 | M12: =IF(M11>0,M11*Pressupostos_Assumpt!D74,0) -> 6644.0824 | N12: =IF(N11>0,N11*Pressupostos_Assumpt!D74,0) -> 6822.8764 | O12: =IF(O11>0,O11*Pressupostos_Assumpt!D74,0) -> 6822.8764 | P12: =IF(P11>0,P11*Pressupostos_Assumpt!D74,0) -> 2274.2921 | Q12: =IF(Q11>0,Q11*Pressupostos_Assumpt!D74,0) -> 4390.6301 | R12: =IF(R11>0,R11*Pressupostos_Assumpt!D74,0) -> 4390.6301 | S12: =C12+D12+E12+F12+G12+H12+I12+J12+K12+L12 -> 13571.871 | T12: =M12+N12+O12+P12+Q12+R12 -> 31345.388
B13: RESULTADO LIQUIDO / NET PROFIT (LOSS) | C13: =C11-C12 -> -901.80114 | D13: =D11-D12 -> -671.51023 | E13: =E11-E12 -> 371.71206 | F13: =F11-F12 -> 779.19316 | G13: =G11-G12 -> 1681.3983 | H13: =H11-H12 -> 1863.3281 | I13: =I11-I12 -> 2314.4307 | J13: =J11-J12 -> 2314.4307 | ... R13: =R11-R12 -> 16517.132 | S13: =C13+D13+E13+F13+G13+H13+I13+J13+K13+L13 -> 49482.774 | T13: =M13+N13+O13+P13+Q13+R13 -> 117918.36
B14: Margem liquida / Net margin % | C14: =IF(C4=0,0,C13/C4) -> -0.19230685 | D14: =IF(D4=0,0,D13/D4) -> -0.090319436 | E14: =IF(E4=0,0,E13/E4) -> 0.033501346 | F14: =IF(F4=0,0,F13/F4) -> 0.052805045 | G14: =IF(G4=0,0,G13/G4) -> 0.091297795 | H14: =IF(H4=0,0,H13/H4) -> 0.088050303 | I14: =IF(I4=0,0,I13/I4) -> 0.10066074 | J14: =IF(J4=0,0,J13/J4) -> 0.10066074 | ... T14: =IF(T4=0,0,T13/T4) -> 0.084687777
B17: RESUMO MENSAL / MONTHLY BREAKDOWN
C18: 2026 (Set-Dez) | G18: 2027
B19: POR MES / BY MONTH | C19: Set/Sep 26 | D19: Out/Oct 26 | E19: Nov 26 | F19: Dez/Dec 26 | G19: Jan 27 | H19: Fev/Feb 27 | I19: Mar 27 | J19: Abr/Apr 27 | K19: Mai/May 27 | L19: Jun 27 | M19: Jul 27 | N19: Ago/Aug 27 | O19: Set/Sep 27 | P19: Out/Oct 27 | Q19: Nov 27 | R19: Dez/Dec 27
B20: RECEITA TOTAL / TOTAL REVENUE | C20: =C4+D4+E4+F4 -> 37975.695 | D20: =G4+H4+I4+J4 -> 85563.495 | E20: =K4 -> 202211.4 | F20: =L4 -> 202211.4 | G20: =(M4)/3 -> 99277.8 | H20: =(M4)/3 -> 99277.8 | I20: =(M4)/3 -> 99277.8 | J20: =(N4)/3 -> 99561.6 | K20: =(N4)/3 -> 99561.6 | L20: =(N4)/3 -> 99561.6 | M20: =(O4)/3 -> 99561.6 | N20: =(O4)/3 -> 99561.6 | O20: =(O4)/3 -> 99561.6 | P20: =P4 -> 99561.6 | Q20: =Q4 -> 198812.4 | R20: =R4 -> 198812.4
B21: Custos operacionais / Operating costs | C21: =C5+D5+E5+F5 -> 38092.165 | D21: =G5+H5+I5+J5 -> 75217.182 | E21: =K5 -> 175799 | F21: =L5 -> 175799 | G21: =(M5)/3 -> 88731.637 | H21: =(M5)/3 -> 88731.637 | I21: =(M5)/3 -> 88731.637 | J21: =(N5)/3 -> 88731.637 | K21: =(N5)/3 -> 88731.637 | L21: =(N5)/3 -> 88731.637 | M21: =(O5)/3 -> 88731.637 | N21: =(O5)/3 -> 88731.637 | O21: =(O5)/3 -> 88731.637 | P21: =P5 -> 88731.638 | Q21: =Q5 -> 177904.64 | R21: =R5 -> 177904.64
B22: EBITDA | C22: =C6+D6+E6+F6 -> -116.46932 | D22: =G6+H6+I6+J6 -> 10346.314 | E22: =K6 -> 26412.4 | F22: =L6 -> 26412.4 | G22: =(M6)/3 -> 10546.163 | H22: =(M6)/3 -> 10546.163 | I22: =(M6)/3 -> 10546.163 | J22: =(N6)/3 -> 10829.963 | K22: =(N6)/3 -> 10829.963 | L22: =(N6)/3 -> 10829.963 | M22: =(O6)/3 -> 10829.963 | N22: =(O6)/3 -> 10829.963 | O22: =(O6)/3 -> 10829.963 | P22: =P6 -> 10829.962 | Q22: =Q6 -> 20907.762 | R22: =R6 -> 20907.762
B23: Margem EBITDA / EBITDA margin % | C23: =IF((C4+D4+E4+F4)=0,0,(C6+D6+E6+F6)/(C4+D4+E4+F4)) -> -0.0030669437 | D23: =IF((G4+H4+I4+J4)=0,0,(G6+H6+I6+J6)/(G4+H4+I4+J4)) -> 0.12091972 | E23: =IF((K4)=0,0,(K6)/(K4)) -> 0.13061776 | F23: =IF((L4)=0,0,(L6)/(L4)) -> 0.13061776 | G23: =IF((M4)=0,0,(M6)/(M4)) -> 0.10622881 | H23: =IF((M4)=0,0,(M6)/(M4)) -> 0.10622881 | I23: =IF((M4)=0,0,(M6)/(M4)) -> 0.10622881 | J23: =IF((N4)=0,0,(N6)/(N4)) -> 0.1087765 | K23: =IF((N4)=0,0,(N6)/(N4)) -> 0.1087765 | L23: =IF((N4)=0,0,(N6)/(N4)) -> 0.1087765 | M23: =IF((O4)=0,0,(O6)/(O4)) -> 0.1087765 | N23: =IF((O4)=0,0,(O6)/(O4)) -> 0.1087765 | O23: =IF((O4)=0,0,(O6)/(O4)) -> 0.1087765 | P23: =IF((P4)=0,0,(P6)/(P4)) -> 0.1087765 | Q23: =IF((Q4)=0,0,(Q6)/(Q4)) -> 0.10516327 | R23: =IF((R4)=0,0,(R6)/(R4)) -> 0.10516327
B24: Depreciacao / Depreciation | C24: =C8+D8+E8+F8 -> 0 | D24: =G8+H8+I8+J8 -> 0 | E24: =K8 -> 0 | F24: =L8 -> 0 | G24: =(M8)/3 -> 0 | H24: =(M8)/3 -> 0 | I24: =(M8)/3 -> 0 | J24: =(N8)/3 -> 0 | K24: =(N8)/3 -> 0 | L24: =(N8)/3 -> 0 | M24: =(O8)/3 -> 0 | N24: =(O8)/3 -> 0 | O24: =(O8)/3 -> 0 | P24: =P8 -> 0 | Q24: =Q8 -> 0 | R24: =R8 -> 0
B25: EBIT | C25: =C9+D9+E9+F9 -> -116.46932 | D25: =G9+H9+I9+J9 -> 10346.314 | E25: =K9 -> 26412.4 | F25: =L9 -> 26412.4 | G25: =(M9)/3 -> 10546.163 | H25: =(M9)/3 -> 10546.163 | I25: =(M9)/3 -> 10546.163 | J25: =(N9)/3 -> 10829.963 | K25: =(N9)/3 -> 10829.963 | L25: =(N9)/3 -> 10829.963 | M25: =(O9)/3 -> 10829.963 | N25: =(O9)/3 -> 10829.963 | O25: =(O9)/3 -> 10829.963 | P25: =P9 -> 10829.962 | Q25: =Q9 -> 20907.762 | R25: =R9 -> 20907.762
B26: IRC (21%) | C26: =C12+D12+E12+F12 -> 305.93683 | D26: =G12+H12+I12+J12 -> 2172.7259 | E26: =K12 -> 5546.604 | F26: =L12 -> 5546.604 | G26: =(M12)/3 -> 2214.6941 | H26: =(M12)/3 -> 2214.6941 | I26: =(M12)/3 -> 2214.6941 | J26: =(N12)/3 -> 2274.2921 | K26: =(N12)/3 -> 2274.2921 | L26: =(N12)/3 -> 2274.2921 | M26: =(O12)/3 -> 2274.2921 | N26: =(O12)/3 -> 2274.2921 | O26: =(O12)/3 -> 2274.2921 | P26: =P12 -> 2274.2921 | Q26: =Q12 -> 4390.6301 | R26: =R12 -> 4390.6301
B27: RESULTADO LIQUIDO / NET PROFIT (LOSS) | C27: =C13+D13+E13+F13 -> -422.40615 | D27: =G13+H13+I13+J13 -> 8173.5878 | E27: =K13 -> 20865.796 | F27: =L13 -> 20865.796 | G27: =(M13)/3 -> 8331.4684 | H27: =(M13)/3 -> 8331.4684 | I27: =(M13)/3 -> 8331.4684 | J27: =(N13)/3 -> 8555.6704 | K27: =(N13)/3 -> 8555.6704 | L27: =(N13)/3 -> 8555.6704 | M27: =(O13)/3 -> 8555.6704 | N27: =(O13)/3 -> 8555.6704 | O27: =(O13)/3 -> 8555.6704 | P27: =P13 -> 8555.6704 | Q27: =Q13 -> 16517.132 | R27: =R13 -> 16517.132
B28: Margem liquida / Net margin % | C28: =IF((C4+D4+E4+F4)=0,0,(C13+D13+E13+F13)/(C4+D4+E4+F4)) -> -0.011123065 | D28: =IF((G4+H4+I4+J4)=0,0,(G13+H13+I13+J13)/(G4+H4+I4+J4)) -> 0.095526576 | E28: =IF((K4)=0,0,(K13)/(K4)) -> 0.10318803 | F28: =IF((L4)=0,0,(L13)/(L4)) -> 0.10318803 | G28: =IF((M4)=0,0,(M13)/(M4)) -> 0.083920759 | H28: =IF((M4)=0,0,(M13)/(M4)) -> 0.083920759 | I28: =IF((M4)=0,0,(M13)/(M4)) -> 0.083920759 | J28: =IF((N4)=0,0,(N13)/(N4)) -> 0.085933436 | K28: =IF((N4)=0,0,(N13)/(N4)) -> 0.085933436 | L28: =IF((N4)=0,0,(N13)/(N4)) -> 0.085933436 | M28: =IF((O4)=0,0,(O13)/(O4)) -> 0.085933436 | N28: =IF((O4)=0,0,(O13)/(O4)) -> 0.085933436 | O28: =IF((O4)=0,0,(O13)/(O4)) -> 0.085933436 | P28: =IF((P4)=0,0,(P13)/(P4)) -> 0.085933436 | Q28: =IF((Q4)=0,0,(Q13)/(Q4)) -> 0.083078985 | R28: =IF((R4)=0,0,(R13)/(R4)) -> 0.083078985
B31: RESUMO TRIMESTRAL / QUARTERLY BREAKDOWN
C32: 2026 | E32: 2027
B33: POR TRIMESTRE / BY QUARTER | C33: Q3 2026 Set/Sep 26 | D33: Q4 2026 Out-Dez/Oct-Dec 26 | E33: Q1 2027 Jan-Mar 27 | F33: Q2 2027 Abr-Jun/Apr-Jun 27 | G33: Q3 2027 Jul-Set/Jul-Sep 27 | H33: Q4 2027 Out-Dez/Oct-Dec 27
B34: RECEITA TOTAL / TOTAL REVENUE | C34: =SUM(C4:F4) -> 37975.695 | D34: =SUM(G4:L4) -> 489986.3 | E34: =SUM(M4:M4) -> 297833.4 | F34: =SUM(N4:N4) -> 298684.8 | G34: =SUM(O4:O4) -> 298684.8 | H34: =SUM(P4:R4) -> 497186.4
B35: Custos operacionais / Operating costs | C35: =SUM(C5:F5) -> 38092.165 | D35: =SUM(G5:L5) -> 426815.18 | E35: =SUM(M5:M5) -> 266194.91 | F35: =SUM(N5:N5) -> 266194.91 | G35: =SUM(O5:O5) -> 266194.91 | H35: =SUM(P5:R5) -> 444540.91
B36: EBITDA | C36: =SUM(C6:F6) -> -116.46932 | D36: =SUM(G6:L6) -> 63171.114 | E36: =SUM(M6:M6) -> 31638.488 | F36: =SUM(N6:N6) -> 32489.888 | G36: =SUM(O6:O6) -> 32489.888 | H36: =SUM(P6:R6) -> 52645.487
B37: Margem EBITDA / EBITDA margin % | C37: =IF(SUM(C4:F4)=0,0,SUM(C6:F6)/SUM(C4:F4)) -> -0.0030669437 | D37: =IF(SUM(G4:L4)=0,0,SUM(G6:L6)/SUM(G4:L4)) -> 0.12892425 | E37: =IF(SUM(M4:M4)=0,0,SUM(M6:M6)/SUM(M4:M4)) -> 0.10622881 | F37: =IF(SUM(N4:N4)=0,0,SUM(N6:N6)/SUM(N4:N4)) -> 0.1087765 | G37: =IF(SUM(O4:O4)=0,0,SUM(O6:O6)/SUM(O4:O4)) -> 0.1087765 | H37: =IF(SUM(P4:R4)=0,0,SUM(P6:R6)/SUM(P4:R4)) -> 0.10588682
B38: Depreciacao / Depreciation | C38: =SUM(C8:F8) -> 0 | D38: =SUM(G8:L8) -> 0 | E38: =SUM(M8:M8) -> 0 | F38: =SUM(N8:N8) -> 0 | G38: =SUM(O8:O8) -> 0 | H38: =SUM(P8:R8) -> 0
B39: EBIT | C39: =SUM(C9:F9) -> -116.46932 | D39: =SUM(G9:L9) -> 63171.114 | E39: =SUM(M9:M9) -> 31638.488 | F39: =SUM(N9:N9) -> 32489.888 | G39: =SUM(O9:O9) -> 32489.888 | H39: =SUM(P9:R9) -> 52645.487
B40: IRC (21%) | C40: =SUM(C12:F12) -> 305.93683 | D40: =SUM(G12:L12) -> 13265.934 | E40: =SUM(M12:M12) -> 6644.0824 | F40: =SUM(N12:N12) -> 6822.8764 | G40: =SUM(O12:O12) -> 6822.8764 | H40: =SUM(P12:R12) -> 11055.552
B41: RESULTADO LIQUIDO / NET PROFIT (LOSS) | C41: =SUM(C13:F13) -> -422.40615 | D41: =SUM(G13:L13) -> 49905.18 | E41: =SUM(M13:M13) -> 24994.405 | F41: =SUM(N13:N13) -> 25667.011 | G41: =SUM(O13:O13) -> 25667.011 | H41: =SUM(P13:R13) -> 41589.935
B42: Margem liquida / Net margin % | C42: =IF(SUM(C4:F4)=0,0,SUM(C13:F13)/SUM(C4:F4)) -> -0.011123065 | D42: =IF(SUM(G4:L4)=0,0,SUM(G13:L13)/SUM(G4:L4)) -> 0.10185015 | E42: =IF(SUM(M4:M4)=0,0,SUM(M13:M13)/SUM(M4:M4)) -> 0.083920759 | F42: =IF(SUM(N4:N4)=0,0,SUM(N13:N13)/SUM(N4:N4)) -> 0.085933436 | G42: =IF(SUM(O4:O4)=0,0,SUM(O13:O13)/SUM(O4:O4)) -> 0.085933436 | H42: =IF(SUM(P4:R4)=0,0,SUM(P13:R13)/SUM(P4:R4)) -> 0.083650589

Sheet Tesouraria_CashFlow
B1: TESOURARIA / CASH FLOW
C2: ANO 2026 / YEAR 2026 (Ago-Dez/Aug-Dec) | M2: ANO 2027 / YEAR 2027
B3: Rubrica / Item | C3: S1 Set/Sep 26 | D3: S2 Set/Sep 26 | E3: S3 Set/Sep 26 | F3: S4 Set/Sep 26 | G3: S5 Out/Oct 26 | H3: S6 Out/Oct 26 | I3: S7 Out/Oct 26 | J3: S8 Out/Oct 26 | K3: Nov Nov 26 (Pico/Peak) | L3: Dez Dez/Dec 26 (Pico/Peak) | M3: Q1'27 Jan-Mar 27 | N3: Q2'27 Abr-Jun/Apr-Jun 27 | O3: Q3'27 Jul-Set/Jul-Sep 27 | P3: Out'27 Out/Oct 27 | Q3: Nov'27 Nov 27 (Pico/Peak) | R3: Dez'27 Dez/Dec 27 (Pico/Peak) | S3: Total 2026 | T3: Total 2027
B4: Resultado liquido / Net profit (loss) | C4: =DRE_PL!C13 -> -901.80114 | D4: =DRE_PL!D13 -> -671.51023 | E4: =DRE_PL!E13 -> 371.71206 | F4: =DRE_PL!F13 -> 779.19316 | G4: =DRE_PL!G13 -> 1681.3983 | H4: =DRE_PL!H13 -> 1863.3281 | I4: =DRE_PL!I13 -> 2314.4307 | J4: =DRE_PL!J13 -> 2314.4307 | ... R4: =DRE_PL!R13 -> 16517.132 | S4: =C4+D4+E4+F4+G4+H4+I4+J4+K4+L4 -> 49482.774 | T4: =M4+N4+O4+P4+Q4+R4 -> 117918.36
B5: (+) Depreciacao / Depreciation add-back | C5: =DRE_PL!C8 -> 0 | D5: =DRE_PL!D8 -> 0 | E5: =DRE_PL!E8 -> 0 | F5: =DRE_PL!F8 -> 0 | G5: =DRE_PL!G8 -> 0 | H5: =DRE_PL!H8 -> 0 | I5: =DRE_PL!I8 -> 0 | J5: =DRE_PL!J8 -> 0 | ... R5: =DRE_PL!R8 -> 0 | S5: =C5+D5+E5+F5+G5+H5+I5+J5+K5+L5 -> 0 | T5: =M5+N5+O5+P5+Q5+R5 -> 0
B6: (+/-) Fundo maneio (receb./pagam.) + IVA / Working capital + VAT | C6: =C22+C23+IVA_VAT!C29 -> -2503.158 | D6: =D22+D23+IVA_VAT!D29 -> -1757.7203 | E6: =E22+E23+IVA_VAT!E29 -> -2676.1025 | F6: =F22+F23+IVA_VAT!F29 -> -2426.746 | G6: =G22+G23+IVA_VAT!G29 -> -2676.1025 | H6: =H22+H23+IVA_VAT!H29 -> -1757.7203 | I6: =I22+I23+IVA_VAT!I29 -> -1338.0512 | J6: =J22+J23+IVA_VAT!J29 -> 0 | ... R6: =R22+R23+IVA_VAT!R29 -> 0 | S6: =C6+D6+E6+F6+G6+H6+I6+J6+K6+L6 -> -138349.12 | T6: =M6+N6+O6+P6+Q6+R6 -> 5357.915
B7: CASH FLOW OPERACIONAL / OPERATING CF | C7: =C4+C5+C6 -> -3404.9591 | D7: =D4+D5+D6 -> -2429.2306 | E7: =E4+E5+E6 -> -2304.3904 | F7: =F4+F5+F6 -> -1647.5528 | G7: =G4+G5+G6 -> -994.7042 | H7: =H4+H5+H6 -> 105.60777 | I7: =I4+I5+I6 -> 976.37943 | J7: =J4+J5+J6 -> 2314.4307 | ... R7: =R4+R5+R6 -> 16517.132 | S7: =C7+D7+E7+F7+G7+H7+I7+J7+K7+L7 -> -88866.348 | T7: =M7+N7+O7+P7+Q7+R7 -> 123276.28
B8: (-) CAPEX | C8: 0 | D8: 0 | E8: 0 | F8: 0 | G8: 0 | H8: 0 | I8: 0 | J8: 0 | K8: 0 | L8: 0 | M8: 0 | N8: 0 | O8: 0 | P8: 0 | Q8: 0 | R8: 0 | S8: =C8+D8+E8+F8+G8+H8+I8+J8+K8+L8 -> 0 | T8: =M8+N8+O8+P8+Q8+R8 -> 0 | X8: Atenção pode haver algum erro- a analisar
B9: (-) Investimento inicial / Initial outlay | C9: 0 | D9: 0 | E9: 0 | F9: 0 | G9: 0 | H9: 0 | I9: 0 | J9: 0 | K9: 0 | L9: 0 | M9: 0 | N9: 0 | O9: 0 | P9: 0 | Q9: 0 | R9: 0 | S9: =C9+D9+E9+F9+G9+H9+I9+J9+K9+L9 -> 0 | T9: =M9+N9+O9+P9+Q9+R9 -> 0
B10: CASH FLOW LIVRE / FREE CASH FLOW | C10: =C7-C8-C9 -> -3404.9591 | D10: =D7-D8-D9 -> -2429.2306 | E10: =E7-E8-E9 -> -2304.3904 | F10: =F7-F8-F9 -> -1647.5528 | G10: =G7-G8-G9 -> -994.7042 | H10: =H7-H8-H9 -> 105.60777 | I10: =I7-I8-I9 -> 976.37943 | J10: =J7-J8-J9 -> 2314.4307 | ... R10: =R7-R8-R9 -> 16517.132 | S10: =C10+D10+E10+F10+G10+H10+I10+J10+K10+L10 -> -88866.348 | T10: =M10+N10+O10+P10+Q10+R10 -> 123276.28
B11: Saldo inicial / Opening balance | C11: =Pressupostos_Assumpt!C73 -> 80000 | D11: =C16 -> 76595.041 | E11: =D16 -> 74165.81 | F11: =E16 -> 71861.42 | G11: =F16 -> 70213.867 | H11: =G16 -> 69219.163 | I11: =H16 -> 69324.771 | J11: =I16 -> 70301.15 | K11: =J16 -> 72615.581 | ... R11: =Q16 -> 97513.292 | S11: =L11 -> 0 | T11: =R11 -> 97513.292
B12: (-) Juros linha credito / Credit interest | C12: 0 | D12: =C17*Pressupostos_Assumpt!C93*Operacao_Operations!D5/12 -> 0 | E12: =D17*Pressupostos_Assumpt!C93*Operacao_Operations!E5/12 -> 0 | F12: =E17*Pressupostos_Assumpt!C93*Operacao_Operations!F5/12 -> 0 | G12: =F17*Pressupostos_Assumpt!C93*Operacao_Operations!G5/12 -> 0 | H12: =G17*Pressupostos_Assumpt!C93*Operacao_Operations!H5/12 -> 0 | I12: =H17*Pressupostos_Assumpt!C93*Operacao_Operations!I5/12 -> 0 | J12: =I17*Pressupostos_Assumpt!C93*Operacao_Operations!J5/12 -> 0 | K12: =J17*Pressupostos_Assumpt!C93*Operacao_Operations!K5/12 -> 0 | L12: =K17*Pressupostos_Assumpt!C93*Operacao_Operations!L5/12 -> 198.21429 | M12: =L17*Pressupostos_Assumpt!C93*Operacao_Operations!M5/12 -> 181.29124 | N12: =M17*Pressupostos_Assumpt!C93*Operacao_Operations!N5/12 -> 0 | O12: =N17*Pressupostos_Assumpt!C93*Operacao_Operations!O5/12 -> 0 | P12: =O17*Pressupostos_Assumpt!C93*Operacao_Operations!P5/12 -> 0 | Q12: =P17*Pressupostos_Assumpt!C93*Operacao_Operations!Q5/12 -> 0 | R12: =Q17*Pressupostos_Assumpt!C93*Operacao_Operations!R5/12 -> 0 | S12: =C12+D12+E12+F12+G12+H12+I12+J12+K12+L12 -> 198.21429 | T12: =M12+N12+O12+P12+Q12+R12 -> 181.29124
B13: Saldo antes financiamento / Cash before financing | C13: =C11+C10-C12 -> 76595.041 | D13: =D11+D10-D12 -> 74165.81 | E13: =E11+E10-E12 -> 71861.42 | F13: =F11+F10-F12 -> 70213.867 | G13: =G11+G10-G12 -> 69219.163 | H13: =H11+H10-H12 -> 69324.771 | I13: =I11+I10-I12 -> 70301.15 | J13: =J11+J10-J12 -> 72615.581 | ... R13: =R11+R10-R12 -> 114030.42 | S13: =L13 -> 20667.582 | T13: =R13 -> 114030.42
B14: (+) Utilizacao linha credito / Credit drawdown | C14: =MIN(MAX(0,-C13),Pressupostos_Assumpt!C92) -> 0 | D14: =MIN(MAX(0,-D13),Pressupostos_Assumpt!C92-C17) -> 0 | E14: =MIN(MAX(0,-E13),Pressupostos_Assumpt!C92-D17) -> 0 | F14: =MIN(MAX(0,-F13),Pressupostos_Assumpt!C92-E17) -> 0 | G14: =MIN(MAX(0,-G13),Pressupostos_Assumpt!C92-F17) -> 0 | H14: =MIN(MAX(0,-H13),Pressupostos_Assumpt!C92-G17) -> 0 | I14: =MIN(MAX(0,-I13),Pressupostos_Assumpt!C92-H17) -> 0 | J14: =MIN(MAX(0,-J13),Pressupostos_Assumpt!C92-I17) -> 0 | K14: =MIN(MAX(0,-K13),Pressupostos_Assumpt!C92-J17) -> 29732.144 | L14: =MIN(MAX(0,-L13),Pressupostos_Assumpt!C92-K17) -> 0 | M14: =MIN(MAX(0,-M13),Pressupostos_Assumpt!C92-L17) -> 0 | N14: =MIN(MAX(0,-N13),Pressupostos_Assumpt!C92-M17) -> 0 | O14: =MIN(MAX(0,-O13),Pressupostos_Assumpt!C92-N17) -> 0 | P14: =MIN(MAX(0,-P13),Pressupostos_Assumpt!C92-O17) -> 0 | Q14: =MIN(MAX(0,-Q13),Pressupostos_Assumpt!C92-P17) -> 0 | R14: =MIN(MAX(0,-R13),Pressupostos_Assumpt!C92-Q17) -> 0 | S14: =C14+D14+E14+F14+G14+H14+I14+J14+K14+L14 -> 29732.144 | T14: =M14+N14+O14+P14+Q14+R14 -> 0
B15: (-) Reembolso linha credito / Repayment | C15: =0 -> 0 | D15: =MIN(C17,MAX(0,D13)) -> 0 | E15: =MIN(D17,MAX(0,E13)) -> 0 | F15: =MIN(E17,MAX(0,F13)) -> 0 | G15: =MIN(F17,MAX(0,G13)) -> 0 | H15: =MIN(G17,MAX(0,H13)) -> 0 | I15: =MIN(H17,MAX(0,I13)) -> 0 | J15: =MIN(I17,MAX(0,J13)) -> 0 | K15: =MIN(J17,MAX(0,K13)) -> 0 | ... R15: =MIN(Q17,MAX(0,R13)) -> 0 | S15: =C15+D15+E15+F15+G15+H15+I15+J15+K15+L15 -> 20667.582 | T15: =M15+N15+O15+P15+Q15+R15 -> 9064.5619
B16: SALDO FINAL / CLOSING BALANCE | C16: =C13+C14-C15 -> 76595.041 | D16: =D13+D14-D15 -> 74165.81 | E16: =E13+E14-E15 -> 71861.42 | F16: =F13+F14-F15 -> 70213.867 | G16: =G13+G14-G15 -> 69219.163 | H16: =H13+H14-H15 -> 69324.771 | I16: =I13+I14-I15 -> 70301.15 | J16: =J13+J14-J15 -> 72615.581 | ... R16: =R13+R14-R15 -> 114030.42 | S16: =L16 -> 0 | T16: =R16 -> 114030.42
B17: Divida linha credito (fim) / Credit outstanding | C17: =C14-C15 -> 0 | D17: =C17+D14-D15 -> 0 | E17: =D17+E14-E15 -> 0 | F17: =E17+F14-F15 -> 0 | G17: =F17+G14-G15 -> 0 | H17: =G17+H14-H15 -> 0 | I17: =H17+I14-I15 -> 0 | J17: =I17+J14-J15 -> 0 | K17: =J17+K14-K15 -> 29732.144 | ... R17: =Q17+R14-R15 -> 0 | S17: =L17 -> 9064.5619 | T17: =R17 -> 0
B19: MEMO - DESFASAMENTO RECEB./PAGAM. / RECEIVABLES & PAYABLES TIMING
B20: Saldo a receber da Amazon (fim periodo) / Receivables (period end) | C20: =Receita_Revenue!C9*(1+Pressupostos_Assumpt!C82)*MIN(1,Pressupostos_Assumpt!C89/7) -> 5767.9452 | D20: =Receita_Revenue!D9*(1+Pressupostos_Assumpt!C82)*MIN(1,Pressupostos_Assumpt!C89/7) -> 9144.8487 | E20: =Receita_Revenue!E9*(1+Pressupostos_Assumpt!C82)*MIN(1,Pressupostos_Assumpt!C89/7) -> 13647.387 | F20: =Receita_Revenue!F9*(1+Pressupostos_Assumpt!C82)*MIN(1,Pressupostos_Assumpt!C89/7) -> 18149.925 | G20: =Receita_Revenue!G9*(1+Pressupostos_Assumpt!C82)*MIN(1,Pressupostos_Assumpt!C89/7) -> 22652.463 | H20: =Receita_Revenue!H9*(1+Pressupostos_Assumpt!C82)*MIN(1,Pressupostos_Assumpt!C89/7) -> 26029.366 | I20: =Receita_Revenue!I9*(1+Pressupostos_Assumpt!C82)*MIN(1,Pressupostos_Assumpt!C89/7) -> 28280.635 | J20: =Receita_Revenue!J9*(1+Pressupostos_Assumpt!C82)*MIN(1,Pressupostos_Assumpt!C89/7) -> 28280.635 | K20: =Receita_Revenue!K9*(1+Pressupostos_Assumpt!C82)*MIN(1,Pressupostos_Assumpt!C89/30) -> 248720.02 | L20: =Receita_Revenue!L9*(1+Pressupostos_Assumpt!C82)*MIN(1,Pressupostos_Assumpt!C89/30) -> 248720.02 | M20: =Receita_Revenue!M9*(1+Pressupostos_Assumpt!D82)*MIN(1,Pressupostos_Assumpt!C89/91) -> 181154.71 | N20: =Receita_Revenue!N9*(1+Pressupostos_Assumpt!D82)*MIN(1,Pressupostos_Assumpt!C89/91) -> 181672.57 | O20: =Receita_Revenue!O9*(1+Pressupostos_Assumpt!D82)*MIN(1,Pressupostos_Assumpt!C89/91) -> 181672.57 | P20: =Receita_Revenue!P9*(1+Pressupostos_Assumpt!D82)*MIN(1,Pressupostos_Assumpt!C89/30) -> 122460.77 | Q20: =Receita_Revenue!Q9*(1+Pressupostos_Assumpt!D82)*MIN(1,Pressupostos_Assumpt!C89/30) -> 244539.25 | R20: =Receita_Revenue!R9*(1+Pressupostos_Assumpt!D82)*MIN(1,Pressupostos_Assumpt!C89/30) -> 244539.25 | S20: =L20 -> 248720.02 | T20: =R20 -> 244539.25
B21: Saldo a pagar fornecedores (fim periodo) / Payables (period end) | C21: =(Custos_Costs!C26-Salarios_Wages!C46)*(1+Pressupostos_Assumpt!C82)*MIN(1,Pressupostos_Assumpt!C90/7) -> 2668.2614 | D21: =(Custos_Costs!D26-Salarios_Wages!D46)*(1+Pressupostos_Assumpt!C82)*MIN(1,Pressupostos_Assumpt!C90/7) -> 3877.2955 | E21: =(Custos_Costs!E26-Salarios_Wages!E46)*(1+Pressupostos_Assumpt!C82)*MIN(1,Pressupostos_Assumpt!C90/7) -> 5090.5227 | F21: =(Custos_Costs!F26-Salarios_Wages!F46)*(1+Pressupostos_Assumpt!C82)*MIN(1,Pressupostos_Assumpt!C90/7) -> 6602.8636 | G21: =(Custos_Costs!G26-Salarios_Wages!G46)*(1+Pressupostos_Assumpt!C82)*MIN(1,Pressupostos_Assumpt!C90/7) -> 7816.0909 | H21: =(Custos_Costs!H26-Salarios_Wages!H46)*(1+Pressupostos_Assumpt!C82)*MIN(1,Pressupostos_Assumpt!C90/7) -> 9025.125 | I21: =(Custos_Costs!I26-Salarios_Wages!I46)*(1+Pressupostos_Assumpt!C82)*MIN(1,Pressupostos_Assumpt!C90/7) -> 9631.7386 | J21: =(Custos_Costs!J26-Salarios_Wages!J46)*(1+Pressupostos_Assumpt!C82)*MIN(1,Pressupostos_Assumpt!C90/7) -> 9631.7386 | K21: =(Custos_Costs!K26-Salarios_Wages!K46)*(1+Pressupostos_Assumpt!C82)*MIN(1,Pressupostos_Assumpt!C90/30) -> 92532.9 | L21: =(Custos_Costs!L26-Salarios_Wages!L46)*(1+Pressupostos_Assumpt!C82)*MIN(1,Pressupostos_Assumpt!C90/30) -> 92532.9 | M21: =(Custos_Costs!M26-Salarios_Wages!M46)*(1+Pressupostos_Assumpt!D82)*MIN(1,Pressupostos_Assumpt!C90/91) -> 42300.781 | N21: =(Custos_Costs!N26-Salarios_Wages!N46)*(1+Pressupostos_Assumpt!D82)*MIN(1,Pressupostos_Assumpt!C90/91) -> 42300.781 | O21: =(Custos_Costs!O26-Salarios_Wages!O46)*(1+Pressupostos_Assumpt!D82)*MIN(1,Pressupostos_Assumpt!C90/91) -> 42300.781 | P21: =(Custos_Costs!P26-Salarios_Wages!P46)*(1+Pressupostos_Assumpt!D82)*MIN(1,Pressupostos_Assumpt!C90/30) -> 42770.79 | Q21: =(Custos_Costs!Q26-Salarios_Wages!Q46)*(1+Pressupostos_Assumpt!D82)*MIN(1,Pressupostos_Assumpt!C90/30) -> 94953.54 | R21: =(Custos_Costs!R26-Salarios_Wages!R46)*(1+Pressupostos_Assumpt!D82)*MIN(1,Pressupostos_Assumpt!C90/30) -> 94953.54 | S21: =L21 -> 92532.9 | T21: =R21 -> 94953.54
B22: Variacao a receber / Change in receivables | C22: =-C20 -> -5767.9452 | D22: =-(D20-C20) -> -3376.9035 | E22: =-(E20-D20) -> -4502.538 | F22: =-(F20-E20) -> -4502.538 | G22: =-(G20-F20) -> -4502.538 | H22: =-(H20-G20) -> -3376.9035 | I22: =-(I20-H20) -> -2251.269 | J22: =-(J20-I20) -> 0 | K22: =-(K20-J20) -> -220439.39 | ... R22: =-(R20-Q20) -> 0 | S22: =L22 -> 0 | T22: =R22 -> 0
B23: Variacao a pagar / Change in payables | C23: =C21 -> 2668.2614 | D23: =D21-C21 -> 1209.0341 | E23: =E21-D21 -> 1213.2273 | F23: =F21-E21 -> 1512.3409 | G23: =G21-F21 -> 1213.2273 | H23: =H21-G21 -> 1209.0341 | I23: =I21-H21 -> 606.61364 | J23: =J21-I21 -> 0 | K23: =K21-J21 -> 82901.161 | ... R23: =R21-Q21 -> 0 | S23: =L23 -> 0 | T23: =R23 -> 0
B25: RESUMO MENSAL / MONTHLY BREAKDOWN
C26: 2026 (Set-Dez) | G26: 2027
B27: POR MES / BY MONTH | C27: Set/Sep 26 | D27: Out/Oct 26 | E27: Nov 26 | F27: Dez/Dec 26 | G27: Jan 27 | H27: Fev/Feb 27 | I27: Mar 27 | J27: Abr/Apr 27 | K27: Mai/May 27 | L27: Jun 27 | M27: Jul 27 | N27: Ago/Aug 27 | O27: Set/Sep 27 | P27: Out/Oct 27 | Q27: Nov 27 | R27: Dez/Dec 27
B28: Resultado liquido / Net profit | C28: =C4+D4+E4+F4 -> -422.40615 | D28: =G4+H4+I4+J4 -> 8173.5878 | E28: =K4 -> 20865.796 | F28: =L4 -> 20865.796 | G28: =(M4)/3 -> 8331.4684 | H28: =(M4)/3 -> 8331.4684 | I28: =(M4)/3 -> 8331.4684 | J28: =(N4)/3 -> 8555.6704 | K28: =(N4)/3 -> 8555.6704 | L28: =(N4)/3 -> 8555.6704 | M28: =(O4)/3 -> 8555.6704 | N28: =(O4)/3 -> 8555.6704 | O28: =(O4)/3 -> 8555.6704 | P28: =P4 -> 8555.6704 | Q28: =Q4 -> 16517.132 | R28: =R4 -> 16517.132
B29: (+) Depreciacao | C29: =C5+D5+E5+F5 -> 0 | D29: =G5+H5+I5+J5 -> 0 | E29: =K5 -> 0 | F29: =L5 -> 0 | G29: =(M5)/3 -> 0 | H29: =(M5)/3 -> 0 | I29: =(M5)/3 -> 0 | J29: =(N5)/3 -> 0 | K29: =(N5)/3 -> 0 | L29: =(N5)/3 -> 0 | M29: =(O5)/3 -> 0 | N29: =(O5)/3 -> 0 | O29: =(O5)/3 -> 0 | P29: =P5 -> 0 | Q29: =Q5 -> 0 | R29: =R5 -> 0
B30: CASH FLOW OPERACIONAL / OPERATING CF | C30: =C7+D7+E7+F7 -> -9786.1329 | D30: =G7+H7+I7+J7 -> 2401.7137 | E30: =K7 -> -102347.72 | F30: =L7 -> 20865.796 | G30: =(M7)/3 -> 23127.212 | H30: =(M7)/3 -> 23127.212 | I30: =(M7)/3 -> 23127.212 | J30: =(N7)/3 -> 8448.3254 | K30: =(N7)/3 -> 8448.3254 | L30: =(N7)/3 -> 8448.3254 | M30: =(O7)/3 -> 8555.6704 | N30: =(O7)/3 -> 8555.6704 | O30: =(O7)/3 -> 8555.6704 | P30: =P7 -> 38178.905 | Q30: =Q7 -> -51813.383 | R30: =R7 -> 16517.132
B31: CASH FLOW LIVRE / FREE CASH FLOW | C31: =C10+D10+E10+F10 -> -9786.1329 | D31: =G10+H10+I10+J10 -> 2401.7137 | E31: =K10 -> -102347.72 | F31: =L10 -> 20865.796 | G31: =(M10)/3 -> 23127.212 | H31: =(M10)/3 -> 23127.212 | I31: =(M10)/3 -> 23127.212 | J31: =(N10)/3 -> 8448.3254 | K31: =(N10)/3 -> 8448.3254 | L31: =(N10)/3 -> 8448.3254 | M31: =(O10)/3 -> 8555.6704 | N31: =(O10)/3 -> 8555.6704 | O31: =(O10)/3 -> 8555.6704 | P31: =P10 -> 38178.905 | Q31: =Q10 -> -51813.383 | R31: =R10 -> 16517.132
B32: SALDO FINAL / CLOSING BALANCE | C32: =F16 -> 70213.867 | D32: =J16 -> 72615.581 | E32: =K16 -> 0 | F32: =L16 -> 0 | G32: =M16 -> 60135.782 | H32: =M16 -> 60135.782 | I32: =M16 -> 60135.782 | J32: =N16 -> 85480.758 | K32: =N16 -> 85480.758 | L32: =N16 -> 85480.758 | M32: =O16 -> 111147.77 | N32: =O16 -> 111147.77 | O32: =O16 -> 111147.77 | P32: =P16 -> 149326.67 | Q32: =Q16 -> 97513.292 | R32: =R16 -> 114030.42
B35: RESUMO TRIMESTRAL / QUARTERLY BREAKDOWN
C36: 2026 | E36: 2027
B37: POR TRIMESTRE / BY QUARTER | C37: Q3 2026 Set/Sep 26 | D37: Q4 2026 Out-Dez/Oct-Dec 26 | E37: Q1 2027 Jan-Mar 27 | F37: Q2 2027 Abr-Jun/Apr-Jun 27 | G37: Q3 2027 Jul-Set/Jul-Sep 27 | H37: Q4 2027 Out-Dez/Oct-Dec 27
B38: Resultado liquido / Net profit | C38: =SUM(C4:F4) -> -422.40615 | D38: =SUM(G4:L4) -> 49905.18 | E38: =SUM(M4:M4) -> 24994.405 | F38: =SUM(N4:N4) -> 25667.011 | G38: =SUM(O4:O4) -> 25667.011 | H38: =SUM(P4:R4) -> 41589.935
B39: (+) Depreciacao | C39: =SUM(C5:F5) -> 0 | D39: =SUM(G5:L5) -> 0 | E39: =SUM(M5:M5) -> 0 | F39: =SUM(N5:N5) -> 0 | G39: =SUM(O5:O5) -> 0 | H39: =SUM(P5:R5) -> 0
B40: CASH FLOW OPERACIONAL / OPERATING CF | C40: =SUM(C7:F7) -> -9786.1329 | D40: =SUM(G7:L7) -> -79080.215 | E40: =SUM(M7:M7) -> 69381.635 | F40: =SUM(N7:N7) -> 25344.976 | G40: =SUM(O7:O7) -> 25667.011 | H40: =SUM(P7:R7) -> 2882.6552
B41: CASH FLOW LIVRE / FREE CASH FLOW | C41: =SUM(C10:F10) -> -9786.1329 | D41: =SUM(G10:L10) -> -79080.215 | E41: =SUM(M10:M10) -> 69381.635 | F41: =SUM(N10:N10) -> 25344.976 | G41: =SUM(O10:O10) -> 25667.011 | H41: =SUM(P10:R10) -> 2882.6552
B42: Saldo inicial / Opening balance | C42: =C11 -> 80000 | D42: =G11 -> 70213.867 | E42: =M11 -> 0 | F42: =N11 -> 60135.782 | G42: =O11 -> 85480.758 | H42: =P11 -> 111147.77
B43: SALDO FINAL / CLOSING BALANCE | C43: =F16 -> 70213.867 | D43: =L16 -> 0 | E43: =M16 -> 60135.782 | F43: =N16 -> 85480.758 | G43: =O16 -> 111147.77 | H43: =R16 -> 114030.42

Sheet IVA_VAT
B1: IVA / VAT - APURAMENTO E IMPACTO NA TESOURARIA / VAT SETTLEMENT & CASH IMPACT
C2: ANO 2026 / YEAR 2026 (Ago-Dez/Aug-Dec) | M2: ANO 2027 / YEAR 2027
B3: Rubrica / Item | C3: S1 Set/Sep 26 | D3: S2 Set/Sep 26 | E3: S3 Set/Sep 26 | F3: S4 Set/Sep 26 | G3: S5 Out/Oct 26 | H3: S6 Out/Oct 26 | I3: S7 Out/Oct 26 | J3: S8 Out/Oct 26 | K3: Nov Nov 26 (Pico/Peak) | L3: Dez Dez/Dec 26 (Pico/Peak) | M3: Q1'27 Jan-Mar 27 | N3: Q2'27 Abr-Jun/Apr-Jun 27 | O3: Q3'27 Jul-Set/Jul-Sep 27 | P3: Out'27 Out/Oct 27 | Q3: Nov'27 Nov 27 (Pico/Peak) | R3: Dez'27 Dez/Dec 27 (Pico/Peak) | S3: Total 2026 | T3: Total 2027
B4: A. IVA LIQUIDADO (cobrado a jusante) / OUTPUT VAT (charged to Amazon)
B5: IVA s/ faturacao Amazon (23%) / VAT on Amazon invoicing | C5: =Receita_Revenue!C9*Pressupostos_Assumpt!C82 -> 1078.5589 | D5: =Receita_Revenue!D9*Pressupostos_Assumpt!C82 -> 1710.0124 | E5: =Receita_Revenue!E9*Pressupostos_Assumpt!C82 -> 2551.9504 | F5: =Receita_Revenue!F9*Pressupostos_Assumpt!C82 -> 3393.8884 | G5: =Receita_Revenue!G9*Pressupostos_Assumpt!C82 -> 4235.8264 | H5: =Receita_Revenue!H9*Pressupostos_Assumpt!C82 -> 4867.2799 | I5: =Receita_Revenue!I9*Pressupostos_Assumpt!C82 -> 5288.2489 | J5: =Receita_Revenue!J9*Pressupostos_Assumpt!C82 -> 5288.2489 | K5: =Receita_Revenue!K9*Pressupostos_Assumpt!C82 -> 46508.622 | L5: =Receita_Revenue!L9*Pressupostos_Assumpt!C82 -> 46508.622 | M5: =Receita_Revenue!M9*Pressupostos_Assumpt!D82 -> 68501.682 | N5: =Receita_Revenue!N9*Pressupostos_Assumpt!D82 -> 68697.504 | O5: =Receita_Revenue!O9*Pressupostos_Assumpt!D82 -> 68697.504 | P5: =Receita_Revenue!P9*Pressupostos_Assumpt!D82 -> 22899.168 | Q5: =Receita_Revenue!Q9*Pressupostos_Assumpt!D82 -> 45726.852 | R5: =Receita_Revenue!R9*Pressupostos_Assumpt!D82 -> 45726.852 | S5: =C5+D5+E5+F5+G5+H5+I5+J5+K5+L5 -> 121431.26 | T5: =M5+N5+O5+P5+Q5+R5 -> 320249.56
B7: B. IVA DEDUTIVEL (suportado a montante) / INPUT VAT (deductible)
B8: Recrutamento (servicos) / Recruitment | C8: =Custos_Costs!C8*Pressupostos_Assumpt!C82 -> 0.58806818 | D8: =Custos_Costs!D8*Pressupostos_Assumpt!C82 -> 0.98011364 | E8: =Custos_Costs!E8*Pressupostos_Assumpt!C82 -> 1.3721591 | F8: =Custos_Costs!F8*Pressupostos_Assumpt!C82 -> 1.8622159 | G8: =Custos_Costs!G8*Pressupostos_Assumpt!C82 -> 2.2542614 | H8: =Custos_Costs!H8*Pressupostos_Assumpt!C82 -> 2.6463068 | I8: =Custos_Costs!I8*Pressupostos_Assumpt!C82 -> 2.8423295 | J8: =Custos_Costs!J8*Pressupostos_Assumpt!C82 -> 2.8423295 | K8: =Custos_Costs!K8*Pressupostos_Assumpt!C82 -> 12.50625 | L8: =Custos_Costs!L8*Pressupostos_Assumpt!C82 -> 12.50625 | M8: =Custos_Costs!M8*Pressupostos_Assumpt!D82 -> 37.51875 | N8: =Custos_Costs!N8*Pressupostos_Assumpt!D82 -> 37.51875 | O8: =Custos_Costs!O8*Pressupostos_Assumpt!D82 -> 37.51875 | P8: =Custos_Costs!P8*Pressupostos_Assumpt!D82 -> 12.50625 | Q8: =Custos_Costs!Q8*Pressupostos_Assumpt!D82 -> 12.50625 | R8: =Custos_Costs!R8*Pressupostos_Assumpt!D82 -> 12.50625 | S8: =C8+D8+E8+F8+G8+H8+I8+J8+K8+L8 -> 40.400284 | T8: =M8+N8+O8+P8+Q8+R8 -> 150.075
B9: Trabalho temporario ETT (servicos) / Temp agency | C9: =Custos_Costs!C6*Pressupostos_Assumpt!C82 -> 0 | D9: =Custos_Costs!D6*Pressupostos_Assumpt!C82 -> 0 | E9: =Custos_Costs!E6*Pressupostos_Assumpt!C82 -> 0 | F9: =Custos_Costs!F6*Pressupostos_Assumpt!C82 -> 0 | G9: =Custos_Costs!G6*Pressupostos_Assumpt!C82 -> 0 | H9: =Custos_Costs!H6*Pressupostos_Assumpt!C82 -> 0 | I9: =Custos_Costs!I6*Pressupostos_Assumpt!C82 -> 0 | J9: =Custos_Costs!J6*Pressupostos_Assumpt!C82 -> 0 | K9: =Custos_Costs!K6*Pressupostos_Assumpt!C82 -> 10752.04 | L9: =Custos_Costs!L6*Pressupostos_Assumpt!C82 -> 10752.04 | M9: =Custos_Costs!M6*Pressupostos_Assumpt!D82 -> 0 | N9: =Custos_Costs!N6*Pressupostos_Assumpt!D82 -> 0 | O9: =Custos_Costs!O6*Pressupostos_Assumpt!D82 -> 0 | P9: =Custos_Costs!P6*Pressupostos_Assumpt!D82 -> 0 | Q9: =Custos_Costs!Q6*Pressupostos_Assumpt!D82 -> 10752.04 | R9: =Custos_Costs!R6*Pressupostos_Assumpt!D82 -> 10752.04 | S9: =C9+D9+E9+F9+G9+H9+I9+J9+K9+L9 -> 21504.08 | T9: =M9+N9+O9+P9+Q9+R9 -> 21504.08 | W9: Atenção pode haver algum erro- a analisar
B10: Leasing viaturas (deducao limitada) / Vehicle lease | C10: =Custos_Costs!C11*Pressupostos_Assumpt!C82*Pressupostos_Assumpt!C84 -> 250.90909 | D10: =Custos_Costs!D11*Pressupostos_Assumpt!C82*Pressupostos_Assumpt!C84 -> 418.18182 | E10: =Custos_Costs!E11*Pressupostos_Assumpt!C82*Pressupostos_Assumpt!C84 -> 585.45455 | F10: =Custos_Costs!F11*Pressupostos_Assumpt!C82*Pressupostos_Assumpt!C84 -> 794.54545 | G10: =Custos_Costs!G11*Pressupostos_Assumpt!C82*Pressupostos_Assumpt!C84 -> 961.81818 | H10: =Custos_Costs!H11*Pressupostos_Assumpt!C82*Pressupostos_Assumpt!C84 -> 1129.0909 | I10: =Custos_Costs!I11*Pressupostos_Assumpt!C82*Pressupostos_Assumpt!C84 -> 1212.7273 | J10: =Custos_Costs!J11*Pressupostos_Assumpt!C82*Pressupostos_Assumpt!C84 -> 1212.7273 | K10: =Custos_Costs!K11*Pressupostos_Assumpt!C82*Pressupostos_Assumpt!C84 -> 5336 | L10: =Custos_Costs!L11*Pressupostos_Assumpt!C82*Pressupostos_Assumpt!C84 -> 5336 | M10: =Custos_Costs!M11*Pressupostos_Assumpt!D82*Pressupostos_Assumpt!D84 -> 16008 | N10: =Custos_Costs!N11*Pressupostos_Assumpt!D82*Pressupostos_Assumpt!D84 -> 16008 | O10: =Custos_Costs!O11*Pressupostos_Assumpt!D82*Pressupostos_Assumpt!D84 -> 16008 | P10: =Custos_Costs!P11*Pressupostos_Assumpt!D82*Pressupostos_Assumpt!D84 -> 5336 | Q10: =Custos_Costs!Q11*Pressupostos_Assumpt!D82*Pressupostos_Assumpt!D84 -> 5336 | R10: =Custos_Costs!R11*Pressupostos_Assumpt!D82*Pressupostos_Assumpt!D84 -> 5336 | S10: =C10+D10+E10+F10+G10+H10+I10+J10+K10+L10 -> 17237.455 | T10: =M10+N10+O10+P10+Q10+R10 -> 64032
B11: Aluguer carrinhas pico (deducao limitada) / Peak rental | C11: =Custos_Costs!C14*Pressupostos_Assumpt!C82*Pressupostos_Assumpt!C84 -> 0 | D11: =Custos_Costs!D14*Pressupostos_Assumpt!C82*Pressupostos_Assumpt!C84 -> 0 | E11: =Custos_Costs!E14*Pressupostos_Assumpt!C82*Pressupostos_Assumpt!C84 -> 0 | F11: =Custos_Costs!F14*Pressupostos_Assumpt!C82*Pressupostos_Assumpt!C84 -> 0 | G11: =Custos_Costs!G14*Pressupostos_Assumpt!C82*Pressupostos_Assumpt!C84 -> 0 | H11: =Custos_Costs!H14*Pressupostos_Assumpt!C82*Pressupostos_Assumpt!C84 -> 0 | I11: =Custos_Costs!I14*Pressupostos_Assumpt!C82*Pressupostos_Assumpt!C84 -> 0 | J11: =Custos_Costs!J14*Pressupostos_Assumpt!C82*Pressupostos_Assumpt!C84 -> 0 | K11: =Custos_Costs!K14*Pressupostos_Assumpt!C82*Pressupostos_Assumpt!C84 -> 9338 | L11: =Custos_Costs!L14*Pressupostos_Assumpt!C82*Pressupostos_Assumpt!C84 -> 9338 | M11: =Custos_Costs!M14*Pressupostos_Assumpt!D82*Pressupostos_Assumpt!D84 -> 0 | N11: =Custos_Costs!N14*Pressupostos_Assumpt!D82*Pressupostos_Assumpt!D84 -> 0 | O11: =Custos_Costs!O14*Pressupostos_Assumpt!D82*Pressupostos_Assumpt!D84 -> 0 | P11: =Custos_Costs!P14*Pressupostos_Assumpt!D82*Pressupostos_Assumpt!D84 -> 0 | Q11: =Custos_Costs!Q14*Pressupostos_Assumpt!D82*Pressupostos_Assumpt!D84 -> 9671.5 | R11: =Custos_Costs!R14*Pressupostos_Assumpt!D82*Pressupostos_Assumpt!D84 -> 9671.5 | S11: =C11+D11+E11+F11+G11+H11+I11+J11+K11+L11 -> 18676 | T11: =M11+N11+O11+P11+Q11+R11 -> 19343
B12: Manutencao / Maintenance | C12: =Custos_Costs!C13*Pressupostos_Assumpt!C82 -> 47.045455 | D12: =Custos_Costs!D13*Pressupostos_Assumpt!C82 -> 78.409091 | E12: =Custos_Costs!E13*Pressupostos_Assumpt!C82 -> 109.77273 | F12: =Custos_Costs!F13*Pressupostos_Assumpt!C82 -> 148.97727 | G12: =Custos_Costs!G13*Pressupostos_Assumpt!C82 -> 180.34091 | H12: =Custos_Costs!H13*Pressupostos_Assumpt!C82 -> 211.70455 | I12: =Custos_Costs!I13*Pressupostos_Assumpt!C82 -> 227.38636 | J12: =Custos_Costs!J13*Pressupostos_Assumpt!C82 -> 227.38636 | K12: =Custos_Costs!K13*Pressupostos_Assumpt!C82 -> 1000.5 | L12: =Custos_Costs!L13*Pressupostos_Assumpt!C82 -> 1000.5 | M12: =Custos_Costs!M13*Pressupostos_Assumpt!D82 -> 3201.6 | N12: =Custos_Costs!N13*Pressupostos_Assumpt!D82 -> 3201.6 | O12: =Custos_Costs!O13*Pressupostos_Assumpt!D82 -> 3201.6 | P12: =Custos_Costs!P13*Pressupostos_Assumpt!D82 -> 1067.2 | Q12: =Custos_Costs!Q13*Pressupostos_Assumpt!D82 -> 1067.2 | R12: =Custos_Costs!R13*Pressupostos_Assumpt!D82 -> 1067.2 | S12: =C12+D12+E12+F12+G12+H12+I12+J12+K12+L12 -> 3232.0227 | T12: =M12+N12+O12+P12+Q12+R12 -> 12806.4
B13: Dispositivos/reserva / Devices | C13: =(Custos_Costs!C15+Custos_Costs!C20)*Pressupostos_Assumpt!C82 -> 9.1477273 | D13: =(Custos_Costs!D15+Custos_Costs!D20)*Pressupostos_Assumpt!C82 -> 11.5 | E13: =(Custos_Costs!E15+Custos_Costs!E20)*Pressupostos_Assumpt!C82 -> 14.636364 | F13: =(Custos_Costs!F15+Custos_Costs!F20)*Pressupostos_Assumpt!C82 -> 17.772727 | G13: =(Custos_Costs!G15+Custos_Costs!G20)*Pressupostos_Assumpt!C82 -> 20.909091 | H13: =(Custos_Costs!H15+Custos_Costs!H20)*Pressupostos_Assumpt!C82 -> 23.261364 | I13: =(Custos_Costs!I15+Custos_Costs!I20)*Pressupostos_Assumpt!C82 -> 24.829545 | J13: =(Custos_Costs!J15+Custos_Costs!J20)*Pressupostos_Assumpt!C82 -> 24.829545 | K13: =(Custos_Costs!K15+Custos_Costs!K20)*Pressupostos_Assumpt!C82 -> 195.5 | L13: =(Custos_Costs!L15+Custos_Costs!L20)*Pressupostos_Assumpt!C82 -> 195.5 | M13: =(Custos_Costs!M15+Custos_Costs!M20)*Pressupostos_Assumpt!D82 -> 327.75 | N13: =(Custos_Costs!N15+Custos_Costs!N20)*Pressupostos_Assumpt!D82 -> 327.75 | O13: =(Custos_Costs!O15+Custos_Costs!O20)*Pressupostos_Assumpt!D82 -> 327.75 | P13: =(Custos_Costs!P15+Custos_Costs!P20)*Pressupostos_Assumpt!D82 -> 109.25 | Q13: =(Custos_Costs!Q15+Custos_Costs!Q20)*Pressupostos_Assumpt!D82 -> 195.5 | R13: =(Custos_Costs!R15+Custos_Costs!R20)*Pressupostos_Assumpt!D82 -> 195.5 | S13: =C13+D13+E13+F13+G13+H13+I13+J13+K13+L13 -> 537.88636 | T13: =M13+N13+O13+P13+Q13+R13 -> 1483.5
B14: Combustivel (deducao parcial) / Fuel | C14: =Receita_Revenue!C6*Pressupostos_Assumpt!C82*Pressupostos_Assumpt!C83 -> 33.20625 | D14: =Receita_Revenue!D6*Pressupostos_Assumpt!C82*Pressupostos_Assumpt!C83 -> 53.13 | E14: =Receita_Revenue!E6*Pressupostos_Assumpt!C82*Pressupostos_Assumpt!C83 -> 79.695 | F14: =Receita_Revenue!F6*Pressupostos_Assumpt!C82*Pressupostos_Assumpt!C83 -> 106.26 | G14: =Receita_Revenue!G6*Pressupostos_Assumpt!C82*Pressupostos_Assumpt!C83 -> 132.825 | H14: =Receita_Revenue!H6*Pressupostos_Assumpt!C82*Pressupostos_Assumpt!C83 -> 152.74875 | I14: =Receita_Revenue!I6*Pressupostos_Assumpt!C82*Pressupostos_Assumpt!C83 -> 166.03125 | J14: =Receita_Revenue!J6*Pressupostos_Assumpt!C82*Pressupostos_Assumpt!C83 -> 166.03125 | K14: =Receita_Revenue!K6*Pressupostos_Assumpt!C82*Pressupostos_Assumpt!C83 -> 1461.075 | L14: =Receita_Revenue!L6*Pressupostos_Assumpt!C82*Pressupostos_Assumpt!C83 -> 1461.075 | M14: =Receita_Revenue!M6*Pressupostos_Assumpt!D82*Pressupostos_Assumpt!D83 -> 2258.025 | N14: =Receita_Revenue!N6*Pressupostos_Assumpt!D82*Pressupostos_Assumpt!D83 -> 2258.025 | O14: =Receita_Revenue!O6*Pressupostos_Assumpt!D82*Pressupostos_Assumpt!D83 -> 2258.025 | P14: =Receita_Revenue!P6*Pressupostos_Assumpt!D82*Pressupostos_Assumpt!D83 -> 752.675 | Q14: =Receita_Revenue!Q6*Pressupostos_Assumpt!D82*Pressupostos_Assumpt!D83 -> 1505.35 | R14: =Receita_Revenue!R6*Pressupostos_Assumpt!D82*Pressupostos_Assumpt!D83 -> 1505.35 | S14: =C14+D14+E14+F14+G14+H14+I14+J14+K14+L14 -> 3812.0775 | T14: =M14+N14+O14+P14+Q14+R14 -> 10537.45
B15: Contabilidade / Accounting | C15: =Custos_Costs!C18*Pressupostos_Assumpt!C82 -> 10.454545 | D15: =Custos_Costs!D18*Pressupostos_Assumpt!C82 -> 10.454545 | E15: =Custos_Costs!E18*Pressupostos_Assumpt!C82 -> 10.454545 | F15: =Custos_Costs!F18*Pressupostos_Assumpt!C82 -> 10.454545 | G15: =Custos_Costs!G18*Pressupostos_Assumpt!C82 -> 10.454545 | H15: =Custos_Costs!H18*Pressupostos_Assumpt!C82 -> 10.454545 | I15: =Custos_Costs!I18*Pressupostos_Assumpt!C82 -> 10.454545 | J15: =Custos_Costs!J18*Pressupostos_Assumpt!C82 -> 10.454545 | K15: =Custos_Costs!K18*Pressupostos_Assumpt!C82 -> 46 | L15: =Custos_Costs!L18*Pressupostos_Assumpt!C82 -> 46 | M15: =Custos_Costs!M18*Pressupostos_Assumpt!D82 -> 142.14 | N15: =Custos_Costs!N18*Pressupostos_Assumpt!D82 -> 142.14 | O15: =Custos_Costs!O18*Pressupostos_Assumpt!D82 -> 142.14 | P15: =Custos_Costs!P18*Pressupostos_Assumpt!D82 -> 47.38 | Q15: =Custos_Costs!Q18*Pressupostos_Assumpt!D82 -> 47.38 | R15: =Custos_Costs!R18*Pressupostos_Assumpt!D82 -> 47.38 | S15: =C15+D15+E15+F15+G15+H15+I15+J15+K15+L15 -> 175.63636 | T15: =M15+N15+O15+P15+Q15+R15 -> 568.56
B16: Diversos / Miscellaneous | C16: =Custos_Costs!C21*Pressupostos_Assumpt!C82 -> 15.681818 | D16: =Custos_Costs!D21*Pressupostos_Assumpt!C82 -> 15.681818 | E16: =Custos_Costs!E21*Pressupostos_Assumpt!C82 -> 15.681818 | F16: =Custos_Costs!F21*Pressupostos_Assumpt!C82 -> 15.681818 | G16: =Custos_Costs!G21*Pressupostos_Assumpt!C82 -> 15.681818 | H16: =Custos_Costs!H21*Pressupostos_Assumpt!C82 -> 15.681818 | I16: =Custos_Costs!I21*Pressupostos_Assumpt!C82 -> 15.681818 | J16: =Custos_Costs!J21*Pressupostos_Assumpt!C82 -> 15.681818 | K16: =Custos_Costs!K21*Pressupostos_Assumpt!C82 -> 69 | L16: =Custos_Costs!L21*Pressupostos_Assumpt!C82 -> 69 | M16: =Custos_Costs!M21*Pressupostos_Assumpt!D82 -> 213.21 | N16: =Custos_Costs!N21*Pressupostos_Assumpt!D82 -> 213.21 | O16: =Custos_Costs!O21*Pressupostos_Assumpt!D82 -> 213.21 | P16: =Custos_Costs!P21*Pressupostos_Assumpt!D82 -> 71.07 | Q16: =Custos_Costs!Q21*Pressupostos_Assumpt!D82 -> 71.07 | R16: =Custos_Costs!R21*Pressupostos_Assumpt!D82 -> 71.07 | S16: =C16+D16+E16+F16+G16+H16+I16+J16+K16+L16 -> 263.45455 | T16: =M16+N16+O16+P16+Q16+R16 -> 852.84
B17: Aluguer parque carrinhas / Van yard rent | C17: =Custos_Costs!C24*Pressupostos_Assumpt!C82 -> 115 | D17: =Custos_Costs!D24*Pressupostos_Assumpt!C82 -> 115 | E17: =Custos_Costs!E24*Pressupostos_Assumpt!C82 -> 115 | F17: =Custos_Costs!F24*Pressupostos_Assumpt!C82 -> 115 | G17: =Custos_Costs!G24*Pressupostos_Assumpt!C82 -> 115 | H17: =Custos_Costs!H24*Pressupostos_Assumpt!C82 -> 115 | I17: =Custos_Costs!I24*Pressupostos_Assumpt!C82 -> 115 | J17: =Custos_Costs!J24*Pressupostos_Assumpt!C82 -> 115 | K17: =Custos_Costs!K24*Pressupostos_Assumpt!C82 -> 460 | L17: =Custos_Costs!L24*Pressupostos_Assumpt!C82 -> 460 | M17: =Custos_Costs!M24*Pressupostos_Assumpt!D82 -> 1421.4 | N17: =Custos_Costs!N24*Pressupostos_Assumpt!D82 -> 1421.4 | O17: =Custos_Costs!O24*Pressupostos_Assumpt!D82 -> 1421.4 | P17: =Custos_Costs!P24*Pressupostos_Assumpt!D82 -> 473.8 | Q17: =Custos_Costs!Q24*Pressupostos_Assumpt!D82 -> 473.8 | R17: =Custos_Costs!R24*Pressupostos_Assumpt!D82 -> 473.8 | S17: =C17+D17+E17+F17+G17+H17+I17+J17+K17+L17 -> 1840 | T17: =M17+N17+O17+P17+Q17+R17 -> 5685.6
B18: TOTAL IVA DEDUTIVEL / TOTAL INPUT VAT | C18: =SUM(C8:C17) -> 482.03295 | D18: =SUM(D8:D17) -> 703.33739 | E18: =SUM(E8:E17) -> 932.06716 | F18: =SUM(F8:F17) -> 1210.554 | G18: =SUM(G8:G17) -> 1439.2838 | H18: =SUM(H8:H17) -> 1660.5882 | I18: =SUM(I8:I17) -> 1774.9531 | J18: =SUM(J8:J17) -> 1774.9531 | ... R18: =SUM(R8:R17) -> 29132.346 | S18: =C18+D18+E18+F18+G18+H18+I18+J18+K18+L18 -> 67319.012 | T18: =M18+N18+O18+P18+Q18+R18 -> 136963.51
B20: C. APURAMENTO / SETTLEMENT
B21: IVA do periodo (liquidado - dedutivel) / VAT of period | C21: =C5-C18 -> 596.52591 | D21: =D5-D18 -> 1006.675 | E21: =E5-E18 -> 1619.8832 | F21: =F5-F18 -> 2183.3343 | G21: =G5-G18 -> 2796.5426 | H21: =H5-H18 -> 3206.6916 | I21: =I5-I18 -> 3513.2957 | J21: =J5-J18 -> 3513.2957 | ... R21: =R5-R18 -> 16594.506 | S21: =C21+D21+E21+F21+G21+H21+I21+J21+K21+L21 -> 54112.246 | T21: =M21+N21+O21+P21+Q21+R21 -> 183286.06
B22: (>0 = a pagar ao Estado / payable | <0 = a recuperar / recoverable)
B24: D. IMPACTO NA TESOURARIA / CASH IMPACT (entrega no periodo seguinte / paid next period)
B25: (+) IVA recebido da Amazon / VAT received from Amazon | C25: =C5 -> 1078.5589 | D25: =D5 -> 1710.0124 | E25: =E5 -> 2551.9504 | F25: =F5 -> 3393.8884 | G25: =G5 -> 4235.8264 | H25: =H5 -> 4867.2799 | I25: =I5 -> 5288.2489 | J25: =J5 -> 5288.2489 | ... R25: =R5 -> 45726.852 | S25: =C25+D25+E25+F25+G25+H25+I25+J25+K25+L25 -> 121431.26 | T25: =M25+N25+O25+P25+Q25+R25 -> 320249.56
B26: (-) IVA pago nas compras / VAT paid on purchases | C26: =C18 -> 482.03295 | D26: =D18 -> 703.33739 | E26: =E18 -> 932.06716 | F26: =F18 -> 1210.554 | G26: =G18 -> 1439.2838 | H26: =H18 -> 1660.5882 | I26: =I18 -> 1774.9531 | J26: =J18 -> 1774.9531 | ... R26: =R18 -> 29132.346 | S26: =C26+D26+E26+F26+G26+H26+I26+J26+K26+L26 -> 67319.012 | T26: =M26+N26+O26+P26+Q26+R26 -> 136963.51
B27: (-) Entrega IVA ao Estado (apuramento periodo anterior) / VAT remittance (prior period) | C27: 0 | D27: =MAX(0,C21) -> 596.52591 | E27: =MAX(0,D21) -> 1006.675 | F27: =MAX(0,E21) -> 1619.8832 | G27: =MAX(0,F21) -> 2183.3343 | H27: =MAX(0,G21) -> 2796.5426 | I27: =MAX(0,H21) -> 3206.6916 | J27: =MAX(0,I21) -> 3513.2957 | K27: =MAX(0,J21) -> 3513.2957 | ... R27: =MAX(0,Q21) -> 16594.506 | S27: =C27+D27+E27+F27+G27+H27+I27+J27+K27+L27 -> 36274.245 | T27: =M27+N27+O27+P27+Q27+R27 -> 184529.55
B28: (+) Recuperacao IVA do Estado (periodo anterior) / VAT refund (prior period) | C28: 0 | D28: =MAX(0,-C21) -> 0 | E28: =MAX(0,-D21) -> 0 | F28: =MAX(0,-E21) -> 0 | G28: =MAX(0,-F21) -> 0 | H28: =MAX(0,-G21) -> 0 | I28: =MAX(0,-H21) -> 0 | J28: =MAX(0,-I21) -> 0 | K28: =MAX(0,-J21) -> 0 | ... R28: =MAX(0,-Q21) -> 0 | S28: =C28+D28+E28+F28+G28+H28+I28+J28+K28+L28 -> 0 | T28: =M28+N28+O28+P28+Q28+R28 -> 0
B29: IMPACTO LIQUIDO IVA NA CAIXA / NET VAT CASH IMPACT | C29: =C25-C26-C27+C28 -> 596.52591 | D29: =D25-D26-D27+D28 -> 410.14907 | E29: =E25-E26-E27+E28 -> 613.20823 | F29: =F25-F26-F27+F28 -> 563.45113 | G29: =G25-G26-G27+G28 -> 613.20823 | H29: =H25-H26-H27+H28 -> 410.14907 | I29: =I25-I26-I27+I28 -> 306.60411 | J29: =J25-J26-J27+J28 -> 0 | ... R29: =R25-R26-R27+R28 -> 0 | S29: =C29+D29+E29+F29+G29+H29+I29+J29+K29+L29 -> 17838.001 | T29: =M29+N29+O29+P29+Q29+R29 -> -1243.495

Sheet Analise_Analysis
B1: ANALISE DE RENTABILIDADE / PROFITABILITY ANALYSIS
B3: Rubrica / Item | C3: 2026 (€) | D3: 2027 (€) | E3: % Rec. 2026 | F3: % Rec. 2027 | I3: Estrutura custos 2027
B4: RECEITA / REVENUE | I4: Mao-de-obra | J4: =Custos_Costs!T9 -> 740999.65
B5: Receita total / Total revenue | C5: =Receita_Revenue!S9 -> 527961.99 | D5: =Receita_Revenue!T9 -> 1392389.4 | E5: =IF(Receita_Revenue!S9=0,0,Receita_Revenue!S9/Receita_Revenue!S9) -> 1 | F5: =IF(Receita_Revenue!T9=0,0,Receita_Revenue!T9/Receita_Revenue!T9) -> 1 | I5: Frota | J5: =Custos_Costs!T16 -> 462880
I6: Overheads | J6: =Custos_Costs!T22 -> 14526
B7: CUSTOS / COSTS (% da receita) | I7: Instalacoes | J7: =Custos_Costs!T25 -> 24720
B8: Mao-de-obra / Labour | C8: =Custos_Costs!S9 -> 270265.53 | D8: =Custos_Costs!T9 -> 740999.65 | E8: =IF(Receita_Revenue!S9=0,0,Custos_Costs!S9/Receita_Revenue!S9) -> 0.51190338 | F8: =IF(Receita_Revenue!T9=0,0,Custos_Costs!T9/Receita_Revenue!T9) -> 0.53217846
B9: Permanentes / Permanent drivers | C9: =Custos_Costs!S5 -> 157718.03 | D9: =Custos_Costs!T5 -> 585875.4 | E9: =IF(Receita_Revenue!S9=0,0,Custos_Costs!S5/Receita_Revenue!S9) -> 0.29872989 | F9: =IF(Receita_Revenue!T9=0,0,Custos_Costs!T5/Receita_Revenue!T9) -> 0.42076979 | I9: Receita/Custos/Resultado
B10: Temporarios ETT / Temp agency | C10: =Custos_Costs!S6 -> 93496 | D10: =Custos_Costs!T6 -> 93496 | E10: =IF(Receita_Revenue!S9=0,0,Custos_Costs!S6/Receita_Revenue!S9) -> 0.17708851 | F10: =IF(Receita_Revenue!T9=0,0,Custos_Costs!T6/Receita_Revenue!T9) -> 0.067147883 | J10: 2026 | K10: 2027
B11: Gestor + Admin / Manager + Admin | C11: =Custos_Costs!S7 -> 18875.85 | D11: =Custos_Costs!T7 -> 60975.75 | E11: =IF(Receita_Revenue!S9=0,0,Custos_Costs!S7/Receita_Revenue!S9) -> 0.03575229 | F11: =IF(Receita_Revenue!T9=0,0,Custos_Costs!T7/Receita_Revenue!T9) -> 0.043792168 | I11: Receita | J11: =Receita_Revenue!S9 -> 527961.99 | K11: =Receita_Revenue!T9 -> 1392389.4
B12: Recrutamento / Recruitment | C12: =Custos_Costs!S8 -> 175.65341 | D12: =Custos_Costs!T8 -> 652.5 | E12: =IF(Receita_Revenue!S9=0,0,Custos_Costs!S8/Receita_Revenue!S9) -> 0.00033270086 | F12: =IF(Receita_Revenue!T9=0,0,Custos_Costs!T8/Receita_Revenue!T9) -> 0.00046861891 | I12: Custos | J12: =Custos_Costs!S26 -> 464907.35 | K12: =Custos_Costs!T26 -> 1243125.6
B13: Frota / Fleet | C13: =Custos_Costs!S16 -> 181821.36 | D13: =Custos_Costs!T16 -> 462880 | E13: =IF(Receita_Revenue!S9=0,0,Custos_Costs!S16/Receita_Revenue!S9) -> 0.34438343 | F13: =IF(Receita_Revenue!T9=0,0,Custos_Costs!T16/Receita_Revenue!T9) -> 0.33243574 | I13: Resultado | J13: =DRE_PL!S13 -> 49482.774 | K13: =DRE_PL!T13 -> 117918.36
B14: Overheads / Overhead | C14: =Custos_Costs!S22 -> 4820.4545 | D14: =Custos_Costs!T22 -> 14526 | E14: =IF(Receita_Revenue!S9=0,0,Custos_Costs!S22/Receita_Revenue!S9) -> 0.009130306 | F14: =IF(Receita_Revenue!T9=0,0,Custos_Costs!T22/Receita_Revenue!T9) -> 0.010432426
B15: Instalacoes / Facilities (parque) | C15: =Custos_Costs!S25 -> 8000 | D15: =Custos_Costs!T25 -> 24720 | E15: =IF(Receita_Revenue!S9=0,0,Custos_Costs!S25/Receita_Revenue!S9) -> 0.015152606 | F15: =IF(Receita_Revenue!T9=0,0,Custos_Costs!T25/Receita_Revenue!T9) -> 0.017753654
B16: CUSTOS TOTAIS / TOTAL COSTS | C16: =Custos_Costs!S26 -> 464907.35 | D16: =Custos_Costs!T26 -> 1243125.6 | E16: =IF(Receita_Revenue!S9=0,0,Custos_Costs!S26/Receita_Revenue!S9) -> 0.88056973 | F16: =IF(Receita_Revenue!T9=0,0,Custos_Costs!T26/Receita_Revenue!T9) -> 0.89280028
B18: RESULTADO / RESULT
B19: EBITDA | C19: =DRE_PL!S6 -> 63054.644 | D19: =DRE_PL!T6 -> 149263.75 | E19: =IF(Receita_Revenue!S9=0,0,DRE_PL!S6/Receita_Revenue!S9) -> 0.11943027 | F19: =IF(Receita_Revenue!T9=0,0,DRE_PL!T6/Receita_Revenue!T9) -> 0.10719972
B20: Resultado liquido / Net profit | C20: =DRE_PL!S13 -> 49482.774 | D20: =DRE_PL!T13 -> 117918.36 | E20: =IF(Receita_Revenue!S9=0,0,DRE_PL!S13/Receita_Revenue!S9) -> 0.093724121 | F20: =IF(Receita_Revenue!T9=0,0,DRE_PL!T13/Receita_Revenue!T9) -> 0.084687777
B54: NOTA: A mao-de-obra e o maior custo. Ajusta o salario/hora e o buffer nos Pressupostos para ver o efeito na margem. / Labour is the biggest cost - adjust hourly wage & buffer in Assumptions.

Sheet Sensibilidades
B1: ANALISE DE SENSIBILIDADES / SENSITIVITY ANALYSIS (ano 2027)
B2: Motor anual 2027 que reproduz o modelo. Cores: verde=lucro, vermelho=prejuizo. Nota: DSO afeta a CAIXA, nao o lucro.
B4: 1. CENARIOS / SCENARIOS
B5: Driver / Variavel | C5: Pessimista | D5: Base (modelo) | E5: Otimista
B6: Salario motorista / Driver wage (€/h) | C6: 8.5 | D6: =Pressupostos_Assumpt!C40 -> 6.2 | E6: 6
B7: Taxa base Amazon / Base rate (€/h) | C7: 16.5 | D7: =Pressupostos_Assumpt!C6 -> 17.9 | E7: 19
B8: Buffer motoristas / Driver buffer | C8: 0.25 | D8: =Pressupostos_Assumpt!C49 -> 0.15 | E8: 0.12
B9: Buffer frota / Fleet buffer | C9: 0.18 | D9: =Pressupostos_Assumpt!C31 -> 0.15 | E9: 0.1
B10: Rotatividade / Turnover | C10: 0.25 | D10: =Pressupostos_Assumpt!C47 -> 0.15 | E10: 0.1
B11: Volume (x base) / Volume mult. | C11: 0.9 | D11: 1 | E11: 1.1
B12: Receita / Revenue | C12: =81900*C7+807750*C11*0.04+146140 -> 1526569 | D12: =81900*D7+807750*D11*0.04+146140 -> 1644460 | E12: =81900*E7+807750*E11*0.04+146140 -> 1737781
B13: Mao-de-obra / Labour | C13: =CEILING(25*(1+C8),1)*((C6*173.3333)*14*1.2375+1584)+CEILING(25*(1+C8),1)*(C6*173.3333)*1.7*2+60975+CEILING(25*(1+C8),1)*300*C10 -> 1091177.5 | D13: =CEILING(25*(1+D8),1)*((D6*173.3333)*14*1.2375+1584)+CEILING(25*(1+D8),1)*(D6*173.3333)*1.7*2+60975+CEILING(25*(1+D8),1)*300*D10 -> 754117.41 | E13: =CEILING(25*(1+E8),1)*((E6*173.3333)*14*1.2375+1584)+CEILING(25*(1+E8),1)*(E6*173.3333)*1.7*2+60975+CEILING(25*(1+E8),1)*300*E10 -> 709678.88
B14: Frota / Fleet | C14: =CEILING(25*(1+C9),1)*12*1085+CEILING(25*(1+C9),1)*1450*2+1200 -> 478800 | D14: =CEILING(25*(1+D9),1)*12*1085+CEILING(25*(1+D9),1)*1450*2+1200 -> 462880 | E14: =CEILING(25*(1+E9),1)*12*1085+CEILING(25*(1+E9),1)*1450*2+1200 -> 446960
B15: Overheads + Instalacoes | C15: =39246 -> 39246 | D15: =39246 -> 39246 | E15: =39246 -> 39246
B16: Depreciacao / Depreciation | C16: =CEILING(25*(1+C9),1)*48 -> 1440 | D16: =CEILING(25*(1+D9),1)*48 -> 1392 | E16: =CEILING(25*(1+E9),1)*48 -> 1344
B17: EBT (antes imp.) / Pre-tax | C17: =C12-C13-C14-C15-C16 -> -84094.479 | D17: =D12-D13-D14-D15-D16 -> 386824.59 | E17: =E12-E13-E14-E15-E16 -> 540552.12
B18: RESULTADO LIQUIDO / NET PROFIT | C18: =IF(C17>0,C17*0.79,C17) -> -84094.479 | D18: =IF(D17>0,D17*0.79,D17) -> 305591.43 | E18: =IF(E17>0,E17*0.79,E17) -> 427036.17
B19: Margem liquida / Net margin | C19: =IF(C12=0,0,C18/C12) -> -0.055087244 | D19: =IF(D12=0,0,D18/D12) -> 0.18583087 | E19: =IF(E12=0,0,E18/E12) -> 0.24573647
B21: 2. SENSIBILIDADE A 1 VARIAVEL / ONE-WAY (resultado liquido)
B22: Salario motorista (€/h) | C22: 6 | D22: 7 | E22: 8 | F22: 9 | G22: 10
B23: -> Resultado liquido / Net profit | C23: =IF(((81900*$D$7+807750*$D$11*0.04+146140)-(CEILING(25*(1+$D$8),1)*((C22*173.3333)*14*1.2375+1584)+CEILING(25*(1+$D$8),1)*(C22*173.3333)*1.7*2+60975+CEILING(25*(1+$D$8),1)*300*$D$10)-(CEILING(25*(1+$D$9),1)*12*1085+CEILING(25*(1+$D$9),1)*1450*2+1200)-39246-(CEILING(25*(1+$D$9),1)*48))>0,((81900*$D$7+807750*$D$11*0.04+146140)-(CEILING(25*(1+$D$8),1)*((C22*173.3333)*14*1.2375+1584)+CEILING(25*(1+$D$8),1)*(C22*173.3333)*1.7*2+60975+CEILING(25*(1+$D$8),1)*300*$D$10)-(CEILING(25*(1+$D$9),1)*12*1085+CEILING(25*(1+$D$9),1)*1450*2+1200)-39246-(CEILING(25*(1+$D$9),1)*48))*0.79,((81900*$D$7+807750*$D$11*0.04+146140)-(CEILING(25*(1+$D$8),1)*((C22*173.3333)*14*1.2375+1584)+CEILING(25*(1+$D$8),1)*(C22*173.3333)*1.7*2+60975+CEILING(25*(1+$D$8),1)*300*$D$10)-(CEILING(25*(1+$D$9),1)*12*1085+CEILING(25*(1+$D$9),1)*1450*2+1200)-39246-(CEILING(25*(1+$D$9),1)*48))) -> 322051.49 | D23: =IF(((81900*$D$7+807750*$D$11*0.04+146140)-(CEILING(25*(1+$D$8),1)*((D22*173.3333)*14*1.2375+1584)+CEILING(25*(1+$D$8),1)*(D22*173.3333)*1.7*2+60975+CEILING(25*(1+$D$8),1)*300*$D$10)-(CEILING(25*(1+$D$9),1)*12*1085+CEILING(25*(1+$D$9),1)*1450*2+1200)-39246-(CEILING(25*(1+$D$9),1)*48))>0,((81900*$D$7+807750*$D$11*0.04+146140)-(CEILING(25*(1+$D$8),1)*((D22*173.3333)*14*1.2375+1584)+CEILING(25*(1+$D$8),1)*(D22*173.3333)*1.7*2+60975+CEILING(25*(1+$D$8),1)*300*$D$10)-(CEILING(25*(1+$D$9),1)*12*1085+CEILING(25*(1+$D$9),1)*1450*2+1200)-39246-(CEILING(25*(1+$D$9),1)*48))*0.79,((81900*$D$7+807750*$D$11*0.04+146140)-(CEILING(25*(1+$D$8),1)*((D22*173.3333)*14*1.2375+1584)+CEILING(25*(1+$D$8),1)*(D22*173.3333)*1.7*2+60975+CEILING(25*(1+$D$8),1)*300*$D$10)-(CEILING(25*(1+$D$9),1)*12*1085+CEILING(25*(1+$D$9),1)*1450*2+1200)-39246-(CEILING(25*(1+$D$9),1)*48))) -> 239751.15 | E23: =IF(((81900*$D$7+807750*$D$11*0.04+146140)-(CEILING(25*(1+$D$8),1)*((E22*173.3333)*14*1.2375+1584)+CEILING(25*(1+$D$8),1)*(E22*173.3333)*1.7*2+60975+CEILING(25*(1+$D$8),1)*300*$D$10)-(CEILING(25*(1+$D$9),1)*12*1085+CEILING(25*(1+$D$9),1)*1450*2+1200)-39246-(CEILING(25*(1+$D$9),1)*48))>0,((81900*$D$7+807750*$D$11*0.04+146140)-(CEILING(25*(1+$D$8),1)*((E22*173.3333)*14*1.2375+1584)+CEILING(25*(1+$D$8),1)*(E22*173.3333)*1.7*2+60975+CEILING(25*(1+$D$8),1)*300*$D$10)-(CEILING(25*(1+$D$9),1)*12*1085+CEILING(25*(1+$D$9),1)*1450*2+1200)-39246-(CEILING(25*(1+$D$9),1)*48))*0.79,((81900*$D$7+807750*$D$11*0.04+146140)-(CEILING(25*(1+$D$8),1)*((E22*173.3333)*14*1.2375+1584)+CEILING(25*(1+$D$8),1)*(E22*173.3333)*1.7*2+60975+CEILING(25*(1+$D$8),1)*300*$D$10)-(CEILING(25*(1+$D$9),1)*12*1085+CEILING(25*(1+$D$9),1)*1450*2+1200)-39246-(CEILING(25*(1+$D$9),1)*48))) -> 157450.81 | F23: =IF(((81900*$D$7+807750*$D$11*0.04+146140)-(CEILING(25*(1+$D$8),1)*((F22*173.3333)*14*1.2375+1584)+CEILING(25*(1+$D$8),1)*(F22*173.3333)*1.7*2+60975+CEILING(25*(1+$D$8),1)*300*$D$10)-(CEILING(25*(1+$D$9),1)*12*1085+CEILING(25*(1+$D$9),1)*1450*2+1200)-39246-(CEILING(25*(1+$D$9),1)*48))>0,((81900*$D$7+807750*$D$11*0.04+146140)-(CEILING(25*(1+$D$8),1)*((F22*173.3333)*14*1.2375+1584)+CEILING(25*(1+$D$8),1)*(F22*173.3333)*1.7*2+60975+CEILING(25*(1+$D$8),1)*300*$D$10)-(CEILING(25*(1+$D$9),1)*12*1085+CEILING(25*(1+$D$9),1)*1450*2+1200)-39246-(CEILING(25*(1+$D$9),1)*48))*0.79,((81900*$D$7+807750*$D$11*0.04+146140)-(CEILING(25*(1+$D$8),1)*((F22*173.3333)*14*1.2375+1584)+CEILING(25*(1+$D$8),1)*(F22*173.3333)*1.7*2+60975+CEILING(25*(1+$D$8),1)*300*$D$10)-(CEILING(25*(1+$D$9),1)*12*1085+CEILING(25*(1+$D$9),1)*1450*2+1200)-39246-(CEILING(25*(1+$D$9),1)*48))) -> 75150.472 | G23: =IF(((81900*$D$7+807750*$D$11*0.04+146140)-(CEILING(25*(1+$D$8),1)*((G22*173.3333)*14*1.2375+1584)+CEILING(25*(1+$D$8),1)*(G22*173.3333)*1.7*2+60975+CEILING(25*(1+$D$8),1)*300*$D$10)-(CEILING(25*(1+$D$9),1)*12*1085+CEILING(25*(1+$D$9),1)*1450*2+1200)-39246-(CEILING(25*(1+$D$9),1)*48))>0,((81900*$D$7+807750*$D$11*0.04+146140)-(CEILING(25*(1+$D$8),1)*((G22*173.3333)*14*1.2375+1584)+CEILING(25*(1+$D$8),1)*(G22*173.3333)*1.7*2+60975+CEILING(25*(1+$D$8),1)*300*$D$10)-(CEILING(25*(1+$D$9),1)*12*1085+CEILING(25*(1+$D$9),1)*1450*2+1200)-39246-(CEILING(25*(1+$D$9),1)*48))*0.79,((81900*$D$7+807750*$D$11*0.04+146140)-(CEILING(25*(1+$D$8),1)*((G22*173.3333)*14*1.2375+1584)+CEILING(25*(1+$D$8),1)*(G22*173.3333)*1.7*2+60975+CEILING(25*(1+$D$8),1)*300*$D$10)-(CEILING(25*(1+$D$9),1)*12*1085+CEILING(25*(1+$D$9),1)*1450*2+1200)-39246-(CEILING(25*(1+$D$9),1)*48))) -> -9050.4663
B24: Taxa base Amazon (€/h) | C24: 16 | D24: 17 | E24: 17.9 | F24: 19 | G24: 20
B25: -> Resultado liquido / Net profit | C25: =IF(((81900*C24+807750*$D$11*0.04+146140)-(CEILING(25*(1+$D$8),1)*(($D$6*173.3333)*14*1.2375+1584)+CEILING(25*(1+$D$8),1)*($D$6*173.3333)*1.7*2+60975+CEILING(25*(1+$D$8),1)*300*$D$10)-(CEILING(25*(1+$D$9),1)*12*1085+CEILING(25*(1+$D$9),1)*1450*2+1200)-39246-(CEILING(25*(1+$D$9),1)*48))>0,((81900*C24+807750*$D$11*0.04+146140)-(CEILING(25*(1+$D$8),1)*(($D$6*173.3333)*14*1.2375+1584)+CEILING(25*(1+$D$8),1)*($D$6*173.3333)*1.7*2+60975+CEILING(25*(1+$D$8),1)*300*$D$10)-(CEILING(25*(1+$D$9),1)*12*1085+CEILING(25*(1+$D$9),1)*1450*2+1200)-39246-(CEILING(25*(1+$D$9),1)*48))*0.79,((81900*C24+807750*$D$11*0.04+146140)-(CEILING(25*(1+$D$8),1)*(($D$6*173.3333)*14*1.2375+1584)+CEILING(25*(1+$D$8),1)*($D$6*173.3333)*1.7*2+60975+CEILING(25*(1+$D$8),1)*300*$D$10)-(CEILING(25*(1+$D$9),1)*12*1085+CEILING(25*(1+$D$9),1)*1450*2+1200)-39246-(CEILING(25*(1+$D$9),1)*48))) -> 182659.53 | D25: =IF(((81900*D24+807750*$D$11*0.04+146140)-(CEILING(25*(1+$D$8),1)*(($D$6*173.3333)*14*1.2375+1584)+CEILING(25*(1+$D$8),1)*($D$6*173.3333)*1.7*2+60975+CEILING(25*(1+$D$8),1)*300*$D$10)-(CEILING(25*(1+$D$9),1)*12*1085+CEILING(25*(1+$D$9),1)*1450*2+1200)-39246-(CEILING(25*(1+$D$9),1)*48))>0,((81900*D24+807750*$D$11*0.04+146140)-(CEILING(25*(1+$D$8),1)*(($D$6*173.3333)*14*1.2375+1584)+CEILING(25*(1+$D$8),1)*($D$6*173.3333)*1.7*2+60975+CEILING(25*(1+$D$8),1)*300*$D$10)-(CEILING(25*(1+$D$9),1)*12*1085+CEILING(25*(1+$D$9),1)*1450*2+1200)-39246-(CEILING(25*(1+$D$9),1)*48))*0.79,((81900*D24+807750*$D$11*0.04+146140)-(CEILING(25*(1+$D$8),1)*(($D$6*173.3333)*14*1.2375+1584)+CEILING(25*(1+$D$8),1)*($D$6*173.3333)*1.7*2+60975+CEILING(25*(1+$D$8),1)*300*$D$10)-(CEILING(25*(1+$D$9),1)*12*1085+CEILING(25*(1+$D$9),1)*1450*2+1200)-39246-(CEILING(25*(1+$D$9),1)*48))) -> 247360.53 | E25: =IF(((81900*E24+807750*$D$11*0.04+146140)-(CEILING(25*(1+$D$8),1)*(($D$6*173.3333)*14*1.2375+1584)+CEILING(25*(1+$D$8),1)*($D$6*173.3333)*1.7*2+60975+CEILING(25*(1+$D$8),1)*300*$D$10)-(CEILING(25*(1+$D$9),1)*12*1085+CEILING(25*(1+$D$9),1)*1450*2+1200)-39246-(CEILING(25*(1+$D$9),1)*48))>0,((81900*E24+807750*$D$11*0.04+146140)-(CEILING(25*(1+$D$8),1)*(($D$6*173.3333)*14*1.2375+1584)+CEILING(25*(1+$D$8),1)*($D$6*173.3333)*1.7*2+60975+CEILING(25*(1+$D$8),1)*300*$D$10)-(CEILING(25*(1+$D$9),1)*12*1085+CEILING(25*(1+$D$9),1)*1450*2+1200)-39246-(CEILING(25*(1+$D$9),1)*48))*0.79,((81900*E24+807750*$D$11*0.04+146140)-(CEILING(25*(1+$D$8),1)*(($D$6*173.3333)*14*1.2375+1584)+CEILING(25*(1+$D$8),1)*($D$6*173.3333)*1.7*2+60975+CEILING(25*(1+$D$8),1)*300*$D$10)-(CEILING(25*(1+$D$9),1)*12*1085+CEILING(25*(1+$D$9),1)*1450*2+1200)-39246-(CEILING(25*(1+$D$9),1)*48))) -> 305591.43 | F25: =IF(((81900*F24+807750*$D$11*0.04+146140)-(CEILING(25*(1+$D$8),1)*(($D$6*173.3333)*14*1.2375+1584)+CEILING(25*(1+$D$8),1)*($D$6*173.3333)*1.7*2+60975+CEILING(25*(1+$D$8),1)*300*$D$10)-(CEILING(25*(1+$D$9),1)*12*1085+CEILING(25*(1+$D$9),1)*1450*2+1200)-39246-(CEILING(25*(1+$D$9),1)*48))>0,((81900*F24+807750*$D$11*0.04+146140)-(CEILING(25*(1+$D$8),1)*(($D$6*173.3333)*14*1.2375+1584)+CEILING(25*(1+$D$8),1)*($D$6*173.3333)*1.7*2+60975+CEILING(25*(1+$D$8),1)*300*$D$10)-(CEILING(25*(1+$D$9),1)*12*1085+CEILING(25*(1+$D$9),1)*1450*2+1200)-39246-(CEILING(25*(1+$D$9),1)*48))*0.79,((81900*F24+807750*$D$11*0.04+146140)-(CEILING(25*(1+$D$8),1)*(($D$6*173.3333)*14*1.2375+1584)+CEILING(25*(1+$D$8),1)*($D$6*173.3333)*1.7*2+60975+CEILING(25*(1+$D$8),1)*300*$D$10)-(CEILING(25*(1+$D$9),1)*12*1085+CEILING(25*(1+$D$9),1)*1450*2+1200)-39246-(CEILING(25*(1+$D$9),1)*48))) -> 376762.53 | G25: =IF(((81900*G24+807750*$D$11*0.04+146140)-(CEILING(25*(1+$D$8),1)*(($D$6*173.3333)*14*1.2375+1584)+CEILING(25*(1+$D$8),1)*($D$6*173.3333)*1.7*2+60975+CEILING(25*(1+$D$8),1)*300*$D$10)-(CEILING(25*(1+$D$9),1)*12*1085+CEILING(25*(1+$D$9),1)*1450*2+1200)-39246-(CEILING(25*(1+$D$9),1)*48))>0,((81900*G24+807750*$D$11*0.04+146140)-(CEILING(25*(1+$D$8),1)*(($D$6*173.3333)*14*1.2375+1584)+CEILING(25*(1+$D$8),1)*($D$6*173.3333)*1.7*2+60975+CEILING(25*(1+$D$8),1)*300*$D$10)-(CEILING(25*(1+$D$9),1)*12*1085+CEILING(25*(1+$D$9),1)*1450*2+1200)-39246-(CEILING(25*(1+$D$9),1)*48))*0.79,((81900*G24+807750*$D$11*0.04+146140)-(CEILING(25*(1+$D$8),1)*(($D$6*173.3333)*14*1.2375+1584)+CEILING(25*(1+$D$8),1)*($D$6*173.3333)*1.7*2+60975+CEILING(25*(1+$D$8),1)*300*$D$10)-(CEILING(25*(1+$D$9),1)*12*1085+CEILING(25*(1+$D$9),1)*1450*2+1200)-39246-(CEILING(25*(1+$D$9),1)*48))) -> 441463.53
B26: Buffer motoristas | C26: 0.1 | D26: 0.15 | E26: 0.2 | F26: 0.25 | G26: 0.3
B27: -> Resultado liquido / Net profit | C27: =IF(((81900*$D$7+807750*$D$11*0.04+146140)-(CEILING(25*(1+C26),1)*(($D$6*173.3333)*14*1.2375+1584)+CEILING(25*(1+C26),1)*($D$6*173.3333)*1.7*2+60975+CEILING(25*(1+C26),1)*300*$D$10)-(CEILING(25*(1+$D$9),1)*12*1085+CEILING(25*(1+$D$9),1)*1450*2+1200)-39246-(CEILING(25*(1+$D$9),1)*48))>0,((81900*$D$7+807750*$D$11*0.04+146140)-(CEILING(25*(1+C26),1)*(($D$6*173.3333)*14*1.2375+1584)+CEILING(25*(1+C26),1)*($D$6*173.3333)*1.7*2+60975+CEILING(25*(1+C26),1)*300*$D$10)-(CEILING(25*(1+$D$9),1)*12*1085+CEILING(25*(1+$D$9),1)*1450*2+1200)-39246-(CEILING(25*(1+$D$9),1)*48))*0.79,((81900*$D$7+807750*$D$11*0.04+146140)-(CEILING(25*(1+C26),1)*(($D$6*173.3333)*14*1.2375+1584)+CEILING(25*(1+C26),1)*($D$6*173.3333)*1.7*2+60975+CEILING(25*(1+C26),1)*300*$D$10)-(CEILING(25*(1+$D$9),1)*12*1085+CEILING(25*(1+$D$9),1)*1450*2+1200)-39246-(CEILING(25*(1+$D$9),1)*48))) -> 324473.58 | D27: =IF(((81900*$D$7+807750*$D$11*0.04+146140)-(CEILING(25*(1+D26),1)*(($D$6*173.3333)*14*1.2375+1584)+CEILING(25*(1+D26),1)*($D$6*173.3333)*1.7*2+60975+CEILING(25*(1+D26),1)*300*$D$10)-(CEILING(25*(1+$D$9),1)*12*1085+CEILING(25*(1+$D$9),1)*1450*2+1200)-39246-(CEILING(25*(1+$D$9),1)*48))>0,((81900*$D$7+807750*$D$11*0.04+146140)-(CEILING(25*(1+D26),1)*(($D$6*173.3333)*14*1.2375+1584)+CEILING(25*(1+D26),1)*($D$6*173.3333)*1.7*2+60975+CEILING(25*(1+D26),1)*300*$D$10)-(CEILING(25*(1+$D$9),1)*12*1085+CEILING(25*(1+$D$9),1)*1450*2+1200)-39246-(CEILING(25*(1+$D$9),1)*48))*0.79,((81900*$D$7+807750*$D$11*0.04+146140)-(CEILING(25*(1+D26),1)*(($D$6*173.3333)*14*1.2375+1584)+CEILING(25*(1+D26),1)*($D$6*173.3333)*1.7*2+60975+CEILING(25*(1+D26),1)*300*$D$10)-(CEILING(25*(1+$D$9),1)*12*1085+CEILING(25*(1+$D$9),1)*1450*2+1200)-39246-(CEILING(25*(1+$D$9),1)*48))) -> 305591.43 | E27: =IF(((81900*$D$7+807750*$D$11*0.04+146140)-(CEILING(25*(1+E26),1)*(($D$6*173.3333)*14*1.2375+1584)+CEILING(25*(1+E26),1)*($D$6*173.3333)*1.7*2+60975+CEILING(25*(1+E26),1)*300*$D$10)-(CEILING(25*(1+$D$9),1)*12*1085+CEILING(25*(1+$D$9),1)*1450*2+1200)-39246-(CEILING(25*(1+$D$9),1)*48))>0,((81900*$D$7+807750*$D$11*0.04+146140)-(CEILING(25*(1+E26),1)*(($D$6*173.3333)*14*1.2375+1584)+CEILING(25*(1+E26),1)*($D$6*173.3333)*1.7*2+60975+CEILING(25*(1+E26),1)*300*$D$10)-(CEILING(25*(1+$D$9),1)*12*1085+CEILING(25*(1+$D$9),1)*1450*2+1200)-39246-(CEILING(25*(1+$D$9),1)*48))*0.79,((81900*$D$7+807750*$D$11*0.04+146140)-(CEILING(25*(1+E26),1)*(($D$6*173.3333)*14*1.2375+1584)+CEILING(25*(1+E26),1)*($D$6*173.3333)*1.7*2+60975+CEILING(25*(1+E26),1)*300*$D$10)-(CEILING(25*(1+$D$9),1)*12*1085+CEILING(25*(1+$D$9),1)*1450*2+1200)-39246-(CEILING(25*(1+$D$9),1)*48))) -> 286709.27 | F27: =IF(((81900*$D$7+807750*$D$11*0.04+146140)-(CEILING(25*(1+F26),1)*(($D$6*173.3333)*14*1.2375+1584)+CEILING(25*(1+F26),1)*($D$6*173.3333)*1.7*2+60975+CEILING(25*(1+F26),1)*300*$D$10)-(CEILING(25*(1+$D$9),1)*12*1085+CEILING(25*(1+$D$9),1)*1450*2+1200)-39246-(CEILING(25*(1+$D$9),1)*48))>0,((81900*$D$7+807750*$D$11*0.04+146140)-(CEILING(25*(1+F26),1)*(($D$6*173.3333)*14*1.2375+1584)+CEILING(25*(1+F26),1)*($D$6*173.3333)*1.7*2+60975+CEILING(25*(1+F26),1)*300*$D$10)-(CEILING(25*(1+$D$9),1)*12*1085+CEILING(25*(1+$D$9),1)*1450*2+1200)-39246-(CEILING(25*(1+$D$9),1)*48))*0.79,((81900*$D$7+807750*$D$11*0.04+146140)-(CEILING(25*(1+F26),1)*(($D$6*173.3333)*14*1.2375+1584)+CEILING(25*(1+F26),1)*($D$6*173.3333)*1.7*2+60975+CEILING(25*(1+F26),1)*300*$D$10)-(CEILING(25*(1+$D$9),1)*12*1085+CEILING(25*(1+$D$9),1)*1450*2+1200)-39246-(CEILING(25*(1+$D$9),1)*48))) -> 248944.96 | G27: =IF(((81900*$D$7+807750*$D$11*0.04+146140)-(CEILING(25*(1+G26),1)*(($D$6*173.3333)*14*1.2375+1584)+CEILING(25*(1+G26),1)*($D$6*173.3333)*1.7*2+60975+CEILING(25*(1+G26),1)*300*$D$10)-(CEILING(25*(1+$D$9),1)*12*1085+CEILING(25*(1+$D$9),1)*1450*2+1200)-39246-(CEILING(25*(1+$D$9),1)*48))>0,((81900*$D$7+807750*$D$11*0.04+146140)-(CEILING(25*(1+G26),1)*(($D$6*173.3333)*14*1.2375+1584)+CEILING(25*(1+G26),1)*($D$6*173.3333)*1.7*2+60975+CEILING(25*(1+G26),1)*300*$D$10)-(CEILING(25*(1+$D$9),1)*12*1085+CEILING(25*(1+$D$9),1)*1450*2+1200)-39246-(CEILING(25*(1+$D$9),1)*48))*0.79,((81900*$D$7+807750*$D$11*0.04+146140)-(CEILING(25*(1+G26),1)*(($D$6*173.3333)*14*1.2375+1584)+CEILING(25*(1+G26),1)*($D$6*173.3333)*1.7*2+60975+CEILING(25*(1+G26),1)*300*$D$10)-(CEILING(25*(1+$D$9),1)*12*1085+CEILING(25*(1+$D$9),1)*1450*2+1200)-39246-(CEILING(25*(1+$D$9),1)*48))) -> 230062.81
B28: Buffer frota | C28: 0.05 | D28: 0.1 | E28: 0.15 | F28: 0.2 | G28: 0.25 | J28: Ver melhor
B29: -> Resultado liquido / Net profit | C29: =IF(((81900*$D$7+807750*$D$11*0.04+146140)-(CEILING(25*(1+$D$8),1)*(($D$6*173.3333)*14*1.2375+1584)+CEILING(25*(1+$D$8),1)*($D$6*173.3333)*1.7*2+60975+CEILING(25*(1+$D$8),1)*300*$D$10)-(CEILING(25*(1+C28),1)*12*1085+CEILING(25*(1+C28),1)*1450*2+1200)-39246-(CEILING(25*(1+C28),1)*48))>0,((81900*$D$7+807750*$D$11*0.04+146140)-(CEILING(25*(1+$D$8),1)*(($D$6*173.3333)*14*1.2375+1584)+CEILING(25*(1+$D$8),1)*($D$6*173.3333)*1.7*2+60975+CEILING(25*(1+$D$8),1)*300*$D$10)-(CEILING(25*(1+C28),1)*12*1085+CEILING(25*(1+C28),1)*1450*2+1200)-39246-(CEILING(25*(1+C28),1)*48))*0.79,((81900*$D$7+807750*$D$11*0.04+146140)-(CEILING(25*(1+$D$8),1)*(($D$6*173.3333)*14*1.2375+1584)+CEILING(25*(1+$D$8),1)*($D$6*173.3333)*1.7*2+60975+CEILING(25*(1+$D$8),1)*300*$D$10)-(CEILING(25*(1+C28),1)*12*1085+CEILING(25*(1+C28),1)*1450*2+1200)-39246-(CEILING(25*(1+C28),1)*48))) -> 330820.87 | D29: =IF(((81900*$D$7+807750*$D$11*0.04+146140)-(CEILING(25*(1+$D$8),1)*(($D$6*173.3333)*14*1.2375+1584)+CEILING(25*(1+$D$8),1)*($D$6*173.3333)*1.7*2+60975+CEILING(25*(1+$D$8),1)*300*$D$10)-(CEILING(25*(1+D28),1)*12*1085+CEILING(25*(1+D28),1)*1450*2+1200)-39246-(CEILING(25*(1+D28),1)*48))>0,((81900*$D$7+807750*$D$11*0.04+146140)-(CEILING(25*(1+$D$8),1)*(($D$6*173.3333)*14*1.2375+1584)+CEILING(25*(1+$D$8),1)*($D$6*173.3333)*1.7*2+60975+CEILING(25*(1+$D$8),1)*300*$D$10)-(CEILING(25*(1+D28),1)*12*1085+CEILING(25*(1+D28),1)*1450*2+1200)-39246-(CEILING(25*(1+D28),1)*48))*0.79,((81900*$D$7+807750*$D$11*0.04+146140)-(CEILING(25*(1+$D$8),1)*(($D$6*173.3333)*14*1.2375+1584)+CEILING(25*(1+$D$8),1)*($D$6*173.3333)*1.7*2+60975+CEILING(25*(1+$D$8),1)*300*$D$10)-(CEILING(25*(1+D28),1)*12*1085+CEILING(25*(1+D28),1)*1450*2+1200)-39246-(CEILING(25*(1+D28),1)*48))) -> 318206.15 | E29: =IF(((81900*$D$7+807750*$D$11*0.04+146140)-(CEILING(25*(1+$D$8),1)*(($D$6*173.3333)*14*1.2375+1584)+CEILING(25*(1+$D$8),1)*($D$6*173.3333)*1.7*2+60975+CEILING(25*(1+$D$8),1)*300*$D$10)-(CEILING(25*(1+E28),1)*12*1085+CEILING(25*(1+E28),1)*1450*2+1200)-39246-(CEILING(25*(1+E28),1)*48))>0,((81900*$D$7+807750*$D$11*0.04+146140)-(CEILING(25*(1+$D$8),1)*(($D$6*173.3333)*14*1.2375+1584)+CEILING(25*(1+$D$8),1)*($D$6*173.3333)*1.7*2+60975+CEILING(25*(1+$D$8),1)*300*$D$10)-(CEILING(25*(1+E28),1)*12*1085+CEILING(25*(1+E28),1)*1450*2+1200)-39246-(CEILING(25*(1+E28),1)*48))*0.79,((81900*$D$7+807750*$D$11*0.04+146140)-(CEILING(25*(1+$D$8),1)*(($D$6*173.3333)*14*1.2375+1584)+CEILING(25*(1+$D$8),1)*($D$6*173.3333)*1.7*2+60975+CEILING(25*(1+$D$8),1)*300*$D$10)-(CEILING(25*(1+E28),1)*12*1085+CEILING(25*(1+E28),1)*1450*2+1200)-39246-(CEILING(25*(1+E28),1)*48))) -> 305591.43 | F29: =IF(((81900*$D$7+807750*$D$11*0.04+146140)-(CEILING(25*(1+$D$8),1)*(($D$6*173.3333)*14*1.2375+1584)+CEILING(25*(1+$D$8),1)*($D$6*173.3333)*1.7*2+60975+CEILING(25*(1+$D$8),1)*300*$D$10)-(CEILING(25*(1+F28),1)*12*1085+CEILING(25*(1+F28),1)*1450*2+1200)-39246-(CEILING(25*(1+F28),1)*48))>0,((81900*$D$7+807750*$D$11*0.04+146140)-(CEILING(25*(1+$D$8),1)*(($D$6*173.3333)*14*1.2375+1584)+CEILING(25*(1+$D$8),1)*($D$6*173.3333)*1.7*2+60975+CEILING(25*(1+$D$8),1)*300*$D$10)-(CEILING(25*(1+F28),1)*12*1085+CEILING(25*(1+F28),1)*1450*2+1200)-39246-(CEILING(25*(1+F28),1)*48))*0.79,((81900*$D$7+807750*$D$11*0.04+146140)-(CEILING(25*(1+$D$8),1)*(($D$6*173.3333)*14*1.2375+1584)+CEILING(25*(1+$D$8),1)*($D$6*173.3333)*1.7*2+60975+CEILING(25*(1+$D$8),1)*300*$D$10)-(CEILING(25*(1+F28),1)*12*1085+CEILING(25*(1+F28),1)*1450*2+1200)-39246-(CEILING(25*(1+F28),1)*48))) -> 292976.71 | G29: =IF(((81900*$D$7+807750*$D$11*0.04+146140)-(CEILING(25*(1+$D$8),1)*(($D$6*173.3333)*14*1.2375+1584)+CEILING(25*(1+$D$8),1)*($D$6*173.3333)*1.7*2+60975+CEILING(25*(1+$D$8),1)*300*$D$10)-(CEILING(25*(1+G28),1)*12*1085+CEILING(25*(1+G28),1)*1450*2+1200)-39246-(CEILING(25*(1+G28),1)*48))>0,((81900*$D$7+807750*$D$11*0.04+146140)-(CEILING(25*(1+$D$8),1)*(($D$6*173.3333)*14*1.2375+1584)+CEILING(25*(1+$D$8),1)*($D$6*173.3333)*1.7*2+60975+CEILING(25*(1+$D$8),1)*300*$D$10)-(CEILING(25*(1+G28),1)*12*1085+CEILING(25*(1+G28),1)*1450*2+1200)-39246-(CEILING(25*(1+G28),1)*48))*0.79,((81900*$D$7+807750*$D$11*0.04+146140)-(CEILING(25*(1+$D$8),1)*(($D$6*173.3333)*14*1.2375+1584)+CEILING(25*(1+$D$8),1)*($D$6*173.3333)*1.7*2+60975+CEILING(25*(1+$D$8),1)*300*$D$10)-(CEILING(25*(1+G28),1)*12*1085+CEILING(25*(1+G28),1)*1450*2+1200)-39246-(CEILING(25*(1+G28),1)*48))) -> 267747.27
B30: Rotatividade | C30: 0.1 | D30: 0.15 | E30: 0.2 | F30: 0.25 | G30: 0.3
B31: -> Resultado liquido / Net profit | C31: =IF(((81900*$D$7+807750*$D$11*0.04+146140)-(CEILING(25*(1+$D$8),1)*(($D$6*173.3333)*14*1.2375+1584)+CEILING(25*(1+$D$8),1)*($D$6*173.3333)*1.7*2+60975+CEILING(25*(1+$D$8),1)*300*C30)-(CEILING(25*(1+$D$9),1)*12*1085+CEILING(25*(1+$D$9),1)*1450*2+1200)-39246-(CEILING(25*(1+$D$9),1)*48))>0,((81900*$D$7+807750*$D$11*0.04+146140)-(CEILING(25*(1+$D$8),1)*(($D$6*173.3333)*14*1.2375+1584)+CEILING(25*(1+$D$8),1)*($D$6*173.3333)*1.7*2+60975+CEILING(25*(1+$D$8),1)*300*C30)-(CEILING(25*(1+$D$9),1)*12*1085+CEILING(25*(1+$D$9),1)*1450*2+1200)-39246-(CEILING(25*(1+$D$9),1)*48))*0.79,((81900*$D$7+807750*$D$11*0.04+146140)-(CEILING(25*(1+$D$8),1)*(($D$6*173.3333)*14*1.2375+1584)+CEILING(25*(1+$D$8),1)*($D$6*173.3333)*1.7*2+60975+CEILING(25*(1+$D$8),1)*300*C30)-(CEILING(25*(1+$D$9),1)*12*1085+CEILING(25*(1+$D$9),1)*1450*2+1200)-39246-(CEILING(25*(1+$D$9),1)*48))) -> 305935.08 | D31: =IF(((81900*$D$7+807750*$D$11*0.04+146140)-(CEILING(25*(1+$D$8),1)*(($D$6*173.3333)*14*1.2375+1584)+CEILING(25*(1+$D$8),1)*($D$6*173.3333)*1.7*2+60975+CEILING(25*(1+$D$8),1)*300*D30)-(CEILING(25*(1+$D$9),1)*12*1085+CEILING(25*(1+$D$9),1)*1450*2+1200)-39246-(CEILING(25*(1+$D$9),1)*48))>0,((81900*$D$7+807750*$D$11*0.04+146140)-(CEILING(25*(1+$D$8),1)*(($D$6*173.3333)*14*1.2375+1584)+CEILING(25*(1+$D$8),1)*($D$6*173.3333)*1.7*2+60975+CEILING(25*(1+$D$8),1)*300*D30)-(CEILING(25*(1+$D$9),1)*12*1085+CEILING(25*(1+$D$9),1)*1450*2+1200)-39246-(CEILING(25*(1+$D$9),1)*48))*0.79,((81900*$D$7+807750*$D$11*0.04+146140)-(CEILING(25*(1+$D$8),1)*(($D$6*173.3333)*14*1.2375+1584)+CEILING(25*(1+$D$8),1)*($D$6*173.3333)*1.7*2+60975+CEILING(25*(1+$D$8),1)*300*D30)-(CEILING(25*(1+$D$9),1)*12*1085+CEILING(25*(1+$D$9),1)*1450*2+1200)-39246-(CEILING(25*(1+$D$9),1)*48))) -> 305591.43 | E31: =IF(((81900*$D$7+807750*$D$11*0.04+146140)-(CEILING(25*(1+$D$8),1)*(($D$6*173.3333)*14*1.2375+1584)+CEILING(25*(1+$D$8),1)*($D$6*173.3333)*1.7*2+60975+CEILING(25*(1+$D$8),1)*300*E30)-(CEILING(25*(1+$D$9),1)*12*1085+CEILING(25*(1+$D$9),1)*1450*2+1200)-39246-(CEILING(25*(1+$D$9),1)*48))>0,((81900*$D$7+807750*$D$11*0.04+146140)-(CEILING(25*(1+$D$8),1)*(($D$6*173.3333)*14*1.2375+1584)+CEILING(25*(1+$D$8),1)*($D$6*173.3333)*1.7*2+60975+CEILING(25*(1+$D$8),1)*300*E30)-(CEILING(25*(1+$D$9),1)*12*1085+CEILING(25*(1+$D$9),1)*1450*2+1200)-39246-(CEILING(25*(1+$D$9),1)*48))*0.79,((81900*$D$7+807750*$D$11*0.04+146140)-(CEILING(25*(1+$D$8),1)*(($D$6*173.3333)*14*1.2375+1584)+CEILING(25*(1+$D$8),1)*($D$6*173.3333)*1.7*2+60975+CEILING(25*(1+$D$8),1)*300*E30)-(CEILING(25*(1+$D$9),1)*12*1085+CEILING(25*(1+$D$9),1)*1450*2+1200)-39246-(CEILING(25*(1+$D$9),1)*48))) -> 305247.78 | F31: =IF(((81900*$D$7+807750*$D$11*0.04+146140)-(CEILING(25*(1+$D$8),1)*(($D$6*173.3333)*14*1.2375+1584)+CEILING(25*(1+$D$8),1)*($D$6*173.3333)*1.7*2+60975+CEILING(25*(1+$D$8),1)*300*F30)-(CEILING(25*(1+$D$9),1)*12*1085+CEILING(25*(1+$D$9),1)*1450*2+1200)-39246-(CEILING(25*(1+$D$9),1)*48))>0,((81900*$D$7+807750*$D$11*0.04+146140)-(CEILING(25*(1+$D$8),1)*(($D$6*173.3333)*14*1.2375+1584)+CEILING(25*(1+$D$8),1)*($D$6*173.3333)*1.7*2+60975+CEILING(25*(1+$D$8),1)*300*F30)-(CEILING(25*(1+$D$9),1)*12*1085+CEILING(25*(1+$D$9),1)*1450*2+1200)-39246-(CEILING(25*(1+$D$9),1)*48))*0.79,((81900*$D$7+807750*$D$11*0.04+146140)-(CEILING(25*(1+$D$8),1)*(($D$6*173.3333)*14*1.2375+1584)+CEILING(25*(1+$D$8),1)*($D$6*173.3333)*1.7*2+60975+CEILING(25*(1+$D$8),1)*300*F30)-(CEILING(25*(1+$D$9),1)*12*1085+CEILING(25*(1+$D$9),1)*1450*2+1200)-39246-(CEILING(25*(1+$D$9),1)*48))) -> 304904.13 | G31: =IF(((81900*$D$7+807750*$D$11*0.04+146140)-(CEILING(25*(1+$D$8),1)*(($D$6*173.3333)*14*1.2375+1584)+CEILING(25*(1+$D$8),1)*($D$6*173.3333)*1.7*2+60975+CEILING(25*(1+$D$8),1)*300*G30)-(CEILING(25*(1+$D$9),1)*12*1085+CEILING(25*(1+$D$9),1)*1450*2+1200)-39246-(CEILING(25*(1+$D$9),1)*48))>0,((81900*$D$7+807750*$D$11*0.04+146140)-(CEILING(25*(1+$D$8),1)*(($D$6*173.3333)*14*1.2375+1584)+CEILING(25*(1+$D$8),1)*($D$6*173.3333)*1.7*2+60975+CEILING(25*(1+$D$8),1)*300*G30)-(CEILING(25*(1+$D$9),1)*12*1085+CEILING(25*(1+$D$9),1)*1450*2+1200)-39246-(CEILING(25*(1+$D$9),1)*48))*0.79,((81900*$D$7+807750*$D$11*0.04+146140)-(CEILING(25*(1+$D$8),1)*(($D$6*173.3333)*14*1.2375+1584)+CEILING(25*(1+$D$8),1)*($D$6*173.3333)*1.7*2+60975+CEILING(25*(1+$D$8),1)*300*G30)-(CEILING(25*(1+$D$9),1)*12*1085+CEILING(25*(1+$D$9),1)*1450*2+1200)-39246-(CEILING(25*(1+$D$9),1)*48))) -> 304560.48
B32: Volume (x base) | C32: 0.85 | D32: 0.95 | E32: 1 | F32: 1.05 | G32: 1.15
B33: -> Resultado liquido / Net profit | C33: =IF(((81900*$D$7+807750*C32*0.04+146140)-(CEILING(25*(1+$D$8),1)*(($D$6*173.3333)*14*1.2375+1584)+CEILING(25*(1+$D$8),1)*($D$6*173.3333)*1.7*2+60975+CEILING(25*(1+$D$8),1)*300*$D$10)-(CEILING(25*(1+$D$9),1)*12*1085+CEILING(25*(1+$D$9),1)*1450*2+1200)-39246-(CEILING(25*(1+$D$9),1)*48))>0,((81900*$D$7+807750*C32*0.04+146140)-(CEILING(25*(1+$D$8),1)*(($D$6*173.3333)*14*1.2375+1584)+CEILING(25*(1+$D$8),1)*($D$6*173.3333)*1.7*2+60975+CEILING(25*(1+$D$8),1)*300*$D$10)-(CEILING(25*(1+$D$9),1)*12*1085+CEILING(25*(1+$D$9),1)*1450*2+1200)-39246-(CEILING(25*(1+$D$9),1)*48))*0.79,((81900*$D$7+807750*C32*0.04+146140)-(CEILING(25*(1+$D$8),1)*(($D$6*173.3333)*14*1.2375+1584)+CEILING(25*(1+$D$8),1)*($D$6*173.3333)*1.7*2+60975+CEILING(25*(1+$D$8),1)*300*$D$10)-(CEILING(25*(1+$D$9),1)*12*1085+CEILING(25*(1+$D$9),1)*1450*2+1200)-39246-(CEILING(25*(1+$D$9),1)*48))) -> 301762.69 | D33: =IF(((81900*$D$7+807750*D32*0.04+146140)-(CEILING(25*(1+$D$8),1)*(($D$6*173.3333)*14*1.2375+1584)+CEILING(25*(1+$D$8),1)*($D$6*173.3333)*1.7*2+60975+CEILING(25*(1+$D$8),1)*300*$D$10)-(CEILING(25*(1+$D$9),1)*12*1085+CEILING(25*(1+$D$9),1)*1450*2+1200)-39246-(CEILING(25*(1+$D$9),1)*48))>0,((81900*$D$7+807750*D32*0.04+146140)-(CEILING(25*(1+$D$8),1)*(($D$6*173.3333)*14*1.2375+1584)+CEILING(25*(1+$D$8),1)*($D$6*173.3333)*1.7*2+60975+CEILING(25*(1+$D$8),1)*300*$D$10)-(CEILING(25*(1+$D$9),1)*12*1085+CEILING(25*(1+$D$9),1)*1450*2+1200)-39246-(CEILING(25*(1+$D$9),1)*48))*0.79,((81900*$D$7+807750*D32*0.04+146140)-(CEILING(25*(1+$D$8),1)*(($D$6*173.3333)*14*1.2375+1584)+CEILING(25*(1+$D$8),1)*($D$6*173.3333)*1.7*2+60975+CEILING(25*(1+$D$8),1)*300*$D$10)-(CEILING(25*(1+$D$9),1)*12*1085+CEILING(25*(1+$D$9),1)*1450*2+1200)-39246-(CEILING(25*(1+$D$9),1)*48))) -> 304315.18 | E33: =IF(((81900*$D$7+807750*E32*0.04+146140)-(CEILING(25*(1+$D$8),1)*(($D$6*173.3333)*14*1.2375+1584)+CEILING(25*(1+$D$8),1)*($D$6*173.3333)*1.7*2+60975+CEILING(25*(1+$D$8),1)*300*$D$10)-(CEILING(25*(1+$D$9),1)*12*1085+CEILING(25*(1+$D$9),1)*1450*2+1200)-39246-(CEILING(25*(1+$D$9),1)*48))>0,((81900*$D$7+807750*E32*0.04+146140)-(CEILING(25*(1+$D$8),1)*(($D$6*173.3333)*14*1.2375+1584)+CEILING(25*(1+$D$8),1)*($D$6*173.3333)*1.7*2+60975+CEILING(25*(1+$D$8),1)*300*$D$10)-(CEILING(25*(1+$D$9),1)*12*1085+CEILING(25*(1+$D$9),1)*1450*2+1200)-39246-(CEILING(25*(1+$D$9),1)*48))*0.79,((81900*$D$7+807750*E32*0.04+146140)-(CEILING(25*(1+$D$8),1)*(($D$6*173.3333)*14*1.2375+1584)+CEILING(25*(1+$D$8),1)*($D$6*173.3333)*1.7*2+60975+CEILING(25*(1+$D$8),1)*300*$D$10)-(CEILING(25*(1+$D$9),1)*12*1085+CEILING(25*(1+$D$9),1)*1450*2+1200)-39246-(CEILING(25*(1+$D$9),1)*48))) -> 305591.43 | F33: =IF(((81900*$D$7+807750*F32*0.04+146140)-(CEILING(25*(1+$D$8),1)*(($D$6*173.3333)*14*1.2375+1584)+CEILING(25*(1+$D$8),1)*($D$6*173.3333)*1.7*2+60975+CEILING(25*(1+$D$8),1)*300*$D$10)-(CEILING(25*(1+$D$9),1)*12*1085+CEILING(25*(1+$D$9),1)*1450*2+1200)-39246-(CEILING(25*(1+$D$9),1)*48))>0,((81900*$D$7+807750*F32*0.04+146140)-(CEILING(25*(1+$D$8),1)*(($D$6*173.3333)*14*1.2375+1584)+CEILING(25*(1+$D$8),1)*($D$6*173.3333)*1.7*2+60975+CEILING(25*(1+$D$8),1)*300*$D$10)-(CEILING(25*(1+$D$9),1)*12*1085+CEILING(25*(1+$D$9),1)*1450*2+1200)-39246-(CEILING(25*(1+$D$9),1)*48))*0.79,((81900*$D$7+807750*F32*0.04+146140)-(CEILING(25*(1+$D$8),1)*(($D$6*173.3333)*14*1.2375+1584)+CEILING(25*(1+$D$8),1)*($D$6*173.3333)*1.7*2+60975+CEILING(25*(1+$D$8),1)*300*$D$10)-(CEILING(25*(1+$D$9),1)*12*1085+CEILING(25*(1+$D$9),1)*1450*2+1200)-39246-(CEILING(25*(1+$D$9),1)*48))) -> 306867.67 | G33: =IF(((81900*$D$7+807750*G32*0.04+146140)-(CEILING(25*(1+$D$8),1)*(($D$6*173.3333)*14*1.2375+1584)+CEILING(25*(1+$D$8),1)*($D$6*173.3333)*1.7*2+60975+CEILING(25*(1+$D$8),1)*300*$D$10)-(CEILING(25*(1+$D$9),1)*12*1085+CEILING(25*(1+$D$9),1)*1450*2+1200)-39246-(CEILING(25*(1+$D$9),1)*48))>0,((81900*$D$7+807750*G32*0.04+146140)-(CEILING(25*(1+$D$8),1)*(($D$6*173.3333)*14*1.2375+1584)+CEILING(25*(1+$D$8),1)*($D$6*173.3333)*1.7*2+60975+CEILING(25*(1+$D$8),1)*300*$D$10)-(CEILING(25*(1+$D$9),1)*12*1085+CEILING(25*(1+$D$9),1)*1450*2+1200)-39246-(CEILING(25*(1+$D$9),1)*48))*0.79,((81900*$D$7+807750*G32*0.04+146140)-(CEILING(25*(1+$D$8),1)*(($D$6*173.3333)*14*1.2375+1584)+CEILING(25*(1+$D$8),1)*($D$6*173.3333)*1.7*2+60975+CEILING(25*(1+$D$8),1)*300*$D$10)-(CEILING(25*(1+$D$9),1)*12*1085+CEILING(25*(1+$D$9),1)*1450*2+1200)-39246-(CEILING(25*(1+$D$9),1)*48))) -> 309420.16
B35: 3. MATRIZ 2D: Salario/h (linhas) x Taxa base (colunas) -> Resultado liquido
B36: Salario \ Taxa base | C36: 16 | D36: 17.9 | E36: 18 | F36: 19 | G36: 20
B37: 6.5 | C37: =IF(((81900*C$36+807750*$D$11*0.04+146140)-(CEILING(25*(1+$D$8),1)*(($B37*173.3333)*14*1.2375+1584)+CEILING(25*(1+$D$8),1)*($B37*173.3333)*1.7*2+60975+CEILING(25*(1+$D$8),1)*300*$D$10)-(CEILING(25*(1+$D$9),1)*12*1085+CEILING(25*(1+$D$9),1)*1450*2+1200)-39246-(CEILING(25*(1+$D$9),1)*48))>0,((81900*C$36+807750*$D$11*0.04+146140)-(CEILING(25*(1+$D$8),1)*(($B37*173.3333)*14*1.2375+1584)+CEILING(25*(1+$D$8),1)*($B37*173.3333)*1.7*2+60975+CEILING(25*(1+$D$8),1)*300*$D$10)-(CEILING(25*(1+$D$9),1)*12*1085+CEILING(25*(1+$D$9),1)*1450*2+1200)-39246-(CEILING(25*(1+$D$9),1)*48))*0.79,((81900*C$36+807750*$D$11*0.04+146140)-(CEILING(25*(1+$D$8),1)*(($B37*173.3333)*14*1.2375+1584)+CEILING(25*(1+$D$8),1)*($B37*173.3333)*1.7*2+60975+CEILING(25*(1+$D$8),1)*300*$D$10)-(CEILING(25*(1+$D$9),1)*12*1085+CEILING(25*(1+$D$9),1)*1450*2+1200)-39246-(CEILING(25*(1+$D$9),1)*48))) -> 157969.42 | D37: =IF(((81900*D$36+807750*$D$11*0.04+146140)-(CEILING(25*(1+$D$8),1)*(($B37*173.3333)*14*1.2375+1584)+CEILING(25*(1+$D$8),1)*($B37*173.3333)*1.7*2+60975+CEILING(25*(1+$D$8),1)*300*$D$10)-(CEILING(25*(1+$D$9),1)*12*1085+CEILING(25*(1+$D$9),1)*1450*2+1200)-39246-(CEILING(25*(1+$D$9),1)*48))>0,((81900*D$36+807750*$D$11*0.04+146140)-(CEILING(25*(1+$D$8),1)*(($B37*173.3333)*14*1.2375+1584)+CEILING(25*(1+$D$8),1)*($B37*173.3333)*1.7*2+60975+CEILING(25*(1+$D$8),1)*300*$D$10)-(CEILING(25*(1+$D$9),1)*12*1085+CEILING(25*(1+$D$9),1)*1450*2+1200)-39246-(CEILING(25*(1+$D$9),1)*48))*0.79,((81900*D$36+807750*$D$11*0.04+146140)-(CEILING(25*(1+$D$8),1)*(($B37*173.3333)*14*1.2375+1584)+CEILING(25*(1+$D$8),1)*($B37*173.3333)*1.7*2+60975+CEILING(25*(1+$D$8),1)*300*$D$10)-(CEILING(25*(1+$D$9),1)*12*1085+CEILING(25*(1+$D$9),1)*1450*2+1200)-39246-(CEILING(25*(1+$D$9),1)*48))) -> 280901.32 | E37: =IF(((81900*E$36+807750*$D$11*0.04+146140)-(CEILING(25*(1+$D$8),1)*(($B37*173.3333)*14*1.2375+1584)+CEILING(25*(1+$D$8),1)*($B37*173.3333)*1.7*2+60975+CEILING(25*(1+$D$8),1)*300*$D$10)-(CEILING(25*(1+$D$9),1)*12*1085+CEILING(25*(1+$D$9),1)*1450*2+1200)-39246-(CEILING(25*(1+$D$9),1)*48))>0,((81900*E$36+807750*$D$11*0.04+146140)-(CEILING(25*(1+$D$8),1)*(($B37*173.3333)*14*1.2375+1584)+CEILING(25*(1+$D$8),1)*($B37*173.3333)*1.7*2+60975+CEILING(25*(1+$D$8),1)*300*$D$10)-(CEILING(25*(1+$D$9),1)*12*1085+CEILING(25*(1+$D$9),1)*1450*2+1200)-39246-(CEILING(25*(1+$D$9),1)*48))*0.79,((81900*E$36+807750*$D$11*0.04+146140)-(CEILING(25*(1+$D$8),1)*(($B37*173.3333)*14*1.2375+1584)+CEILING(25*(1+$D$8),1)*($B37*173.3333)*1.7*2+60975+CEILING(25*(1+$D$8),1)*300*$D$10)-(CEILING(25*(1+$D$9),1)*12*1085+CEILING(25*(1+$D$9),1)*1450*2+1200)-39246-(CEILING(25*(1+$D$9),1)*48))) -> 287371.42 | F37: =IF(((81900*F$36+807750*$D$11*0.04+146140)-(CEILING(25*(1+$D$8),1)*(($B37*173.3333)*14*1.2375+1584)+CEILING(25*(1+$D$8),1)*($B37*173.3333)*1.7*2+60975+CEILING(25*(1+$D$8),1)*300*$D$10)-(CEILING(25*(1+$D$9),1)*12*1085+CEILING(25*(1+$D$9),1)*1450*2+1200)-39246-(CEILING(25*(1+$D$9),1)*48))>0,((81900*F$36+807750*$D$11*0.04+146140)-(CEILING(25*(1+$D$8),1)*(($B37*173.3333)*14*1.2375+1584)+CEILING(25*(1+$D$8),1)*($B37*173.3333)*1.7*2+60975+CEILING(25*(1+$D$8),1)*300*$D$10)-(CEILING(25*(1+$D$9),1)*12*1085+CEILING(25*(1+$D$9),1)*1450*2+1200)-39246-(CEILING(25*(1+$D$9),1)*48))*0.79,((81900*F$36+807750*$D$11*0.04+146140)-(CEILING(25*(1+$D$8),1)*(($B37*173.3333)*14*1.2375+1584)+CEILING(25*(1+$D$8),1)*($B37*173.3333)*1.7*2+60975+CEILING(25*(1+$D$8),1)*300*$D$10)-(CEILING(25*(1+$D$9),1)*12*1085+CEILING(25*(1+$D$9),1)*1450*2+1200)-39246-(CEILING(25*(1+$D$9),1)*48))) -> 352072.42 | G37: =IF(((81900*G$36+807750*$D$11*0.04+146140)-(CEILING(25*(1+$D$8),1)*(($B37*173.3333)*14*1.2375+1584)+CEILING(25*(1+$D$8),1)*($B37*173.3333)*1.7*2+60975+CEILING(25*(1+$D$8),1)*300*$D$10)-(CEILING(25*(1+$D$9),1)*12*1085+CEILING(25*(1+$D$9),1)*1450*2+1200)-39246-(CEILING(25*(1+$D$9),1)*48))>0,((81900*G$36+807750*$D$11*0.04+146140)-(CEILING(25*(1+$D$8),1)*(($B37*173.3333)*14*1.2375+1584)+CEILING(25*(1+$D$8),1)*($B37*173.3333)*1.7*2+60975+CEILING(25*(1+$D$8),1)*300*$D$10)-(CEILING(25*(1+$D$9),1)*12*1085+CEILING(25*(1+$D$9),1)*1450*2+1200)-39246-(CEILING(25*(1+$D$9),1)*48))*0.79,((81900*G$36+807750*$D$11*0.04+146140)-(CEILING(25*(1+$D$8),1)*(($B37*173.3333)*14*1.2375+1584)+CEILING(25*(1+$D$8),1)*($B37*173.3333)*1.7*2+60975+CEILING(25*(1+$D$8),1)*300*$D$10)-(CEILING(25*(1+$D$9),1)*12*1085+CEILING(25*(1+$D$9),1)*1450*2+1200)-39246-(CEILING(25*(1+$D$9),1)*48))) -> 416773.42
B38: 7.5 | C38: =IF(((81900*C$36+807750*$D$11*0.04+146140)-(CEILING(25*(1+$D$8),1)*(($B38*173.3333)*14*1.2375+1584)+CEILING(25*(1+$D$8),1)*($B38*173.3333)*1.7*2+60975+CEILING(25*(1+$D$8),1)*300*$D$10)-(CEILING(25*(1+$D$9),1)*12*1085+CEILING(25*(1+$D$9),1)*1450*2+1200)-39246-(CEILING(25*(1+$D$9),1)*48))>0,((81900*C$36+807750*$D$11*0.04+146140)-(CEILING(25*(1+$D$8),1)*(($B38*173.3333)*14*1.2375+1584)+CEILING(25*(1+$D$8),1)*($B38*173.3333)*1.7*2+60975+CEILING(25*(1+$D$8),1)*300*$D$10)-(CEILING(25*(1+$D$9),1)*12*1085+CEILING(25*(1+$D$9),1)*1450*2+1200)-39246-(CEILING(25*(1+$D$9),1)*48))*0.79,((81900*C$36+807750*$D$11*0.04+146140)-(CEILING(25*(1+$D$8),1)*(($B38*173.3333)*14*1.2375+1584)+CEILING(25*(1+$D$8),1)*($B38*173.3333)*1.7*2+60975+CEILING(25*(1+$D$8),1)*300*$D$10)-(CEILING(25*(1+$D$9),1)*12*1085+CEILING(25*(1+$D$9),1)*1450*2+1200)-39246-(CEILING(25*(1+$D$9),1)*48))) -> 75669.084 | D38: =IF(((81900*D$36+807750*$D$11*0.04+146140)-(CEILING(25*(1+$D$8),1)*(($B38*173.3333)*14*1.2375+1584)+CEILING(25*(1+$D$8),1)*($B38*173.3333)*1.7*2+60975+CEILING(25*(1+$D$8),1)*300*$D$10)-(CEILING(25*(1+$D$9),1)*12*1085+CEILING(25*(1+$D$9),1)*1450*2+1200)-39246-(CEILING(25*(1+$D$9),1)*48))>0,((81900*D$36+807750*$D$11*0.04+146140)-(CEILING(25*(1+$D$8),1)*(($B38*173.3333)*14*1.2375+1584)+CEILING(25*(1+$D$8),1)*($B38*173.3333)*1.7*2+60975+CEILING(25*(1+$D$8),1)*300*$D$10)-(CEILING(25*(1+$D$9),1)*12*1085+CEILING(25*(1+$D$9),1)*1450*2+1200)-39246-(CEILING(25*(1+$D$9),1)*48))*0.79,((81900*D$36+807750*$D$11*0.04+146140)-(CEILING(25*(1+$D$8),1)*(($B38*173.3333)*14*1.2375+1584)+CEILING(25*(1+$D$8),1)*($B38*173.3333)*1.7*2+60975+CEILING(25*(1+$D$8),1)*300*$D$10)-(CEILING(25*(1+$D$9),1)*12*1085+CEILING(25*(1+$D$9),1)*1450*2+1200)-39246-(CEILING(25*(1+$D$9),1)*48))) -> 198600.98 | E38: =IF(((81900*E$36+807750*$D$11*0.04+146140)-(CEILING(25*(1+$D$8),1)*(($B38*173.3333)*14*1.2375+1584)+CEILING(25*(1+$D$8),1)*($B38*173.3333)*1.7*2+60975+CEILING(25*(1+$D$8),1)*300*$D$10)-(CEILING(25*(1+$D$9),1)*12*1085+CEILING(25*(1+$D$9),1)*1450*2+1200)-39246-(CEILING(25*(1+$D$9),1)*48))>0,((81900*E$36+807750*$D$11*0.04+146140)-(CEILING(25*(1+$D$8),1)*(($B38*173.3333)*14*1.2375+1584)+CEILING(25*(1+$D$8),1)*($B38*173.3333)*1.7*2+60975+CEILING(25*(1+$D$8),1)*300*$D$10)-(CEILING(25*(1+$D$9),1)*12*1085+CEILING(25*(1+$D$9),1)*1450*2+1200)-39246-(CEILING(25*(1+$D$9),1)*48))*0.79,((81900*E$36+807750*$D$11*0.04+146140)-(CEILING(25*(1+$D$8),1)*(($B38*173.3333)*14*1.2375+1584)+CEILING(25*(1+$D$8),1)*($B38*173.3333)*1.7*2+60975+CEILING(25*(1+$D$8),1)*300*$D$10)-(CEILING(25*(1+$D$9),1)*12*1085+CEILING(25*(1+$D$9),1)*1450*2+1200)-39246-(CEILING(25*(1+$D$9),1)*48))) -> 205071.08 | F38: =IF(((81900*F$36+807750*$D$11*0.04+146140)-(CEILING(25*(1+$D$8),1)*(($B38*173.3333)*14*1.2375+1584)+CEILING(25*(1+$D$8),1)*($B38*173.3333)*1.7*2+60975+CEILING(25*(1+$D$8),1)*300*$D$10)-(CEILING(25*(1+$D$9),1)*12*1085+CEILING(25*(1+$D$9),1)*1450*2+1200)-39246-(CEILING(25*(1+$D$9),1)*48))>0,((81900*F$36+807750*$D$11*0.04+146140)-(CEILING(25*(1+$D$8),1)*(($B38*173.3333)*14*1.2375+1584)+CEILING(25*(1+$D$8),1)*($B38*173.3333)*1.7*2+60975+CEILING(25*(1+$D$8),1)*300*$D$10)-(CEILING(25*(1+$D$9),1)*12*1085+CEILING(25*(1+$D$9),1)*1450*2+1200)-39246-(CEILING(25*(1+$D$9),1)*48))*0.79,((81900*F$36+807750*$D$11*0.04+146140)-(CEILING(25*(1+$D$8),1)*(($B38*173.3333)*14*1.2375+1584)+CEILING(25*(1+$D$8),1)*($B38*173.3333)*1.7*2+60975+CEILING(25*(1+$D$8),1)*300*$D$10)-(CEILING(25*(1+$D$9),1)*12*1085+CEILING(25*(1+$D$9),1)*1450*2+1200)-39246-(CEILING(25*(1+$D$9),1)*48))) -> 269772.08 | G38: =IF(((81900*G$36+807750*$D$11*0.04+146140)-(CEILING(25*(1+$D$8),1)*(($B38*173.3333)*14*1.2375+1584)+CEILING(25*(1+$D$8),1)*($B38*173.3333)*1.7*2+60975+CEILING(25*(1+$D$8),1)*300*$D$10)-(CEILING(25*(1+$D$9),1)*12*1085+CEILING(25*(1+$D$9),1)*1450*2+1200)-39246-(CEILING(25*(1+$D$9),1)*48))>0,((81900*G$36+807750*$D$11*0.04+146140)-(CEILING(25*(1+$D$8),1)*(($B38*173.3333)*14*1.2375+1584)+CEILING(25*(1+$D$8),1)*($B38*173.3333)*1.7*2+60975+CEILING(25*(1+$D$8),1)*300*$D$10)-(CEILING(25*(1+$D$9),1)*12*1085+CEILING(25*(1+$D$9),1)*1450*2+1200)-39246-(CEILING(25*(1+$D$9),1)*48))*0.79,((81900*G$36+807750*$D$11*0.04+146140)-(CEILING(25*(1+$D$8),1)*(($B38*173.3333)*14*1.2375+1584)+CEILING(25*(1+$D$8),1)*($B38*173.3333)*1.7*2+60975+CEILING(25*(1+$D$8),1)*300*$D$10)-(CEILING(25*(1+$D$9),1)*12*1085+CEILING(25*(1+$D$9),1)*1450*2+1200)-39246-(CEILING(25*(1+$D$9),1)*48))) -> 334473.08
