Workbook

Sheet Capa
B2: MÁQUINAS DE VENDA DE PIZZA — FROTA / PIZZA VENDING FLEET
B3: Modelo Financeiro / Financial Model · Portugal Continental
B4: Máquinas fixas + móveis (circuito de feiras e festivais) / Fixed + mobile (fairs & festivals circuit)
B5: Dados de referência: Adial Pizzadoor (custo/pizza, eletricidade, margem) / Reference data: Adial
B7: PARÂMETROS-CHAVE / KEY PARAMETERS
B8: Máquinas fixas / Fixed machines | D8: 2
B9: Máquinas móveis (eventos) / Mobile machines | D9: 1
B10: Preço por pizza (c/IVA) / Price (incl. VAT) | D10: €10.00 (Adial: €11)
B11: Custo por pizza / Cost per pizza (Adial) | D11: ~€3.30
B12: Margem contribuição / Contribution | D12: ~€5.6/pizza
B13: Pizzas/dia fixa / day, fixed | D13: 20
B14: Pizzas/dia em evento / day, event | D14: 90-200
B15: Investimento máquina / Machine CAPEX | D15: ~€32,000 (estimativa - pedir orçamento)
B16: Financiamento / Financing | D16: 80% · 8% · 5 anos
B17: IVA / VAT · IRC | D17: 13% · 16%
B18: Revenda / Resale | D18: NÃO — máquinas mantidas / NO — kept
B20: ESTRUTURA / STRUCTURE
B21: 1. Pressupostos / Assumptions | D21: Inputs (frota, custos Adial, eventos)
B22: 2. Custos por Máquina / Per-machine | D22: Custo individual por máquina e local
B23: 3. Eventos / Events | D23: Calendário de feiras e festivais PT continental
B24: 4. Financiamento / Financing | D24: Amortização / Loan schedule
B25: 5. Receita / Revenue | D25: Fixas + circuito móvel / Fixed + mobile
B26: 6. Custos / Costs | D26: COGS + opex (da folha Máquinas) + eventos
B27: 7. DRE / P&L | D27: Resultados / P&L
B28: 8. Resumo Multianual / Multi-Year | D28: Ano 1-5
B29: 9. Tesouraria / Cash Flow | D29: Fluxo de caixa (sem revenda)
B30: 10. Ponto Crítico / Break-Even | D30: Pizzas/dia mínimas
B31: 11. Sensibilidades / Sensitivity | D31: Preço × volume
B32: 12. ROI | D32: Retorno do investidor (operação)
B34: Legenda: Azul=input · Verde=referência · Preto=fórmula · Amarelo=pressuposto-chave

Sheet Pressupostos
B1: PRESSUPOSTOS / ASSUMPTIONS
B2: Edite as células azuis. Custos de produção baseados na Adial Pizzadoor. / Edit blue cells. Production costs per Adial.
B4: A. RECEITA / REVENUE
B5: Parâmetro / Parameter | C5: Valor / Value | D5: Unidade / Unit | E5: Fonte-Nota / Source-Note
B6: Preço por pizza (consumidor, c/IVA) / Price incl. VAT | C6: 10 | D6: € | E6: Adial usa €11; PT ajustável
B7: Taxa de IVA / VAT rate | C7: 0.13 | D7: % | E7: Taxa intermédia restauração - confirmar
B8: Preço líquido s/IVA / Net price | C8: =C6/(1+C7) -> 8.8495575 | D8: € | E8: Calculado
B9: Taxa de pagamento (cartão) / Card fee | C9: 0.015 | D9: % | E9: Sobre vendas brutas
B10: Pizzas/dia - máquina fixa / Pizzas-day, fixed | C10: 20 | D10: un/dia | E10: Adial 'Expected'=20
B11: Dias operacionais/mês (fixa) / Op. days/month | C11: 30 | D11: dias | E11: 24/7
B12: Crescimento volume anual / Annual volume growth | C12: 0.05 | D12: % | E12: Anos 2+
B14: B. CUSTO DO PRODUTO (Adial) / COST OF GOODS (Adial)
B15: Parâmetro / Parameter | C15: Valor / Value | D15: Unidade / Unit | E15: Fonte-Nota / Source-Note
B16: Massa / Dough (280g @ €0,80/kg) | C16: 0.22 | D16: € | E16: Adial
B17: Molho tomate / Tomato sauce (80g @ €3/kg) | C17: 0.24 | D17: € | E17: Adial
B18: Queijo / Cheese (120g @ €7/kg) | C18: 0.84 | D18: € | E18: Adial
B19: Ingredientes / Toppings (120g @ €12/kg) | C19: 1.44 | D19: € | E19: Adial
B20: Caixa / Pizza box | C20: 0.361 | D20: € | E20: Adial
B21: Disco de cozedura / Baking disc | C21: 0.096 | D21: € | E21: Adial
B22: Desperdício / Waste | C22: 0.03 | D22: % | E22: Adial 3%
B23: Custo total por pizza / Total cost per pizza | C23: =(C16+C17+C18+C19+C20+C21)*(1+C22) -> 3.29291 | D23: € | E23: Calculado (Adial ~€3,30)
B25: C. CUSTOS OPERACIONAIS (por máquina, mensal) / OPERATING COSTS (per machine, monthly)
B26: Parâmetro / Parameter | C26: Valor / Value | D26: Unidade / Unit | E26: Fonte-Nota / Source-Note
B27: Renda localização (fixa) / Location rent (fixed) | C27: 300 | D27: €/mês | E27: Só máquinas fixas
B28: Reabastecimento (fixa) / Restocking (fixed) | C28: 350 | D28: €/mês | E28: Por máquina fixa
B29: Eletricidade / Electricity | C29: 140 | D29: €/mês | E29: Adial (1 kW contínuo)
B30: Seguro / Insurance | C30: 45 | D30: €/mês | E30: Adial
B31: Internet (ADSL/4G) | C31: 15 | D31: €/mês | E31: Adial
B32: Gestão de frota / Fleet mgmt (Silver) | C32: 12 | D32: €/mês | E32: Adial
B33: Manutenção / Maintenance | C33: 80 | D33: €/mês | E33: Peças/contrato
B35: D. CUSTOS DO NEGÓCIO (mensal) / BUSINESS-LEVEL COSTS (monthly)
B36: Parâmetro / Parameter | C36: Valor / Value | D36: Unidade / Unit | E36: Fonte-Nota / Source-Note
B37: Contabilidade / Accounting | C37: 150 | D37: €/mês | E37: Toda a empresa
B38: Diversos/contingência / Misc | C38: 100 | D38: €/mês | E38: Licenças, consumíveis
B39: Veículo transporte (seguro+manut.) / Transport vehicle | C39: 150 | D39: €/mês | E39: Carrinha/reboque
B41: E. CIRCUITO MÓVEL / MOBILE EVENT CIRCUIT
B42: Parâmetro / Parameter | C42: Valor / Value | D42: Unidade / Unit | E42: Fonte-Nota / Source-Note
B43: Mão-de-obra por dia de evento / Labour per event-day | C43: 90 | D43: €/dia | E43: Operador no evento
B44: Ver folha 'Eventos' para taxas de lugar, transporte e seleção de rota.
B45: See 'Eventos' sheet for pitch fees, transport and route selection.
B47: F. FROTA E INVESTIMENTO / FLEET & CAPEX
B48: Parâmetro / Parameter | C48: Valor / Value | D48: Unidade / Unit | E48: Fonte-Nota / Source-Note
B49: Nº máquinas fixas / Fixed machines | C49: 2 | D49: un
B50: Nº máquinas móveis / Mobile machines | C50: 1 | D50: un
B51: Total máquinas / Total machines | C51: =C49+C50 -> 3 | D51: un | E51: Calculado
B52: Preço por máquina / Price per machine | C52: 41900 | D52: € | E52: ESTIMATIVA mercado EU €25-65k - pedir orçamento
B53: Instalação/máquina / Install per machine | C53: 2500 | D53: € | E53: Transporte, ligação
B54: Veículo/reboque transporte / Transport vehicle | C54: 0 | D54: € | E54: Para máquina móvel
B55: Stock inicial / Initial stock | C55: 2000 | D55: € | E55: Primeiro enchimento frota
B56: Base financiável (máquinas+veículo) / Financeable base | C56: =C51*C52+C54 -> 125700 | D56: € | E56: Calculado
B57: Setup total / Total setup | C57: =C51*C53 -> 7500 | D57: € | E57: Calculado
B58: INVESTIMENTO TOTAL / TOTAL CAPEX | C58: =C56+C57+C55 -> 135200 | D58: € | E58: Calculado
B60: G. FINANCIAMENTO, IMPOSTOS, HORIZONTE / FINANCING, TAX, HORIZON
B61: Parâmetro / Parameter | C61: Valor / Value | D61: Unidade / Unit | E61: Fonte-Nota / Source-Note
B62: Entrada / Down payment | C62: 0.2 | D62: % | E62: Sobre base financiável
B63: Valor financiado / Loan amount | C63: =C56*(1-C62) -> 100560 | D63: € | E63: Calculado
B64: Taxa de juro anual / Annual rate | C64: 0.08 | D64: % | E64: Crédito equipamento PME
B65: Prazo / Term | C65: 5 | D65: anos | E65: 60 prestações
B66: Prestação mensal / Monthly payment | C66: =PMT(C64/12,C65*12,-C63) -> 2038.9942 | D66: € | E66: Calculado
B67: IRC (PME) / Corporate tax | C67: 0.16 | D67: % | E67: 16% 1os €50k PT 2025
B68: Vida útil (deprec.) / Useful life | C68: 8 | D68: anos | E68: Equipamento+veículo
B69: Depreciação anual / Annual depreciation | C69: =(C56+C57)/C68 -> 16650 | D69: € | E69: Linear
B70: Horizonte de análise / Hold period | C70: 5 | D70: anos | E70: Ano 1 mensal; 2-5 anual
B71: Capital inicial investidor / Initial equity | C71: =C56*C62+C57+C55 -> 34640 | D71: € | E71: Entrada+setup+stock
B73: H. ÍNDICE DE VOLUME ANO 1 - MÁQUINAS FIXAS / YEAR-1 INDEX, FIXED
B74: Mês / Month | C74: M1 | D74: M2 | E74: M3 | F74: M4 | G74: M5 | H74: M6 | I74: M7 | J74: M8 | K74: M9 | L74: M10 | M74: M11 | N74: M12
B75: Índice (ramp) / Index | C75: 0.4 | D75: 0.55 | E75: 0.7 | F75: 0.8 | G75: 0.9 | H75: 1 | I75: 1.05 | J75: 1.1 | K75: 1 | L75: 0.95 | M75: 0.95 | N75: 1.05

Sheet Maquinas
B1: CUSTOS POR MÁQUINA / PER-MACHINE COSTS
B2: Uma linha por máquina. Cada local pode ter custos diferentes — edite as células. / One row per machine; costs differ by location.
B4: Máquina / Machine | C4: Tipo / Type | D4: Local / Location | E4: Ativa? | F4: Renda | G4: Reabast. | H4: Eletric. | I4: Seguro | J4: Internet+gestão | K4: Manut. | L4: Total/mês
B5: Fixa 1 | C5: Fixa | D5: Local A | E5: 1 | F5: =Pressupostos!C27 -> 300 | G5: =Pressupostos!C28 -> 350 | H5: =Pressupostos!C29 -> 140 | I5: =Pressupostos!C30 -> 45 | J5: =Pressupostos!C31+Pressupostos!C32 -> 27 | K5: =Pressupostos!C33 -> 80 | L5: =E5*(F5+G5+H5+I5+J5+K5) -> 942
B6: Fixa 2 | C6: Fixa | D6: Local B | E6: 1 | F6: =Pressupostos!C27 -> 300 | G6: =Pressupostos!C28 -> 350 | H6: =Pressupostos!C29 -> 140 | I6: =Pressupostos!C30 -> 45 | J6: =Pressupostos!C31+Pressupostos!C32 -> 27 | K6: =Pressupostos!C33 -> 80 | L6: =E6*(F6+G6+H6+I6+J6+K6) -> 942
B7: Móvel 1 | C7: Móvel | D7: Circuito de eventos | E7: 1 | F7: =0 -> 0 | G7: =0 -> 0 | H7: =Pressupostos!C29 -> 140 | I7: =Pressupostos!C30 -> 45 | J7: =Pressupostos!C31+Pressupostos!C32 -> 27 | K7: =Pressupostos!C33 -> 80 | L7: =E7*(F7+G7+H7+I7+J7+K7) -> 292
B8: (livre / free) | E8: 0 | F8: 0 | G8: 0 | H8: 0 | I8: 0 | J8: 0 | K8: 0 | L8: =E8*(F8+G8+H8+I8+J8+K8) -> 0
B9: (livre / free) | E9: 0 | F9: 0 | G9: 0 | H9: 0 | I9: 0 | J9: 0 | K9: 0 | L9: =E9*(F9+G9+H9+I9+J9+K9) -> 0
B10: (livre / free) | E10: 0 | F10: 0 | G10: 0 | H10: 0 | I10: 0 | J10: 0 | K10: 0 | L10: =E10*(F10+G10+H10+I10+J10+K10) -> 0
B12: TOTAL FROTA (ativas) / FLEET TOTAL | F12: =SUMPRODUCT($E$5:$E$10,F5:F10) -> 600 | G12: =SUMPRODUCT($E$5:$E$10,G5:G10) -> 700 | H12: =SUMPRODUCT($E$5:$E$10,H5:H10) -> 420 | I12: =SUMPRODUCT($E$5:$E$10,I5:I10) -> 135 | J12: =SUMPRODUCT($E$5:$E$10,J5:J10) -> 81 | K12: =SUMPRODUCT($E$5:$E$10,K5:K10) -> 240 | L12: =SUM(F12:K12) -> 2176
B14: Custos op. Fixas/mês / Fixed op. costs | L14: =SUMPRODUCT(($C$5:$C$10="Fixa")*$E$5:$E$10*(F5:F10+G5:G10+H5:H10+I5:I10+J5:J10+K5:K10)) -> 1884
B15: Custos op. Móveis/mês / Mobile op. costs | L15: =SUMPRODUCT(($C$5:$C$10="Móvel")*$E$5:$E$10*(F5:F10+G5:G10+H5:H10+I5:I10+J5:J10+K5:K10)) -> 292
B17: Nº fixas ativas / Active fixed | E17: =SUMPRODUCT(($C$5:$C$10="Fixa")*$E$5:$E$10) -> 2
B18: Nº móveis ativas / Active mobile | E18: =SUMPRODUCT(($C$5:$C$10="Móvel")*$E$5:$E$10) -> 1
B19: Coerência com Pressupostos / Check vs Assumptions | E19: =IF(AND(E17=Pressupostos!C49,E18=Pressupostos!C50),"OK","VERIFICAR") -> OK
B21: Nota: alimenta a folha Custos e o Ponto Crítico. CAPEX/financiamento/receita seguem o nº de máquinas dos Pressupostos.

Sheet Eventos
B1: EVENTOS / EVENTS — Portugal Continental
B2: Calendário de feiras, festas e festivais para o circuito móvel. 'Em rota?'=1 inclui no modelo. / Set 'On route?'=1 to include.
B4: Evento / Event | C4: Concelho | D4: Distrito | E4: Mês | F4: Período 2026 / Dates | G4: Tipo / Type | H4: Dias | I4: Afluência | J4: Pizzas/dia | K4: Taxa lugar | L4: Transporte | M4: Em rota? | N4: Unidades | O4: Custo log. | P4: Receita liq. | Q4: Fonte / Source
B5: Festa das Fogaceiras | C5: Santa Maria da Feira | D5: Aveiro | E5: 1 | F5: 20 Jan 2026 | G5: Religiosa/Cívica | H5: 3 | I5: M | J5: 90 | K5: 400 | L5: 200 | M5: 1 | N5: =H5*J5*M5 -> 270 | O5: =(K5+L5)*M5 -> 600 | P5: =N5*Pressupostos!C8 -> 2389.3805 | Q5: CM Santa Maria da Feira
B6: Festas de São Gonçalinho | C6: Aveiro | D6: Aveiro | E6: 1 | F6: 9-12 Jan 2026 | G6: Religiosa | H6: 4 | I6: M | J6: 90 | K6: 400 | L6: 250 | M6: 1 | N6: =H6*J6*M6 -> 360 | O6: =(K6+L6)*M6 -> 650 | P6: =N6*Pressupostos!C8 -> 3185.8407 | Q6: CM Aveiro
B7: Festa dos Rapazes | C7: Bragança (aldeias) | D7: Bragança | E7: 1 | F7: 24 Dez-6 Jan | G7: Caretos/Tradicional | H7: 4 | I7: S | J7: 50 | K7: 150 | L7: 500 | M7: 1 | N7: =H7*J7*M7 -> 200 | O7: =(K7+L7)*M7 -> 650 | P7: =N7*Pressupostos!C8 -> 1769.9115 | Q7: VisitPortugal
B8: Carnaval de Loures | C8: Loures | D8: Lisboa | E8: 2 | F8: 15 e 17 Fev 2026 | G8: Carnaval | H8: 4 | I8: M | J8: 90 | K8: 400 | L8: 120 | M8: 2 | N8: =H8*J8*M8 -> 720 | O8: =(K8+L8)*M8 -> 1040 | P8: =N8*Pressupostos!C8 -> 6371.6814 | Q8: Carnaval de Loures
B9: Carnaval de Torres Vedras | C9: Torres Vedras | D9: Lisboa | E9: 2 | F9: 13-18 Fev 2026 | G9: Carnaval | H9: 6 | I9: L | J9: 150 | K9: 1000 | L9: 150 | M9: 0 | N9: =H9*J9*M9 -> 0 | O9: =(K9+L9)*M9 -> 0 | P9: =N9*Pressupostos!C8 -> 0 | Q9: Oficial
B10: Carnaval de Ovar | C10: Ovar | D10: Aveiro | E10: 2 | F10: Fev 2026 | G10: Carnaval | H10: 6 | I10: L | J10: 150 | K10: 1000 | L10: 250 | M10: 0 | N10: =H10*J10*M10 -> 0 | O10: =(K10+L10)*M10 -> 0 | P10: =N10*Pressupostos!C8 -> 0 | Q10: Oficial
B11: Carnaval de Loulé | C11: Loulé | D11: Faro | E11: 2 | F11: Fev 2026 | G11: Carnaval | H11: 5 | I11: L | J11: 150 | K11: 1000 | L11: 400 | M11: 0 | N11: =H11*J11*M11 -> 0 | O11: =(K11+L11)*M11 -> 0 | P11: =N11*Pressupostos!C8 -> 0 | Q11: Oficial
B12: Carnaval de Estarreja | C12: Estarreja | D12: Aveiro | E12: 2 | F12: Fev 2026 | G12: Carnaval | H12: 4 | I12: M | J12: 90 | K12: 400 | L12: 250 | M12: 0 | N12: =H12*J12*M12 -> 0 | O12: =(K12+L12)*M12 -> 0 | P12: =N12*Pressupostos!C8 -> 0 | Q12: Oficial
B13: Entrudo Chocalheiro (Caretos) | C13: Podence (Macedo de Cavaleiros) | D13: Bragança | E13: 2 | F13: Fev 2026 | G13: Carnaval UNESCO | H13: 4 | I13: M | J13: 90 | K13: 400 | L13: 450 | M13: 0 | N13: =H13*J13*M13 -> 0 | O13: =(K13+L13)*M13 -> 0 | P13: =N13*Pressupostos!C8 -> 0 | Q13: VisitPortugal/UNESCO
B14: Entrudo de Lazarim | C14: Lazarim (Lamego) | D14: Viseu | E14: 2 | F14: Fev 2026 | G14: Carnaval | H14: 4 | I14: S | J14: 50 | K14: 150 | L14: 300 | M14: 0 | N14: =H14*J14*M14 -> 0 | O14: =(K14+L14)*M14 -> 0 | P14: =N14*Pressupostos!C8 -> 0 | Q14: VisitPortugal
B15: Carnaval de Sesimbra | C15: Sesimbra | D15: Setúbal | E15: 2 | F15: Fev 2026 | G15: Carnaval | H15: 5 | I15: M | J15: 90 | K15: 400 | L15: 200 | M15: 1 | N15: =H15*J15*M15 -> 450 | O15: =(K15+L15)*M15 -> 600 | P15: =N15*Pressupostos!C8 -> 3982.3009 | Q15: Carnaval Sesimbra
B16: Semana Santa de Braga | C16: Braga | D16: Braga | E16: 3 | F16: Mar/Abr 2026 | G16: Religiosa | H16: 7 | I16: L | J16: 150 | K16: 1000 | L16: 350 | M16: 1 | N16: =H16*J16*M16 -> 1050 | O16: =(K16+L16)*M16 -> 1350 | P16: =N16*Pressupostos!C8 -> 9292.0354 | Q16: Oficial
B17: Semana Santa de Óbidos | C17: Óbidos | D17: Leiria | E17: 3 | F17: Mar/Abr 2026 | G17: Religiosa/Histórica | H17: 7 | I17: M | J17: 90 | K17: 400 | L17: 150 | M17: 1 | N17: =H17*J17*M17 -> 630 | O17: =(K17+L17)*M17 -> 550 | P17: =N17*Pressupostos!C8 -> 5575.2212 | Q17: CM Óbidos
B18: Semana Santa de Buarcos | C18: Figueira da Foz | D18: Coimbra | E18: 3 | F18: 18 Mar-5 Abr 2026 | G18: Religiosa | H18: 10 | I18: M | J18: 90 | K18: 400 | L18: 250 | M18: 0 | N18: =H18*J18*M18 -> 0 | O18: =(K18+L18)*M18 -> 0 | P18: =N18*Pressupostos!C8 -> 0 | Q18: CM Figueira da Foz
B19: Festival Int. de Chocolate | C19: Óbidos | D19: Leiria | E19: 3 | F19: Mar-Abr 2026 | G19: Gastronomia | H19: 10 | I19: L | J19: 150 | K19: 1000 | L19: 150 | M19: 0 | N19: =H19*J19*M19 -> 0 | O19: =(K19+L19)*M19 -> 0 | P19: =N19*Pressupostos!C8 -> 0 | Q19: CM Óbidos
B20: Feira de Março | C20: Aveiro | D20: Aveiro | E20: 3 | F20: fim Mar-Abr 2026 | G20: Feira | H20: 30 | I20: L | J20: 150 | K20: 1000 | L20: 250 | M20: 0 | N20: =H20*J20*M20 -> 0 | O20: =(K20+L20)*M20 -> 0 | P20: =N20*Pressupostos!C8 -> 0 | Q20: CM Aveiro
B21: Festa das Tochas Floridas | C21: São Brás de Alportel | D21: Faro | E21: 4 | F21: 5 Abr 2026 (Páscoa) | G21: Religiosa/Tradicional | H21: 1 | I21: M | J21: 90 | K21: 400 | L21: 450 | M21: 0 | N21: =H21*J21*M21 -> 0 | O21: =(K21+L21)*M21 -> 0 | P21: =N21*Pressupostos!C8 -> 0 | Q21: Turismo do Algarve
B22: Festa Grande da Mãe Soberana | C22: Loulé | D22: Faro | E22: 4 | F22: 19 Abr 2026 | G22: Religiosa/Popular | H22: 3 | I22: L | J22: 150 | K22: 1000 | L22: 400 | M22: 0 | N22: =H22*J22*M22 -> 0 | O22: =(K22+L22)*M22 -> 0 | P22: =N22*Pressupostos!C8 -> 0 | Q22: CM Loulé
B23: Romaria a Cavalo Moita-Viana Alentejo | C23: Moita / Viana do Alentejo | D23: Setúbal | E23: 4 | F23: 21-26 Abr 2026 | G23: Religiosa/Equestre | H23: 6 | I23: M | J23: 90 | K23: 400 | L23: 200 | M23: 0 | N23: =H23*J23*M23 -> 0 | O23: =(K23+L23)*M23 -> 0 | P23: =N23*Pressupostos!C8 -> 0 | Q23: CM Moita / Viana
B24: Romaria de Santa Marinha | C24: Segura (Idanha-a-Nova) | D24: Castelo Branco | E24: 4 | F24: 8 dias após Páscoa | G24: Religiosa | H24: 2 | I24: S | J24: 50 | K24: 150 | L24: 400 | M24: 0 | N24: =H24*J24*M24 -> 0 | O24: =(K24+L24)*M24 -> 0 | P24: =N24*Pressupostos!C8 -> 0 | Q24: CM Idanha-a-Nova
B25: Romaria N. Sra do Almortão | C25: Idanha-a-Nova | D25: Castelo Branco | E25: 4 | F25: 15 dias após Páscoa | G25: Religiosa | H25: 3 | I25: M | J25: 90 | K25: 400 | L25: 420 | M25: 0 | N25: =H25*J25*M25 -> 0 | O25: =(K25+L25)*M25 -> 0 | P25: =N25*Pressupostos!C8 -> 0 | Q25: VisitPortugal
B26: Queima das Fitas do Porto | C26: Porto | D26: Porto | E26: 4 | F26: Abr/Mai 2026 | G26: Académica | H26: 8 | I26: XL | J26: 200 | K26: 2500 | L26: 350 | M26: 0 | N26: =H26*J26*M26 -> 0 | O26: =(K26+L26)*M26 -> 0 | P26: =N26*Pressupostos!C8 -> 0 | Q26: Oficial
B27: Festas de São Jorge | C27: Gondomar | D27: Porto | E27: 4 | F27: 18-27 Abr 2026 | G27: Religiosa/Festa | H27: 6 | I27: M | J27: 90 | K27: 400 | L27: 350 | M27: 0 | N27: =H27*J27*M27 -> 0 | O27: =(K27+L27)*M27 -> 0 | P27: =N27*Pressupostos!C8 -> 0 | Q27: Oficial
B28: Festa das Cruzes | C28: Barcelos | D28: Braga | E28: 5 | F28: in. Maio 2026 | G28: Religiosa/Feira | H28: 4 | I28: M | J28: 90 | K28: 400 | L28: 350 | M28: 0 | N28: =H28*J28*M28 -> 0 | O28: =(K28+L28)*M28 -> 0 | P28: =N28*Pressupostos!C8 -> 0 | Q28: VisitPortugal
B29: Festa das Cruzes de Monsanto | C29: Monsanto (Idanha) | D29: Castelo Branco | E29: 5 | F29: 3 Mai 2026 | G29: Tradicional/Histórica | H29: 2 | I29: M | J29: 90 | K29: 400 | L29: 420 | M29: 0 | N29: =H29*J29*M29 -> 0 | O29: =(K29+L29)*M29 -> 0 | P29: =N29*Pressupostos!C8 -> 0 | Q29: VisitPortugal
B30: Círio de N. Sra da Victória | C30: Nazaré | D30: Leiria | E30: 5 | F30: 14 Mai 2026 (Ascensão) | G30: Religiosa | H30: 2 | I30: M | J30: 90 | K30: 400 | L30: 200 | M30: 0 | N30: =H30*J30*M30 -> 0 | O30: =(K30+L30)*M30 -> 0 | P30: =N30*Pressupostos!C8 -> 0 | Q30: CM Nazaré
B31: Feira de Maio | C31: Azambuja | D31: Lisboa | E31: 5 | F31: 28 Mai-1 Jun 2026 | G31: Feira/Taurina | H31: 5 | I31: M | J31: 90 | K31: 400 | L31: 120 | M31: 1 | N31: =H31*J31*M31 -> 450 | O31: =(K31+L31)*M31 -> 520 | P31: =N31*Pressupostos!C8 -> 3982.3009 | Q31: CM Azambuja
B32: Festas do Município e Santa Joana | C32: Aveiro | D32: Aveiro | E32: 5 | F32: 6-16 Mai 2026 | G32: Religiosa/Municipal | H32: 10 | I32: M | J32: 90 | K32: 400 | L32: 250 | M32: 0 | N32: =H32*J32*M32 -> 0 | O32: =(K32+L32)*M32 -> 0 | P32: =N32*Pressupostos!C8 -> 0 | Q32: CM Aveiro
B33: Senhor de Matosinhos | C33: Matosinhos | D33: Porto | E33: 5 | F33: 15 Mai-7 Jun 2026 | G33: Religiosa/Municipal | H33: 10 | I33: L | J33: 150 | K33: 1000 | L33: 350 | M33: 0 | N33: =H33*J33*M33 -> 0 | O33: =(K33+L33)*M33 -> 0 | P33: =N33*Pressupostos!C8 -> 0 | Q33: CM Matosinhos
B34: Beja Romana | C34: Beja | D34: Beja | E34: 5 | F34: 29-31 Mai 2026 | G34: Histórica/Municipal | H34: 3 | I34: M | J34: 90 | K34: 400 | L34: 250 | M34: 0 | N34: =H34*J34*M34 -> 0 | O34: =(K34+L34)*M34 -> 0 | P34: =N34*Pressupostos!C8 -> 0 | Q34: CM Beja
B35: Algarve Smooth Jazz | C35: Albufeira | D35: Faro | E35: 5 | F35: 12-17 Mai 2026 | G35: Festival | H35: 6 | I35: M | J35: 90 | K35: 400 | L35: 400 | M35: 0 | N35: =H35*J35*M35 -> 0 | O35: =(K35+L35)*M35 -> 0 | P35: =N35*Pressupostos!C8 -> 0 | Q35: Oficial
B36: MOGA Caparica | C36: Almada | D36: Setúbal | E36: 5 | F36: 27-31 Mai 2026 | G36: Festival | H36: 5 | I36: M | J36: 90 | K36: 400 | L36: 150 | M36: 0 | N36: =H36*J36*M36 -> 0 | O36: =(K36+L36)*M36 -> 0 | P36: =N36*Pressupostos!C8 -> 0 | Q36: Oficial
B37: Feira de Doçaria Conventual | C37: Portalegre | D37: Portalegre | E37: 5 | F37: Maio 2026 | G37: Gastronomia | H37: 4 | I37: S | J37: 50 | K37: 150 | L37: 400 | M37: 0 | N37: =H37*J37*M37 -> 0 | O37: =(K37+L37)*M37 -> 0 | P37: =N37*Pressupostos!C8 -> 0 | Q37: VisitPortugal
B38: Festas de São Gonçalo | C38: Amarante | D38: Porto | E38: 6 | F38: 1º fds Jun 2026 | G38: Religiosa/Popular | H38: 4 | I38: M | J38: 90 | K38: 400 | L38: 380 | M38: 0 | N38: =H38*J38*M38 -> 0 | O38: =(K38+L38)*M38 -> 0 | P38: =N38*Pressupostos!C8 -> 0 | Q38: Agenda Amarante
B39: Romaria do Senhor da Pedra | C39: Miramar (V.N. Gaia) | D39: Porto | E39: 6 | F39: Jun 2026 (móvel) | G39: Religiosa/Popular | H39: 3 | I39: M | J39: 90 | K39: 400 | L39: 340 | M39: 0 | N39: =H39*J39*M39 -> 0 | O39: =(K39+L39)*M39 -> 0 | P39: =N39*Pressupostos!C8 -> 0 | Q39: VisitPortugal
B40: Festas de Lisboa / Santo António | C40: Lisboa | D40: Lisboa | E40: 6 | F40: 29 Mai-28 Jun; St.António 12-13 | G40: Santos Populares | H40: 15 | I40: XL | J40: 200 | K40: 2500 | L40: 100 | M40: 1 | N40: =H40*J40*M40 -> 3000 | O40: =(K40+L40)*M40 -> 2600 | P40: =N40*Pressupostos!C8 -> 26548.673 | Q40: Visit Lisboa
B41: Primavera Sound Porto | C41: Porto | D41: Porto | E41: 6 | F41: 11-14 Jun 2026 | G41: Festival | H41: 4 | I41: XL | J41: 200 | K41: 2500 | L41: 350 | M41: 0 | N41: =H41*J41*M41 -> 0 | O41: =(K41+L41)*M41 -> 0 | P41: =N41*Pressupostos!C8 -> 0 | Q41: Oficial
B42: Feira Medieval de Belver | C42: Gavião | D42: Portalegre | E42: 6 | F42: 19-21 Jun 2026 | G42: Histórica | H42: 3 | I42: M | J42: 90 | K42: 400 | L42: 300 | M42: 0 | N42: =H42*J42*M42 -> 0 | O42: =(K42+L42)*M42 -> 0 | P42: =N42*Pressupostos!C8 -> 0 | Q42: VisitPortugal
B43: Festas da Vila de Mértola | C43: Mértola | D43: Beja | E43: 6 | F43: 19-24 Jun 2026 | G43: Municipal/Popular | H43: 6 | I43: M | J43: 90 | K43: 400 | L43: 400 | M43: 0 | N43: =H43*J43*M43 -> 0 | O43: =(K43+L43)*M43 -> 0 | P43: =N43*Pressupostos!C8 -> 0 | Q43: CM Mértola
B44: Festas da Vila de Castro Verde | C44: Castro Verde | D44: Beja | E44: 6 | F44: 26-28 Jun 2026 | G44: Municipal/Popular | H44: 3 | I44: S | J44: 50 | K44: 150 | L44: 380 | M44: 0 | N44: =H44*J44*M44 -> 0 | O44: =(K44+L44)*M44 -> 0 | P44: =N44*Pressupostos!C8 -> 0 | Q44: VisitPortugal
B45: Feira de São João de Évora | C45: Évora | D45: Évora | E45: 6 | F45: 23 Jun-5 Jul 2026 | G45: Feira/Popular | H45: 13 | I45: M | J45: 90 | K45: 400 | L45: 250 | M45: 0 | N45: =H45*J45*M45 -> 0 | O45: =(K45+L45)*M45 -> 0 | P45: =N45*Pressupostos!C8 -> 0 | Q45: VisitPortugal
B46: Festa de São João da Lousã | C46: Lousã | D46: Coimbra | E46: 6 | F46: 18-24 Jun 2026 | G46: Popular/Religiosa | H46: 7 | I46: S | J46: 50 | K46: 150 | L46: 260 | M46: 0 | N46: =H46*J46*M46 -> 0 | O46: =(K46+L46)*M46 -> 0 | P46: =N46*Pressupostos!C8 -> 0 | Q46: CM Lousã
B47: Festas de São João de Braga | C47: Braga | D47: Braga | E47: 6 | F47: 17-24 Jun 2026 | G47: Santos Populares | H47: 8 | I47: L | J47: 150 | K47: 1000 | L47: 350 | M47: 0 | N47: =H47*J47*M47 -> 0 | O47: =(K47+L47)*M47 -> 0 | P47: =N47*Pressupostos!C8 -> 0 | Q47: Turismo Porto e Norte
B48: São João do Porto | C48: Porto | D48: Porto | E48: 6 | F48: 23-24 Jun 2026 | G48: Santos Populares | H48: 3 | I48: XL | J48: 200 | K48: 2500 | L48: 350 | M48: 1 | N48: =H48*J48*M48 -> 600 | O48: =(K48+L48)*M48 -> 2850 | P48: =N48*Pressupostos!C8 -> 5309.7345 | Q48: VisitPortugal
B49: Festas de São Pedro (S.Pedro) | C49: Porto de Mós | D49: Leiria | E49: 6 | F49: ~29 Jun 2026 | G49: Feira/Religiosa | H49: 5 | I49: M | J49: 90 | K49: 400 | L49: 140 | M49: 1 | N49: =H49*J49*M49 -> 450 | O49: =(K49+L49)*M49 -> 540 | P49: =N49*Pressupostos!C8 -> 3982.3009 | Q49: Oficial
B50: Feira Nacional da Agricultura | C50: Santarém | D50: Santarém | E50: 6 | F50: in.-meados Jun 2026 | G50: Feira | H50: 10 | I50: L | J50: 150 | K50: 1000 | L50: 120 | M50: 0 | N50: =H50*J50*M50 -> 0 | O50: =(K50+L50)*M50 -> 0 | P50: =N50*Pressupostos!C8 -> 0 | Q50: Oficial
B51: Festival MED | C51: Loulé | D51: Faro | E51: 6 | F51: fim Jun 2026 | G51: Festival | H51: 4 | I51: L | J51: 150 | K51: 1000 | L51: 400 | M51: 0 | N51: =H51*J51*M51 -> 0 | O51: =(K51+L51)*M51 -> 0 | P51: =N51*Pressupostos!C8 -> 0 | Q51: Oficial
B52: Rock in Rio Lisboa | C52: Lisboa | D52: Lisboa | E52: 6 | F52: 20-28 Jun 2026 | G52: Festival | H52: 4 | I52: XL | J52: 200 | K52: 2500 | L52: 100 | M52: 0 | N52: =H52*J52*M52 -> 0 | O52: =(K52+L52)*M52 -> 0 | P52: =N52*Pressupostos!C8 -> 0 | Q52: Oficial
B53: Feira de São Pedro de Sintra | C53: Sintra | D53: Lisboa | E53: 6 | F53: ~29 Jun 2026 | G53: Feira | H53: 3 | I53: M | J53: 90 | K53: 400 | L53: 120 | M53: 0 | N53: =H53*J53*M53 -> 0 | O53: =(K53+L53)*M53 -> 0 | P53: =N53*Pressupostos!C8 -> 0 | Q53: Oficial
B54: Festas da Cidade e Rainha Santa | C54: Coimbra | D54: Coimbra | E54: 7 | F54: 3-19 Jul 2026 | G54: Religiosa/Municipal | H54: 17 | I54: L | J54: 150 | K54: 1000 | L54: 250 | M54: 0 | N54: =H54*J54*M54 -> 0 | O54: =(K54+L54)*M54 -> 0 | P54: =N54*Pressupostos!C8 -> 0 | Q54: CM Coimbra
B55: Feira Medieval de Coimbra | C55: Coimbra | D55: Coimbra | E55: 7 | F55: 17-19 Jul 2026 | G55: Histórica | H55: 3 | I55: M | J55: 90 | K55: 400 | L55: 250 | M55: 0 | N55: =H55*J55*M55 -> 0 | O55: =(K55+L55)*M55 -> 0 | P55: =N55*Pressupostos!C8 -> 0 | Q55: VisitPortugal
B56: Festas da Cidade de Chaves | C56: Chaves | D56: Vila Real | E56: 7 | F56: 4-8 Jul 2026 | G56: Municipal/Popular | H56: 5 | I56: M | J56: 90 | K56: 400 | L56: 450 | M56: 0 | N56: =H56*J56*M56 -> 0 | O56: =(K56+L56)*M56 -> 0 | P56: =N56*Pressupostos!C8 -> 0 | Q56: CM Chaves
B57: Festas do Colete Encarnado | C57: Vila Franca de Xira | D57: Lisboa | E57: 7 | F57: 1ª sem Jul 2026 | G57: Taurina/Feira | H57: 4 | I57: L | J57: 150 | K57: 1000 | L57: 110 | M57: 1 | N57: =H57*J57*M57 -> 600 | O57: =(K57+L57)*M57 -> 1110 | P57: =N57*Pressupostos!C8 -> 5309.7345 | Q57: Oficial
B58: Mercado Medieval de Óbidos | C58: Óbidos | D58: Leiria | E58: 7 | F58: 16-26 Jul 2026 | G58: Histórica | H58: 11 | I58: L | J58: 150 | K58: 1000 | L58: 150 | M58: 0 | N58: =H58*J58*M58 -> 0 | O58: =(K58+L58)*M58 -> 0 | P58: =N58*Pressupostos!C8 -> 0 | Q58: CM Óbidos
B59: Festas do Bodo | C59: Pombal | D59: Leiria | E59: 7 | F59: 23-28 Jul 2026 | G59: Popular/Municipal | H59: 6 | I59: M | J59: 90 | K59: 400 | L59: 170 | M59: 0 | N59: =H59*J59*M59 -> 0 | O59: =(K59+L59)*M59 -> 0 | P59: =N59*Pressupostos!C8 -> 0 | Q59: VisitPortugal
B60: Feira Medieval de Sintra | C60: Sintra | D60: Lisboa | E60: 7 | F60: 9-12 Jul 2026 | G60: Histórica | H60: 4 | I60: M | J60: 90 | K60: 400 | L60: 120 | M60: 0 | N60: =H60*J60*M60 -> 0 | O60: =(K60+L60)*M60 -> 0 | P60: =N60*Pressupostos!C8 -> 0 | Q60: VisitPortugal
B61: Festa Templária | C61: Tomar | D61: Santarém | E61: 7 | F61: 9-12 Jul 2026 | G61: Histórica | H61: 4 | I61: M | J61: 90 | K61: 400 | L61: 180 | M61: 0 | N61: =H61*J61*M61 -> 0 | O61: =(K61+L61)*M61 -> 0 | P61: =N61*Pressupostos!C8 -> 0 | Q61: CM Tomar
B62: Festa dos Tabuleiros (quadrienal) | C62: Tomar | D62: Santarém | E62: 7 | F62: Próxima 2027 (não 2026) | G62: Religiosa/Histórica | H62: 10 | I62: XL | J62: 200 | K62: 2500 | L62: 180 | M62: 0 | N62: =H62*J62*M62 -> 0 | O62: =(K62+L62)*M62 -> 0 | P62: =N62*Pressupostos!C8 -> 0 | Q62: CM Tomar
B63: Festas da Cidade de Odivelas | C63: Odivelas | D63: Lisboa | E63: 7 | F63: Jul 2026 | G63: Municipal/Popular | H63: 4 | I63: M | J63: 90 | K63: 400 | L63: 90 | M63: 0 | N63: =H63*J63*M63 -> 0 | O63: =(K63+L63)*M63 -> 0 | P63: =N63*Pressupostos!C8 -> 0 | Q63: VisitPortugal
B64: NOS Alive | C64: Oeiras | D64: Lisboa | E64: 7 | F64: 9-11 Jul 2026 | G64: Festival | H64: 3 | I64: XL | J64: 200 | K64: 2500 | L64: 100 | M64: 1 | N64: =H64*J64*M64 -> 600 | O64: =(K64+L64)*M64 -> 2600 | P64: =N64*Pressupostos!C8 -> 5309.7345 | Q64: Oficial
B65: Super Bock Super Rock | C65: Sesimbra (Meco) | D65: Setúbal | E65: 7 | F65: Jul 2026 | G65: Festival | H65: 3 | I65: L | J65: 150 | K65: 1000 | L65: 200 | M65: 0 | N65: =H65*J65*M65 -> 0 | O65: =(K65+L65)*M65 -> 0 | P65: =N65*Pressupostos!C8 -> 0 | Q65: Oficial
B66: Afro Nation | C66: Portimão | D66: Faro | E66: 7 | F66: 3-5 Jul 2026 | G66: Festival | H66: 3 | I66: XL | J66: 200 | K66: 2500 | L66: 450 | M66: 0 | N66: =H66*J66*M66 -> 0 | O66: =(K66+L66)*M66 -> 0 | P66: =N66*Pressupostos!C8 -> 0 | Q66: Oficial
B67: RFM Somnii | C67: Figueira da Foz | D67: Coimbra | E67: 7 | F67: 10-12 Jul 2026 | G67: Festival | H67: 4 | I67: L | J67: 150 | K67: 1000 | L67: 250 | M67: 0 | N67: =H67*J67*M67 -> 0 | O67: =(K67+L67)*M67 -> 0 | P67: =N67*Pressupostos!C8 -> 0 | Q67: Oficial
B68: MEO Marés Vivas | C68: Matosinhos | D68: Porto | E68: 7 | F68: Jul 2026 | G68: Festival | H68: 3 | I68: L | J68: 150 | K68: 1000 | L68: 350 | M68: 0 | N68: =H68*J68*M68 -> 0 | O68: =(K68+L68)*M68 -> 0 | P68: =N68*Pressupostos!C8 -> 0 | Q68: Oficial
B69: Ageas Cooljazz | C69: Cascais | D69: Lisboa | E69: 7 | F69: Jul 2026 | G69: Festival | H69: 8 | I69: M | J69: 90 | K69: 400 | L69: 120 | M69: 0 | N69: =H69*J69*M69 -> 0 | O69: =(K69+L69)*M69 -> 0 | P69: =N69*Pressupostos!C8 -> 0 | Q69: Oficial
B70: Salir no Tempo | C70: Salir (Loulé) | D70: Faro | E70: 7 | F70: 18-20 Jul 2026 | G70: Histórica | H70: 3 | I70: M | J70: 90 | K70: 400 | L70: 420 | M70: 0 | N70: =H70*J70*M70 -> 0 | O70: =(K70+L70)*M70 -> 0 | P70: =N70*Pressupostos!C8 -> 0 | Q70: Turismo do Algarve
B71: Feira de Sant'Iago | C71: Setúbal | D71: Setúbal | E71: 7 | F71: 23 Jul-2 Ago 2026 | G71: Feira/Popular | H71: 11 | I71: L | J71: 150 | K71: 1000 | L71: 200 | M71: 0 | N71: =H71*J71*M71 -> 0 | O71: =(K71+L71)*M71 -> 0 | P71: =N71*Pressupostos!C8 -> 0 | Q71: VisitPortugal
B72: Expofacic | C72: Cantanhede | D72: Coimbra | E72: 8 | F72: 30 Jul-9 Ago 2026 | G72: Feira-festa | H72: 11 | I72: L | J72: 150 | K72: 1000 | L72: 280 | M72: 0 | N72: =H72*J72*M72 -> 0 | O72: =(K72+L72)*M72 -> 0 | P72: =N72*Pressupostos!C8 -> 0 | Q72: CM Cantanhede
B73: Festas Gualterianas | C73: Guimarães | D73: Braga | E73: 8 | F73: 1º fds Ago 2026 | G73: Cidade/Feira | H73: 4 | I73: L | J73: 150 | K73: 1000 | L73: 350 | M73: 1 | N73: =H73*J73*M73 -> 600 | O73: =(K73+L73)*M73 -> 1350 | P73: =N73*Pressupostos!C8 -> 5309.7345 | Q73: Turismo Porto e Norte
B74: Feira Medieval de Silves | C74: Silves | D74: Faro | E74: 8 | F74: 7-15 Ago 2026 | G74: Histórica | H74: 9 | I74: L | J74: 150 | K74: 1000 | L74: 480 | M74: 0 | N74: =H74*J74*M74 -> 0 | O74: =(K74+L74)*M74 -> 0 | P74: =N74*Pressupostos!C8 -> 0 | Q74: Turismo do Algarve
B75: Feira de São Bartolomeu | C75: Trancoso | D75: Guarda | E75: 8 | F75: 7-16 Ago 2026 | G75: Feira/Popular | H75: 10 | I75: M | J75: 90 | K75: 400 | L75: 400 | M75: 0 | N75: =H75*J75*M75 -> 0 | O75: =(K75+L75)*M75 -> 0 | P75: =N75*Pressupostos!C8 -> 0 | Q75: CM Trancoso
B76: Festas do Povo | C76: Campo Maior | D76: Portalegre | E76: 8 | F76: 8-16 Ago 2026 | G76: Popular UNESCO | H76: 9 | I76: L | J76: 150 | K76: 1000 | L76: 400 | M76: 0 | N76: =H76*J76*M76 -> 0 | O76: =(K76+L76)*M76 -> 0 | P76: =N76*Pressupostos!C8 -> 0 | Q76: VisitPortugal
B77: Festas do Barrete Verde e Salinas | C77: Alcochete | D77: Setúbal | E77: 8 | F77: 8-13 Ago 2026 | G77: Taurina/Popular | H77: 6 | I77: M | J77: 90 | K77: 400 | L77: 150 | M77: 0 | N77: =H77*J77*M77 -> 0 | O77: =(K77+L77)*M77 -> 0 | P77: =N77*Pressupostos!C8 -> 0 | Q77: CM Alcochete
B78: Festa dos Povos (Aquae Flaviae) | C78: Chaves | D78: Vila Real | E78: 8 | F78: 14-16 Ago 2026 | G78: Histórica | H78: 3 | I78: M | J78: 90 | K78: 400 | L78: 450 | M78: 0 | N78: =H78*J78*M78 -> 0 | O78: =(K78+L78)*M78 -> 0 | P78: =N78*Pressupostos!C8 -> 0 | Q78: CM Chaves
B79: Senhora da Agonia | C79: Viana do Castelo | D79: Viana do Castelo | E79: 8 | F79: 15-23 Ago 2026 | G79: Romaria | H79: 9 | I79: XL | J79: 200 | K79: 2500 | L79: 400 | M79: 1 | N79: =H79*J79*M79 -> 1800 | O79: =(K79+L79)*M79 -> 2900 | P79: =N79*Pressupostos!C8 -> 15929.204 | Q79: VianaFestas
B80: Romaria de São Bartolomeu | C80: Ponte da Barca | D80: Viana do Castelo | E80: 8 | F80: 19-24 Ago 2026 | G80: Religiosa/Popular | H80: 6 | I80: M | J80: 90 | K80: 400 | L80: 420 | M80: 0 | N80: =H80*J80*M80 -> 0 | O80: =(K80+L80)*M80 -> 0 | P80: =N80*Pressupostos!C8 -> 0 | Q80: VisitPortugal
B81: Romaria de N. Sra da Abadia | C81: Amares | D81: Braga | E81: 8 | F81: Ago 2026 (Assunção) | G81: Religiosa | H81: 4 | I81: M | J81: 90 | K81: 400 | L81: 380 | M81: 0 | N81: =H81*J81*M81 -> 0 | O81: =(K81+L81)*M81 -> 0 | P81: =N81*Pressupostos!C8 -> 0 | Q81: VisitPortugal
B82: Romaria de São João d'Arga | C82: Caminha | D82: Viana do Castelo | E82: 8 | F82: 28-29 Ago 2026 | G82: Religiosa/Popular | H82: 2 | I82: M | J82: 90 | K82: 400 | L82: 440 | M82: 0 | N82: =H82*J82*M82 -> 0 | O82: =(K82+L82)*M82 -> 0 | P82: =N82*Pressupostos!C8 -> 0 | Q82: VisitPortugal
B83: Feira de São Mateus | C83: Viseu | D83: Viseu | E83: 8 | F83: 6 Ago-6 Set 2026 | G83: Feira (mais antiga) | H83: 32 | I83: XL | J83: 200 | K83: 2500 | L83: 300 | M83: 0 | N83: =H83*J83*M83 -> 0 | O83: =(K83+L83)*M83 -> 0 | P83: =N83*Pressupostos!C8 -> 0 | Q83: CM Viseu
B84: FATACIL | C84: Lagoa | D84: Faro | E84: 8 | F84: ~15-24 Ago 2026 | G84: Feira | H84: 10 | I84: L | J84: 150 | K84: 1000 | L84: 450 | M84: 0 | N84: =H84*J84*M84 -> 0 | O84: =(K84+L84)*M84 -> 0 | P84: =N84*Pressupostos!C8 -> 0 | Q84: Oficial
B85: Festival do Marisco | C85: Olhão | D85: Faro | E85: 8 | F85: ~13-17 Ago 2026 | G85: Gastronomia | H85: 5 | I85: L | J85: 150 | K85: 1000 | L85: 450 | M85: 0 | N85: =H85*J85*M85 -> 0 | O85: =(K85+L85)*M85 -> 0 | P85: =N85*Pressupostos!C8 -> 0 | Q85: Oficial
B86: MEO Sudoeste | C86: Odemira (Zambujeira) | D86: Beja | E86: 8 | F86: in. Ago 2026 | G86: Festival | H86: 5 | I86: XL | J86: 200 | K86: 2500 | L86: 400 | M86: 0 | N86: =H86*J86*M86 -> 0 | O86: =(K86+L86)*M86 -> 0 | P86: =N86*Pressupostos!C8 -> 0 | Q86: Oficial
B87: Vodafone Paredes de Coura | C87: Paredes de Coura | D87: Viana do Castelo | E87: 8 | F87: 12-15 Ago 2026 | G87: Festival | H87: 4 | I87: L | J87: 150 | K87: 1000 | L87: 420 | M87: 0 | N87: =H87*J87*M87 -> 0 | O87: =(K87+L87)*M87 -> 0 | P87: =N87*Pressupostos!C8 -> 0 | Q87: Oficial
B88: Vagos Metal Fest | C88: Vagos | D88: Aveiro | E88: 8 | F88: 5-9 Ago 2026 | G88: Festival | H88: 5 | I88: M | J88: 90 | K88: 400 | L88: 250 | M88: 0 | N88: =H88*J88*M88 -> 0 | O88: =(K88+L88)*M88 -> 0 | P88: =N88*Pressupostos!C8 -> 0 | Q88: Oficial
B89: Sol da Caparica | C89: Almada | D89: Setúbal | E89: 8 | F89: 13-16 Ago 2026 | G89: Festival | H89: 4 | I89: L | J89: 150 | K89: 1000 | L89: 150 | M89: 0 | N89: =H89*J89*M89 -> 0 | O89: =(K89+L89)*M89 -> 0 | P89: =N89*Pressupostos!C8 -> 0 | Q89: Oficial
B90: MEO Kalorama | C90: Lisboa | D90: Lisboa | E90: 8 | F90: 28-30 Ago 2026 | G90: Festival | H90: 3 | I90: L | J90: 150 | K90: 1000 | L90: 100 | M90: 0 | N90: =H90*J90*M90 -> 0 | O90: =(K90+L90)*M90 -> 0 | P90: =N90*Pressupostos!C8 -> 0 | Q90: Oficial
B91: Viagem Medieval | C91: Santa Maria da Feira | D91: Aveiro | E91: 8 | F91: 29 Jul-9 Ago 2026 | G91: Recriação | H91: 11 | I91: XL | J91: 200 | K91: 2500 | L91: 250 | M91: 0 | N91: =H91*J91*M91 -> 0 | O91: =(K91+L91)*M91 -> 0 | P91: =N91*Pressupostos!C8 -> 0 | Q91: VisitPortugal
B92: São Bento da Porta Aberta | C92: Terras de Bouro | D92: Braga | E92: 8 | F92: Ago 2026 | G92: Romaria | H92: 5 | I92: L | J92: 150 | K92: 1000 | L92: 400 | M92: 0 | N92: =H92*J92*M92 -> 0 | O92: =(K92+L92)*M92 -> 0 | P92: =N92*Pressupostos!C8 -> 0 | Q92: VisitPortugal
B93: Feira de São Bernardo | C93: Alcobaça | D93: Leiria | E93: 8 | F93: ~20 Ago 2026 | G93: Feira/Religiosa | H93: 5 | I93: M | J93: 90 | K93: 400 | L93: 130 | M93: 0 | N93: =H93*J93*M93 -> 0 | O93: =(K93+L93)*M93 -> 0 | P93: =N93*Pressupostos!C8 -> 0 | Q93: Estimativa
B94: Festas da Assunção | C94: Póvoa de Varzim | D94: Porto | E94: 8 | F94: ~15 Ago 2026 | G94: Cidade | H94: 5 | I94: L | J94: 150 | K94: 1000 | L94: 350 | M94: 0 | N94: =H94*J94*M94 -> 0 | O94: =(K94+L94)*M94 -> 0 | P94: =N94*Pressupostos!C8 -> 0 | Q94: Estimativa
B95: Capeias Arraianas | C95: Sabugal (várias) | D95: Guarda | E95: 8 | F95: Verão 2026 (13 locais) | G95: Taurina/Tradicional | H95: 10 | I95: M | J95: 90 | K95: 400 | L95: 450 | M95: 0 | N95: =H95*J95*M95 -> 0 | O95: =(K95+L95)*M95 -> 0 | P95: =N95*Pressupostos!C8 -> 0 | Q95: CM Sabugal
B96: Festas de São Paio da Torreira | C96: Murtosa | D96: Aveiro | E96: 9 | F96: 4-8 Set 2026 | G96: Religiosa/Popular | H96: 5 | I96: M | J96: 90 | K96: 400 | L96: 280 | M96: 0 | N96: =H96*J96*M96 -> 0 | O96: =(K96+L96)*M96 -> 0 | P96: =N96*Pressupostos!C8 -> 0 | Q96: VisitPortugal
B97: Feira Sabores de Perdição | C97: Castelo Branco | D97: Castelo Branco | E97: 9 | F97: 3-6 Set 2026 | G97: Gastronomia | H97: 4 | I97: M | J97: 90 | K97: 400 | L97: 400 | M97: 0 | N97: =H97*J97*M97 -> 0 | O97: =(K97+L97)*M97 -> 0 | P97: =N97*Pressupostos!C8 -> 0 | Q97: CM Castelo Branco
B98: Festa das Vindimas | C98: Palmela | D98: Setúbal | E98: 9 | F98: 3-8 Set 2026 | G98: Vínica/Popular | H98: 6 | I98: M | J98: 90 | K98: 400 | L98: 180 | M98: 0 | N98: =H98*J98*M98 -> 0 | O98: =(K98+L98)*M98 -> 0 | P98: =N98*Pressupostos!C8 -> 0 | Q98: CM Palmela
B99: Festa dos Capuchos | C99: Vila Viçosa | D99: Évora | E99: 9 | F99: 10-15 Set 2026 | G99: Religiosa/Popular | H99: 6 | I99: M | J99: 90 | K99: 400 | L99: 350 | M99: 0 | N99: =H99*J99*M99 -> 0 | O99: =(K99+L99)*M99 -> 0 | P99: =N99*Pressupostos!C8 -> 0 | Q99: VisitPortugal
B100: Senhor Jesus da Piedade (S.Mateus) | C100: Elvas | D100: Portalegre | E100: 9 | F100: 18-27 Set 2026 | G100: Religiosa/Feira | H100: 10 | I100: L | J100: 150 | K100: 1000 | L100: 380 | M100: 0 | N100: =H100*J100*M100 -> 0 | O100: =(K100+L100)*M100 -> 0 | P100: =N100*Pressupostos!C8 -> 0 | Q100: CM Elvas
B101: Feiras Novas | C101: Ponte de Lima | D101: Viana do Castelo | E101: 9 | F101: meados Set 2026 | G101: Romaria | H101: 5 | I101: XL | J101: 200 | K101: 2500 | L101: 400 | M101: 1 | N101: =H101*J101*M101 -> 1000 | O101: =(K101+L101)*M101 -> 2900 | P101: =N101*Pressupostos!C8 -> 8849.5575 | Q101: Turismo Porto e Norte
...

Sheet Financiamento
B1: FINANCIAMENTO / FINANCING
B2: Amortização (máquinas + veículo) / Loan amortization
B4: Valor financiado / Loan | C4: =Pressupostos!C63 -> 100560
B5: Taxa anual / Rate | C5: =Pressupostos!C64 -> 0.08
B6: Prestação / Payment | C6: =Pressupostos!C66 -> 2038.9942
B8: Mês | C8: Saldo inicial | D8: Prestação | E8: Juros | F8: Capital | G8: Saldo final
B9: 1 | C9: =Pressupostos!C63 -> 100560 | D9: =$C$6 -> 2038.9942 | E9: =C9*$C$5/12 -> 670.4 | F9: =D9-E9 -> 1368.5942 | G9: =C9-F9 -> 99191.406
B10: 2 | C10: =G9 -> 99191.406 | D10: =$C$6 -> 2038.9942 | E10: =C10*$C$5/12 -> 661.27604 | F10: =D10-E10 -> 1377.7182 | G10: =C10-F10 -> 97813.688
B11: 3 | C11: =G10 -> 97813.688 | D11: =$C$6 -> 2038.9942 | E11: =C11*$C$5/12 -> 652.09125 | F11: =D11-E11 -> 1386.903 | G11: =C11-F11 -> 96426.785
B12: 4 | C12: =G11 -> 96426.785 | D12: =$C$6 -> 2038.9942 | E12: =C12*$C$5/12 -> 642.84523 | F12: =D12-E12 -> 1396.149 | G12: =C12-F12 -> 95030.636
B13: 5 | C13: =G12 -> 95030.636 | D13: =$C$6 -> 2038.9942 | E13: =C13*$C$5/12 -> 633.53757 | F13: =D13-E13 -> 1405.4566 | G13: =C13-F13 -> 93625.179
B14: 6 | C14: =G13 -> 93625.179 | D14: =$C$6 -> 2038.9942 | E14: =C14*$C$5/12 -> 624.16786 | F14: =D14-E14 -> 1414.8263 | G14: =C14-F14 -> 92210.353
B15: 7 | C15: =G14 -> 92210.353 | D15: =$C$6 -> 2038.9942 | E15: =C15*$C$5/12 -> 614.73568 | F15: =D15-E15 -> 1424.2585 | G15: =C15-F15 -> 90786.094
B16: 8 | C16: =G15 -> 90786.094 | D16: =$C$6 -> 2038.9942 | E16: =C16*$C$5/12 -> 605.24063 | F16: =D16-E16 -> 1433.7536 | G16: =C16-F16 -> 89352.341
B17: 9 | C17: =G16 -> 89352.341 | D17: =$C$6 -> 2038.9942 | E17: =C17*$C$5/12 -> 595.68227 | F17: =D17-E17 -> 1443.3119 | G17: =C17-F17 -> 87909.029
B18: 10 | C18: =G17 -> 87909.029 | D18: =$C$6 -> 2038.9942 | E18: =C18*$C$5/12 -> 586.06019 | F18: =D18-E18 -> 1452.934 | G18: =C18-F18 -> 86456.095
B19: 11 | C19: =G18 -> 86456.095 | D19: =$C$6 -> 2038.9942 | E19: =C19*$C$5/12 -> 576.37396 | F19: =D19-E19 -> 1462.6202 | G19: =C19-F19 -> 84993.474
B20: 12 | C20: =G19 -> 84993.474 | D20: =$C$6 -> 2038.9942 | E20: =C20*$C$5/12 -> 566.62316 | F20: =D20-E20 -> 1472.371 | G20: =C20-F20 -> 83521.103
B21: 13 | C21: =G20 -> 83521.103 | D21: =$C$6 -> 2038.9942 | E21: =C21*$C$5/12 -> 556.80736 | F21: =D21-E21 -> 1482.1869 | G21: =C21-F21 -> 82038.916
... B68: 60 | C68: =G67 -> 2025.4909 | D68: =$C$6 -> 2038.9942 | E68: =C68*$C$5/12 -> 13.503273 | F68: =D68-E68 -> 2025.4909 | G68: =C68-F68 -> 1.2050805e-11
B70: POR PERÍODO / BY PERIOD
C71: M1 | D71: M2 | E71: M3 | F71: M4 | G71: M5 | H71: M6 | I71: M7 | J71: M8 | K71: M9 | L71: M10 | M71: M11 | N71: M12
B72: Juros mensais Ano 1 / Monthly interest Y1 | C72: =E9 -> 670.4 | D72: =E10 -> 661.27604 | E72: =E11 -> 652.09125 | F72: =E12 -> 642.84523 | G72: =E13 -> 633.53757 | H72: =E14 -> 624.16786 | I72: =E15 -> 614.73568 | J72: =E16 -> 605.24063 | K72: =E17 -> 595.68227 | L72: =E18 -> 586.06019 | M72: =E19 -> 576.37396 | N72: =E20 -> 566.62316
C73: Ano1 | D73: Ano2 | E73: Ano3 | F73: Ano4 | G73: Ano5
B74: Juros anuais / Annual interest | C74: =SUM(E9:E20) -> 7429.0339 | D74: =SUM(E21:E32) -> 6014.8138 | E74: =SUM(E33:E44) -> 4483.2142 | F74: =SUM(E45:E56) -> 2824.4927 | G74: =SUM(E57:E68) -> 1028.098
B76: Capital anual / Annual principal | C76: =SUM(F9:F20) -> 17038.897 | D76: =SUM(F21:F32) -> 18453.117 | E76: =SUM(F33:F44) -> 19984.716 | F76: =SUM(F45:F56) -> 21643.438 | G76: =SUM(F57:F68) -> 23439.833

Sheet Receita
B1: RECEITA / REVENUE
B2: Máquinas fixas (ramp) + circuito móvel (eventos) / Fixed + mobile event circuit
B4: Métrica / Metric | C4: M1 | D4: M2 | E4: M3 | F4: M4 | G4: M5 | H4: M6 | I4: M7 | J4: M8 | K4: M9 | L4: M10 | M4: M11 | N4: M12 | O4: Ano 1 Y1 | P4: Ano 2 Y2 | Q4: Ano 3 Y3 | R4: Ano 4 Y4 | S4: Ano 5 Y5
B5: Unidades — fixas / Fixed-machine units | C5: =Pressupostos!C49*Pressupostos!C10*Pressupostos!C75*Pressupostos!C11 -> 480 | D5: =Pressupostos!C49*Pressupostos!C10*Pressupostos!D75*Pressupostos!C11 -> 660 | E5: =Pressupostos!C49*Pressupostos!C10*Pressupostos!E75*Pressupostos!C11 -> 840 | F5: =Pressupostos!C49*Pressupostos!C10*Pressupostos!F75*Pressupostos!C11 -> 960 | G5: =Pressupostos!C49*Pressupostos!C10*Pressupostos!G75*Pressupostos!C11 -> 1080 | H5: =Pressupostos!C49*Pressupostos!C10*Pressupostos!H75*Pressupostos!C11 -> 1200 | I5: =Pressupostos!C49*Pressupostos!C10*Pressupostos!I75*Pressupostos!C11 -> 1260 | J5: =Pressupostos!C49*Pressupostos!C10*Pressupostos!J75*Pressupostos!C11 -> 1320 | K5: =Pressupostos!C49*Pressupostos!C10*Pressupostos!K75*Pressupostos!C11 -> 1200 | L5: =Pressupostos!C49*Pressupostos!C10*Pressupostos!L75*Pressupostos!C11 -> 1140 | M5: =Pressupostos!C49*Pressupostos!C10*Pressupostos!M75*Pressupostos!C11 -> 1140 | N5: =Pressupostos!C49*Pressupostos!C10*Pressupostos!N75*Pressupostos!C11 -> 1260 | O5: =SUM(C5:N5) -> 12540 | P5: =Pressupostos!C49*Pressupostos!C10*Pressupostos!C11*12*(1+Pressupostos!C12)^1 -> 15120 | Q5: =Pressupostos!C49*Pressupostos!C10*Pressupostos!C11*12*(1+Pressupostos!C12)^2 -> 15876 | R5: =Pressupostos!C49*Pressupostos!C10*Pressupostos!C11*12*(1+Pressupostos!C12)^3 -> 16669.8 | S5: =Pressupostos!C49*Pressupostos!C10*Pressupostos!C11*12*(1+Pressupostos!C12)^4 -> 17503.29
B6: Unidades — eventos (móvel) / Event units | C6: =SUMIFS(Eventos!$N$5:$N$116,Eventos!$E$5:$E$116,1) -> 830 | D6: =SUMIFS(Eventos!$N$5:$N$116,Eventos!$E$5:$E$116,2) -> 1170 | E6: =SUMIFS(Eventos!$N$5:$N$116,Eventos!$E$5:$E$116,3) -> 1680 | F6: =SUMIFS(Eventos!$N$5:$N$116,Eventos!$E$5:$E$116,4) -> 0 | G6: =SUMIFS(Eventos!$N$5:$N$116,Eventos!$E$5:$E$116,5) -> 450 | H6: =SUMIFS(Eventos!$N$5:$N$116,Eventos!$E$5:$E$116,6) -> 4050 | I6: =SUMIFS(Eventos!$N$5:$N$116,Eventos!$E$5:$E$116,7) -> 1200 | J6: =SUMIFS(Eventos!$N$5:$N$116,Eventos!$E$5:$E$116,8) -> 2400 | K6: =SUMIFS(Eventos!$N$5:$N$116,Eventos!$E$5:$E$116,9) -> 1600 | L6: =SUMIFS(Eventos!$N$5:$N$116,Eventos!$E$5:$E$116,10) -> 600 | M6: =SUMIFS(Eventos!$N$5:$N$116,Eventos!$E$5:$E$116,11) -> 1500 | N6: =SUMIFS(Eventos!$N$5:$N$116,Eventos!$E$5:$E$116,12) -> 2450 | O6: =Eventos!N121 -> 17930 | P6: =Eventos!N121*(1+Pressupostos!C12)^1 -> 18826.5 | Q6: =Eventos!N121*(1+Pressupostos!C12)^2 -> 19767.825 | R6: =Eventos!N121*(1+Pressupostos!C12)^3 -> 20756.216 | S6: =Eventos!N121*(1+Pressupostos!C12)^4 -> 21794.027
B7: Unidades totais / Total units | C7: =C5+C6 -> 1310 | D7: =D5+D6 -> 1830 | E7: =E5+E6 -> 2520 | F7: =F5+F6 -> 960 | G7: =G5+G6 -> 1530 | H7: =H5+H6 -> 5250 | I7: =I5+I6 -> 2460 | J7: =J5+J6 -> 3720 | ... S7: =S5+S6 -> 39297.317
B8: Preço c/IVA / Price incl. VAT | C8: =Pressupostos!C6 -> 10 | D8: =Pressupostos!C6 -> 10 | E8: =Pressupostos!C6 -> 10 | F8: =Pressupostos!C6 -> 10 | G8: =Pressupostos!C6 -> 10 | H8: =Pressupostos!C6 -> 10 | I8: =Pressupostos!C6 -> 10 | J8: =Pressupostos!C6 -> 10 | K8: =Pressupostos!C6 -> 10 | L8: =Pressupostos!C6 -> 10 | M8: =Pressupostos!C6 -> 10 | N8: =Pressupostos!C6 -> 10 | O8: =Pressupostos!C6 -> 10 | P8: =Pressupostos!C6 -> 10 | Q8: =Pressupostos!C6 -> 10 | R8: =Pressupostos!C6 -> 10 | S8: =Pressupostos!C6 -> 10
B9: Vendas brutas c/IVA / Gross sales | C9: =C7*C8 -> 13100 | D9: =D7*D8 -> 18300 | E9: =E7*E8 -> 25200 | F9: =F7*F8 -> 9600 | G9: =G7*G8 -> 15300 | H9: =H7*H8 -> 52500 | I9: =I7*I8 -> 24600 | J9: =J7*J8 -> 37200 | ... S9: =S7*S8 -> 392973.17
B10: IVA / VAT | C10: =C9*Pressupostos!C7/(1+Pressupostos!C7) -> 1507.0796 | D10: =D9*Pressupostos!C7/(1+Pressupostos!C7) -> 2105.3097 | E10: =E9*Pressupostos!C7/(1+Pressupostos!C7) -> 2899.115 | F10: =F9*Pressupostos!C7/(1+Pressupostos!C7) -> 1104.4248 | G10: =G9*Pressupostos!C7/(1+Pressupostos!C7) -> 1760.177 | H10: =H9*Pressupostos!C7/(1+Pressupostos!C7) -> 6039.823 | I10: =I9*Pressupostos!C7/(1+Pressupostos!C7) -> 2830.0885 | J10: =J9*Pressupostos!C7/(1+Pressupostos!C7) -> 4279.646 | K10: =K9*Pressupostos!C7/(1+Pressupostos!C7) -> 3221.2389 | L10: =L9*Pressupostos!C7/(1+Pressupostos!C7) -> 2001.7699 | M10: =M9*Pressupostos!C7/(1+Pressupostos!C7) -> 3037.1681 | N10: =N9*Pressupostos!C7/(1+Pressupostos!C7) -> 4268.1416 | O10: =O9*Pressupostos!C7/(1+Pressupostos!C7) -> 35053.982 | P10: =P9*Pressupostos!C7/(1+Pressupostos!C7) -> 39053.496 | Q10: =Q9*Pressupostos!C7/(1+Pressupostos!C7) -> 41006.17 | R10: =R9*Pressupostos!C7/(1+Pressupostos!C7) -> 43056.479 | S10: =S9*Pressupostos!C7/(1+Pressupostos!C7) -> 45209.303
B11: Vendas líquidas s/IVA / Net sales | C11: =C9-C10 -> 11592.92 | D11: =D9-D10 -> 16194.69 | E11: =E9-E10 -> 22300.885 | F11: =F9-F10 -> 8495.5752 | G11: =G9-G10 -> 13539.823 | H11: =H9-H10 -> 46460.177 | I11: =I9-I10 -> 21769.912 | J11: =J9-J10 -> 32920.354 | ... S11: =S9-S10 -> 347763.87
B12: Taxa de pagamento / Card fee | C12: =-C9*Pressupostos!C9 -> -196.5 | D12: =-D9*Pressupostos!C9 -> -274.5 | E12: =-E9*Pressupostos!C9 -> -378 | F12: =-F9*Pressupostos!C9 -> -144 | G12: =-G9*Pressupostos!C9 -> -229.5 | H12: =-H9*Pressupostos!C9 -> -787.5 | I12: =-I9*Pressupostos!C9 -> -369 | J12: =-J9*Pressupostos!C9 -> -558 | K12: =-K9*Pressupostos!C9 -> -420 | L12: =-L9*Pressupostos!C9 -> -261 | M12: =-M9*Pressupostos!C9 -> -396 | N12: =-N9*Pressupostos!C9 -> -556.5 | O12: =-O9*Pressupostos!C9 -> -4570.5 | P12: =-P9*Pressupostos!C9 -> -5091.975 | Q12: =-Q9*Pressupostos!C9 -> -5346.5737 | R12: =-R9*Pressupostos!C9 -> -5613.9024 | S12: =-S9*Pressupostos!C9 -> -5894.5976
B13: RECEITA LÍQUIDA / NET REVENUE | C13: =C11+C12 -> 11396.42 | D13: =D11+D12 -> 15920.19 | E13: =E11+E12 -> 21922.885 | F13: =F11+F12 -> 8351.5752 | G13: =G11+G12 -> 13310.323 | H13: =H11+H12 -> 45672.677 | I13: =I11+I12 -> 21400.912 | J13: =J11+J12 -> 32362.354 | ... S13: =S11+S12 -> 341869.27

Sheet Custos
B1: CUSTOS / COSTS
B2: COGS + opex por máquina + logística de eventos / COGS + per-machine opex + event logistics
B4: Métrica / Metric | C4: M1 | D4: M2 | E4: M3 | F4: M4 | G4: M5 | H4: M6 | I4: M7 | J4: M8 | K4: M9 | L4: M10 | M4: M11 | N4: M12 | O4: Ano 1 Y1 | P4: Ano 2 Y2 | Q4: Ano 3 Y3 | R4: Ano 4 Y4 | S4: Ano 5 Y5
B5: COGS (Adial) | C5: =-Receita!C7*Pressupostos!C23 -> -4313.7121 | D5: =-Receita!D7*Pressupostos!C23 -> -6026.0253 | E5: =-Receita!E7*Pressupostos!C23 -> -8298.1332 | F5: =-Receita!F7*Pressupostos!C23 -> -3161.1936 | G5: =-Receita!G7*Pressupostos!C23 -> -5038.1523 | H5: =-Receita!H7*Pressupostos!C23 -> -17287.778 | I5: =-Receita!I7*Pressupostos!C23 -> -8100.5586 | J5: =-Receita!J7*Pressupostos!C23 -> -12249.625 | K5: =-Receita!K7*Pressupostos!C23 -> -9220.148 | L5: =-Receita!L7*Pressupostos!C23 -> -5729.6634 | M5: =-Receita!M7*Pressupostos!C23 -> -8693.2824 | N5: =-Receita!N7*Pressupostos!C23 -> -12216.696 | O5: =-Receita!O7*Pressupostos!C23 -> -100334.97 | P5: =-Receita!P7*Pressupostos!C23 -> -111782.77 | Q5: =-Receita!Q7*Pressupostos!C23 -> -117371.91 | R5: =-Receita!R7*Pressupostos!C23 -> -123240.5 | S5: =-Receita!S7*Pressupostos!C23 -> -129402.53
B6: Renda (fixas) / Rent (fixed) | C6: =-Maquinas!F12 -> -600 | D6: =-Maquinas!F12 -> -600 | E6: =-Maquinas!F12 -> -600 | F6: =-Maquinas!F12 -> -600 | G6: =-Maquinas!F12 -> -600 | H6: =-Maquinas!F12 -> -600 | I6: =-Maquinas!F12 -> -600 | J6: =-Maquinas!F12 -> -600 | K6: =-Maquinas!F12 -> -600 | L6: =-Maquinas!F12 -> -600 | M6: =-Maquinas!F12 -> -600 | N6: =-Maquinas!F12 -> -600 | O6: =SUM(C6:N6) -> -7200 | P6: =-Maquinas!F12*12 -> -7200 | Q6: =-Maquinas!F12*12 -> -7200 | R6: =-Maquinas!F12*12 -> -7200 | S6: =-Maquinas!F12*12 -> -7200
B7: Reabastecimento (fixas) / Restock (fixed) | C7: =-Maquinas!G12 -> -700 | D7: =-Maquinas!G12 -> -700 | E7: =-Maquinas!G12 -> -700 | F7: =-Maquinas!G12 -> -700 | G7: =-Maquinas!G12 -> -700 | H7: =-Maquinas!G12 -> -700 | I7: =-Maquinas!G12 -> -700 | J7: =-Maquinas!G12 -> -700 | K7: =-Maquinas!G12 -> -700 | L7: =-Maquinas!G12 -> -700 | M7: =-Maquinas!G12 -> -700 | N7: =-Maquinas!G12 -> -700 | O7: =SUM(C7:N7) -> -8400 | P7: =-Maquinas!G12*12 -> -8400 | Q7: =-Maquinas!G12*12 -> -8400 | R7: =-Maquinas!G12*12 -> -8400 | S7: =-Maquinas!G12*12 -> -8400
B8: Eletricidade / Electricity | C8: =-Maquinas!H12 -> -420 | D8: =-Maquinas!H12 -> -420 | E8: =-Maquinas!H12 -> -420 | F8: =-Maquinas!H12 -> -420 | G8: =-Maquinas!H12 -> -420 | H8: =-Maquinas!H12 -> -420 | I8: =-Maquinas!H12 -> -420 | J8: =-Maquinas!H12 -> -420 | K8: =-Maquinas!H12 -> -420 | L8: =-Maquinas!H12 -> -420 | M8: =-Maquinas!H12 -> -420 | N8: =-Maquinas!H12 -> -420 | O8: =SUM(C8:N8) -> -5040 | P8: =-Maquinas!H12*12 -> -5040 | Q8: =-Maquinas!H12*12 -> -5040 | R8: =-Maquinas!H12*12 -> -5040 | S8: =-Maquinas!H12*12 -> -5040
B9: Seguro / Insurance | C9: =-Maquinas!I12 -> -135 | D9: =-Maquinas!I12 -> -135 | E9: =-Maquinas!I12 -> -135 | F9: =-Maquinas!I12 -> -135 | G9: =-Maquinas!I12 -> -135 | H9: =-Maquinas!I12 -> -135 | I9: =-Maquinas!I12 -> -135 | J9: =-Maquinas!I12 -> -135 | K9: =-Maquinas!I12 -> -135 | L9: =-Maquinas!I12 -> -135 | M9: =-Maquinas!I12 -> -135 | N9: =-Maquinas!I12 -> -135 | O9: =SUM(C9:N9) -> -1620 | P9: =-Maquinas!I12*12 -> -1620 | Q9: =-Maquinas!I12*12 -> -1620 | R9: =-Maquinas!I12*12 -> -1620 | S9: =-Maquinas!I12*12 -> -1620
B10: Internet+gestão frota / Internet+fleet | C10: =-Maquinas!J12 -> -81 | D10: =-Maquinas!J12 -> -81 | E10: =-Maquinas!J12 -> -81 | F10: =-Maquinas!J12 -> -81 | G10: =-Maquinas!J12 -> -81 | H10: =-Maquinas!J12 -> -81 | I10: =-Maquinas!J12 -> -81 | J10: =-Maquinas!J12 -> -81 | K10: =-Maquinas!J12 -> -81 | L10: =-Maquinas!J12 -> -81 | M10: =-Maquinas!J12 -> -81 | N10: =-Maquinas!J12 -> -81 | O10: =SUM(C10:N10) -> -972 | P10: =-Maquinas!J12*12 -> -972 | Q10: =-Maquinas!J12*12 -> -972 | R10: =-Maquinas!J12*12 -> -972 | S10: =-Maquinas!J12*12 -> -972
B11: Manutenção / Maintenance | C11: =-Maquinas!K12 -> -240 | D11: =-Maquinas!K12 -> -240 | E11: =-Maquinas!K12 -> -240 | F11: =-Maquinas!K12 -> -240 | G11: =-Maquinas!K12 -> -240 | H11: =-Maquinas!K12 -> -240 | I11: =-Maquinas!K12 -> -240 | J11: =-Maquinas!K12 -> -240 | K11: =-Maquinas!K12 -> -240 | L11: =-Maquinas!K12 -> -240 | M11: =-Maquinas!K12 -> -240 | N11: =-Maquinas!K12 -> -240 | O11: =SUM(C11:N11) -> -2880 | P11: =-Maquinas!K12*12 -> -2880 | Q11: =-Maquinas!K12*12 -> -2880 | R11: =-Maquinas!K12*12 -> -2880 | S11: =-Maquinas!K12*12 -> -2880
B12: Contabilidade / Accounting | C12: =-(Pressupostos!C37) -> -150 | D12: =-(Pressupostos!C37) -> -150 | E12: =-(Pressupostos!C37) -> -150 | F12: =-(Pressupostos!C37) -> -150 | G12: =-(Pressupostos!C37) -> -150 | H12: =-(Pressupostos!C37) -> -150 | I12: =-(Pressupostos!C37) -> -150 | J12: =-(Pressupostos!C37) -> -150 | K12: =-(Pressupostos!C37) -> -150 | L12: =-(Pressupostos!C37) -> -150 | M12: =-(Pressupostos!C37) -> -150 | N12: =-(Pressupostos!C37) -> -150 | O12: =SUM(C12:N12) -> -1800 | P12: =-(Pressupostos!C37)*12 -> -1800 | Q12: =-(Pressupostos!C37)*12 -> -1800 | R12: =-(Pressupostos!C37)*12 -> -1800 | S12: =-(Pressupostos!C37)*12 -> -1800
B13: Diversos / Misc | C13: =-(Pressupostos!C38) -> -100 | D13: =-(Pressupostos!C38) -> -100 | E13: =-(Pressupostos!C38) -> -100 | F13: =-(Pressupostos!C38) -> -100 | G13: =-(Pressupostos!C38) -> -100 | H13: =-(Pressupostos!C38) -> -100 | I13: =-(Pressupostos!C38) -> -100 | J13: =-(Pressupostos!C38) -> -100 | K13: =-(Pressupostos!C38) -> -100 | L13: =-(Pressupostos!C38) -> -100 | M13: =-(Pressupostos!C38) -> -100 | N13: =-(Pressupostos!C38) -> -100 | O13: =SUM(C13:N13) -> -1200 | P13: =-(Pressupostos!C38)*12 -> -1200 | Q13: =-(Pressupostos!C38)*12 -> -1200 | R13: =-(Pressupostos!C38)*12 -> -1200 | S13: =-(Pressupostos!C38)*12 -> -1200
B14: Veículo transporte / Transport vehicle | C14: =-(Pressupostos!C39) -> -150 | D14: =-(Pressupostos!C39) -> -150 | E14: =-(Pressupostos!C39) -> -150 | F14: =-(Pressupostos!C39) -> -150 | G14: =-(Pressupostos!C39) -> -150 | H14: =-(Pressupostos!C39) -> -150 | I14: =-(Pressupostos!C39) -> -150 | J14: =-(Pressupostos!C39) -> -150 | K14: =-(Pressupostos!C39) -> -150 | L14: =-(Pressupostos!C39) -> -150 | M14: =-(Pressupostos!C39) -> -150 | N14: =-(Pressupostos!C39) -> -150 | O14: =SUM(C14:N14) -> -1800 | P14: =-(Pressupostos!C39)*12 -> -1800 | Q14: =-(Pressupostos!C39)*12 -> -1800 | R14: =-(Pressupostos!C39)*12 -> -1800 | S14: =-(Pressupostos!C39)*12 -> -1800
B15: Logística eventos (lugar+transporte) / Event logistics | C15: =-SUMIFS(Eventos!$O$5:$O$116,Eventos!$E$5:$E$116,1) -> -1900 | D15: =-SUMIFS(Eventos!$O$5:$O$116,Eventos!$E$5:$E$116,2) -> -1640 | E15: =-SUMIFS(Eventos!$O$5:$O$116,Eventos!$E$5:$E$116,3) -> -1900 | F15: =-SUMIFS(Eventos!$O$5:$O$116,Eventos!$E$5:$E$116,4) -> 0 | G15: =-SUMIFS(Eventos!$O$5:$O$116,Eventos!$E$5:$E$116,5) -> -520 | H15: =-SUMIFS(Eventos!$O$5:$O$116,Eventos!$E$5:$E$116,6) -> -5990 | I15: =-SUMIFS(Eventos!$O$5:$O$116,Eventos!$E$5:$E$116,7) -> -3710 | J15: =-SUMIFS(Eventos!$O$5:$O$116,Eventos!$E$5:$E$116,8) -> -4250 | K15: =-SUMIFS(Eventos!$O$5:$O$116,Eventos!$E$5:$E$116,9) -> -5530 | L15: =-SUMIFS(Eventos!$O$5:$O$116,Eventos!$E$5:$E$116,10) -> -1110 | M15: =-SUMIFS(Eventos!$O$5:$O$116,Eventos!$E$5:$E$116,11) -> -1180 | N15: =-SUMIFS(Eventos!$O$5:$O$116,Eventos!$E$5:$E$116,12) -> -3750 | O15: =-Eventos!O122 -> -31480 | P15: =-Eventos!O122 -> -31480 | Q15: =-Eventos!O122 -> -31480 | R15: =-Eventos!O122 -> -31480 | S15: =-Eventos!O122 -> -31480
B16: Mão-de-obra eventos / Event labour | C16: =-SUMIFS(Eventos!$H$5:$H$116,Eventos!$E$5:$E$116,1,Eventos!$M$5:$M$116,1)*Pressupostos!C43 -> -990 | D16: =-SUMIFS(Eventos!$H$5:$H$116,Eventos!$E$5:$E$116,2,Eventos!$M$5:$M$116,1)*Pressupostos!C43 -> -450 | E16: =-SUMIFS(Eventos!$H$5:$H$116,Eventos!$E$5:$E$116,3,Eventos!$M$5:$M$116,1)*Pressupostos!C43 -> -1260 | F16: =-SUMIFS(Eventos!$H$5:$H$116,Eventos!$E$5:$E$116,4,Eventos!$M$5:$M$116,1)*Pressupostos!C43 -> 0 | G16: =-SUMIFS(Eventos!$H$5:$H$116,Eventos!$E$5:$E$116,5,Eventos!$M$5:$M$116,1)*Pressupostos!C43 -> -450 | H16: =-SUMIFS(Eventos!$H$5:$H$116,Eventos!$E$5:$E$116,6,Eventos!$M$5:$M$116,1)*Pressupostos!C43 -> -2070 | I16: =-SUMIFS(Eventos!$H$5:$H$116,Eventos!$E$5:$E$116,7,Eventos!$M$5:$M$116,1)*Pressupostos!C43 -> -630 | J16: =-SUMIFS(Eventos!$H$5:$H$116,Eventos!$E$5:$E$116,8,Eventos!$M$5:$M$116,1)*Pressupostos!C43 -> -1170 | K16: =-SUMIFS(Eventos!$H$5:$H$116,Eventos!$E$5:$E$116,9,Eventos!$M$5:$M$116,1)*Pressupostos!C43 -> -720 | L16: =-SUMIFS(Eventos!$H$5:$H$116,Eventos!$E$5:$E$116,10,Eventos!$M$5:$M$116,1)*Pressupostos!C43 -> -360 | M16: =-SUMIFS(Eventos!$H$5:$H$116,Eventos!$E$5:$E$116,11,Eventos!$M$5:$M$116,1)*Pressupostos!C43 -> -900 | N16: =-SUMIFS(Eventos!$H$5:$H$116,Eventos!$E$5:$E$116,12,Eventos!$M$5:$M$116,1)*Pressupostos!C43 -> -1440 | O16: =-Eventos!H120*Pressupostos!C43 -> -11160 | P16: =-Eventos!H120*Pressupostos!C43 -> -11160 | Q16: =-Eventos!H120*Pressupostos!C43 -> -11160 | R16: =-Eventos!H120*Pressupostos!C43 -> -11160 | S16: =-Eventos!H120*Pressupostos!C43 -> -11160
B17: Custos operacionais (s/COGS) / Operating costs (excl. COGS) | C17: =SUM(C6:C16) -> -5466 | D17: =SUM(D6:D16) -> -4666 | E17: =SUM(E6:E16) -> -5736 | F17: =SUM(F6:F16) -> -2576 | G17: =SUM(G6:G16) -> -3546 | H17: =SUM(H6:H16) -> -10636 | I17: =SUM(I6:I16) -> -6916 | J17: =SUM(J6:J16) -> -7996 | ... S17: =SUM(S6:S16) -> -73552
B18: CUSTOS TOTAIS / TOTAL COSTS | C18: =C5+C17 -> -9779.7121 | D18: =D5+D17 -> -10692.025 | E18: =E5+E17 -> -14034.133 | F18: =F5+F17 -> -5737.1936 | G18: =G5+G17 -> -8584.1523 | H18: =H5+H17 -> -27923.778 | I18: =I5+I17 -> -15016.559 | J18: =J5+J17 -> -20245.625 | ... S18: =S5+S17 -> -202954.53

Sheet DRE
B1: DEMONSTRAÇÃO DE RESULTADOS / PROFIT & LOSS
B4: Métrica / Metric | C4: M1 | D4: M2 | E4: M3 | F4: M4 | G4: M5 | H4: M6 | I4: M7 | J4: M8 | K4: M9 | L4: M10 | M4: M11 | N4: M12 | O4: Ano 1 Y1 | P4: Ano 2 Y2 | Q4: Ano 3 Y3 | R4: Ano 4 Y4 | S4: Ano 5 Y5
B5: Receita líquida / Net revenue | C5: =Receita!C13 -> 11396.42 | D5: =Receita!D13 -> 15920.19 | E5: =Receita!E13 -> 21922.885 | F5: =Receita!F13 -> 8351.5752 | G5: =Receita!G13 -> 13310.323 | H5: =Receita!H13 -> 45672.677 | I5: =Receita!I13 -> 21400.912 | J5: =Receita!J13 -> 32362.354 | ... S5: =Receita!S13 -> 341869.27
B6: COGS | C6: =Custos!C5 -> -4313.7121 | D6: =Custos!D5 -> -6026.0253 | E6: =Custos!E5 -> -8298.1332 | F6: =Custos!F5 -> -3161.1936 | G6: =Custos!G5 -> -5038.1523 | H6: =Custos!H5 -> -17287.778 | I6: =Custos!I5 -> -8100.5586 | J6: =Custos!J5 -> -12249.625 | ... S6: =Custos!S5 -> -129402.53
B7: Margem bruta / Gross margin | C7: =C5+C6 -> 7082.7083 | D7: =D5+D6 -> 9894.165 | E7: =E5+E6 -> 13624.752 | F7: =F5+F6 -> 5190.3816 | G7: =G5+G6 -> 8272.1707 | H7: =H5+H6 -> 28384.899 | I7: =I5+I6 -> 13300.353 | J7: =J5+J6 -> 20112.729 | ... S7: =S5+S6 -> 212466.74
B8: Custos operacionais / Operating costs | C8: =Custos!C17 -> -5466 | D8: =Custos!D17 -> -4666 | E8: =Custos!E17 -> -5736 | F8: =Custos!F17 -> -2576 | G8: =Custos!G17 -> -3546 | H8: =Custos!H17 -> -10636 | I8: =Custos!I17 -> -6916 | J8: =Custos!J17 -> -7996 | ... S8: =Custos!S17 -> -73552
B9: EBITDA | C9: =C7+C8 -> 1616.7083 | D9: =D7+D8 -> 5228.165 | E9: =E7+E8 -> 7888.7518 | F9: =F7+F8 -> 2614.3816 | G9: =G7+G8 -> 4726.1707 | H9: =H7+H8 -> 17748.899 | I9: =I7+I8 -> 6384.3529 | J9: =J7+J8 -> 12116.729 | ... S9: =S7+S8 -> 138914.74
B10: Margem EBITDA % / EBITDA % | C10: =IF(C5=0,0,C9/C5) -> 0.14186106 | D10: =IF(D5=0,0,D9/D5) -> 0.3283984 | E10: =IF(E5=0,0,E9/E5) -> 0.35984095 | F10: =IF(F5=0,0,F9/F5) -> 0.31304054 | G10: =IF(G5=0,0,G9/G5) -> 0.35507558 | H10: =IF(H5=0,0,H9/H5) -> 0.38861089 | I10: =IF(I5=0,0,I9/I5) -> 0.29832154 | J10: =IF(J5=0,0,J9/J5) -> 0.37440814 | ... S10: =IF(S5=0,0,S9/S5) -> 0.40633878
B11: Depreciação / Depreciation | C11: =-Pressupostos!C69/12 -> -1387.5 | D11: =-Pressupostos!C69/12 -> -1387.5 | E11: =-Pressupostos!C69/12 -> -1387.5 | F11: =-Pressupostos!C69/12 -> -1387.5 | G11: =-Pressupostos!C69/12 -> -1387.5 | H11: =-Pressupostos!C69/12 -> -1387.5 | I11: =-Pressupostos!C69/12 -> -1387.5 | J11: =-Pressupostos!C69/12 -> -1387.5 | K11: =-Pressupostos!C69/12 -> -1387.5 | L11: =-Pressupostos!C69/12 -> -1387.5 | M11: =-Pressupostos!C69/12 -> -1387.5 | N11: =-Pressupostos!C69/12 -> -1387.5 | O11: =-Pressupostos!C69 -> -16650 | P11: =-Pressupostos!C69 -> -16650 | Q11: =-Pressupostos!C69 -> -16650 | R11: =-Pressupostos!C69 -> -16650 | S11: =-Pressupostos!C69 -> -16650
B12: EBIT | C12: =C9+C11 -> 229.20825 | D12: =D9+D11 -> 3840.665 | E12: =E9+E11 -> 6501.2518 | F12: =F9+F11 -> 1226.8816 | G12: =G9+G11 -> 3338.6707 | H12: =H9+H11 -> 16361.399 | I12: =I9+I11 -> 4996.8529 | J12: =J9+J11 -> 10729.229 | ... S12: =S9+S11 -> 122264.74
B13: Juros / Interest | C13: =-Financiamento!C72 -> -670.4 | D13: =-Financiamento!D72 -> -661.27604 | E13: =-Financiamento!E72 -> -652.09125 | F13: =-Financiamento!F72 -> -642.84523 | G13: =-Financiamento!G72 -> -633.53757 | H13: =-Financiamento!H72 -> -624.16786 | I13: =-Financiamento!I72 -> -614.73568 | J13: =-Financiamento!J72 -> -605.24063 | ... N13: =-Financiamento!N72 -> -566.62316 | O13: =-Financiamento!C74 -> -7429.0339 | P13: =-Financiamento!D74 -> -6014.8138 | Q13: =-Financiamento!E74 -> -4483.2142 | R13: =-Financiamento!F74 -> -2824.4927 | S13: =-Financiamento!G74 -> -1028.098
B14: EBT / Pre-tax | C14: =C12+C13 -> -441.19175 | D14: =D12+D13 -> 3179.3889 | E14: =E12+E13 -> 5849.1605 | F14: =F12+F13 -> 584.03639 | G14: =G12+G13 -> 2705.1331 | H14: =H12+H13 -> 15737.232 | I14: =I12+I13 -> 4382.1172 | J14: =J12+J13 -> 10123.988 | ... S14: =S12+S13 -> 121236.64
B15: IRC / Corporate tax | C15: =-MAX(C14,0)*Pressupostos!C67 -> 0 | D15: =-MAX(D14,0)*Pressupostos!C67 -> -508.70223 | E15: =-MAX(E14,0)*Pressupostos!C67 -> -935.86568 | F15: =-MAX(F14,0)*Pressupostos!C67 -> -93.445822 | G15: =-MAX(G14,0)*Pressupostos!C67 -> -432.8213 | H15: =-MAX(H14,0)*Pressupostos!C67 -> -2517.9571 | I15: =-MAX(I14,0)*Pressupostos!C67 -> -701.13876 | J15: =-MAX(J14,0)*Pressupostos!C67 -> -1619.8381 | K15: =-MAX(K14,0)*Pressupostos!C67 -> -692.70893 | L15: =-MAX(L14,0)*Pressupostos!C67 -> -542.08104 | M15: =-MAX(M14,0)*Pressupostos!C67 -> -1224.5881 | N15: =-MAX(N14,0)*Pressupostos!C67 -> -1654.1663 | O15: =-MAX(O14,0)*Pressupostos!C67 -> -10737.523 | P15: =-MAX(P14,0)*Pressupostos!C67 -> -13971.191 | Q15: =-MAX(Q14,0)*Pressupostos!C67 -> -15684.541 | R15: =-MAX(R14,0)*Pressupostos!C67 -> -17491.646 | S15: =-MAX(S14,0)*Pressupostos!C67 -> -19397.863
B16: RESULTADO LÍQUIDO / NET PROFIT | C16: =C14+C15 -> -441.19175 | D16: =D14+D15 -> 2670.6867 | E16: =E14+E15 -> 4913.2948 | F16: =F14+F15 -> 490.59057 | G16: =G14+G15 -> 2272.3118 | H16: =H14+H15 -> 13219.275 | I16: =I14+I15 -> 3680.9785 | J16: =J14+J15 -> 8504.15 | ... S16: =S14+S15 -> 101838.78

Sheet ResumoMultianual
B1: RESUMO MULTIANUAL / MULTI-YEAR SUMMARY
B4: Métrica / Metric | C4: Ano 1 | D4: Ano 2 | E4: Ano 3 | F4: Ano 4 | G4: Ano 5 | H4: Total 5a
B5: Receita líquida / Net revenue | C5: =DRE!O5 -> 265075.52 | D5: =DRE!P5 -> 295319.53 | E5: =DRE!Q5 -> 310085.51 | F5: =DRE!R5 -> 325589.78 | G5: =DRE!S5 -> 341869.27 | H5: =SUM(C5:G5) -> 1537939.6
B6: EBITDA | C6: =DRE!O9 -> 91188.55 | D6: =DRE!P9 -> 109984.76 | E6: =DRE!Q9 -> 119161.6 | F6: =DRE!R9 -> 128797.28 | G6: =DRE!S9 -> 138914.74 | H6: =SUM(C6:G6) -> 588046.93
B7: Margem EBITDA % / EBITDA % | C7: =DRE!O10 -> 0.3440097 | D7: =DRE!P10 -> 0.3724263 | E7: =DRE!Q10 -> 0.38428626 | F7: =DRE!R10 -> 0.39558145 | G7: =DRE!S10 -> 0.40633878
B8: Resultado líquido / Net profit | C8: =DRE!O16 -> 56371.994 | D8: =DRE!P16 -> 73348.755 | E8: =DRE!Q16 -> 82343.842 | F8: =DRE!R16 -> 91831.14 | G8: =DRE!S16 -> 101838.78 | H8: =SUM(C8:G8) -> 405734.51
B9: Resultado acumulado / Cumulative | C9: =C8 -> 56371.994 | D9: =C9+D8 -> 129720.75 | E9: =D9+E8 -> 212064.59 | F9: =E9+F8 -> 303895.73 | G9: =F9+G8 -> 405734.51

Sheet Tesouraria
B1: TESOURARIA / CASH FLOW
B2: Sem revenda de máquinas / No machine resale
B4: Métrica / Metric | C4: M1 | D4: M2 | E4: M3 | F4: M4 | G4: M5 | H4: M6 | I4: M7 | J4: M8 | K4: M9 | L4: M10 | M4: M11 | N4: M12 | O4: Ano 1 Y1 | P4: Ano 2 Y2 | Q4: Ano 3 Y3 | R4: Ano 4 Y4 | S4: Ano 5 Y5
B5: Resultado líquido / Net profit | C5: =DRE!C16 -> -441.19175 | D5: =DRE!D16 -> 2670.6867 | E5: =DRE!E16 -> 4913.2948 | F5: =DRE!F16 -> 490.59057 | G5: =DRE!G16 -> 2272.3118 | H5: =DRE!H16 -> 13219.275 | I5: =DRE!I16 -> 3680.9785 | J5: =DRE!J16 -> 8504.15 | ... S5: =DRE!S16 -> 101838.78
B6: + Depreciação / + Depreciation | C6: =-DRE!C11 -> 1387.5 | D6: =-DRE!D11 -> 1387.5 | E6: =-DRE!E11 -> 1387.5 | F6: =-DRE!F11 -> 1387.5 | G6: =-DRE!G11 -> 1387.5 | H6: =-DRE!H11 -> 1387.5 | I6: =-DRE!I11 -> 1387.5 | J6: =-DRE!J11 -> 1387.5 | ... S6: =-DRE!S11 -> 16650
B7: Cash flow operacional / Operating CF | C7: =C5+C6 -> 946.30825 | D7: =D5+D6 -> 4058.1867 | E7: =E5+E6 -> 6300.7948 | F7: =F5+F6 -> 1878.0906 | G7: =G5+G6 -> 3659.8118 | H7: =H5+H6 -> 14606.775 | I7: =I5+I6 -> 5068.4785 | J7: =J5+J6 -> 9891.65 | ... S7: =S5+S6 -> 118488.78
B8: Amortização capital / Loan principal | C8: =-Financiamento!F9 -> -1368.5942 | D8: =-Financiamento!F10 -> -1377.7182 | E8: =-Financiamento!F11 -> -1386.903 | F8: =-Financiamento!F12 -> -1396.149 | G8: =-Financiamento!F13 -> -1405.4566 | H8: =-Financiamento!F14 -> -1414.8263 | I8: =-Financiamento!F15 -> -1424.2585 | J8: =-Financiamento!F16 -> -1433.7536 | K8: =-Financiamento!F17 -> -1443.3119 | L8: =-Financiamento!F18 -> -1452.934 | M8: =-Financiamento!F19 -> -1462.6202 | N8: =-Financiamento!F20 -> -1472.371 | O8: =-Financiamento!C76 -> -17038.897 | P8: =-Financiamento!D76 -> -18453.117 | Q8: =-Financiamento!E76 -> -19984.716 | R8: =-Financiamento!F76 -> -21643.438 | S8: =-Financiamento!G76 -> -23439.833
B9: FLUXO LÍQUIDO / NET CASH FLOW | C9: =C7+C8 -> -422.28596 | D9: =D7+D8 -> 2680.4685 | E9: =E7+E8 -> 4913.8919 | F9: =F7+F8 -> 481.94159 | G9: =G7+G8 -> 2254.3552 | H9: =H7+H8 -> 13191.948 | I9: =I7+I8 -> 3644.2199 | J9: =J7+J8 -> 8457.8965 | ... S9: =S7+S8 -> 95048.948
B10: Caixa acumulada (oper.) / Cumulative | C10: =C9 -> -422.28596 | D10: =C10+D9 -> 2258.1826 | E10: =D10+E9 -> 7172.0744 | F10: =E10+F9 -> 7654.016 | G10: =F10+G9 -> 9908.3712 | H10: =G10+H9 -> 23100.319 | I10: =H10+I9 -> 26744.539 | J10: =I10+J9 -> 35202.436 | K10: =J10+K9 -> 38783.346 | ... N10: =M10+N9 -> 56517.306 | P10: =N10+P9 -> 128062.94 | Q10: =P10+Q9 -> 207072.07 | R10: =Q10+R9 -> 293909.77 | S10: =R10+S9 -> 388958.72

Sheet PontoCritico
B1: PONTO CRÍTICO / BREAK-EVEN
B2: Base mensal, frota fixa em regime / Steady-state monthly, fixed fleet
B4: CONTRIBUIÇÃO / UNIT CONTRIBUTION
B5: Preço líquido / Net price | C5: =Pressupostos!C8 -> 8.8495575 | D5: €/un
B6: Menos taxa pagamento / Less card fee | C6: =-Pressupostos!C6*Pressupostos!C9 -> -0.15 | D6: €/un
B7: Menos COGS / Less COGS | C7: =-Pressupostos!C23 -> -3.29291 | D7: €/un
B8: Contribuição / Contribution | C8: =C5+C6+C7 -> 5.4066475 | D8: €/un
B10: CUSTOS FIXOS MENSAIS (frota fixa) / MONTHLY FIXED
B11: Custos fixos mensais / Monthly fixed | C11: =Maquinas!L12+Pressupostos!C37+Pressupostos!C38+Pressupostos!C39 -> 2576 | D11: €/mês | G11: =Maquinas!L12 -> 2176
B12: Prestação empréstimo / Loan payment | C12: =Pressupostos!C66 -> 2038.9942 | D12: €/mês | G12: =Pressupostos!C37+Pressupostos!C38+Pressupostos!C39 -> 400
B13: Total fixos (caixa) / Total fixed | C13: =C11+C12 -> 4614.9942 | D13: €/mês
B15: PONTO CRÍTICO / BREAK-EVEN
B16: Pizzas/mês equilíbrio / Pizzas-month | C16: =C13/C8 -> 853.57778 | D16: un/mês
B17: Pizzas/dia equilíbrio / Pizzas-day | C17: =C16/Pressupostos!C11 -> 28.452593 | D17: un/dia | E17: =Pressupostos!C49 -> 2
B18: Por máquina fixa / Per fixed machine | C18: =C17/Pressupostos!C49 -> 14.226296 | D18: un/dia
B19: Pizzas/dia assumidas/máquina / Assumed per machine | C19: =Pressupostos!C10 -> 20
B20: Margem de segurança / Safety margin | C20: =C19/C18-1 -> 0.40584727
B22: Nota: inclui custos recorrentes de TODA a frota (3 máquinas) + veículo, igual à folha Custos (mês sem eventos).
B23: É um piso conservador: assume eventos a contribuir zero. A receita de eventos ajuda a cobrir estes fixos.

Sheet Sensibilidades
B1: SENSIBILIDADES / SENSITIVITY
B2: EBITDA anual frota fixa (ano estabilizado) / Annual fixed-fleet EBITDA
B4: Preço ↓ / Pizzas/dia por máq. → | C4: 14 | D4: 17 | E4: 20 | F4: 23 | G4: 26
B5: 8 | C5: =(Pressupostos!C49*C$4*Pressupostos!C11*12)*(($B5/(1+Pressupostos!C7))-$B5*Pressupostos!C9-Pressupostos!C23)-(Maquinas!L12+Pressupostos!C37+Pressupostos!C38+Pressupostos!C39)*12 -> 6048.6991 | D5: =(Pressupostos!C49*D$4*Pressupostos!C11*12)*(($B5/(1+Pressupostos!C7))-$B5*Pressupostos!C9-Pressupostos!C23)-(Maquinas!L12+Pressupostos!C37+Pressupostos!C38+Pressupostos!C39)*12 -> 13968.849 | E5: =(Pressupostos!C49*E$4*Pressupostos!C11*12)*(($B5/(1+Pressupostos!C7))-$B5*Pressupostos!C9-Pressupostos!C23)-(Maquinas!L12+Pressupostos!C37+Pressupostos!C38+Pressupostos!C39)*12 -> 21888.999 | F5: =(Pressupostos!C49*F$4*Pressupostos!C11*12)*(($B5/(1+Pressupostos!C7))-$B5*Pressupostos!C9-Pressupostos!C23)-(Maquinas!L12+Pressupostos!C37+Pressupostos!C38+Pressupostos!C39)*12 -> 29809.148 | G5: =(Pressupostos!C49*G$4*Pressupostos!C11*12)*(($B5/(1+Pressupostos!C7))-$B5*Pressupostos!C9-Pressupostos!C23)-(Maquinas!L12+Pressupostos!C37+Pressupostos!C38+Pressupostos!C39)*12 -> 37729.298
B6: 9 | C6: =(Pressupostos!C49*C$4*Pressupostos!C11*12)*(($B6/(1+Pressupostos!C7))-$B6*Pressupostos!C9-Pressupostos!C23)-(Maquinas!L12+Pressupostos!C37+Pressupostos!C38+Pressupostos!C39)*12 -> 14817.853 | D6: =(Pressupostos!C49*D$4*Pressupostos!C11*12)*(($B6/(1+Pressupostos!C7))-$B6*Pressupostos!C9-Pressupostos!C23)-(Maquinas!L12+Pressupostos!C37+Pressupostos!C38+Pressupostos!C39)*12 -> 24617.107 | E6: =(Pressupostos!C49*E$4*Pressupostos!C11*12)*(($B6/(1+Pressupostos!C7))-$B6*Pressupostos!C9-Pressupostos!C23)-(Maquinas!L12+Pressupostos!C37+Pressupostos!C38+Pressupostos!C39)*12 -> 34416.361 | F6: =(Pressupostos!C49*F$4*Pressupostos!C11*12)*(($B6/(1+Pressupostos!C7))-$B6*Pressupostos!C9-Pressupostos!C23)-(Maquinas!L12+Pressupostos!C37+Pressupostos!C38+Pressupostos!C39)*12 -> 44215.616 | G6: =(Pressupostos!C49*G$4*Pressupostos!C11*12)*(($B6/(1+Pressupostos!C7))-$B6*Pressupostos!C9-Pressupostos!C23)-(Maquinas!L12+Pressupostos!C37+Pressupostos!C38+Pressupostos!C39)*12 -> 54014.87
B7: 10 | C7: =(Pressupostos!C49*C$4*Pressupostos!C11*12)*(($B7/(1+Pressupostos!C7))-$B7*Pressupostos!C9-Pressupostos!C23)-(Maquinas!L12+Pressupostos!C37+Pressupostos!C38+Pressupostos!C39)*12 -> 23587.007 | D7: =(Pressupostos!C49*D$4*Pressupostos!C11*12)*(($B7/(1+Pressupostos!C7))-$B7*Pressupostos!C9-Pressupostos!C23)-(Maquinas!L12+Pressupostos!C37+Pressupostos!C38+Pressupostos!C39)*12 -> 35265.366 | E7: =(Pressupostos!C49*E$4*Pressupostos!C11*12)*(($B7/(1+Pressupostos!C7))-$B7*Pressupostos!C9-Pressupostos!C23)-(Maquinas!L12+Pressupostos!C37+Pressupostos!C38+Pressupostos!C39)*12 -> 46943.724 | F7: =(Pressupostos!C49*F$4*Pressupostos!C11*12)*(($B7/(1+Pressupostos!C7))-$B7*Pressupostos!C9-Pressupostos!C23)-(Maquinas!L12+Pressupostos!C37+Pressupostos!C38+Pressupostos!C39)*12 -> 58622.083 | G7: =(Pressupostos!C49*G$4*Pressupostos!C11*12)*(($B7/(1+Pressupostos!C7))-$B7*Pressupostos!C9-Pressupostos!C23)-(Maquinas!L12+Pressupostos!C37+Pressupostos!C38+Pressupostos!C39)*12 -> 70300.442
B8: 11 | C8: =(Pressupostos!C49*C$4*Pressupostos!C11*12)*(($B8/(1+Pressupostos!C7))-$B8*Pressupostos!C9-Pressupostos!C23)-(Maquinas!L12+Pressupostos!C37+Pressupostos!C38+Pressupostos!C39)*12 -> 32356.161 | D8: =(Pressupostos!C49*D$4*Pressupostos!C11*12)*(($B8/(1+Pressupostos!C7))-$B8*Pressupostos!C9-Pressupostos!C23)-(Maquinas!L12+Pressupostos!C37+Pressupostos!C38+Pressupostos!C39)*12 -> 45913.624 | E8: =(Pressupostos!C49*E$4*Pressupostos!C11*12)*(($B8/(1+Pressupostos!C7))-$B8*Pressupostos!C9-Pressupostos!C23)-(Maquinas!L12+Pressupostos!C37+Pressupostos!C38+Pressupostos!C39)*12 -> 59471.087 | F8: =(Pressupostos!C49*F$4*Pressupostos!C11*12)*(($B8/(1+Pressupostos!C7))-$B8*Pressupostos!C9-Pressupostos!C23)-(Maquinas!L12+Pressupostos!C37+Pressupostos!C38+Pressupostos!C39)*12 -> 73028.55 | G8: =(Pressupostos!C49*G$4*Pressupostos!C11*12)*(($B8/(1+Pressupostos!C7))-$B8*Pressupostos!C9-Pressupostos!C23)-(Maquinas!L12+Pressupostos!C37+Pressupostos!C38+Pressupostos!C39)*12 -> 86586.013
B9: 12 | C9: =(Pressupostos!C49*C$4*Pressupostos!C11*12)*(($B9/(1+Pressupostos!C7))-$B9*Pressupostos!C9-Pressupostos!C23)-(Maquinas!L12+Pressupostos!C37+Pressupostos!C38+Pressupostos!C39)*12 -> 41125.315 | D9: =(Pressupostos!C49*D$4*Pressupostos!C11*12)*(($B9/(1+Pressupostos!C7))-$B9*Pressupostos!C9-Pressupostos!C23)-(Maquinas!L12+Pressupostos!C37+Pressupostos!C38+Pressupostos!C39)*12 -> 56561.882 | E9: =(Pressupostos!C49*E$4*Pressupostos!C11*12)*(($B9/(1+Pressupostos!C7))-$B9*Pressupostos!C9-Pressupostos!C23)-(Maquinas!L12+Pressupostos!C37+Pressupostos!C38+Pressupostos!C39)*12 -> 71998.45 | F9: =(Pressupostos!C49*F$4*Pressupostos!C11*12)*(($B9/(1+Pressupostos!C7))-$B9*Pressupostos!C9-Pressupostos!C23)-(Maquinas!L12+Pressupostos!C37+Pressupostos!C38+Pressupostos!C39)*12 -> 87435.017 | G9: =(Pressupostos!C49*G$4*Pressupostos!C11*12)*(($B9/(1+Pressupostos!C7))-$B9*Pressupostos!C9-Pressupostos!C23)-(Maquinas!L12+Pressupostos!C37+Pressupostos!C38+Pressupostos!C39)*12 -> 102871.58
B11: Célula amarela = caso base (€10, 20/dia) / Yellow = base case
B12: Exclui circuito móvel — ver folha Eventos. / Excludes mobile circuit.

Sheet ROI
B1: ROI — RETORNO DO INVESTIDOR / INVESTOR RETURN
B2: Retorno apenas da operação — máquinas não são vendidas / Operations only — machines not sold
B4: FLUXO DE CAIXA DO INVESTIDOR / INVESTOR CASH FLOWS
B5: Período / Period | C5: Ano 0 | D5: Ano 1 | E5: Ano 2 | F5: Ano 3 | G5: Ano 4 | H5: Ano 5
B6: Investimento inicial / Initial outlay | C6: =-Pressupostos!C71 -> -34640 | D6: 0 | E6: 0 | F6: 0 | G6: 0 | H6: 0
B7: Fluxo líquido operacional / Net operating cash | C7: 0 | D7: =Tesouraria!O9 -> 55983.097 | E7: =Tesouraria!P9 -> 71545.638 | F7: =Tesouraria!Q9 -> 79009.126 | G7: =Tesouraria!R9 -> 86837.702 | H7: =Tesouraria!S9 -> 95048.948
B8: FLUXO DO INVESTIDOR / INVESTOR CASH FLOW | C8: =C6+C7 -> -34640 | D8: =D6+D7 -> 55983.097 | E8: =E6+E7 -> 71545.638 | F8: =F6+F7 -> 79009.126 | G8: =G6+G7 -> 86837.702 | H8: =H6+H7 -> 95048.948
B9: Caixa acumulada / Cumulative | C9: =C8 -> -34640 | D9: =C9+D8 -> 21343.097 | E9: =D9+E8 -> 92888.735 | F9: =E9+F8 -> 171897.86 | G9: =F9+G8 -> 258735.56 | H9: =G9+H8 -> 353784.51
B11: INDICADORES / METRICS
B12: Investimento inicial / Initial investment | C12: =Pressupostos!C71 -> 34640
B13: Total entradas (5a) / Net inflows | C13: =SUM(D7:H7) -> 388424.51
B14: Ganho líquido / Net gain | C14: =C13-C12 -> 353784.51
B15: Múltiplo / Cash multiple | C15: =C13/C12 -> 11.213179
B16: TIR / IRR | C16: =IRR(C8:H8) -> 1.8021431
B17: Payback (anos aprox.) / Payback (yrs) | C17: =C12/AVERAGE(D7:H7) -> 0.44590389
B19: MEMO: valor residual das máquinas (NÃO vendido) / residual value (NOT sold) | C19: =(Pressupostos!C56+Pressupostos!C57)-Pressupostos!C69*Pressupostos!C70 -> 49950
B20: As máquinas são mantidas em operação; este valor não entra no retorno de caixa.
B21: Machines are kept operating; this value is excluded from the cash return.
